Compiled from "ScreenEffectRenderer.java"
public class mchorse.bbs_mod.client.screen.ScreenEffectRenderer {
  public mchorse.bbs_mod.client.screen.ScreenEffectRenderer();
    Code:
       0: aload_0
       1: invokespecial #9                  // Method java/lang/Object."<init>":()V
       4: return

  public static void render(mchorse.bbs_mod.ui.framework.elements.utils.Batcher2D, mchorse.bbs_mod.utils.clips.ClipContext, int, int);
    Code:
       0: aload_1
       1: invokestatic  #23                 // Method mchorse/bbs_mod/camera/clips/screen/ColorClip.getEffects:(Lmchorse/bbs_mod/utils/clips/ClipContext;)Ljava/util/List;
       4: astore        4
       6: aload_1
       7: invokestatic  #26                 // Method mchorse/bbs_mod/camera/clips/screen/LetterboxClip.getEffects:(Lmchorse/bbs_mod/utils/clips/ClipContext;)Ljava/util/List;
      10: astore        5
      12: aload_1
      13: invokestatic  #29                 // Method mchorse/bbs_mod/camera/clips/screen/EyeClip.getEffects:(Lmchorse/bbs_mod/utils/clips/ClipContext;)Ljava/util/List;
      16: astore        6
      18: aload_1
      19: invokestatic  #32                 // Method mchorse/bbs_mod/camera/clips/screen/GrainClip.getEffects:(Lmchorse/bbs_mod/utils/clips/ClipContext;)Ljava/util/List;
      22: astore        7
      24: aload_1
      25: invokestatic  #35                 // Method mchorse/bbs_mod/camera/clips/screen/ScreenNodeEffect.getEffects:(Lmchorse/bbs_mod/utils/clips/ClipContext;)Ljava/util/List;
      28: astore        8
      30: aload         8
      32: invokeinterface #41,  1           // InterfaceMethod java/util/List.iterator:()Ljava/util/Iterator;
      37: astore        9
      39: aload         9
      41: invokeinterface #51,  1           // InterfaceMethod java/util/Iterator.hasNext:()Z
      46: ifeq          405
      49: aload         9
      51: invokeinterface #55,  1           // InterfaceMethod java/util/Iterator.next:()Ljava/lang/Object;
      56: checkcast     #34                 // class mchorse/bbs_mod/camera/clips/screen/ScreenNodeEffect
      59: astore        10
      61: new           #57                 // class mchorse/bbs_mod/camera/clips/screen/ColorEffect
      64: dup
      65: invokespecial #58                 // Method mchorse/bbs_mod/camera/clips/screen/ColorEffect."<init>":()V
      68: astore        11
      70: aload         10
      72: getfield      #62                 // Field mchorse/bbs_mod/camera/clips/screen/ScreenNodeEffect.brightness:F
      75: fconst_0
      76: fcmpl
      77: ifne          100
      80: aload         10
      82: getfield      #65                 // Field mchorse/bbs_mod/camera/clips/screen/ScreenNodeEffect.contrast:F
      85: fconst_0
      86: fcmpl
      87: ifne          100
      90: aload         10
      92: getfield      #68                 // Field mchorse/bbs_mod/camera/clips/screen/ScreenNodeEffect.saturation:F
      95: fconst_0
      96: fcmpl
      97: ifeq          136
     100: aload         11
     102: iconst_1
     103: putfield      #72                 // Field mchorse/bbs_mod/camera/clips/screen/ColorEffect.hasGrade:Z
     106: aload         11
     108: aload         10
     110: getfield      #62                 // Field mchorse/bbs_mod/camera/clips/screen/ScreenNodeEffect.brightness:F
     113: putfield      #73                 // Field mchorse/bbs_mod/camera/clips/screen/ColorEffect.brightness:F
     116: aload         11
     118: aload         10
     120: getfield      #65                 // Field mchorse/bbs_mod/camera/clips/screen/ScreenNodeEffect.contrast:F
     123: putfield      #74                 // Field mchorse/bbs_mod/camera/clips/screen/ColorEffect.contrast:F
     126: aload         11
     128: aload         10
     130: getfield      #68                 // Field mchorse/bbs_mod/camera/clips/screen/ScreenNodeEffect.saturation:F
     133: putfield      #75                 // Field mchorse/bbs_mod/camera/clips/screen/ColorEffect.saturation:F
     136: aload         10
     138: getfield      #78                 // Field mchorse/bbs_mod/camera/clips/screen/ScreenNodeEffect.vignetteStrength:F
     141: fconst_0
     142: fcmpl
     143: ifle          182
     146: aload         11
     148: iconst_1
     149: putfield      #81                 // Field mchorse/bbs_mod/camera/clips/screen/ColorEffect.hasVignette:Z
     152: aload         11
     154: aload         10
     156: getfield      #78                 // Field mchorse/bbs_mod/camera/clips/screen/ScreenNodeEffect.vignetteStrength:F
     159: putfield      #82                 // Field mchorse/bbs_mod/camera/clips/screen/ColorEffect.vignetteStrength:F
     162: aload         11
     164: aload         10
     166: getfield      #85                 // Field mchorse/bbs_mod/camera/clips/screen/ScreenNodeEffect.vignetteSmoothness:F
     169: putfield      #86                 // Field mchorse/bbs_mod/camera/clips/screen/ColorEffect.vignetteSmoothness:F
     172: aload         11
     174: aload         10
     176: getfield      #90                 // Field mchorse/bbs_mod/camera/clips/screen/ScreenNodeEffect.vignetteColor:I
     179: putfield      #91                 // Field mchorse/bbs_mod/camera/clips/screen/ColorEffect.vignetteColor:I
     182: aload         10
     184: getfield      #94                 // Field mchorse/bbs_mod/camera/clips/screen/ScreenNodeEffect.overlayAlpha:F
     187: fconst_0
     188: fcmpl
     189: ifle          216
     192: aload         11
     194: iconst_1
     195: putfield      #97                 // Field mchorse/bbs_mod/camera/clips/screen/ColorEffect.hasOverlay:Z
     198: aload         11
     200: aload         10
     202: getfield      #100                // Field mchorse/bbs_mod/camera/clips/screen/ScreenNodeEffect.overlayColor:I
     205: aload         10
     207: getfield      #94                 // Field mchorse/bbs_mod/camera/clips/screen/ScreenNodeEffect.overlayAlpha:F
     210: invokestatic  #106                // Method mchorse/bbs_mod/utils/colors/Colors.setA:(IF)I
     213: putfield      #107                // Field mchorse/bbs_mod/camera/clips/screen/ColorEffect.overlayColor:I
     216: aload         10
     218: getfield      #110                // Field mchorse/bbs_mod/camera/clips/screen/ScreenNodeEffect.distortX:F
     221: fconst_0
     222: fcmpl
     223: ifne          236
     226: aload         10
     228: getfield      #113                // Field mchorse/bbs_mod/camera/clips/screen/ScreenNodeEffect.distortY:F
     231: fconst_0
     232: fcmpl
     233: ifeq          262
     236: aload         11
     238: iconst_1
     239: putfield      #116                // Field mchorse/bbs_mod/camera/clips/screen/ColorEffect.hasDistort:Z
     242: aload         11
     244: aload         10
     246: getfield      #110                // Field mchorse/bbs_mod/camera/clips/screen/ScreenNodeEffect.distortX:F
     249: putfield      #117                // Field mchorse/bbs_mod/camera/clips/screen/ColorEffect.distortX:F
     252: aload         11
     254: aload         10
     256: getfield      #113                // Field mchorse/bbs_mod/camera/clips/screen/ScreenNodeEffect.distortY:F
     259: putfield      #118                // Field mchorse/bbs_mod/camera/clips/screen/ColorEffect.distortY:F
     262: aload         11
     264: getfield      #72                 // Field mchorse/bbs_mod/camera/clips/screen/ColorEffect.hasGrade:Z
     267: ifne          294
     270: aload         11
     272: getfield      #81                 // Field mchorse/bbs_mod/camera/clips/screen/ColorEffect.hasVignette:Z
     275: ifne          294
     278: aload         11
     280: getfield      #97                 // Field mchorse/bbs_mod/camera/clips/screen/ColorEffect.hasOverlay:Z
     283: ifne          294
     286: aload         11
     288: getfield      #116                // Field mchorse/bbs_mod/camera/clips/screen/ColorEffect.hasDistort:Z
     291: ifeq          304
     294: aload         4
     296: aload         11
     298: invokeinterface #122,  2          // InterfaceMethod java/util/List.add:(Ljava/lang/Object;)Z
     303: pop
     304: aload         10
     306: getfield      #125                // Field mchorse/bbs_mod/camera/clips/screen/ScreenNodeEffect.grainStrength:F
     309: fconst_0
     310: fcmpl
     311: ifle          353
     314: new           #127                // class mchorse/bbs_mod/camera/clips/screen/GrainEffect
     317: dup
     318: invokespecial #128                // Method mchorse/bbs_mod/camera/clips/screen/GrainEffect."<init>":()V
     321: astore        12
     323: aload         12
     325: aload         10
     327: getfield      #125                // Field mchorse/bbs_mod/camera/clips/screen/ScreenNodeEffect.grainStrength:F
     330: putfield      #131                // Field mchorse/bbs_mod/camera/clips/screen/GrainEffect.strength:F
     333: aload         12
     335: aload         10
     337: getfield      #134                // Field mchorse/bbs_mod/camera/clips/screen/ScreenNodeEffect.grainSize:F
     340: putfield      #137                // Field mchorse/bbs_mod/camera/clips/screen/GrainEffect.size:F
     343: aload         7
     345: aload         12
     347: invokeinterface #122,  2          // InterfaceMethod java/util/List.add:(Ljava/lang/Object;)Z
     352: pop
     353: aload         10
     355: getfield      #140                // Field mchorse/bbs_mod/camera/clips/screen/ScreenNodeEffect.letterboxSize:F
     358: fconst_0
     359: fcmpl
     360: ifle          402
     363: new           #142                // class mchorse/bbs_mod/camera/clips/screen/LetterboxEffect
     366: dup
     367: invokespecial #143                // Method mchorse/bbs_mod/camera/clips/screen/LetterboxEffect."<init>":()V
     370: astore        12
     372: aload         12
     374: aload         10
     376: getfield      #140                // Field mchorse/bbs_mod/camera/clips/screen/ScreenNodeEffect.letterboxSize:F
     379: putfield      #144                // Field mchorse/bbs_mod/camera/clips/screen/LetterboxEffect.size:F
     382: aload         12
     384: aload         10
     386: getfield      #147                // Field mchorse/bbs_mod/camera/clips/screen/ScreenNodeEffect.letterboxColor:I
     389: putfield      #150                // Field mchorse/bbs_mod/camera/clips/screen/LetterboxEffect.color:I
     392: aload         5
     394: aload         12
     396: invokeinterface #122,  2          // InterfaceMethod java/util/List.add:(Ljava/lang/Object;)Z
     401: pop
     402: goto          39
     405: aload         8
     407: invokeinterface #153,  1          // InterfaceMethod java/util/List.clear:()V
     412: aload         4
     414: invokeinterface #41,  1           // InterfaceMethod java/util/List.iterator:()Ljava/util/Iterator;
     419: astore        9
     421: aload         9
     423: invokeinterface #51,  1           // InterfaceMethod java/util/Iterator.hasNext:()Z
     428: ifeq          469
     431: aload         9
     433: invokeinterface #55,  1           // InterfaceMethod java/util/Iterator.next:()Ljava/lang/Object;
     438: checkcast     #57                 // class mchorse/bbs_mod/camera/clips/screen/ColorEffect
     441: astore        10
     443: aload         10
     445: getfield      #97                 // Field mchorse/bbs_mod/camera/clips/screen/ColorEffect.hasOverlay:Z
     448: ifeq          466
     451: aload_0
     452: fconst_0
     453: fconst_0
     454: iload_2
     455: i2f
     456: iload_3
     457: i2f
     458: aload         10
     460: getfield      #107                // Field mchorse/bbs_mod/camera/clips/screen/ColorEffect.overlayColor:I
     463: invokevirtual #157                // Method mchorse/bbs_mod/ui/framework/elements/utils/Batcher2D.box:(FFFFI)V
     466: goto          421
     469: aload         4
     471: aload         7
     473: invokestatic  #163                // Method mchorse/bbs_mod/client/screen/ColorGradeRenderer.apply:(Ljava/util/List;Ljava/util/List;)V
     476: aload         5
     478: invokeinterface #41,  1           // InterfaceMethod java/util/List.iterator:()Ljava/util/Iterator;
     483: astore        9
     485: aload         9
     487: invokeinterface #51,  1           // InterfaceMethod java/util/Iterator.hasNext:()Z
     492: ifeq          518
     495: aload         9
     497: invokeinterface #55,  1           // InterfaceMethod java/util/Iterator.next:()Ljava/lang/Object;
     502: checkcast     #142                // class mchorse/bbs_mod/camera/clips/screen/LetterboxEffect
     505: astore        10
     507: aload_0
     508: aload         10
     510: iload_2
     511: iload_3
     512: invokestatic  #167                // Method renderLetterbox:(Lmchorse/bbs_mod/ui/framework/elements/utils/Batcher2D;Lmchorse/bbs_mod/camera/clips/screen/LetterboxEffect;II)V
     515: goto          485
     518: aload         6
     520: invokeinterface #41,  1           // InterfaceMethod java/util/List.iterator:()Ljava/util/Iterator;
     525: astore        9
     527: aload         9
     529: invokeinterface #51,  1           // InterfaceMethod java/util/Iterator.hasNext:()Z
     534: ifeq          560
     537: aload         9
     539: invokeinterface #55,  1           // InterfaceMethod java/util/Iterator.next:()Ljava/lang/Object;
     544: checkcast     #169                // class mchorse/bbs_mod/camera/clips/screen/EyeEffect
     547: astore        10
     549: aload_0
     550: aload         10
     552: iload_2
     553: iload_3
     554: invokestatic  #173                // Method renderEye:(Lmchorse/bbs_mod/ui/framework/elements/utils/Batcher2D;Lmchorse/bbs_mod/camera/clips/screen/EyeEffect;II)V
     557: goto          527
     560: aload         4
     562: invokeinterface #153,  1          // InterfaceMethod java/util/List.clear:()V
     567: aload         5
     569: invokeinterface #153,  1          // InterfaceMethod java/util/List.clear:()V
     574: aload         6
     576: invokeinterface #153,  1          // InterfaceMethod java/util/List.clear:()V
     581: aload         7
     583: invokeinterface #153,  1          // InterfaceMethod java/util/List.clear:()V
     588: return

  private static void renderLetterbox(mchorse.bbs_mod.ui.framework.elements.utils.Batcher2D, mchorse.bbs_mod.camera.clips.screen.LetterboxEffect, int, int);
    Code:
       0: iload_3
       1: i2f
       2: aload_1
       3: getfield      #144                // Field mchorse/bbs_mod/camera/clips/screen/LetterboxEffect.size:F
       6: fmul
       7: f2i
       8: istore        4
      10: iload         4
      12: ifgt          16
      15: return
      16: aload_1
      17: getfield      #199                // Field mchorse/bbs_mod/camera/clips/screen/LetterboxEffect.zoom:F
      20: fconst_0
      21: fcmpg
      22: ifgt          29
      25: fconst_1
      26: goto          33
      29: aload_1
      30: getfield      #199                // Field mchorse/bbs_mod/camera/clips/screen/LetterboxEffect.zoom:F
      33: fstore        5
      35: aload_1
      36: getfield      #202                // Field mchorse/bbs_mod/camera/clips/screen/LetterboxEffect.rotation:F
      39: fconst_0
      40: fcmpl
      41: ifne          69
      44: fload         5
      46: fconst_1
      47: fcmpl
      48: ifne          69
      51: aload_1
      52: getfield      #205                // Field mchorse/bbs_mod/camera/clips/screen/LetterboxEffect.offsetX:F
      55: fconst_0
      56: fcmpl
      57: ifne          69
      60: aload_1
      61: getfield      #208                // Field mchorse/bbs_mod/camera/clips/screen/LetterboxEffect.offsetY:F
      64: fconst_0
      65: fcmpl
      66: ifeq          73
      69: iconst_1
      70: goto          74
      73: iconst_0
      74: istore        6
      76: iload         6
      78: ifeq          192
      81: aload_0
      82: invokevirtual #212                // Method mchorse/bbs_mod/ui/framework/elements/utils/Batcher2D.getContext:()Lnet/minecraft/class_332;
      85: invokevirtual #218                // Method net/minecraft/class_332.method_51448:()Lnet/minecraft/class_4587;
      88: astore        7
      90: aload         7
      92: invokevirtual #223                // Method net/minecraft/class_4587.method_22903:()V
      95: aload         7
      97: aload_1
      98: getfield      #205                // Field mchorse/bbs_mod/camera/clips/screen/LetterboxEffect.offsetX:F
     101: iload_2
     102: i2f
     103: fmul
     104: aload_1
     105: getfield      #208                // Field mchorse/bbs_mod/camera/clips/screen/LetterboxEffect.offsetY:F
     108: iload_3
     109: i2f
     110: fmul
     111: fconst_0
     112: invokevirtual #227                // Method net/minecraft/class_4587.method_46416:(FFF)V
     115: aload         7
     117: iload_2
     118: i2f
     119: fconst_2
     120: fdiv
     121: iload_3
     122: i2f
     123: fconst_2
     124: fdiv
     125: fconst_0
     126: invokevirtual #227                // Method net/minecraft/class_4587.method_46416:(FFF)V
     129: aload         7
     131: getstatic     #233                // Field net/minecraft/class_7833.field_40718:Lnet/minecraft/class_7833;
     134: aload_1
     135: getfield      #202                // Field mchorse/bbs_mod/camera/clips/screen/LetterboxEffect.rotation:F
     138: invokestatic  #239                // Method mchorse/bbs_mod/utils/MathUtils.toRad:(F)F
     141: invokeinterface #242,  2          // InterfaceMethod net/minecraft/class_7833.rotation:(F)Lorg/joml/Quaternionf;
     146: invokevirtual #246                // Method net/minecraft/class_4587.method_22907:(Lorg/joml/Quaternionf;)V
     149: aload         7
     151: fload         5
     153: fload         5
     155: fconst_1
     156: invokevirtual #249                // Method net/minecraft/class_4587.method_22905:(FFF)V
     159: aload         7
     161: iload_2
     162: ineg
     163: i2f
     164: fconst_2
     165: fdiv
     166: iload_3
     167: ineg
     168: i2f
     169: fconst_2
     170: fdiv
     171: fconst_0
     172: invokevirtual #227                // Method net/minecraft/class_4587.method_46416:(FFF)V
     175: aload_0
     176: aload_1
     177: iload_2
     178: iload_3
     179: iload         4
     181: invokestatic  #253                // Method renderLetterboxBars:(Lmchorse/bbs_mod/ui/framework/elements/utils/Batcher2D;Lmchorse/bbs_mod/camera/clips/screen/LetterboxEffect;III)V
     184: aload         7
     186: invokevirtual #256                // Method net/minecraft/class_4587.method_22909:()V
     189: goto          201
     192: aload_0
     193: aload_1
     194: iload_2
     195: iload_3
     196: iload         4
     198: invokestatic  #253                // Method renderLetterboxBars:(Lmchorse/bbs_mod/ui/framework/elements/utils/Batcher2D;Lmchorse/bbs_mod/camera/clips/screen/LetterboxEffect;III)V
     201: return

  private static void renderLetterboxBars(mchorse.bbs_mod.ui.framework.elements.utils.Batcher2D, mchorse.bbs_mod.camera.clips.screen.LetterboxEffect, int, int, int);
    Code:
       0: aload_1
       1: getfield      #150                // Field mchorse/bbs_mod/camera/clips/screen/LetterboxEffect.color:I
       4: istore        5
       6: iload_3
       7: i2f
       8: aload_1
       9: getfield      #263                // Field mchorse/bbs_mod/camera/clips/screen/LetterboxEffect.smoothness:F
      12: fmul
      13: f2i
      14: istore        6
      16: aload_1
      17: getfield      #266                // Field mchorse/bbs_mod/camera/clips/screen/LetterboxEffect.width:F
      20: fconst_0
      21: fcmpg
      22: ifgt          29
      25: fconst_1
      26: goto          33
      29: aload_1
      30: getfield      #266                // Field mchorse/bbs_mod/camera/clips/screen/LetterboxEffect.width:F
      33: fstore        7
      35: iconst_1
      36: iload_2
      37: i2f
      38: fload         7
      40: fmul
      41: invokestatic  #272                // Method java/lang/Math.round:(F)I
      44: invokestatic  #276                // Method java/lang/Math.max:(II)I
      47: istore        8
      49: iload_2
      50: iload         8
      52: isub
      53: iconst_2
      54: idiv
      55: istore        9
      57: iload         6
      59: ifle          178
      62: iload         6
      64: iload         4
      66: if_icmpge     178
      69: iload         4
      71: iload         6
      73: isub
      74: istore        10
      76: iload         5
      78: fconst_0
      79: invokestatic  #106                // Method mchorse/bbs_mod/utils/colors/Colors.setA:(IF)I
      82: istore        11
      84: aload_0
      85: iload         9
      87: i2f
      88: fconst_0
      89: iload         9
      91: iload         8
      93: iadd
      94: i2f
      95: iload         10
      97: i2f
      98: iload         5
     100: invokevirtual #157                // Method mchorse/bbs_mod/ui/framework/elements/utils/Batcher2D.box:(FFFFI)V
     103: aload_0
     104: iload         9
     106: i2f
     107: iload         10
     109: i2f
     110: iload         9
     112: iload         8
     114: iadd
     115: i2f
     116: iload         4
     118: i2f
     119: iload         5
     121: iload         11
     123: invokevirtual #280                // Method mchorse/bbs_mod/ui/framework/elements/utils/Batcher2D.gradientVBox:(FFFFII)V
     126: aload_0
     127: iload         9
     129: i2f
     130: iload_3
     131: iload         4
     133: isub
     134: i2f
     135: iload         9
     137: iload         8
     139: iadd
     140: i2f
     141: iload_3
     142: iload         10
     144: isub
     145: i2f
     146: iload         11
     148: iload         5
     150: invokevirtual #280                // Method mchorse/bbs_mod/ui/framework/elements/utils/Batcher2D.gradientVBox:(FFFFII)V
     153: aload_0
     154: iload         9
     156: i2f
     157: iload_3
     158: iload         10
     160: isub
     161: i2f
     162: iload         9
     164: iload         8
     166: iadd
     167: i2f
     168: iload_3
     169: i2f
     170: iload         5
     172: invokevirtual #157                // Method mchorse/bbs_mod/ui/framework/elements/utils/Batcher2D.box:(FFFFI)V
     175: goto          219
     178: aload_0
     179: iload         9
     181: i2f
     182: fconst_0
     183: iload         9
     185: iload         8
     187: iadd
     188: i2f
     189: iload         4
     191: i2f
     192: iload         5
     194: invokevirtual #157                // Method mchorse/bbs_mod/ui/framework/elements/utils/Batcher2D.box:(FFFFI)V
     197: aload_0
     198: iload         9
     200: i2f
     201: iload_3
     202: iload         4
     204: isub
     205: i2f
     206: iload         9
     208: iload         8
     210: iadd
     211: i2f
     212: iload_3
     213: i2f
     214: iload         5
     216: invokevirtual #157                // Method mchorse/bbs_mod/ui/framework/elements/utils/Batcher2D.box:(FFFFI)V
     219: return

  private static void renderEye(mchorse.bbs_mod.ui.framework.elements.utils.Batcher2D, mchorse.bbs_mod.camera.clips.screen.EyeEffect, int, int);
    Code:
       0: fconst_1
       1: aload_1
       2: getfield      #287                // Field mchorse/bbs_mod/camera/clips/screen/EyeEffect.size:F
       5: ldc_w         #288                // float 0.025f
       8: fdiv
       9: invokestatic  #292                // Method java/lang/Math.min:(FF)F
      12: fstore        4
      14: fload         4
      16: ldc_w         #293                // float 0.001f
      19: fcmpg
      20: ifgt          24
      23: return
      24: aload_1
      25: getfield      #294                // Field mchorse/bbs_mod/camera/clips/screen/EyeEffect.zoom:F
      28: fconst_0
      29: fcmpg
      30: ifgt          37
      33: fconst_1
      34: goto          41
      37: aload_1
      38: getfield      #294                // Field mchorse/bbs_mod/camera/clips/screen/EyeEffect.zoom:F
      41: fstore        5
      43: aload_1
      44: getfield      #295                // Field mchorse/bbs_mod/camera/clips/screen/EyeEffect.rotation:F
      47: fconst_0
      48: fcmpl
      49: ifne          77
      52: fload         5
      54: fconst_1
      55: fcmpl
      56: ifne          77
      59: aload_1
      60: getfield      #296                // Field mchorse/bbs_mod/camera/clips/screen/EyeEffect.offsetX:F
      63: fconst_0
      64: fcmpl
      65: ifne          77
      68: aload_1
      69: getfield      #297                // Field mchorse/bbs_mod/camera/clips/screen/EyeEffect.offsetY:F
      72: fconst_0
      73: fcmpl
      74: ifeq          81
      77: iconst_1
      78: goto          82
      81: iconst_0
      82: istore        6
      84: iload         6
      86: ifeq          200
      89: aload_0
      90: invokevirtual #212                // Method mchorse/bbs_mod/ui/framework/elements/utils/Batcher2D.getContext:()Lnet/minecraft/class_332;
      93: invokevirtual #218                // Method net/minecraft/class_332.method_51448:()Lnet/minecraft/class_4587;
      96: astore        7
      98: aload         7
     100: invokevirtual #223                // Method net/minecraft/class_4587.method_22903:()V
     103: aload         7
     105: aload_1
     106: getfield      #296                // Field mchorse/bbs_mod/camera/clips/screen/EyeEffect.offsetX:F
     109: iload_2
     110: i2f
     111: fmul
     112: aload_1
     113: getfield      #297                // Field mchorse/bbs_mod/camera/clips/screen/EyeEffect.offsetY:F
     116: iload_3
     117: i2f
     118: fmul
     119: fconst_0
     120: invokevirtual #227                // Method net/minecraft/class_4587.method_46416:(FFF)V
     123: aload         7
     125: iload_2
     126: i2f
     127: fconst_2
     128: fdiv
     129: iload_3
     130: i2f
     131: fconst_2
     132: fdiv
     133: fconst_0
     134: invokevirtual #227                // Method net/minecraft/class_4587.method_46416:(FFF)V
     137: aload         7
     139: getstatic     #233                // Field net/minecraft/class_7833.field_40718:Lnet/minecraft/class_7833;
     142: aload_1
     143: getfield      #295                // Field mchorse/bbs_mod/camera/clips/screen/EyeEffect.rotation:F
     146: invokestatic  #239                // Method mchorse/bbs_mod/utils/MathUtils.toRad:(F)F
     149: invokeinterface #242,  2          // InterfaceMethod net/minecraft/class_7833.rotation:(F)Lorg/joml/Quaternionf;
     154: invokevirtual #246                // Method net/minecraft/class_4587.method_22907:(Lorg/joml/Quaternionf;)V
     157: aload         7
     159: fload         5
     161: fload         5
     163: fconst_1
     164: invokevirtual #249                // Method net/minecraft/class_4587.method_22905:(FFF)V
     167: aload         7
     169: iload_2
     170: ineg
     171: i2f
     172: fconst_2
     173: fdiv
     174: iload_3
     175: ineg
     176: i2f
     177: fconst_2
     178: fdiv
     179: fconst_0
     180: invokevirtual #227                // Method net/minecraft/class_4587.method_46416:(FFF)V
     183: aload_0
     184: aload_1
     185: iload_2
     186: iload_3
     187: fload         4
     189: invokestatic  #301                // Method renderEyeMask:(Lmchorse/bbs_mod/ui/framework/elements/utils/Batcher2D;Lmchorse/bbs_mod/camera/clips/screen/EyeEffect;IIF)V
     192: aload         7
     194: invokevirtual #256                // Method net/minecraft/class_4587.method_22909:()V
     197: goto          209
     200: aload_0
     201: aload_1
     202: iload_2
     203: iload_3
     204: fload         4
     206: invokestatic  #301                // Method renderEyeMask:(Lmchorse/bbs_mod/ui/framework/elements/utils/Batcher2D;Lmchorse/bbs_mod/camera/clips/screen/EyeEffect;IIF)V
     209: return

  private static void renderEyeMask(mchorse.bbs_mod.ui.framework.elements.utils.Batcher2D, mchorse.bbs_mod.camera.clips.screen.EyeEffect, int, int, float);
    Code:
       0: aload_1
       1: getfield      #303                // Field mchorse/bbs_mod/camera/clips/screen/EyeEffect.color:I
       4: istore        5
       6: iload         5
       8: iload         5
      10: invokestatic  #307                // Method mchorse/bbs_mod/utils/colors/Colors.getA:(I)F
      13: fload         4
      15: fmul
      16: invokestatic  #106                // Method mchorse/bbs_mod/utils/colors/Colors.setA:(IF)I
      19: istore        6
      21: iload         6
      23: fconst_0
      24: invokestatic  #106                // Method mchorse/bbs_mod/utils/colors/Colors.setA:(IF)I
      27: istore        7
      29: aload_1
      30: getfield      #308                // Field mchorse/bbs_mod/camera/clips/screen/EyeEffect.width:F
      33: fconst_0
      34: fcmpg
      35: ifgt          42
      38: fconst_1
      39: goto          46
      42: aload_1
      43: getfield      #308                // Field mchorse/bbs_mod/camera/clips/screen/EyeEffect.width:F
      46: fstore        8
      48: fconst_0
      49: fconst_1
      50: aload_1
      51: getfield      #287                // Field mchorse/bbs_mod/camera/clips/screen/EyeEffect.size:F
      54: fsub
      55: invokestatic  #310                // Method java/lang/Math.max:(FF)F
      58: fstore        9
      60: iload_2
      61: i2f
      62: fconst_2
      63: fdiv
      64: fload         8
      66: fmul
      67: fstore        10
      69: iload_3
      70: i2f
      71: fconst_2
      72: fdiv
      73: fload         9
      75: fmul
      76: fstore        11
      78: iload_2
      79: i2f
      80: fconst_2
      81: fdiv
      82: fstore        12
      84: iload_3
      85: i2f
      86: fconst_2
      87: fdiv
      88: fstore        13
      90: iconst_0
      91: fload         10
      93: aload_1
      94: getfield      #311                // Field mchorse/bbs_mod/camera/clips/screen/EyeEffect.smoothness:F
      97: fmul
      98: invokestatic  #272                // Method java/lang/Math.round:(F)I
     101: invokestatic  #276                // Method java/lang/Math.max:(II)I
     104: istore        14
     106: iload         14
     108: ifle          115
     111: iconst_1
     112: goto          116
     115: iconst_0
     116: istore        15
     118: fload         9
     120: ldc_w         #312                // float 0.3f
     123: fcmpl
     124: ifle          201
     127: fload         8
     129: fconst_0
     130: fcmpl
     131: ifle          201
     134: dconst_1
     135: iload_2
     136: i2d
     137: iload_3
     138: i2d
     139: ddiv
     140: fload         8
     142: f2d
     143: ddiv
     144: ldc2_w        #313                // double 2.0d
     147: invokestatic  #318                // Method java/lang/Math.pow:(DD)D
     150: dadd
     151: invokestatic  #322                // Method java/lang/Math.sqrt:(D)D
     154: d2f
     155: fstore        16
     157: fconst_1
     158: fload         9
     160: ldc_w         #312                // float 0.3f
     163: fsub
     164: ldc_w         #323                // float 0.7f
     167: fdiv
     168: invokestatic  #292                // Method java/lang/Math.min:(FF)F
     171: fstore        17
     173: fload         10
     175: fconst_1
     176: fload         16
     178: fconst_1
     179: fsub
     180: fload         17
     182: fmul
     183: fadd
     184: fmul
     185: fstore        10
     187: fload         11
     189: fconst_1
     190: fload         16
     192: fconst_1
     193: fsub
     194: fload         17
     196: fmul
     197: fadd
     198: fmul
     199: fstore        11
     201: fload         11
     203: fconst_0
     204: fcmpg
     205: ifgt          221
     208: aload_0
     209: fconst_0
     210: fconst_0
     211: iload_2
     212: i2f
     213: iload_3
     214: i2f
     215: iload         6
     217: invokevirtual #157                // Method mchorse/bbs_mod/ui/framework/elements/utils/Batcher2D.box:(FFFFI)V
     220: return
     221: iconst_m1
     222: istore        16
     224: iconst_0
     225: istore        17
     227: iload         17
     229: iload_3
     230: if_icmpgt     569
     233: iload         17
     235: iload_3
     236: if_icmpge     264
     239: iload         17
     241: i2f
     242: ldc_w         #324                // float 0.5f
     245: fadd
     246: fload         13
     248: fsub
     249: invokestatic  #327                // Method java/lang/Math.abs:(F)F
     252: fload         11
     254: fdiv
     255: fconst_1
     256: fcmpl
     257: iflt          264
     260: iconst_1
     261: goto          265
     264: iconst_0
     265: istore        18
     267: iload         18
     269: ifeq          284
     272: iload         16
     274: ifge          563
     277: iload         17
     279: istore        16
     281: goto          563
     284: iload         16
     286: iflt          307
     289: aload_0
     290: fconst_0
     291: iload         16
     293: i2f
     294: iload_2
     295: i2f
     296: iload         17
     298: i2f
     299: iload         6
     301: invokevirtual #157                // Method mchorse/bbs_mod/ui/framework/elements/utils/Batcher2D.box:(FFFFI)V
     304: iconst_m1
     305: istore        16
     307: iload         17
     309: iload_3
     310: if_icmplt     316
     313: goto          563
     316: iload         17
     318: i2f
     319: ldc_w         #324                // float 0.5f
     322: fadd
     323: fload         13
     325: fsub
     326: invokestatic  #327                // Method java/lang/Math.abs:(F)F
     329: fload         11
     331: fdiv
     332: fstore        19
     334: fload         10
     336: dconst_0
     337: dconst_1
     338: fload         19
     340: fload         19
     342: fmul
     343: f2d
     344: dsub
     345: invokestatic  #329                // Method java/lang/Math.max:(DD)D
     348: invokestatic  #322                // Method java/lang/Math.sqrt:(D)D
     351: d2f
     352: fmul
     353: fstore        20
     355: fload         12
     357: fload         20
     359: fsub
     360: f2d
     361: invokestatic  #332                // Method java/lang/Math.ceil:(D)D
     364: d2i
     365: istore        21
     367: fload         12
     369: fload         20
     371: fadd
     372: f2d
     373: invokestatic  #335                // Method java/lang/Math.floor:(D)D
     376: d2i
     377: istore        22
     379: iload         15
     381: ifeq          515
     384: iconst_0
     385: iload         21
     387: iload         14
     389: isub
     390: invokestatic  #276                // Method java/lang/Math.max:(II)I
     393: istore        23
     395: iload_2
     396: iload         22
     398: iload         14
     400: iadd
     401: invokestatic  #337                // Method java/lang/Math.min:(II)I
     404: istore        24
     406: iload         23
     408: ifle          429
     411: aload_0
     412: fconst_0
     413: iload         17
     415: i2f
     416: iload         23
     418: i2f
     419: iload         17
     421: iconst_1
     422: iadd
     423: i2f
     424: iload         6
     426: invokevirtual #157                // Method mchorse/bbs_mod/ui/framework/elements/utils/Batcher2D.box:(FFFFI)V
     429: iload         21
     431: iload         23
     433: if_icmple     458
     436: aload_0
     437: iload         23
     439: i2f
     440: iload         17
     442: i2f
     443: iload         21
     445: i2f
     446: iload         17
     448: iconst_1
     449: iadd
     450: i2f
     451: iload         6
     453: iload         7
     455: invokevirtual #340                // Method mchorse/bbs_mod/ui/framework/elements/utils/Batcher2D.gradientHBox:(FFFFII)V
     458: iload         24
     460: iload_2
     461: if_icmpge     483
     464: aload_0
     465: iload         24
     467: i2f
     468: iload         17
     470: i2f
     471: iload_2
     472: i2f
     473: iload         17
     475: iconst_1
     476: iadd
     477: i2f
     478: iload         6
     480: invokevirtual #157                // Method mchorse/bbs_mod/ui/framework/elements/utils/Batcher2D.box:(FFFFI)V
     483: iload         24
     485: iload         22
     487: if_icmple     512
     490: aload_0
     491: iload         22
     493: i2f
     494: iload         17
     496: i2f
     497: iload         24
     499: i2f
     500: iload         17
     502: iconst_1
     503: iadd
     504: i2f
     505: iload         7
     507: iload         6
     509: invokevirtual #340                // Method mchorse/bbs_mod/ui/framework/elements/utils/Batcher2D.gradientHBox:(FFFFII)V
     512: goto          563
     515: iload         21
     517: ifle          538
     520: aload_0
     521: fconst_0
     522: iload         17
     524: i2f
     525: iload         21
     527: i2f
     528: iload         17
     530: iconst_1
     531: iadd
     532: i2f
     533: iload         6
     535: invokevirtual #157                // Method mchorse/bbs_mod/ui/framework/elements/utils/Batcher2D.box:(FFFFI)V
     538: iload         22
     540: iload_2
     541: if_icmpge     563
     544: aload_0
     545: iload         22
     547: i2f
     548: iload         17
     550: i2f
     551: iload_2
     552: i2f
     553: iload         17
     555: iconst_1
     556: iadd
     557: i2f
     558: iload         6
     560: invokevirtual #157                // Method mchorse/bbs_mod/ui/framework/elements/utils/Batcher2D.box:(FFFFI)V
     563: iinc          17, 1
     566: goto          227
     569: return
}
