Compiled from "UIFilmPreview.java"
public class mchorse.bbs_mod.ui.film.UIFilmPreview extends mchorse.bbs_mod.ui.framework.elements.UIElement {
  public static final java.util.List<java.util.function.Consumer<mchorse.bbs_mod.ui.film.UIFilmPreview>> extensions;

  private java.util.List<mchorse.bbs_mod.camera.clips.misc.AudioClip> clips;

  private java.io.File pendingThumbnail;

  private java.lang.Runnable pendingThumbnailCallback;

  private mchorse.bbs_mod.ui.film.UIFilmPanel panel;

  private boolean viewportButtonsHidden;

  private final java.util.List<mchorse.bbs_mod.ui.framework.elements.buttons.UIIcon> viewportButtons;

  private final java.util.Map<java.lang.String, mchorse.bbs_mod.ui.framework.elements.buttons.UIIcon> viewportButtonMap;

  private final java.util.Map<java.lang.String, mchorse.bbs_mod.ui.framework.elements.buttons.UIIcon> gizmoButtonMap;

  public mchorse.bbs_mod.ui.framework.elements.UIElement icons;

  public mchorse.bbs_mod.ui.framework.elements.UIElement gizmos;

  public mchorse.bbs_mod.ui.framework.elements.buttons.UIIcon gizmoMove;

  public mchorse.bbs_mod.ui.framework.elements.buttons.UIIcon gizmoScale;

  public mchorse.bbs_mod.ui.framework.elements.buttons.UIIcon gizmoRotate;

  public mchorse.bbs_mod.ui.framework.elements.buttons.UIIcon gizmoCombined;

  public mchorse.bbs_mod.ui.framework.elements.buttons.UIIcon gizmoTop;

  public mchorse.bbs_mod.ui.framework.elements.buttons.UIIcon gizmoSize;

  public mchorse.bbs_mod.ui.framework.elements.buttons.UIIcon gizmoTranslateSpeed;

  public mchorse.bbs_mod.ui.framework.elements.buttons.UIIcon onionSkin;

  public mchorse.bbs_mod.ui.framework.elements.buttons.UIIcon hideOverlays;

  public mchorse.bbs_mod.ui.framework.elements.buttons.UIIcon toggleShaders;

  public mchorse.bbs_mod.ui.framework.elements.buttons.UIIcon plause;

  public mchorse.bbs_mod.ui.framework.elements.buttons.UIIcon teleport;

  public mchorse.bbs_mod.ui.framework.elements.buttons.UIIcon flight;

  public mchorse.bbs_mod.ui.framework.elements.buttons.UIIcon control;

  public mchorse.bbs_mod.ui.framework.elements.buttons.UIIcon perspective;

  public mchorse.bbs_mod.ui.framework.elements.buttons.UIIcon recordReplay;

  public mchorse.bbs_mod.ui.framework.elements.buttons.UIIcon recordVideo;

  public mchorse.bbs_mod.ui.framework.elements.buttons.UIIcon renderQueue;

  public mchorse.bbs_mod.ui.framework.elements.buttons.UIButton joinWorld;

  public mchorse.bbs_mod.ui.film.UIFilmPreview(mchorse.bbs_mod.ui.film.UIFilmPanel);
    Code:
       0: aload_0
       1: invokespecial #78                 // Method mchorse/bbs_mod/ui/framework/elements/UIElement."<init>":()V
       4: aload_0
       5: new           #80                 // class java/util/ArrayList
       8: dup
       9: invokespecial #81                 // Method java/util/ArrayList."<init>":()V
      12: putfield      #83                 // Field clips:Ljava/util/List;
      15: aload_0
      16: new           #80                 // class java/util/ArrayList
      19: dup
      20: invokespecial #81                 // Method java/util/ArrayList."<init>":()V
      23: putfield      #85                 // Field viewportButtons:Ljava/util/List;
      26: aload_0
      27: new           #87                 // class java/util/HashMap
      30: dup
      31: invokespecial #88                 // Method java/util/HashMap."<init>":()V
      34: putfield      #90                 // Field viewportButtonMap:Ljava/util/Map;
      37: aload_0
      38: new           #87                 // class java/util/HashMap
      41: dup
      42: invokespecial #88                 // Method java/util/HashMap."<init>":()V
      45: putfield      #92                 // Field gizmoButtonMap:Ljava/util/Map;
      48: aload_0
      49: aload_1
      50: putfield      #94                 // Field panel:Lmchorse/bbs_mod/ui/film/UIFilmPanel;
      53: aload_0
      54: iconst_0
      55: iconst_0
      56: iconst_0
      57: anewarray     #4                  // class mchorse/bbs_mod/ui/framework/elements/UIElement
      60: invokestatic  #100                // Method mchorse/bbs_mod/ui/utils/UI.row:(II[Lmchorse/bbs_mod/ui/framework/elements/UIElement;)Lmchorse/bbs_mod/ui/framework/elements/UIElement;
      63: putfield      #102                // Field icons:Lmchorse/bbs_mod/ui/framework/elements/UIElement;
      66: aload_0
      67: getfield      #102                // Field icons:Lmchorse/bbs_mod/ui/framework/elements/UIElement;
      70: invokevirtual #105                // Method mchorse/bbs_mod/ui/framework/elements/UIElement.row:()Lmchorse/bbs_mod/ui/utils/resizers/layout/RowResizer;
      73: invokevirtual #110                // Method mchorse/bbs_mod/ui/utils/resizers/layout/RowResizer.resize:()Lmchorse/bbs_mod/ui/utils/resizers/layout/RowResizer;
      76: pop
      77: aload_0
      78: getfield      #102                // Field icons:Lmchorse/bbs_mod/ui/framework/elements/UIElement;
      81: aload_0
      82: invokevirtual #114                // Method mchorse/bbs_mod/ui/framework/elements/UIElement.relative:(Lmchorse/bbs_mod/ui/framework/elements/UIElement;)Lmchorse/bbs_mod/ui/framework/elements/UIElement;
      85: ldc           #115                // float 0.5f
      87: invokevirtual #119                // Method mchorse/bbs_mod/ui/framework/elements/UIElement.x:(F)Lmchorse/bbs_mod/ui/framework/elements/UIElement;
      90: fconst_1
      91: invokevirtual #122                // Method mchorse/bbs_mod/ui/framework/elements/UIElement.y:(F)Lmchorse/bbs_mod/ui/framework/elements/UIElement;
      94: ldc           #115                // float 0.5f
      96: fconst_1
      97: invokevirtual #126                // Method mchorse/bbs_mod/ui/framework/elements/UIElement.anchor:(FF)Lmchorse/bbs_mod/ui/framework/elements/UIElement;
     100: pop
     101: aload_0
     102: aload_0
     103: getstatic     #132                // Field mchorse/bbs_mod/ui/utils/icons/Icons.ALL_DIRECTIONS:Lmchorse/bbs_mod/ui/utils/icons/Icon;
     106: getstatic     #136                // Field mchorse/bbs_mod/ui/utils/Gizmo$Mode.TRANSLATE:Lmchorse/bbs_mod/ui/utils/Gizmo$Mode;
     109: getstatic     #142                // Field mchorse/bbs_mod/ui/UIKeys.FILM_GIZMO_MOVE:Lmchorse/bbs_mod/l10n/keys/IKey;
     112: invokevirtual #146                // Method createGizmoButton:(Lmchorse/bbs_mod/ui/utils/icons/Icon;Lmchorse/bbs_mod/ui/utils/Gizmo$Mode;Lmchorse/bbs_mod/l10n/keys/IKey;)Lmchorse/bbs_mod/ui/framework/elements/buttons/UIIcon;
     115: putfield      #148                // Field gizmoMove:Lmchorse/bbs_mod/ui/framework/elements/buttons/UIIcon;
     118: aload_0
     119: aload_0
     120: getstatic     #151                // Field mchorse/bbs_mod/ui/utils/icons/Icons.SCALE:Lmchorse/bbs_mod/ui/utils/icons/Icon;
     123: getstatic     #153                // Field mchorse/bbs_mod/ui/utils/Gizmo$Mode.SCALE:Lmchorse/bbs_mod/ui/utils/Gizmo$Mode;
     126: getstatic     #156                // Field mchorse/bbs_mod/ui/UIKeys.FILM_GIZMO_SCALE:Lmchorse/bbs_mod/l10n/keys/IKey;
     129: invokevirtual #146                // Method createGizmoButton:(Lmchorse/bbs_mod/ui/utils/icons/Icon;Lmchorse/bbs_mod/ui/utils/Gizmo$Mode;Lmchorse/bbs_mod/l10n/keys/IKey;)Lmchorse/bbs_mod/ui/framework/elements/buttons/UIIcon;
     132: putfield      #158                // Field gizmoScale:Lmchorse/bbs_mod/ui/framework/elements/buttons/UIIcon;
     135: aload_0
     136: aload_0
     137: getstatic     #161                // Field mchorse/bbs_mod/ui/utils/icons/Icons.ARC:Lmchorse/bbs_mod/ui/utils/icons/Icon;
     140: getstatic     #164                // Field mchorse/bbs_mod/ui/utils/Gizmo$Mode.ROTATE:Lmchorse/bbs_mod/ui/utils/Gizmo$Mode;
     143: getstatic     #167                // Field mchorse/bbs_mod/ui/UIKeys.FILM_GIZMO_ROTATE:Lmchorse/bbs_mod/l10n/keys/IKey;
     146: invokevirtual #146                // Method createGizmoButton:(Lmchorse/bbs_mod/ui/utils/icons/Icon;Lmchorse/bbs_mod/ui/utils/Gizmo$Mode;Lmchorse/bbs_mod/l10n/keys/IKey;)Lmchorse/bbs_mod/ui/framework/elements/buttons/UIIcon;
     149: putfield      #169                // Field gizmoRotate:Lmchorse/bbs_mod/ui/framework/elements/buttons/UIIcon;
     152: aload_0
     153: aload_0
     154: getstatic     #172                // Field mchorse/bbs_mod/ui/utils/icons/Icons.SHAPES:Lmchorse/bbs_mod/ui/utils/icons/Icon;
     157: getstatic     #175                // Field mchorse/bbs_mod/ui/utils/Gizmo$Mode.COMBINED:Lmchorse/bbs_mod/ui/utils/Gizmo$Mode;
     160: getstatic     #178                // Field mchorse/bbs_mod/ui/UIKeys.FILM_GIZMO_COMBINED:Lmchorse/bbs_mod/l10n/keys/IKey;
     163: invokevirtual #146                // Method createGizmoButton:(Lmchorse/bbs_mod/ui/utils/icons/Icon;Lmchorse/bbs_mod/ui/utils/Gizmo$Mode;Lmchorse/bbs_mod/l10n/keys/IKey;)Lmchorse/bbs_mod/ui/framework/elements/buttons/UIIcon;
     166: putfield      #180                // Field gizmoCombined:Lmchorse/bbs_mod/ui/framework/elements/buttons/UIIcon;
     169: aload_0
     170: aload_0
     171: getstatic     #183                // Field mchorse/bbs_mod/ui/utils/icons/Icons.SPHERE:Lmchorse/bbs_mod/ui/utils/icons/Icon;
     174: getstatic     #186                // Field mchorse/bbs_mod/ui/utils/Gizmo$Mode.TOP:Lmchorse/bbs_mod/ui/utils/Gizmo$Mode;
     177: getstatic     #189                // Field mchorse/bbs_mod/ui/UIKeys.FILM_GIZMO_TOP:Lmchorse/bbs_mod/l10n/keys/IKey;
     180: invokevirtual #146                // Method createGizmoButton:(Lmchorse/bbs_mod/ui/utils/icons/Icon;Lmchorse/bbs_mod/ui/utils/Gizmo$Mode;Lmchorse/bbs_mod/l10n/keys/IKey;)Lmchorse/bbs_mod/ui/framework/elements/buttons/UIIcon;
     183: putfield      #191                // Field gizmoTop:Lmchorse/bbs_mod/ui/framework/elements/buttons/UIIcon;
     186: aload_0
     187: new           #193                // class mchorse/bbs_mod/ui/framework/elements/buttons/UIIcon
     190: dup
     191: getstatic     #196                // Field mchorse/bbs_mod/ui/utils/icons/Icons.MAXIMIZE:Lmchorse/bbs_mod/ui/utils/icons/Icon;
     194: aload_0
     195: invokedynamic #215,  0            // InvokeDynamic #0:accept:(Lmchorse/bbs_mod/ui/film/UIFilmPreview;)Ljava/util/function/Consumer;
     200: invokespecial #218                // Method mchorse/bbs_mod/ui/framework/elements/buttons/UIIcon."<init>":(Lmchorse/bbs_mod/ui/utils/icons/Icon;Ljava/util/function/Consumer;)V
     203: putfield      #220                // Field gizmoSize:Lmchorse/bbs_mod/ui/framework/elements/buttons/UIIcon;
     206: aload_0
     207: getfield      #220                // Field gizmoSize:Lmchorse/bbs_mod/ui/framework/elements/buttons/UIIcon;
     210: getstatic     #223                // Field mchorse/bbs_mod/ui/UIKeys.FILM_GIZMO_SIZE:Lmchorse/bbs_mod/l10n/keys/IKey;
     213: invokevirtual #227                // Method mchorse/bbs_mod/ui/framework/elements/buttons/UIIcon.tooltip:(Lmchorse/bbs_mod/l10n/keys/IKey;)Lmchorse/bbs_mod/ui/framework/elements/UIElement;
     216: pop
     217: aload_0
     218: new           #193                // class mchorse/bbs_mod/ui/framework/elements/buttons/UIIcon
     221: dup
     222: getstatic     #230                // Field mchorse/bbs_mod/ui/utils/icons/Icons.FORWARD:Lmchorse/bbs_mod/ui/utils/icons/Icon;
     225: aload_0
     226: invokedynamic #235,  0            // InvokeDynamic #1:accept:(Lmchorse/bbs_mod/ui/film/UIFilmPreview;)Ljava/util/function/Consumer;
     231: invokespecial #218                // Method mchorse/bbs_mod/ui/framework/elements/buttons/UIIcon."<init>":(Lmchorse/bbs_mod/ui/utils/icons/Icon;Ljava/util/function/Consumer;)V
     234: putfield      #237                // Field gizmoTranslateSpeed:Lmchorse/bbs_mod/ui/framework/elements/buttons/UIIcon;
     237: aload_0
     238: getfield      #237                // Field gizmoTranslateSpeed:Lmchorse/bbs_mod/ui/framework/elements/buttons/UIIcon;
     241: getstatic     #240                // Field mchorse/bbs_mod/ui/UIKeys.FILM_GIZMO_TRANSLATE_SPEED:Lmchorse/bbs_mod/l10n/keys/IKey;
     244: invokevirtual #227                // Method mchorse/bbs_mod/ui/framework/elements/buttons/UIIcon.tooltip:(Lmchorse/bbs_mod/l10n/keys/IKey;)Lmchorse/bbs_mod/ui/framework/elements/UIElement;
     247: pop
     248: aload_0
     249: getfield      #92                 // Field gizmoButtonMap:Ljava/util/Map;
     252: ldc           #242                // String move
     254: aload_0
     255: getfield      #148                // Field gizmoMove:Lmchorse/bbs_mod/ui/framework/elements/buttons/UIIcon;
     258: invokeinterface #248,  3          // InterfaceMethod java/util/Map.put:(Ljava/lang/Object;Ljava/lang/Object;)Ljava/lang/Object;
     263: pop
     264: aload_0
     265: getfield      #92                 // Field gizmoButtonMap:Ljava/util/Map;
     268: ldc           #250                // String scale
     270: aload_0
     271: getfield      #158                // Field gizmoScale:Lmchorse/bbs_mod/ui/framework/elements/buttons/UIIcon;
     274: invokeinterface #248,  3          // InterfaceMethod java/util/Map.put:(Ljava/lang/Object;Ljava/lang/Object;)Ljava/lang/Object;
     279: pop
     280: aload_0
     281: getfield      #92                 // Field gizmoButtonMap:Ljava/util/Map;
     284: ldc           #252                // String rotate
     286: aload_0
     287: getfield      #169                // Field gizmoRotate:Lmchorse/bbs_mod/ui/framework/elements/buttons/UIIcon;
     290: invokeinterface #248,  3          // InterfaceMethod java/util/Map.put:(Ljava/lang/Object;Ljava/lang/Object;)Ljava/lang/Object;
     295: pop
     296: aload_0
     297: getfield      #92                 // Field gizmoButtonMap:Ljava/util/Map;
     300: ldc           #254                // String combined
     302: aload_0
     303: getfield      #180                // Field gizmoCombined:Lmchorse/bbs_mod/ui/framework/elements/buttons/UIIcon;
     306: invokeinterface #248,  3          // InterfaceMethod java/util/Map.put:(Ljava/lang/Object;Ljava/lang/Object;)Ljava/lang/Object;
     311: pop
     312: aload_0
     313: getfield      #92                 // Field gizmoButtonMap:Ljava/util/Map;
     316: ldc_w         #256                // String top
     319: aload_0
     320: getfield      #191                // Field gizmoTop:Lmchorse/bbs_mod/ui/framework/elements/buttons/UIIcon;
     323: invokeinterface #248,  3          // InterfaceMethod java/util/Map.put:(Ljava/lang/Object;Ljava/lang/Object;)Ljava/lang/Object;
     328: pop
     329: aload_0
     330: getfield      #92                 // Field gizmoButtonMap:Ljava/util/Map;
     333: ldc_w         #258                // String size
     336: aload_0
     337: getfield      #220                // Field gizmoSize:Lmchorse/bbs_mod/ui/framework/elements/buttons/UIIcon;
     340: invokeinterface #248,  3          // InterfaceMethod java/util/Map.put:(Ljava/lang/Object;Ljava/lang/Object;)Ljava/lang/Object;
     345: pop
     346: aload_0
     347: getfield      #92                 // Field gizmoButtonMap:Ljava/util/Map;
     350: ldc_w         #260                // String translate_speed
     353: aload_0
     354: getfield      #237                // Field gizmoTranslateSpeed:Lmchorse/bbs_mod/ui/framework/elements/buttons/UIIcon;
     357: invokeinterface #248,  3          // InterfaceMethod java/util/Map.put:(Ljava/lang/Object;Ljava/lang/Object;)Ljava/lang/Object;
     362: pop
     363: aload_0
     364: iconst_0
     365: iconst_0
     366: anewarray     #4                  // class mchorse/bbs_mod/ui/framework/elements/UIElement
     369: invokestatic  #264                // Method mchorse/bbs_mod/ui/utils/UI.column:(I[Lmchorse/bbs_mod/ui/framework/elements/UIElement;)Lmchorse/bbs_mod/ui/framework/elements/UIElement;
     372: putfield      #266                // Field gizmos:Lmchorse/bbs_mod/ui/framework/elements/UIElement;
     375: aload_0
     376: getfield      #266                // Field gizmos:Lmchorse/bbs_mod/ui/framework/elements/UIElement;
     379: aload_0
     380: invokevirtual #114                // Method mchorse/bbs_mod/ui/framework/elements/UIElement.relative:(Lmchorse/bbs_mod/ui/framework/elements/UIElement;)Lmchorse/bbs_mod/ui/framework/elements/UIElement;
     383: iconst_4
     384: invokevirtual #269                // Method mchorse/bbs_mod/ui/framework/elements/UIElement.x:(I)Lmchorse/bbs_mod/ui/framework/elements/UIElement;
     387: iconst_4
     388: invokevirtual #271                // Method mchorse/bbs_mod/ui/framework/elements/UIElement.y:(I)Lmchorse/bbs_mod/ui/framework/elements/UIElement;
     391: bipush        20
     393: invokevirtual #274                // Method mchorse/bbs_mod/ui/framework/elements/UIElement.w:(I)Lmchorse/bbs_mod/ui/framework/elements/UIElement;
     396: pop
     397: aload_0
     398: invokevirtual #277                // Method rebuildGizmoToolbar:()V
     401: getstatic     #283                // Field mchorse/bbs_mod/BBSSettings.editorGizmoToolbar:Lmchorse/bbs_mod/settings/values/ui/ValueGizmoToolbar;
     404: aload_0
     405: invokedynamic #292,  0            // InvokeDynamic #2:accept:(Lmchorse/bbs_mod/ui/film/UIFilmPreview;)Lmchorse/bbs_mod/settings/values/IValueListener;
     410: invokevirtual #298                // Method mchorse/bbs_mod/settings/values/ui/ValueGizmoToolbar.postCallback:(Lmchorse/bbs_mod/settings/values/IValueListener;)Lmchorse/bbs_mod/settings/values/base/BaseValue;
     413: pop
     414: aload_0
     415: aload_0
     416: getfield      #266                // Field gizmos:Lmchorse/bbs_mod/ui/framework/elements/UIElement;
     419: invokevirtual #302                // Method add:(Lmchorse/bbs_mod/ui/framework/elements/IUIElement;)V
     422: aload_0
     423: invokevirtual #306                // Method keys:()Lmchorse/bbs_mod/ui/utils/keys/KeybindManager;
     426: getstatic     #312                // Field mchorse/bbs_mod/ui/Keys.TRANSFORMATIONS_COMBINED:Lmchorse/bbs_mod/ui/utils/keys/KeyCombo;
     429: invokedynamic #321,  0            // InvokeDynamic #3:run:()Ljava/lang/Runnable;
     434: invokevirtual #327                // Method mchorse/bbs_mod/ui/utils/keys/KeybindManager.register:(Lmchorse/bbs_mod/ui/utils/keys/KeyCombo;Ljava/lang/Runnable;)Lmchorse/bbs_mod/ui/utils/keys/Keybind;
     437: pop
     438: aload_0
     439: invokevirtual #306                // Method keys:()Lmchorse/bbs_mod/ui/utils/keys/KeybindManager;
     442: getstatic     #330                // Field mchorse/bbs_mod/ui/Keys.TRANSFORMATIONS_TOP:Lmchorse/bbs_mod/ui/utils/keys/KeyCombo;
     445: invokedynamic #335,  0            // InvokeDynamic #4:run:()Ljava/lang/Runnable;
     450: invokevirtual #327                // Method mchorse/bbs_mod/ui/utils/keys/KeybindManager.register:(Lmchorse/bbs_mod/ui/utils/keys/KeyCombo;Ljava/lang/Runnable;)Lmchorse/bbs_mod/ui/utils/keys/Keybind;
     453: pop
     454: aload_0
     455: new           #193                // class mchorse/bbs_mod/ui/framework/elements/buttons/UIIcon
     458: dup
     459: getstatic     #338                // Field mchorse/bbs_mod/ui/utils/icons/Icons.ONION_SKIN:Lmchorse/bbs_mod/ui/utils/icons/Icon;
     462: aload_0
     463: invokedynamic #343,  0            // InvokeDynamic #5:accept:(Lmchorse/bbs_mod/ui/film/UIFilmPreview;)Ljava/util/function/Consumer;
     468: invokespecial #218                // Method mchorse/bbs_mod/ui/framework/elements/buttons/UIIcon."<init>":(Lmchorse/bbs_mod/ui/utils/icons/Icon;Ljava/util/function/Consumer;)V
     471: putfield      #345                // Field onionSkin:Lmchorse/bbs_mod/ui/framework/elements/buttons/UIIcon;
     474: aload_0
     475: getfield      #345                // Field onionSkin:Lmchorse/bbs_mod/ui/framework/elements/buttons/UIIcon;
     478: getstatic     #348                // Field mchorse/bbs_mod/ui/UIKeys.FILM_CONTROLLER_ONION_SKIN_TITLE:Lmchorse/bbs_mod/l10n/keys/IKey;
     481: invokevirtual #227                // Method mchorse/bbs_mod/ui/framework/elements/buttons/UIIcon.tooltip:(Lmchorse/bbs_mod/l10n/keys/IKey;)Lmchorse/bbs_mod/ui/framework/elements/UIElement;
     484: pop
     485: aload_0
     486: new           #9                  // class mchorse/bbs_mod/ui/film/UIFilmPreview$1
     489: dup
     490: aload_0
     491: aload_0
     492: invokedynamic #360,  0            // InvokeDynamic #6:get:(Lmchorse/bbs_mod/ui/film/UIFilmPreview;)Ljava/util/function/Supplier;
     497: invokedynamic #367,  0            // InvokeDynamic #7:accept:()Ljava/util/function/Consumer;
     502: invokespecial #370                // Method mchorse/bbs_mod/ui/film/UIFilmPreview$1."<init>":(Lmchorse/bbs_mod/ui/film/UIFilmPreview;Ljava/util/function/Supplier;Ljava/util/function/Consumer;)V
     505: putfield      #372                // Field hideOverlays:Lmchorse/bbs_mod/ui/framework/elements/buttons/UIIcon;
     508: aload_0
     509: getfield      #372                // Field hideOverlays:Lmchorse/bbs_mod/ui/framework/elements/buttons/UIIcon;
     512: getstatic     #375                // Field mchorse/bbs_mod/ui/UIKeys.FILM_PREVIEW_TOGGLE_OVERLAYS:Lmchorse/bbs_mod/l10n/keys/IKey;
     515: invokevirtual #227                // Method mchorse/bbs_mod/ui/framework/elements/buttons/UIIcon.tooltip:(Lmchorse/bbs_mod/l10n/keys/IKey;)Lmchorse/bbs_mod/ui/framework/elements/UIElement;
     518: pop
     519: aload_0
     520: new           #7                  // class mchorse/bbs_mod/ui/film/UIFilmPreview$2
     523: dup
     524: aload_0
     525: getstatic     #378                // Field mchorse/bbs_mod/ui/utils/icons/Icons.GLOBE:Lmchorse/bbs_mod/ui/utils/icons/Icon;
     528: invokedynamic #383,  0            // InvokeDynamic #8:accept:()Ljava/util/function/Consumer;
     533: invokespecial #386                // Method mchorse/bbs_mod/ui/film/UIFilmPreview$2."<init>":(Lmchorse/bbs_mod/ui/film/UIFilmPreview;Lmchorse/bbs_mod/ui/utils/icons/Icon;Ljava/util/function/Consumer;)V
     536: putfield      #388                // Field toggleShaders:Lmchorse/bbs_mod/ui/framework/elements/buttons/UIIcon;
     539: aload_0
     540: getfield      #388                // Field toggleShaders:Lmchorse/bbs_mod/ui/framework/elements/buttons/UIIcon;
     543: getstatic     #391                // Field mchorse/bbs_mod/ui/UIKeys.FILM_PREVIEW_TOGGLE_SHADERS:Lmchorse/bbs_mod/l10n/keys/IKey;
     546: invokevirtual #227                // Method mchorse/bbs_mod/ui/framework/elements/buttons/UIIcon.tooltip:(Lmchorse/bbs_mod/l10n/keys/IKey;)Lmchorse/bbs_mod/ui/framework/elements/UIElement;
     549: pop
     550: aload_0
     551: getfield      #388                // Field toggleShaders:Lmchorse/bbs_mod/ui/framework/elements/buttons/UIIcon;
     554: invokestatic  #397                // Method mchorse/bbs_mod/client/BBSRendering.isIrisLoaded:()Z
     557: invokevirtual #401                // Method mchorse/bbs_mod/ui/framework/elements/buttons/UIIcon.setVisible:(Z)V
     560: aload_0
     561: new           #193                // class mchorse/bbs_mod/ui/framework/elements/buttons/UIIcon
     564: dup
     565: aload_0
     566: invokedynamic #406,  0            // InvokeDynamic #9:get:(Lmchorse/bbs_mod/ui/film/UIFilmPreview;)Ljava/util/function/Supplier;
     571: aload_0
     572: invokedynamic #411,  0            // InvokeDynamic #10:accept:(Lmchorse/bbs_mod/ui/film/UIFilmPreview;)Ljava/util/function/Consumer;
     577: invokespecial #414                // Method mchorse/bbs_mod/ui/framework/elements/buttons/UIIcon."<init>":(Ljava/util/function/Supplier;Ljava/util/function/Consumer;)V
     580: putfield      #416                // Field plause:Lmchorse/bbs_mod/ui/framework/elements/buttons/UIIcon;
     583: aload_0
     584: getfield      #416                // Field plause:Lmchorse/bbs_mod/ui/framework/elements/buttons/UIIcon;
     587: getstatic     #419                // Field mchorse/bbs_mod/ui/UIKeys.CAMERA_EDITOR_KEYS_EDITOR_PLAUSE:Lmchorse/bbs_mod/l10n/keys/IKey;
     590: invokevirtual #227                // Method mchorse/bbs_mod/ui/framework/elements/buttons/UIIcon.tooltip:(Lmchorse/bbs_mod/l10n/keys/IKey;)Lmchorse/bbs_mod/ui/framework/elements/UIElement;
     593: pop
     594: aload_0
     595: getfield      #416                // Field plause:Lmchorse/bbs_mod/ui/framework/elements/buttons/UIIcon;
     598: aload_0
     599: invokedynamic #426,  0            // InvokeDynamic #11:accept:(Lmchorse/bbs_mod/ui/film/UIFilmPreview;)Ljava/util/function/Consumer;
     604: invokevirtual #430                // Method mchorse/bbs_mod/ui/framework/elements/buttons/UIIcon.context:(Ljava/util/function/Consumer;)Lmchorse/bbs_mod/ui/framework/elements/UIElement;
     607: pop
     608: aload_0
     609: new           #193                // class mchorse/bbs_mod/ui/framework/elements/buttons/UIIcon
     612: dup
     613: getstatic     #433                // Field mchorse/bbs_mod/ui/utils/icons/Icons.MOVE_TO:Lmchorse/bbs_mod/ui/utils/icons/Icon;
     616: aload_0
     617: invokedynamic #438,  0            // InvokeDynamic #12:accept:(Lmchorse/bbs_mod/ui/film/UIFilmPreview;)Ljava/util/function/Consumer;
     622: invokespecial #218                // Method mchorse/bbs_mod/ui/framework/elements/buttons/UIIcon."<init>":(Lmchorse/bbs_mod/ui/utils/icons/Icon;Ljava/util/function/Consumer;)V
     625: putfield      #440                // Field teleport:Lmchorse/bbs_mod/ui/framework/elements/buttons/UIIcon;
     628: aload_0
     629: getfield      #440                // Field teleport:Lmchorse/bbs_mod/ui/framework/elements/buttons/UIIcon;
     632: getstatic     #443                // Field mchorse/bbs_mod/ui/UIKeys.FILM_TELEPORT_TITLE:Lmchorse/bbs_mod/l10n/keys/IKey;
     635: invokevirtual #227                // Method mchorse/bbs_mod/ui/framework/elements/buttons/UIIcon.tooltip:(Lmchorse/bbs_mod/l10n/keys/IKey;)Lmchorse/bbs_mod/ui/framework/elements/UIElement;
     638: pop
     639: aload_0
     640: getfield      #440                // Field teleport:Lmchorse/bbs_mod/ui/framework/elements/buttons/UIIcon;
     643: aload_0
     644: invokedynamic #448,  0            // InvokeDynamic #13:accept:(Lmchorse/bbs_mod/ui/film/UIFilmPreview;)Ljava/util/function/Consumer;
     649: invokevirtual #430                // Method mchorse/bbs_mod/ui/framework/elements/buttons/UIIcon.context:(Ljava/util/function/Consumer;)Lmchorse/bbs_mod/ui/framework/elements/UIElement;
     652: pop
     653: aload_0
     654: new           #193                // class mchorse/bbs_mod/ui/framework/elements/buttons/UIIcon
     657: dup
     658: getstatic     #451                // Field mchorse/bbs_mod/ui/utils/icons/Icons.PLANE:Lmchorse/bbs_mod/ui/utils/icons/Icon;
     661: aload_0
     662: invokedynamic #456,  0            // InvokeDynamic #14:accept:(Lmchorse/bbs_mod/ui/film/UIFilmPreview;)Ljava/util/function/Consumer;
     667: invokespecial #218                // Method mchorse/bbs_mod/ui/framework/elements/buttons/UIIcon."<init>":(Lmchorse/bbs_mod/ui/utils/icons/Icon;Ljava/util/function/Consumer;)V
     670: putfield      #458                // Field flight:Lmchorse/bbs_mod/ui/framework/elements/buttons/UIIcon;
     673: aload_0
     674: getfield      #458                // Field flight:Lmchorse/bbs_mod/ui/framework/elements/buttons/UIIcon;
     677: getstatic     #461                // Field mchorse/bbs_mod/ui/UIKeys.CAMERA_EDITOR_KEYS_MODES_FLIGHT:Lmchorse/bbs_mod/l10n/keys/IKey;
     680: invokevirtual #227                // Method mchorse/bbs_mod/ui/framework/elements/buttons/UIIcon.tooltip:(Lmchorse/bbs_mod/l10n/keys/IKey;)Lmchorse/bbs_mod/ui/framework/elements/UIElement;
     683: pop
     684: aload_0
     685: new           #193                // class mchorse/bbs_mod/ui/framework/elements/buttons/UIIcon
     688: dup
     689: getstatic     #464                // Field mchorse/bbs_mod/ui/utils/icons/Icons.POSE:Lmchorse/bbs_mod/ui/utils/icons/Icon;
     692: aload_0
     693: invokedynamic #469,  0            // InvokeDynamic #15:accept:(Lmchorse/bbs_mod/ui/film/UIFilmPreview;)Ljava/util/function/Consumer;
     698: invokespecial #218                // Method mchorse/bbs_mod/ui/framework/elements/buttons/UIIcon."<init>":(Lmchorse/bbs_mod/ui/utils/icons/Icon;Ljava/util/function/Consumer;)V
     701: putfield      #471                // Field control:Lmchorse/bbs_mod/ui/framework/elements/buttons/UIIcon;
     704: aload_0
     705: getfield      #471                // Field control:Lmchorse/bbs_mod/ui/framework/elements/buttons/UIIcon;
     708: getstatic     #474                // Field mchorse/bbs_mod/ui/UIKeys.FILM_CONTROLLER_KEYS_TOGGLE_CONTROL:Lmchorse/bbs_mod/l10n/keys/IKey;
     711: invokevirtual #227                // Method mchorse/bbs_mod/ui/framework/elements/buttons/UIIcon.tooltip:(Lmchorse/bbs_mod/l10n/keys/IKey;)Lmchorse/bbs_mod/ui/framework/elements/UIElement;
     714: pop
     715: aload_0
     716: new           #193                // class mchorse/bbs_mod/ui/framework/elements/buttons/UIIcon
     719: dup
     720: aload_0
     721: getfield      #94                 // Field panel:Lmchorse/bbs_mod/ui/film/UIFilmPanel;
     724: invokevirtual #480                // Method mchorse/bbs_mod/ui/film/UIFilmPanel.getController:()Lmchorse/bbs_mod/ui/film/controller/UIFilmController;
     727: dup
     728: invokestatic  #486                // Method java/util/Objects.requireNonNull:(Ljava/lang/Object;)Ljava/lang/Object;
     731: pop
     732: invokedynamic #495,  0            // InvokeDynamic #16:get:(Lmchorse/bbs_mod/ui/film/controller/UIFilmController;)Ljava/util/function/Supplier;
     737: aload_0
     738: invokedynamic #500,  0            // InvokeDynamic #17:accept:(Lmchorse/bbs_mod/ui/film/UIFilmPreview;)Ljava/util/function/Consumer;
     743: invokespecial #414                // Method mchorse/bbs_mod/ui/framework/elements/buttons/UIIcon."<init>":(Ljava/util/function/Supplier;Ljava/util/function/Consumer;)V
     746: putfield      #502                // Field perspective:Lmchorse/bbs_mod/ui/framework/elements/buttons/UIIcon;
     749: aload_0
     750: getfield      #502                // Field perspective:Lmchorse/bbs_mod/ui/framework/elements/buttons/UIIcon;
     753: getstatic     #505                // Field mchorse/bbs_mod/ui/UIKeys.FILM_CONTROLLER_KEYS_CHANGE_CAMERA_MODE:Lmchorse/bbs_mod/l10n/keys/IKey;
     756: invokevirtual #227                // Method mchorse/bbs_mod/ui/framework/elements/buttons/UIIcon.tooltip:(Lmchorse/bbs_mod/l10n/keys/IKey;)Lmchorse/bbs_mod/ui/framework/elements/UIElement;
     759: pop
     760: aload_0
     761: new           #193                // class mchorse/bbs_mod/ui/framework/elements/buttons/UIIcon
     764: dup
     765: getstatic     #183                // Field mchorse/bbs_mod/ui/utils/icons/Icons.SPHERE:Lmchorse/bbs_mod/ui/utils/icons/Icon;
     768: aload_0
     769: invokedynamic #510,  0            // InvokeDynamic #18:accept:(Lmchorse/bbs_mod/ui/film/UIFilmPreview;)Ljava/util/function/Consumer;
     774: invokespecial #218                // Method mchorse/bbs_mod/ui/framework/elements/buttons/UIIcon."<init>":(Lmchorse/bbs_mod/ui/utils/icons/Icon;Ljava/util/function/Consumer;)V
     777: putfield      #512                // Field recordReplay:Lmchorse/bbs_mod/ui/framework/elements/buttons/UIIcon;
     780: aload_0
     781: getfield      #512                // Field recordReplay:Lmchorse/bbs_mod/ui/framework/elements/buttons/UIIcon;
     784: getstatic     #515                // Field mchorse/bbs_mod/ui/UIKeys.FILM_REPLAY_RECORD:Lmchorse/bbs_mod/l10n/keys/IKey;
     787: invokevirtual #227                // Method mchorse/bbs_mod/ui/framework/elements/buttons/UIIcon.tooltip:(Lmchorse/bbs_mod/l10n/keys/IKey;)Lmchorse/bbs_mod/ui/framework/elements/UIElement;
     790: pop
     791: aload_0
     792: getfield      #512                // Field recordReplay:Lmchorse/bbs_mod/ui/framework/elements/buttons/UIIcon;
     795: aload_0
     796: invokedynamic #520,  0            // InvokeDynamic #19:accept:(Lmchorse/bbs_mod/ui/film/UIFilmPreview;)Ljava/util/function/Consumer;
     801: invokevirtual #430                // Method mchorse/bbs_mod/ui/framework/elements/buttons/UIIcon.context:(Ljava/util/function/Consumer;)Lmchorse/bbs_mod/ui/framework/elements/UIElement;
     804: pop
     805: aload_0
     806: new           #193                // class mchorse/bbs_mod/ui/framework/elements/buttons/UIIcon
     809: dup
     810: getstatic     #523                // Field mchorse/bbs_mod/ui/utils/icons/Icons.VIDEO_CAMERA:Lmchorse/bbs_mod/ui/utils/icons/Icon;
     813: aload_0
     814: invokedynamic #528,  0            // InvokeDynamic #20:accept:(Lmchorse/bbs_mod/ui/film/UIFilmPreview;)Ljava/util/function/Consumer;
     819: invokespecial #218                // Method mchorse/bbs_mod/ui/framework/elements/buttons/UIIcon."<init>":(Lmchorse/bbs_mod/ui/utils/icons/Icon;Ljava/util/function/Consumer;)V
     822: putfield      #530                // Field recordVideo:Lmchorse/bbs_mod/ui/framework/elements/buttons/UIIcon;
     825: aload_0
     826: getfield      #530                // Field recordVideo:Lmchorse/bbs_mod/ui/framework/elements/buttons/UIIcon;
     829: getstatic     #533                // Field mchorse/bbs_mod/ui/UIKeys.CAMERA_TOOLTIPS_RECORD:Lmchorse/bbs_mod/l10n/keys/IKey;
     832: invokevirtual #227                // Method mchorse/bbs_mod/ui/framework/elements/buttons/UIIcon.tooltip:(Lmchorse/bbs_mod/l10n/keys/IKey;)Lmchorse/bbs_mod/ui/framework/elements/UIElement;
     835: pop
     836: aload_0
     837: getfield      #530                // Field recordVideo:Lmchorse/bbs_mod/ui/framework/elements/buttons/UIIcon;
     840: aload_0
     841: invokedynamic #538,  0            // InvokeDynamic #21:accept:(Lmchorse/bbs_mod/ui/film/UIFilmPreview;)Ljava/util/function/Consumer;
     846: invokevirtual #430                // Method mchorse/bbs_mod/ui/framework/elements/buttons/UIIcon.context:(Ljava/util/function/Consumer;)Lmchorse/bbs_mod/ui/framework/elements/UIElement;
     849: pop
     850: aload_0
     851: new           #193                // class mchorse/bbs_mod/ui/framework/elements/buttons/UIIcon
     854: dup
     855: getstatic     #541                // Field mchorse/bbs_mod/ui/utils/icons/Icons.FILM:Lmchorse/bbs_mod/ui/utils/icons/Icon;
     858: aload_0
     859: invokedynamic #546,  0            // InvokeDynamic #22:accept:(Lmchorse/bbs_mod/ui/film/UIFilmPreview;)Ljava/util/function/Consumer;
     864: invokespecial #218                // Method mchorse/bbs_mod/ui/framework/elements/buttons/UIIcon."<init>":(Lmchorse/bbs_mod/ui/utils/icons/Icon;Ljava/util/function/Consumer;)V
     867: putfield      #548                // Field renderQueue:Lmchorse/bbs_mod/ui/framework/elements/buttons/UIIcon;
     870: aload_0
     871: getfield      #548                // Field renderQueue:Lmchorse/bbs_mod/ui/framework/elements/buttons/UIIcon;
     874: getstatic     #551                // Field mchorse/bbs_mod/ui/UIKeys.FILM_OPEN_RENDER_QUEUE:Lmchorse/bbs_mod/l10n/keys/IKey;
     877: invokevirtual #227                // Method mchorse/bbs_mod/ui/framework/elements/buttons/UIIcon.tooltip:(Lmchorse/bbs_mod/l10n/keys/IKey;)Lmchorse/bbs_mod/ui/framework/elements/UIElement;
     880: pop
     881: aload_0
     882: getfield      #90                 // Field viewportButtonMap:Ljava/util/Map;
     885: ldc_w         #553                // String hide_overlays
     888: aload_0
     889: getfield      #372                // Field hideOverlays:Lmchorse/bbs_mod/ui/framework/elements/buttons/UIIcon;
     892: invokeinterface #248,  3          // InterfaceMethod java/util/Map.put:(Ljava/lang/Object;Ljava/lang/Object;)Ljava/lang/Object;
     897: pop
     898: aload_0
     899: getfield      #90                 // Field viewportButtonMap:Ljava/util/Map;
     902: ldc_w         #555                // String onion_skin
     905: aload_0
     906: getfield      #345                // Field onionSkin:Lmchorse/bbs_mod/ui/framework/elements/buttons/UIIcon;
     909: invokeinterface #248,  3          // InterfaceMethod java/util/Map.put:(Ljava/lang/Object;Ljava/lang/Object;)Ljava/lang/Object;
     914: pop
     915: aload_0
     916: getfield      #90                 // Field viewportButtonMap:Ljava/util/Map;
     919: ldc_w         #557                // String toggle_shaders
     922: aload_0
     923: getfield      #388                // Field toggleShaders:Lmchorse/bbs_mod/ui/framework/elements/buttons/UIIcon;
     926: invokeinterface #248,  3          // InterfaceMethod java/util/Map.put:(Ljava/lang/Object;Ljava/lang/Object;)Ljava/lang/Object;
     931: pop
     932: aload_0
     933: getfield      #90                 // Field viewportButtonMap:Ljava/util/Map;
     936: ldc_w         #559                // String playback
     939: aload_0
     940: getfield      #416                // Field plause:Lmchorse/bbs_mod/ui/framework/elements/buttons/UIIcon;
     943: invokeinterface #248,  3          // InterfaceMethod java/util/Map.put:(Ljava/lang/Object;Ljava/lang/Object;)Ljava/lang/Object;
     948: pop
     949: aload_0
     950: getfield      #90                 // Field viewportButtonMap:Ljava/util/Map;
     953: ldc_w         #560                // String teleport
     956: aload_0
     957: getfield      #440                // Field teleport:Lmchorse/bbs_mod/ui/framework/elements/buttons/UIIcon;
     960: invokeinterface #248,  3          // InterfaceMethod java/util/Map.put:(Ljava/lang/Object;Ljava/lang/Object;)Ljava/lang/Object;
     965: pop
     966: aload_0
     967: getfield      #90                 // Field viewportButtonMap:Ljava/util/Map;
     970: ldc_w         #561                // String flight
     973: aload_0
     974: getfield      #458                // Field flight:Lmchorse/bbs_mod/ui/framework/elements/buttons/UIIcon;
     977: invokeinterface #248,  3          // InterfaceMethod java/util/Map.put:(Ljava/lang/Object;Ljava/lang/Object;)Ljava/lang/Object;
     982: pop
     983: aload_0
     984: getfield      #90                 // Field viewportButtonMap:Ljava/util/Map;
     987: ldc_w         #562                // String control
     990: aload_0
     991: getfield      #471                // Field control:Lmchorse/bbs_mod/ui/framework/elements/buttons/UIIcon;
     994: invokeinterface #248,  3          // InterfaceMethod java/util/Map.put:(Ljava/lang/Object;Ljava/lang/Object;)Ljava/lang/Object;
     999: pop
    1000: aload_0
    1001: getfield      #90                 // Field viewportButtonMap:Ljava/util/Map;
    1004: ldc_w         #563                // String perspective
    1007: aload_0
    1008: getfield      #502                // Field perspective:Lmchorse/bbs_mod/ui/framework/elements/buttons/UIIcon;
    1011: invokeinterface #248,  3          // InterfaceMethod java/util/Map.put:(Ljava/lang/Object;Ljava/lang/Object;)Ljava/lang/Object;
    1016: pop
    1017: aload_0
    1018: getfield      #90                 // Field viewportButtonMap:Ljava/util/Map;
    1021: ldc_w         #565                // String record_replay
    1024: aload_0
    1025: getfield      #512                // Field recordReplay:Lmchorse/bbs_mod/ui/framework/elements/buttons/UIIcon;
    1028: invokeinterface #248,  3          // InterfaceMethod java/util/Map.put:(Ljava/lang/Object;Ljava/lang/Object;)Ljava/lang/Object;
    1033: pop
    1034: aload_0
    1035: getfield      #90                 // Field viewportButtonMap:Ljava/util/Map;
    1038: ldc_w         #567                // String record_video
    1041: aload_0
    1042: getfield      #530                // Field recordVideo:Lmchorse/bbs_mod/ui/framework/elements/buttons/UIIcon;
    1045: invokeinterface #248,  3          // InterfaceMethod java/util/Map.put:(Ljava/lang/Object;Ljava/lang/Object;)Ljava/lang/Object;
    1050: pop
    1051: aload_0
    1052: getfield      #90                 // Field viewportButtonMap:Ljava/util/Map;
    1055: ldc_w         #569                // String render_queue
    1058: aload_0
    1059: getfield      #548                // Field renderQueue:Lmchorse/bbs_mod/ui/framework/elements/buttons/UIIcon;
    1062: invokeinterface #248,  3          // InterfaceMethod java/util/Map.put:(Ljava/lang/Object;Ljava/lang/Object;)Ljava/lang/Object;
    1067: pop
    1068: aload_0
    1069: invokevirtual #572                // Method rebuildViewportToolbar:()V
    1072: getstatic     #576                // Field mchorse/bbs_mod/BBSSettings.editorViewportToolbar:Lmchorse/bbs_mod/settings/values/ui/ValueViewportToolbar;
    1075: aload_0
    1076: invokedynamic #581,  0            // InvokeDynamic #23:accept:(Lmchorse/bbs_mod/ui/film/UIFilmPreview;)Lmchorse/bbs_mod/settings/values/IValueListener;
    1081: invokevirtual #584                // Method mchorse/bbs_mod/settings/values/ui/ValueViewportToolbar.postCallback:(Lmchorse/bbs_mod/settings/values/IValueListener;)Lmchorse/bbs_mod/settings/values/base/BaseValue;
    1084: pop
    1085: aload_0
    1086: aload_0
    1087: getfield      #102                // Field icons:Lmchorse/bbs_mod/ui/framework/elements/UIElement;
    1090: invokevirtual #302                // Method add:(Lmchorse/bbs_mod/ui/framework/elements/IUIElement;)V
    1093: aload_0
    1094: new           #586                // class mchorse/bbs_mod/ui/framework/elements/buttons/UIButton
    1097: dup
    1098: getstatic     #589                // Field mchorse/bbs_mod/ui/UIKeys.FILM_JOIN_WORLD:Lmchorse/bbs_mod/l10n/keys/IKey;
    1101: aload_0
    1102: invokedynamic #596,  0            // InvokeDynamic #24:accept:(Lmchorse/bbs_mod/ui/film/UIFilmPreview;)Ljava/util/function/Consumer;
    1107: invokespecial #599                // Method mchorse/bbs_mod/ui/framework/elements/buttons/UIButton."<init>":(Lmchorse/bbs_mod/l10n/keys/IKey;Ljava/util/function/Consumer;)V
    1110: putfield      #601                // Field joinWorld:Lmchorse/bbs_mod/ui/framework/elements/buttons/UIButton;
    1113: aload_0
    1114: getfield      #601                // Field joinWorld:Lmchorse/bbs_mod/ui/framework/elements/buttons/UIButton;
    1117: aload_0
    1118: invokevirtual #602                // Method mchorse/bbs_mod/ui/framework/elements/buttons/UIButton.relative:(Lmchorse/bbs_mod/ui/framework/elements/UIElement;)Lmchorse/bbs_mod/ui/framework/elements/UIElement;
    1121: fconst_1
    1122: bipush        -12
    1124: invokevirtual #605                // Method mchorse/bbs_mod/ui/framework/elements/UIElement.x:(FI)Lmchorse/bbs_mod/ui/framework/elements/UIElement;
    1127: fconst_1
    1128: bipush        -28
    1130: invokevirtual #607                // Method mchorse/bbs_mod/ui/framework/elements/UIElement.y:(FI)Lmchorse/bbs_mod/ui/framework/elements/UIElement;
    1133: fconst_1
    1134: fconst_1
    1135: invokevirtual #126                // Method mchorse/bbs_mod/ui/framework/elements/UIElement.anchor:(FF)Lmchorse/bbs_mod/ui/framework/elements/UIElement;
    1138: bipush        120
    1140: invokevirtual #274                // Method mchorse/bbs_mod/ui/framework/elements/UIElement.w:(I)Lmchorse/bbs_mod/ui/framework/elements/UIElement;
    1143: bipush        20
    1145: invokevirtual #610                // Method mchorse/bbs_mod/ui/framework/elements/UIElement.h:(I)Lmchorse/bbs_mod/ui/framework/elements/UIElement;
    1148: pop
    1149: aload_0
    1150: getfield      #601                // Field joinWorld:Lmchorse/bbs_mod/ui/framework/elements/buttons/UIButton;
    1153: iconst_0
    1154: invokevirtual #611                // Method mchorse/bbs_mod/ui/framework/elements/buttons/UIButton.setVisible:(Z)V
    1157: aload_0
    1158: aload_0
    1159: getfield      #601                // Field joinWorld:Lmchorse/bbs_mod/ui/framework/elements/buttons/UIButton;
    1162: invokevirtual #302                // Method add:(Lmchorse/bbs_mod/ui/framework/elements/IUIElement;)V
    1165: getstatic     #613                // Field extensions:Ljava/util/List;
    1168: invokeinterface #619,  1          // InterfaceMethod java/util/List.iterator:()Ljava/util/Iterator;
    1173: astore_2
    1174: aload_2
    1175: invokeinterface #624,  1          // InterfaceMethod java/util/Iterator.hasNext:()Z
    1180: ifeq          1203
    1183: aload_2
    1184: invokeinterface #627,  1          // InterfaceMethod java/util/Iterator.next:()Ljava/lang/Object;
    1189: checkcast     #629                // class java/util/function/Consumer
    1192: astore_3
    1193: aload_3
    1194: aload_0
    1195: invokeinterface #631,  2          // InterfaceMethod java/util/function/Consumer.accept:(Ljava/lang/Object;)V
    1200: goto          1174
    1203: return

  public void rebuildGizmoToolbar();
    Code:
       0: aload_0
       1: getfield      #266                // Field gizmos:Lmchorse/bbs_mod/ui/framework/elements/UIElement;
       4: invokevirtual #639                // Method mchorse/bbs_mod/ui/framework/elements/UIElement.removeAll:()V
       7: getstatic     #283                // Field mchorse/bbs_mod/BBSSettings.editorGizmoToolbar:Lmchorse/bbs_mod/settings/values/ui/ValueGizmoToolbar;
      10: invokevirtual #643                // Method mchorse/bbs_mod/settings/values/ui/ValueGizmoToolbar.getVisibleOrder:()Ljava/util/List;
      13: invokeinterface #619,  1          // InterfaceMethod java/util/List.iterator:()Ljava/util/Iterator;
      18: astore_1
      19: aload_1
      20: invokeinterface #624,  1          // InterfaceMethod java/util/Iterator.hasNext:()Z
      25: ifeq          75
      28: aload_1
      29: invokeinterface #627,  1          // InterfaceMethod java/util/Iterator.next:()Ljava/lang/Object;
      34: checkcast     #645                // class java/lang/String
      37: astore_2
      38: aload_0
      39: getfield      #92                 // Field gizmoButtonMap:Ljava/util/Map;
      42: aload_2
      43: invokeinterface #647,  2          // InterfaceMethod java/util/Map.get:(Ljava/lang/Object;)Ljava/lang/Object;
      48: checkcast     #193                // class mchorse/bbs_mod/ui/framework/elements/buttons/UIIcon
      51: astore_3
      52: aload_3
      53: ifnonnull     59
      56: goto          19
      59: aload_3
      60: iconst_1
      61: invokevirtual #401                // Method mchorse/bbs_mod/ui/framework/elements/buttons/UIIcon.setVisible:(Z)V
      64: aload_0
      65: getfield      #266                // Field gizmos:Lmchorse/bbs_mod/ui/framework/elements/UIElement;
      68: aload_3
      69: invokevirtual #648                // Method mchorse/bbs_mod/ui/framework/elements/UIElement.add:(Lmchorse/bbs_mod/ui/framework/elements/IUIElement;)V
      72: goto          19
      75: aload_0
      76: getfield      #266                // Field gizmos:Lmchorse/bbs_mod/ui/framework/elements/UIElement;
      79: invokevirtual #651                // Method mchorse/bbs_mod/ui/framework/elements/UIElement.getChildren:()Ljava/util/List;
      82: invokeinterface #654,  1          // InterfaceMethod java/util/List.size:()I
      87: istore_1
      88: aload_0
      89: getfield      #266                // Field gizmos:Lmchorse/bbs_mod/ui/framework/elements/UIElement;
      92: bipush        20
      94: iload_1
      95: bipush        20
      97: imul
      98: invokestatic  #660                // Method java/lang/Math.max:(II)I
     101: invokevirtual #610                // Method mchorse/bbs_mod/ui/framework/elements/UIElement.h:(I)Lmchorse/bbs_mod/ui/framework/elements/UIElement;
     104: pop
     105: aload_0
     106: getfield      #266                // Field gizmos:Lmchorse/bbs_mod/ui/framework/elements/UIElement;
     109: invokevirtual #662                // Method mchorse/bbs_mod/ui/framework/elements/UIElement.resize:()V
     112: aload_0
     113: getfield      #664                // Field viewportButtonsHidden:Z
     116: ifeq          127
     119: aload_0
     120: getfield      #266                // Field gizmos:Lmchorse/bbs_mod/ui/framework/elements/UIElement;
     123: iconst_0
     124: invokevirtual #665                // Method mchorse/bbs_mod/ui/framework/elements/UIElement.setVisible:(Z)V
     127: return

  public void rebuildViewportToolbar();
    Code:
       0: aload_0
       1: getfield      #102                // Field icons:Lmchorse/bbs_mod/ui/framework/elements/UIElement;
       4: invokevirtual #639                // Method mchorse/bbs_mod/ui/framework/elements/UIElement.removeAll:()V
       7: aload_0
       8: getfield      #85                 // Field viewportButtons:Ljava/util/List;
      11: invokeinterface #673,  1          // InterfaceMethod java/util/List.clear:()V
      16: getstatic     #576                // Field mchorse/bbs_mod/BBSSettings.editorViewportToolbar:Lmchorse/bbs_mod/settings/values/ui/ValueViewportToolbar;
      19: invokevirtual #674                // Method mchorse/bbs_mod/settings/values/ui/ValueViewportToolbar.getVisibleOrder:()Ljava/util/List;
      22: invokeinterface #619,  1          // InterfaceMethod java/util/List.iterator:()Ljava/util/Iterator;
      27: astore_1
      28: aload_1
      29: invokeinterface #624,  1          // InterfaceMethod java/util/Iterator.hasNext:()Z
      34: ifeq          125
      37: aload_1
      38: invokeinterface #627,  1          // InterfaceMethod java/util/Iterator.next:()Ljava/lang/Object;
      43: checkcast     #645                // class java/lang/String
      46: astore_2
      47: aload_0
      48: getfield      #90                 // Field viewportButtonMap:Ljava/util/Map;
      51: aload_2
      52: invokeinterface #647,  2          // InterfaceMethod java/util/Map.get:(Ljava/lang/Object;)Ljava/lang/Object;
      57: checkcast     #193                // class mchorse/bbs_mod/ui/framework/elements/buttons/UIIcon
      60: astore_3
      61: aload_3
      62: ifnonnull     68
      65: goto          28
      68: ldc_w         #557                // String toggle_shaders
      71: aload_2
      72: invokevirtual #678                // Method java/lang/String.equals:(Ljava/lang/Object;)Z
      75: ifeq          88
      78: aload_3
      79: invokestatic  #397                // Method mchorse/bbs_mod/client/BBSRendering.isIrisLoaded:()Z
      82: invokevirtual #401                // Method mchorse/bbs_mod/ui/framework/elements/buttons/UIIcon.setVisible:(Z)V
      85: goto          93
      88: aload_3
      89: iconst_1
      90: invokevirtual #401                // Method mchorse/bbs_mod/ui/framework/elements/buttons/UIIcon.setVisible:(Z)V
      93: aload_0
      94: getfield      #102                // Field icons:Lmchorse/bbs_mod/ui/framework/elements/UIElement;
      97: aload_3
      98: invokevirtual #648                // Method mchorse/bbs_mod/ui/framework/elements/UIElement.add:(Lmchorse/bbs_mod/ui/framework/elements/IUIElement;)V
     101: ldc_w         #553                // String hide_overlays
     104: aload_2
     105: invokevirtual #678                // Method java/lang/String.equals:(Ljava/lang/Object;)Z
     108: ifne          122
     111: aload_0
     112: getfield      #85                 // Field viewportButtons:Ljava/util/List;
     115: aload_3
     116: invokeinterface #680,  2          // InterfaceMethod java/util/List.add:(Ljava/lang/Object;)Z
     121: pop
     122: goto          28
     125: aload_0
     126: getfield      #102                // Field icons:Lmchorse/bbs_mod/ui/framework/elements/UIElement;
     129: invokevirtual #105                // Method mchorse/bbs_mod/ui/framework/elements/UIElement.row:()Lmchorse/bbs_mod/ui/utils/resizers/layout/RowResizer;
     132: invokevirtual #110                // Method mchorse/bbs_mod/ui/utils/resizers/layout/RowResizer.resize:()Lmchorse/bbs_mod/ui/utils/resizers/layout/RowResizer;
     135: pop
     136: aload_0
     137: getfield      #664                // Field viewportButtonsHidden:Z
     140: ifeq          180
     143: aload_0
     144: getfield      #85                 // Field viewportButtons:Ljava/util/List;
     147: invokeinterface #619,  1          // InterfaceMethod java/util/List.iterator:()Ljava/util/Iterator;
     152: astore_1
     153: aload_1
     154: invokeinterface #624,  1          // InterfaceMethod java/util/Iterator.hasNext:()Z
     159: ifeq          180
     162: aload_1
     163: invokeinterface #627,  1          // InterfaceMethod java/util/Iterator.next:()Ljava/lang/Object;
     168: checkcast     #193                // class mchorse/bbs_mod/ui/framework/elements/buttons/UIIcon
     171: astore_2
     172: aload_2
     173: iconst_0
     174: invokevirtual #401                // Method mchorse/bbs_mod/ui/framework/elements/buttons/UIIcon.setVisible:(Z)V
     177: goto          153
     180: return

  private mchorse.bbs_mod.ui.framework.elements.buttons.UIIcon createGizmoButton(mchorse.bbs_mod.ui.utils.icons.Icon, mchorse.bbs_mod.ui.utils.Gizmo$Mode, mchorse.bbs_mod.l10n.keys.IKey);
    Code:
       0: new           #193                // class mchorse/bbs_mod/ui/framework/elements/buttons/UIIcon
       3: dup
       4: aload_1
       5: aload_2
       6: invokedynamic #690,  0            // InvokeDynamic #25:accept:(Lmchorse/bbs_mod/ui/utils/Gizmo$Mode;)Ljava/util/function/Consumer;
      11: invokespecial #218                // Method mchorse/bbs_mod/ui/framework/elements/buttons/UIIcon."<init>":(Lmchorse/bbs_mod/ui/utils/icons/Icon;Ljava/util/function/Consumer;)V
      14: astore        4
      16: aload         4
      18: aload_3
      19: invokevirtual #227                // Method mchorse/bbs_mod/ui/framework/elements/buttons/UIIcon.tooltip:(Lmchorse/bbs_mod/l10n/keys/IKey;)Lmchorse/bbs_mod/ui/framework/elements/UIElement;
      22: pop
      23: aload         4
      25: ldc_w         #691                // int -2009897217
      28: invokevirtual #695                // Method mchorse/bbs_mod/ui/framework/elements/buttons/UIIcon.activeBackground:(I)Lmchorse/bbs_mod/ui/framework/elements/buttons/UIIcon;
      31: pop
      32: aload         4
      34: areturn

  public void openReplays();
    Code:
       0: aload_0
       1: getfield      #94                 // Field panel:Lmchorse/bbs_mod/ui/film/UIFilmPanel;
       4: invokevirtual #699                // Method mchorse/bbs_mod/ui/film/UIFilmPanel.focusAnchoredReplaysPanel:()V
       7: return

  public void openOnionSkin();
    Code:
       0: aload_0
       1: invokevirtual #704                // Method getContext:()Lmchorse/bbs_mod/ui/framework/UIContext;
       4: new           #706                // class mchorse/bbs_mod/ui/film/controller/UIOnionSkinContextMenu
       7: dup
       8: aload_0
       9: getfield      #94                 // Field panel:Lmchorse/bbs_mod/ui/film/UIFilmPanel;
      12: aload_0
      13: getfield      #94                 // Field panel:Lmchorse/bbs_mod/ui/film/UIFilmPanel;
      16: invokevirtual #480                // Method mchorse/bbs_mod/ui/film/UIFilmPanel.getController:()Lmchorse/bbs_mod/ui/film/controller/UIFilmController;
      19: invokevirtual #710                // Method mchorse/bbs_mod/ui/film/controller/UIFilmController.getOnionSkin:()Lmchorse/bbs_mod/settings/values/ui/ValueOnionSkin;
      22: invokespecial #713                // Method mchorse/bbs_mod/ui/film/controller/UIOnionSkinContextMenu."<init>":(Lmchorse/bbs_mod/ui/film/UIFilmPanel;Lmchorse/bbs_mod/settings/values/ui/ValueOnionSkin;)V
      25: invokevirtual #719                // Method mchorse/bbs_mod/ui/framework/UIContext.replaceContextMenu:(Lmchorse/bbs_mod/ui/framework/elements/context/UIContextMenu;)V
      28: return

  public boolean isViewportButtonsHidden();
    Code:
       0: aload_0
       1: getfield      #664                // Field viewportButtonsHidden:Z
       4: ireturn

  public void setViewportButtonsHidden(boolean);
    Code:
       0: aload_0
       1: getfield      #664                // Field viewportButtonsHidden:Z
       4: iload_1
       5: if_icmpne     9
       8: return
       9: aload_0
      10: iload_1
      11: putfield      #664                // Field viewportButtonsHidden:Z
      14: aload_0
      15: getfield      #85                 // Field viewportButtons:Ljava/util/List;
      18: invokeinterface #619,  1          // InterfaceMethod java/util/List.iterator:()Ljava/util/Iterator;
      23: astore_2
      24: aload_2
      25: invokeinterface #624,  1          // InterfaceMethod java/util/Iterator.hasNext:()Z
      30: ifeq          59
      33: aload_2
      34: invokeinterface #627,  1          // InterfaceMethod java/util/Iterator.next:()Ljava/lang/Object;
      39: checkcast     #193                // class mchorse/bbs_mod/ui/framework/elements/buttons/UIIcon
      42: astore_3
      43: aload_3
      44: iload_1
      45: ifne          52
      48: iconst_1
      49: goto          53
      52: iconst_0
      53: invokevirtual #401                // Method mchorse/bbs_mod/ui/framework/elements/buttons/UIIcon.setVisible:(Z)V
      56: goto          24
      59: aload_0
      60: getfield      #266                // Field gizmos:Lmchorse/bbs_mod/ui/framework/elements/UIElement;
      63: iload_1
      64: ifne          71
      67: iconst_1
      68: goto          72
      71: iconst_0
      72: invokevirtual #665                // Method mchorse/bbs_mod/ui/framework/elements/UIElement.setVisible:(Z)V
      75: return

  private void toggleViewportButtonsHidden();
    Code:
       0: aload_0
       1: aload_0
       2: getfield      #664                // Field viewportButtonsHidden:Z
       5: ifne          12
       8: iconst_1
       9: goto          13
      12: iconst_0
      13: invokevirtual #725                // Method setViewportButtonsHidden:(Z)V
      16: return

  private void renderAudio();
    Code:
       0: aload_0
       1: getfield      #94                 // Field panel:Lmchorse/bbs_mod/ui/film/UIFilmPanel;
       4: invokevirtual #730                // Method mchorse/bbs_mod/ui/film/UIFilmPanel.getData:()Lmchorse/bbs_mod/settings/values/core/ValueGroup;
       7: ifnonnull     11
      10: return
      11: aload_0
      12: getfield      #94                 // Field panel:Lmchorse/bbs_mod/ui/film/UIFilmPanel;
      15: invokevirtual #730                // Method mchorse/bbs_mod/ui/film/UIFilmPanel.getData:()Lmchorse/bbs_mod/settings/values/core/ValueGroup;
      18: checkcast     #732                // class mchorse/bbs_mod/film/Film
      21: getfield      #736                // Field mchorse/bbs_mod/film/Film.camera:Lmchorse/bbs_mod/utils/clips/Clips;
      24: astore_1
      25: aload_1
      26: ldc_w         #738                // class mchorse/bbs_mod/camera/clips/misc/AudioClip
      29: invokevirtual #744                // Method mchorse/bbs_mod/utils/clips/Clips.getClips:(Ljava/lang/Class;)Ljava/util/List;
      32: astore_2
      33: invokestatic  #750                // Method mchorse/bbs_mod/utils/StringUtils.createTimestampFilename:()Ljava/lang/String;
      36: invokedynamic #762,  0            // InvokeDynamic #26:makeConcatWithConstants:(Ljava/lang/String;)Ljava/lang/String;
      41: astore_3
      42: invokestatic  #766                // Method mchorse/bbs_mod/client/BBSRendering.getVideoFolder:()Ljava/io/File;
      45: astore        4
      47: aload_0
      48: invokevirtual #704                // Method getContext:()Lmchorse/bbs_mod/ui/framework/UIContext;
      51: astore        5
      53: getstatic     #770                // Field mchorse/bbs_mod/BBSSettings.editorLoop:Lmchorse/bbs_mod/settings/values/numeric/ValueBoolean;
      56: invokevirtual #774                // Method mchorse/bbs_mod/settings/values/numeric/ValueBoolean.get:()Ljava/lang/Object;
      59: checkcast     #776                // class java/lang/Boolean
      62: invokevirtual #779                // Method java/lang/Boolean.booleanValue:()Z
      65: ifeq          78
      68: aload_0
      69: getfield      #94                 // Field panel:Lmchorse/bbs_mod/ui/film/UIFilmPanel;
      72: invokevirtual #783                // Method mchorse/bbs_mod/ui/film/UIFilmPanel.getLoopingRange:()Lorg/joml/Vector2i;
      75: goto          85
      78: new           #787                // class org/joml/Vector2i
      81: dup
      82: invokespecial #788                // Method org/joml/Vector2i."<init>":()V
      85: astore        6
      87: new           #785                // class java/io/File
      90: dup
      91: aload         4
      93: aload_3
      94: invokespecial #791                // Method java/io/File."<init>":(Ljava/io/File;Ljava/lang/String;)V
      97: aload_2
      98: aload_1
      99: invokevirtual #794                // Method mchorse/bbs_mod/utils/clips/Clips.calculateDuration:()I
     102: ldc_w         #795                // int 48000
     105: aload         6
     107: getfield      #797                // Field org/joml/Vector2i.x:I
     110: i2f
     111: invokestatic  #803                // Method mchorse/bbs_mod/camera/utils/TimeUtils.toSeconds:(F)F
     114: aload         6
     116: getfield      #805                // Field org/joml/Vector2i.y:I
     119: i2f
     120: invokestatic  #803                // Method mchorse/bbs_mod/camera/utils/TimeUtils.toSeconds:(F)F
     123: invokestatic  #810                // Method mchorse/bbs_mod/audio/AudioRenderer.renderAudio:(Ljava/io/File;Ljava/util/List;IIFF)Z
     126: ifeq          153
     129: aload         5
     131: new           #812                // class mchorse/bbs_mod/ui/framework/elements/overlay/UIMessageFolderOverlayPanel
     134: dup
     135: getstatic     #815                // Field mchorse/bbs_mod/ui/UIKeys.GENERAL_SUCCESS:Lmchorse/bbs_mod/l10n/keys/IKey;
     138: getstatic     #818                // Field mchorse/bbs_mod/ui/UIKeys.FILM_RENDER_AUDIO_SUCCESS:Lmchorse/bbs_mod/l10n/keys/IKey;
     141: aload         4
     143: invokespecial #821                // Method mchorse/bbs_mod/ui/framework/elements/overlay/UIMessageFolderOverlayPanel."<init>":(Lmchorse/bbs_mod/l10n/keys/IKey;Lmchorse/bbs_mod/l10n/keys/IKey;Ljava/io/File;)V
     146: invokestatic  #827                // Method mchorse/bbs_mod/ui/framework/elements/overlay/UIOverlay.addOverlay:(Lmchorse/bbs_mod/ui/framework/UIContext;Lmchorse/bbs_mod/ui/framework/elements/overlay/UIOverlayPanel;)Lmchorse/bbs_mod/ui/framework/elements/overlay/UIOverlay;
     149: pop
     150: goto          172
     153: aload         5
     155: new           #829                // class mchorse/bbs_mod/ui/framework/elements/overlay/UIMessageOverlayPanel
     158: dup
     159: getstatic     #832                // Field mchorse/bbs_mod/ui/UIKeys.GENERAL_ERROR:Lmchorse/bbs_mod/l10n/keys/IKey;
     162: getstatic     #835                // Field mchorse/bbs_mod/ui/UIKeys.FILM_RENDER_AUDIO_ERROR:Lmchorse/bbs_mod/l10n/keys/IKey;
     165: invokespecial #838                // Method mchorse/bbs_mod/ui/framework/elements/overlay/UIMessageOverlayPanel."<init>":(Lmchorse/bbs_mod/l10n/keys/IKey;Lmchorse/bbs_mod/l10n/keys/IKey;)V
     168: invokestatic  #827                // Method mchorse/bbs_mod/ui/framework/elements/overlay/UIOverlay.addOverlay:(Lmchorse/bbs_mod/ui/framework/UIContext;Lmchorse/bbs_mod/ui/framework/elements/overlay/UIOverlayPanel;)Lmchorse/bbs_mod/ui/framework/elements/overlay/UIOverlay;
     171: pop
     172: return

  public mchorse.bbs_mod.ui.utils.Area getViewport();
    Code:
       0: getstatic     #850                // Field mchorse/bbs_mod/BBSSettings.videoSettings:Lmchorse/bbs_mod/settings/values/ui/ValueVideoSettings;
       3: getfield      #856                // Field mchorse/bbs_mod/settings/values/ui/ValueVideoSettings.width:Lmchorse/bbs_mod/settings/values/numeric/ValueInt;
       6: invokevirtual #859                // Method mchorse/bbs_mod/settings/values/numeric/ValueInt.get:()Ljava/lang/Object;
       9: checkcast     #861                // class java/lang/Integer
      12: invokevirtual #864                // Method java/lang/Integer.intValue:()I
      15: istore_1
      16: getstatic     #850                // Field mchorse/bbs_mod/BBSSettings.videoSettings:Lmchorse/bbs_mod/settings/values/ui/ValueVideoSettings;
      19: getfield      #867                // Field mchorse/bbs_mod/settings/values/ui/ValueVideoSettings.height:Lmchorse/bbs_mod/settings/values/numeric/ValueInt;
      22: invokevirtual #859                // Method mchorse/bbs_mod/settings/values/numeric/ValueInt.get:()Ljava/lang/Object;
      25: checkcast     #861                // class java/lang/Integer
      28: invokevirtual #864                // Method java/lang/Integer.intValue:()I
      31: istore_2
      32: aload_0
      33: getfield      #871                // Field area:Lmchorse/bbs_mod/ui/utils/Area;
      36: getfield      #875                // Field mchorse/bbs_mod/ui/utils/Area.w:I
      39: istore_3
      40: aload_0
      41: getfield      #871                // Field area:Lmchorse/bbs_mod/ui/utils/Area;
      44: getfield      #877                // Field mchorse/bbs_mod/ui/utils/Area.h:I
      47: istore        4
      49: iload_1
      50: i2f
      51: iload_2
      52: i2f
      53: fdiv
      54: iload_3
      55: iload         4
      57: invokestatic  #882                // Method mchorse/bbs_mod/utils/joml/Vectors.resize:(FII)Lorg/joml/Vector2i;
      60: astore        5
      62: new           #873                // class mchorse/bbs_mod/ui/utils/Area
      65: dup
      66: invokespecial #883                // Method mchorse/bbs_mod/ui/utils/Area."<init>":()V
      69: astore        6
      71: aload         6
      73: aload         5
      75: getfield      #797                // Field org/joml/Vector2i.x:I
      78: aload         5
      80: getfield      #805                // Field org/joml/Vector2i.y:I
      83: invokevirtual #887                // Method mchorse/bbs_mod/ui/utils/Area.setSize:(II)V
      86: aload         6
      88: aload_0
      89: getfield      #871                // Field area:Lmchorse/bbs_mod/ui/utils/Area;
      92: invokevirtual #890                // Method mchorse/bbs_mod/ui/utils/Area.mx:()I
      95: aload         6
      97: getfield      #875                // Field mchorse/bbs_mod/ui/utils/Area.w:I
     100: iconst_2
     101: idiv
     102: isub
     103: aload_0
     104: getfield      #871                // Field area:Lmchorse/bbs_mod/ui/utils/Area;
     107: invokevirtual #893                // Method mchorse/bbs_mod/ui/utils/Area.my:()I
     110: aload         6
     112: getfield      #877                // Field mchorse/bbs_mod/ui/utils/Area.h:I
     115: iconst_2
     116: idiv
     117: isub
     118: invokevirtual #896                // Method mchorse/bbs_mod/ui/utils/Area.setPos:(II)V
     121: aload         6
     123: areturn

  protected boolean subMouseClicked(mchorse.bbs_mod.ui.framework.UIContext);
    Code:
       0: aload_0
       1: invokevirtual #902                // Method getViewport:()Lmchorse/bbs_mod/ui/utils/Area;
       4: astore_2
       5: aload_2
       6: aload_1
       7: invokevirtual #905                // Method mchorse/bbs_mod/ui/utils/Area.isInside:(Lmchorse/bbs_mod/ui/framework/UIContext;)Z
      10: ifeq          243
      13: aload_0
      14: getfield      #94                 // Field panel:Lmchorse/bbs_mod/ui/film/UIFilmPanel;
      17: invokevirtual #908                // Method mchorse/bbs_mod/ui/film/UIFilmPanel.isFlying:()Z
      20: ifeq          152
      23: getstatic     #911                // Field mchorse/bbs_mod/BBSSettings.editorFlightFreeLook:Lmchorse/bbs_mod/settings/values/numeric/ValueBoolean;
      26: invokevirtual #774                // Method mchorse/bbs_mod/settings/values/numeric/ValueBoolean.get:()Ljava/lang/Object;
      29: checkcast     #776                // class java/lang/Boolean
      32: invokevirtual #779                // Method java/lang/Boolean.booleanValue:()Z
      35: ifne          150
      38: aload_0
      39: getfield      #94                 // Field panel:Lmchorse/bbs_mod/ui/film/UIFilmPanel;
      42: invokevirtual #480                // Method mchorse/bbs_mod/ui/film/UIFilmPanel.getController:()Lmchorse/bbs_mod/ui/film/controller/UIFilmController;
      45: invokevirtual #914                // Method mchorse/bbs_mod/ui/film/controller/UIFilmController.getPovMode:()I
      48: iconst_2
      49: if_icmpne     101
      52: aload_0
      53: getfield      #94                 // Field panel:Lmchorse/bbs_mod/ui/film/UIFilmPanel;
      56: invokevirtual #480                // Method mchorse/bbs_mod/ui/film/UIFilmPanel.getController:()Lmchorse/bbs_mod/ui/film/controller/UIFilmController;
      59: getfield      #918                // Field mchorse/bbs_mod/ui/film/controller/UIFilmController.orbit:Lmchorse/bbs_mod/ui/film/controller/OrbitFilmCameraController;
      62: invokevirtual #923                // Method mchorse/bbs_mod/ui/film/controller/OrbitFilmCameraController.isAnimating:()Z
      65: ifne          150
      68: aload_0
      69: getfield      #94                 // Field panel:Lmchorse/bbs_mod/ui/film/UIFilmPanel;
      72: invokevirtual #480                // Method mchorse/bbs_mod/ui/film/UIFilmPanel.getController:()Lmchorse/bbs_mod/ui/film/controller/UIFilmController;
      75: getfield      #918                // Field mchorse/bbs_mod/ui/film/controller/UIFilmController.orbit:Lmchorse/bbs_mod/ui/film/controller/OrbitFilmCameraController;
      78: aload_1
      79: invokevirtual #927                // Method mchorse/bbs_mod/ui/film/controller/OrbitFilmCameraController.canStart:(Lmchorse/bbs_mod/ui/framework/UIContext;)I
      82: iflt          150
      85: aload_0
      86: getfield      #94                 // Field panel:Lmchorse/bbs_mod/ui/film/UIFilmPanel;
      89: invokevirtual #480                // Method mchorse/bbs_mod/ui/film/UIFilmPanel.getController:()Lmchorse/bbs_mod/ui/film/controller/UIFilmController;
      92: getfield      #918                // Field mchorse/bbs_mod/ui/film/controller/UIFilmController.orbit:Lmchorse/bbs_mod/ui/film/controller/OrbitFilmCameraController;
      95: aload_1
      96: invokevirtual #931                // Method mchorse/bbs_mod/ui/film/controller/OrbitFilmCameraController.start:(Lmchorse/bbs_mod/ui/framework/UIContext;)V
      99: iconst_1
     100: ireturn
     101: aload_0
     102: getfield      #94                 // Field panel:Lmchorse/bbs_mod/ui/film/UIFilmPanel;
     105: getfield      #935                // Field mchorse/bbs_mod/ui/film/UIFilmPanel.dashboard:Lmchorse/bbs_mod/ui/dashboard/UIDashboard;
     108: getfield      #941                // Field mchorse/bbs_mod/ui/dashboard/UIDashboard.orbitUI:Lmchorse/bbs_mod/ui/dashboard/utils/UIOrbitCamera;
     111: getfield      #946                // Field mchorse/bbs_mod/ui/dashboard/utils/UIOrbitCamera.orbit:Lmchorse/bbs_mod/camera/OrbitCamera;
     114: aload_1
     115: invokevirtual #949                // Method mchorse/bbs_mod/camera/OrbitCamera.canStart:(Lmchorse/bbs_mod/ui/framework/UIContext;)I
     118: istore_3
     119: iload_3
     120: iflt          150
     123: aload_0
     124: getfield      #94                 // Field panel:Lmchorse/bbs_mod/ui/film/UIFilmPanel;
     127: getfield      #935                // Field mchorse/bbs_mod/ui/film/UIFilmPanel.dashboard:Lmchorse/bbs_mod/ui/dashboard/UIDashboard;
     130: getfield      #941                // Field mchorse/bbs_mod/ui/dashboard/UIDashboard.orbitUI:Lmchorse/bbs_mod/ui/dashboard/utils/UIOrbitCamera;
     133: getfield      #946                // Field mchorse/bbs_mod/ui/dashboard/utils/UIOrbitCamera.orbit:Lmchorse/bbs_mod/camera/OrbitCamera;
     136: iload_3
     137: aload_1
     138: getfield      #952                // Field mchorse/bbs_mod/ui/framework/UIContext.mouseX:I
     141: aload_1
     142: getfield      #955                // Field mchorse/bbs_mod/ui/framework/UIContext.mouseY:I
     145: invokevirtual #958                // Method mchorse/bbs_mod/camera/OrbitCamera.start:(III)V
     148: iconst_1
     149: ireturn
     150: iconst_0
     151: ireturn
     152: aload_0
     153: getfield      #94                 // Field panel:Lmchorse/bbs_mod/ui/film/UIFilmPanel;
     156: invokevirtual #480                // Method mchorse/bbs_mod/ui/film/UIFilmPanel.getController:()Lmchorse/bbs_mod/ui/film/controller/UIFilmController;
     159: invokevirtual #914                // Method mchorse/bbs_mod/ui/film/controller/UIFilmController.getPovMode:()I
     162: iconst_2
     163: if_icmpne     230
     166: getstatic     #961                // Field mchorse/bbs_mod/BBSSettings.editorOrbitWithoutFlight:Lmchorse/bbs_mod/settings/values/numeric/ValueBoolean;
     169: invokevirtual #774                // Method mchorse/bbs_mod/settings/values/numeric/ValueBoolean.get:()Ljava/lang/Object;
     172: checkcast     #776                // class java/lang/Boolean
     175: invokevirtual #779                // Method java/lang/Boolean.booleanValue:()Z
     178: ifeq          230
     181: aload_0
     182: getfield      #94                 // Field panel:Lmchorse/bbs_mod/ui/film/UIFilmPanel;
     185: invokevirtual #480                // Method mchorse/bbs_mod/ui/film/UIFilmPanel.getController:()Lmchorse/bbs_mod/ui/film/controller/UIFilmController;
     188: getfield      #918                // Field mchorse/bbs_mod/ui/film/controller/UIFilmController.orbit:Lmchorse/bbs_mod/ui/film/controller/OrbitFilmCameraController;
     191: invokevirtual #923                // Method mchorse/bbs_mod/ui/film/controller/OrbitFilmCameraController.isAnimating:()Z
     194: ifne          230
     197: aload_0
     198: getfield      #94                 // Field panel:Lmchorse/bbs_mod/ui/film/UIFilmPanel;
     201: invokevirtual #480                // Method mchorse/bbs_mod/ui/film/UIFilmPanel.getController:()Lmchorse/bbs_mod/ui/film/controller/UIFilmController;
     204: getfield      #918                // Field mchorse/bbs_mod/ui/film/controller/UIFilmController.orbit:Lmchorse/bbs_mod/ui/film/controller/OrbitFilmCameraController;
     207: aload_1
     208: invokevirtual #927                // Method mchorse/bbs_mod/ui/film/controller/OrbitFilmCameraController.canStart:(Lmchorse/bbs_mod/ui/framework/UIContext;)I
     211: iflt          230
     214: aload_0
     215: getfield      #94                 // Field panel:Lmchorse/bbs_mod/ui/film/UIFilmPanel;
     218: invokevirtual #480                // Method mchorse/bbs_mod/ui/film/UIFilmPanel.getController:()Lmchorse/bbs_mod/ui/film/controller/UIFilmController;
     221: getfield      #918                // Field mchorse/bbs_mod/ui/film/controller/UIFilmController.orbit:Lmchorse/bbs_mod/ui/film/controller/OrbitFilmCameraController;
     224: aload_1
     225: invokevirtual #931                // Method mchorse/bbs_mod/ui/film/controller/OrbitFilmCameraController.start:(Lmchorse/bbs_mod/ui/framework/UIContext;)V
     228: iconst_1
     229: ireturn
     230: aload_0
     231: getfield      #94                 // Field panel:Lmchorse/bbs_mod/ui/film/UIFilmPanel;
     234: getfield      #965                // Field mchorse/bbs_mod/ui/film/UIFilmPanel.replayEditor:Lmchorse/bbs_mod/ui/film/replays/UIReplaysEditor;
     237: aload_1
     238: aload_2
     239: invokevirtual #971                // Method mchorse/bbs_mod/ui/film/replays/UIReplaysEditor.clickViewport:(Lmchorse/bbs_mod/ui/framework/UIContext;Lmchorse/bbs_mod/ui/utils/Area;)Z
     242: ireturn
     243: aload_0
     244: aload_1
     245: invokespecial #973                // Method mchorse/bbs_mod/ui/framework/elements/UIElement.subMouseClicked:(Lmchorse/bbs_mod/ui/framework/UIContext;)Z
     248: ireturn

  protected boolean subMouseReleased(mchorse.bbs_mod.ui.framework.UIContext);
    Code:
       0: aload_0
       1: getfield      #94                 // Field panel:Lmchorse/bbs_mod/ui/film/UIFilmPanel;
       4: invokevirtual #480                // Method mchorse/bbs_mod/ui/film/UIFilmPanel.getController:()Lmchorse/bbs_mod/ui/film/controller/UIFilmController;
       7: invokevirtual #914                // Method mchorse/bbs_mod/ui/film/controller/UIFilmController.getPovMode:()I
      10: iconst_2
      11: if_icmpne     46
      14: aload_0
      15: getfield      #94                 // Field panel:Lmchorse/bbs_mod/ui/film/UIFilmPanel;
      18: invokevirtual #480                // Method mchorse/bbs_mod/ui/film/UIFilmPanel.getController:()Lmchorse/bbs_mod/ui/film/controller/UIFilmController;
      21: getfield      #918                // Field mchorse/bbs_mod/ui/film/controller/UIFilmController.orbit:Lmchorse/bbs_mod/ui/film/controller/OrbitFilmCameraController;
      24: getfield      #977                // Field mchorse/bbs_mod/ui/film/controller/OrbitFilmCameraController.enabled:Z
      27: ifeq          46
      30: aload_0
      31: getfield      #94                 // Field panel:Lmchorse/bbs_mod/ui/film/UIFilmPanel;
      34: invokevirtual #480                // Method mchorse/bbs_mod/ui/film/UIFilmPanel.getController:()Lmchorse/bbs_mod/ui/film/controller/UIFilmController;
      37: getfield      #918                // Field mchorse/bbs_mod/ui/film/controller/UIFilmController.orbit:Lmchorse/bbs_mod/ui/film/controller/OrbitFilmCameraController;
      40: invokevirtual #980                // Method mchorse/bbs_mod/ui/film/controller/OrbitFilmCameraController.stop:()V
      43: goto          66
      46: aload_0
      47: getfield      #94                 // Field panel:Lmchorse/bbs_mod/ui/film/UIFilmPanel;
      50: invokevirtual #908                // Method mchorse/bbs_mod/ui/film/UIFilmPanel.isFlying:()Z
      53: ifne          66
      56: aload_0
      57: getfield      #94                 // Field panel:Lmchorse/bbs_mod/ui/film/UIFilmPanel;
      60: getfield      #965                // Field mchorse/bbs_mod/ui/film/UIFilmPanel.replayEditor:Lmchorse/bbs_mod/ui/film/replays/UIReplaysEditor;
      63: invokevirtual #983                // Method mchorse/bbs_mod/ui/film/replays/UIReplaysEditor.stopGizmoDrag:()V
      66: aload_0
      67: aload_1
      68: invokespecial #985                // Method mchorse/bbs_mod/ui/framework/elements/UIElement.subMouseReleased:(Lmchorse/bbs_mod/ui/framework/UIContext;)Z
      71: ireturn

  public void render(mchorse.bbs_mod.ui.framework.UIContext);
    Code:
       0: aload_0
       1: getfield      #601                // Field joinWorld:Lmchorse/bbs_mod/ui/framework/elements/buttons/UIButton;
       4: ifnull        21
       7: aload_0
       8: getfield      #601                // Field joinWorld:Lmchorse/bbs_mod/ui/framework/elements/buttons/UIButton;
      11: aload_0
      12: getfield      #94                 // Field panel:Lmchorse/bbs_mod/ui/film/UIFilmPanel;
      15: invokevirtual #989                // Method mchorse/bbs_mod/ui/film/UIFilmPanel.canShowJoinWorld:()Z
      18: invokevirtual #611                // Method mchorse/bbs_mod/ui/framework/elements/buttons/UIButton.setVisible:(Z)V
      21: getstatic     #993                // Field mchorse/bbs_mod/ui/utils/Gizmo.INSTANCE:Lmchorse/bbs_mod/ui/utils/Gizmo;
      24: invokevirtual #997                // Method mchorse/bbs_mod/ui/utils/Gizmo.getMode:()Lmchorse/bbs_mod/ui/utils/Gizmo$Mode;
      27: astore_2
      28: aload_0
      29: getfield      #148                // Field gizmoMove:Lmchorse/bbs_mod/ui/framework/elements/buttons/UIIcon;
      32: aload_2
      33: getstatic     #136                // Field mchorse/bbs_mod/ui/utils/Gizmo$Mode.TRANSLATE:Lmchorse/bbs_mod/ui/utils/Gizmo$Mode;
      36: if_acmpne     43
      39: iconst_1
      40: goto          44
      43: iconst_0
      44: invokevirtual #1001               // Method mchorse/bbs_mod/ui/framework/elements/buttons/UIIcon.active:(Z)Lmchorse/bbs_mod/ui/framework/elements/buttons/UIIcon;
      47: pop
      48: aload_0
      49: getfield      #158                // Field gizmoScale:Lmchorse/bbs_mod/ui/framework/elements/buttons/UIIcon;
      52: aload_2
      53: getstatic     #153                // Field mchorse/bbs_mod/ui/utils/Gizmo$Mode.SCALE:Lmchorse/bbs_mod/ui/utils/Gizmo$Mode;
      56: if_acmpne     63
      59: iconst_1
      60: goto          64
      63: iconst_0
      64: invokevirtual #1001               // Method mchorse/bbs_mod/ui/framework/elements/buttons/UIIcon.active:(Z)Lmchorse/bbs_mod/ui/framework/elements/buttons/UIIcon;
      67: pop
      68: aload_0
      69: getfield      #169                // Field gizmoRotate:Lmchorse/bbs_mod/ui/framework/elements/buttons/UIIcon;
      72: aload_2
      73: getstatic     #164                // Field mchorse/bbs_mod/ui/utils/Gizmo$Mode.ROTATE:Lmchorse/bbs_mod/ui/utils/Gizmo$Mode;
      76: if_acmpne     83
      79: iconst_1
      80: goto          84
      83: iconst_0
      84: invokevirtual #1001               // Method mchorse/bbs_mod/ui/framework/elements/buttons/UIIcon.active:(Z)Lmchorse/bbs_mod/ui/framework/elements/buttons/UIIcon;
      87: pop
      88: aload_0
      89: getfield      #180                // Field gizmoCombined:Lmchorse/bbs_mod/ui/framework/elements/buttons/UIIcon;
      92: aload_2
      93: getstatic     #175                // Field mchorse/bbs_mod/ui/utils/Gizmo$Mode.COMBINED:Lmchorse/bbs_mod/ui/utils/Gizmo$Mode;
      96: if_acmpne     103
      99: iconst_1
     100: goto          104
     103: iconst_0
     104: invokevirtual #1001               // Method mchorse/bbs_mod/ui/framework/elements/buttons/UIIcon.active:(Z)Lmchorse/bbs_mod/ui/framework/elements/buttons/UIIcon;
     107: pop
     108: aload_0
     109: getfield      #191                // Field gizmoTop:Lmchorse/bbs_mod/ui/framework/elements/buttons/UIIcon;
     112: aload_2
     113: getstatic     #186                // Field mchorse/bbs_mod/ui/utils/Gizmo$Mode.TOP:Lmchorse/bbs_mod/ui/utils/Gizmo$Mode;
     116: if_acmpne     123
     119: iconst_1
     120: goto          124
     123: iconst_0
     124: invokevirtual #1001               // Method mchorse/bbs_mod/ui/framework/elements/buttons/UIIcon.active:(Z)Lmchorse/bbs_mod/ui/framework/elements/buttons/UIIcon;
     127: pop
     128: invokestatic  #397                // Method mchorse/bbs_mod/client/BBSRendering.isIrisLoaded:()Z
     131: ifeq          145
     134: aload_0
     135: getfield      #388                // Field toggleShaders:Lmchorse/bbs_mod/ui/framework/elements/buttons/UIIcon;
     138: invokestatic  #1004               // Method mchorse/bbs_mod/client/BBSRendering.isIrisShadersEnabled:()Z
     141: invokevirtual #1001               // Method mchorse/bbs_mod/ui/framework/elements/buttons/UIIcon.active:(Z)Lmchorse/bbs_mod/ui/framework/elements/buttons/UIIcon;
     144: pop
     145: invokestatic  #1008               // Method mchorse/bbs_mod/client/BBSRendering.getTexture:()Lmchorse/bbs_mod/graphics/texture/Texture;
     148: astore_3
     149: aload_0
     150: invokevirtual #902                // Method getViewport:()Lmchorse/bbs_mod/ui/utils/Area;
     153: astore        4
     155: aload_0
     156: getfield      #94                 // Field panel:Lmchorse/bbs_mod/ui/film/UIFilmPanel;
     159: invokevirtual #1012               // Method mchorse/bbs_mod/ui/film/UIFilmPanel.getCamera:()Lmchorse/bbs_mod/camera/Camera;
     162: astore        5
     164: aload         5
     166: aload_0
     167: getfield      #94                 // Field panel:Lmchorse/bbs_mod/ui/film/UIFilmPanel;
     170: invokevirtual #1015               // Method mchorse/bbs_mod/ui/film/UIFilmPanel.getWorldCamera:()Lmchorse/bbs_mod/camera/Camera;
     173: invokevirtual #1021               // Method mchorse/bbs_mod/camera/Camera.copy:(Lmchorse/bbs_mod/camera/Camera;)V
     176: aload         5
     178: getfield      #1025               // Field mchorse/bbs_mod/camera/Camera.view:Lorg/joml/Matrix4f;
     181: aload_0
     182: getfield      #94                 // Field panel:Lmchorse/bbs_mod/ui/film/UIFilmPanel;
     185: getfield      #1028               // Field mchorse/bbs_mod/ui/film/UIFilmPanel.lastView:Lorg/joml/Matrix4f;
     188: invokevirtual #1034               // Method org/joml/Matrix4f.set:(Lorg/joml/Matrix4fc;)Lorg/joml/Matrix4f;
     191: pop
     192: aload         5
     194: getfield      #1037               // Field mchorse/bbs_mod/camera/Camera.projection:Lorg/joml/Matrix4f;
     197: aload_0
     198: getfield      #94                 // Field panel:Lmchorse/bbs_mod/ui/film/UIFilmPanel;
     201: getfield      #1040               // Field mchorse/bbs_mod/ui/film/UIFilmPanel.lastProjection:Lorg/joml/Matrix4f;
     204: invokevirtual #1034               // Method org/joml/Matrix4f.set:(Lorg/joml/Matrix4fc;)Lorg/joml/Matrix4f;
     207: pop
     208: aload_1
     209: getfield      #1044               // Field mchorse/bbs_mod/ui/framework/UIContext.batcher:Lmchorse/bbs_mod/ui/framework/elements/utils/Batcher2D;
     212: invokevirtual #1049               // Method mchorse/bbs_mod/ui/framework/elements/utils/Batcher2D.flush:()V
     215: aload_3
     216: ifnull        291
     219: aload         4
     221: getfield      #875                // Field mchorse/bbs_mod/ui/utils/Area.w:I
     224: ifle          291
     227: aload         4
     229: getfield      #877                // Field mchorse/bbs_mod/ui/utils/Area.h:I
     232: ifle          291
     235: aload_1
     236: getfield      #1044               // Field mchorse/bbs_mod/ui/framework/UIContext.batcher:Lmchorse/bbs_mod/ui/framework/elements/utils/Batcher2D;
     239: aload_3
     240: getfield      #1053               // Field mchorse/bbs_mod/graphics/texture/Texture.id:I
     243: iconst_m1
     244: aload         4
     246: getfield      #1054               // Field mchorse/bbs_mod/ui/utils/Area.x:I
     249: i2f
     250: aload         4
     252: getfield      #1055               // Field mchorse/bbs_mod/ui/utils/Area.y:I
     255: i2f
     256: aload         4
     258: getfield      #875                // Field mchorse/bbs_mod/ui/utils/Area.w:I
     261: i2f
     262: aload         4
     264: getfield      #877                // Field mchorse/bbs_mod/ui/utils/Area.h:I
     267: i2f
     268: fconst_0
     269: aload_3
     270: getfield      #1057               // Field mchorse/bbs_mod/graphics/texture/Texture.height:I
     273: i2f
     274: aload_3
     275: getfield      #1059               // Field mchorse/bbs_mod/graphics/texture/Texture.width:I
     278: i2f
     279: fconst_0
     280: aload_3
     281: getfield      #1059               // Field mchorse/bbs_mod/graphics/texture/Texture.width:I
     284: aload_3
     285: getfield      #1057               // Field mchorse/bbs_mod/graphics/texture/Texture.height:I
     288: invokevirtual #1063               // Method mchorse/bbs_mod/ui/framework/elements/utils/Batcher2D.texturedBox:(IIFFFFFFFFII)V
     291: aload_0
     292: getfield      #1065               // Field pendingThumbnail:Ljava/io/File;
     295: ifnull        362
     298: getstatic     #1068               // Field mchorse/bbs_mod/BBSSettings.editorReplayHudDisplayName:Lmchorse/bbs_mod/settings/values/numeric/ValueBoolean;
     301: invokevirtual #774                // Method mchorse/bbs_mod/settings/values/numeric/ValueBoolean.get:()Ljava/lang/Object;
     304: checkcast     #776                // class java/lang/Boolean
     307: invokevirtual #779                // Method java/lang/Boolean.booleanValue:()Z
     310: istore        6
     312: getstatic     #1068               // Field mchorse/bbs_mod/BBSSettings.editorReplayHudDisplayName:Lmchorse/bbs_mod/settings/values/numeric/ValueBoolean;
     315: iconst_0
     316: invokestatic  #1072               // Method java/lang/Boolean.valueOf:(Z)Ljava/lang/Boolean;
     319: invokevirtual #1074               // Method mchorse/bbs_mod/settings/values/numeric/ValueBoolean.set:(Ljava/lang/Object;)V
     322: aload_1
     323: getfield      #1044               // Field mchorse/bbs_mod/ui/framework/UIContext.batcher:Lmchorse/bbs_mod/ui/framework/elements/utils/Batcher2D;
     326: invokevirtual #1049               // Method mchorse/bbs_mod/ui/framework/elements/utils/Batcher2D.flush:()V
     329: aload_0
     330: aload_0
     331: getfield      #1065               // Field pendingThumbnail:Ljava/io/File;
     334: aload_0
     335: getfield      #1076               // Field pendingThumbnailCallback:Ljava/lang/Runnable;
     338: invokevirtual #1080               // Method captureThumbnailInternal:(Ljava/io/File;Ljava/lang/Runnable;)V
     341: aload_0
     342: aconst_null
     343: putfield      #1065               // Field pendingThumbnail:Ljava/io/File;
     346: aload_0
     347: aconst_null
     348: putfield      #1076               // Field pendingThumbnailCallback:Ljava/lang/Runnable;
     351: getstatic     #1068               // Field mchorse/bbs_mod/BBSSettings.editorReplayHudDisplayName:Lmchorse/bbs_mod/settings/values/numeric/ValueBoolean;
     354: iload         6
     356: invokestatic  #1072               // Method java/lang/Boolean.valueOf:(Z)Ljava/lang/Boolean;
     359: invokevirtual #1074               // Method mchorse/bbs_mod/settings/values/numeric/ValueBoolean.set:(Ljava/lang/Object;)V
     362: aload_0
     363: getfield      #94                 // Field panel:Lmchorse/bbs_mod/ui/film/UIFilmPanel;
     366: invokevirtual #730                // Method mchorse/bbs_mod/ui/film/UIFilmPanel.getData:()Lmchorse/bbs_mod/settings/values/core/ValueGroup;
     369: ifnull        456
     372: aload_1
     373: getfield      #1044               // Field mchorse/bbs_mod/ui/framework/UIContext.batcher:Lmchorse/bbs_mod/ui/framework/elements/utils/Batcher2D;
     376: invokevirtual #1083               // Method mchorse/bbs_mod/ui/framework/elements/utils/Batcher2D.getContext:()Lnet/minecraft/class_332;
     379: invokevirtual #1089               // Method net/minecraft/class_332.method_51448:()Lnet/minecraft/class_4587;
     382: aload_1
     383: getfield      #1044               // Field mchorse/bbs_mod/ui/framework/UIContext.batcher:Lmchorse/bbs_mod/ui/framework/elements/utils/Batcher2D;
     386: aload_0
     387: getfield      #94                 // Field panel:Lmchorse/bbs_mod/ui/film/UIFilmPanel;
     390: invokevirtual #730                // Method mchorse/bbs_mod/ui/film/UIFilmPanel.getData:()Lmchorse/bbs_mod/settings/values/core/ValueGroup;
     393: checkcast     #732                // class mchorse/bbs_mod/film/Film
     396: getfield      #736                // Field mchorse/bbs_mod/film/Film.camera:Lmchorse/bbs_mod/utils/clips/Clips;
     399: aload_0
     400: getfield      #94                 // Field panel:Lmchorse/bbs_mod/ui/film/UIFilmPanel;
     403: invokevirtual #1092               // Method mchorse/bbs_mod/ui/film/UIFilmPanel.getCursor:()I
     406: invokevirtual #1095               // Method mchorse/bbs_mod/utils/clips/Clips.getClips:(I)Ljava/util/List;
     409: aload_0
     410: getfield      #94                 // Field panel:Lmchorse/bbs_mod/ui/film/UIFilmPanel;
     413: invokevirtual #1092               // Method mchorse/bbs_mod/ui/film/UIFilmPanel.getCursor:()I
     416: aload_0
     417: getfield      #94                 // Field panel:Lmchorse/bbs_mod/ui/film/UIFilmPanel;
     420: invokevirtual #1099               // Method mchorse/bbs_mod/ui/film/UIFilmPanel.getRunner:()Lmchorse/bbs_mod/camera/controller/RunnerCameraController;
     423: invokevirtual #1104               // Method mchorse/bbs_mod/camera/controller/RunnerCameraController.isRunning:()Z
     426: aload_0
     427: invokevirtual #902                // Method getViewport:()Lmchorse/bbs_mod/ui/utils/Area;
     430: aload_1
     431: getfield      #1108               // Field mchorse/bbs_mod/ui/framework/UIContext.menu:Lmchorse/bbs_mod/ui/framework/UIBaseMenu;
     434: getfield      #1113               // Field mchorse/bbs_mod/ui/framework/UIBaseMenu.viewport:Lmchorse/bbs_mod/ui/utils/Area;
     437: aload_1
     438: aload_1
     439: getfield      #1108               // Field mchorse/bbs_mod/ui/framework/UIContext.menu:Lmchorse/bbs_mod/ui/framework/UIBaseMenu;
     442: getfield      #1114               // Field mchorse/bbs_mod/ui/framework/UIBaseMenu.width:I
     445: aload_1
     446: getfield      #1108               // Field mchorse/bbs_mod/ui/framework/UIContext.menu:Lmchorse/bbs_mod/ui/framework/UIBaseMenu;
     449: getfield      #1115               // Field mchorse/bbs_mod/ui/framework/UIBaseMenu.height:I
     452: iconst_1
     453: invokestatic  #1121               // Method mchorse/bbs_mod/client/video/VideoRenderer.renderClips:(Lnet/minecraft/class_4587;Lmchorse/bbs_mod/ui/framework/elements/utils/Batcher2D;Ljava/util/List;IZLmchorse/bbs_mod/ui/utils/Area;Lmchorse/bbs_mod/ui/utils/Area;Lmchorse/bbs_mod/ui/framework/UIContext;IIZ)V
     456: aload_0
     457: aload_1
     458: invokevirtual #1124               // Method renderCursor:(Lmchorse/bbs_mod/ui/framework/UIContext;)V
     461: getstatic     #1127               // Field mchorse/bbs_mod/BBSSettings.editorRuleOfThirds:Lmchorse/bbs_mod/settings/values/numeric/ValueBoolean;
     464: invokevirtual #774                // Method mchorse/bbs_mod/settings/values/numeric/ValueBoolean.get:()Ljava/lang/Object;
     467: checkcast     #776                // class java/lang/Boolean
     470: invokevirtual #779                // Method java/lang/Boolean.booleanValue:()Z
     473: ifeq          742
     476: getstatic     #1130               // Field mchorse/bbs_mod/BBSSettings.editorGuidesColor:Lmchorse/bbs_mod/settings/values/numeric/ValueInt;
     479: invokevirtual #859                // Method mchorse/bbs_mod/settings/values/numeric/ValueInt.get:()Ljava/lang/Object;
     482: checkcast     #861                // class java/lang/Integer
     485: invokevirtual #864                // Method java/lang/Integer.intValue:()I
     488: istore        6
     490: aload_1
     491: getfield      #1044               // Field mchorse/bbs_mod/ui/framework/UIContext.batcher:Lmchorse/bbs_mod/ui/framework/elements/utils/Batcher2D;
     494: aload         4
     496: getfield      #1054               // Field mchorse/bbs_mod/ui/utils/Area.x:I
     499: aload         4
     501: getfield      #875                // Field mchorse/bbs_mod/ui/utils/Area.w:I
     504: iconst_3
     505: idiv
     506: iadd
     507: iconst_1
     508: isub
     509: i2f
     510: aload         4
     512: getfield      #1055               // Field mchorse/bbs_mod/ui/utils/Area.y:I
     515: i2f
     516: aload         4
     518: getfield      #1054               // Field mchorse/bbs_mod/ui/utils/Area.x:I
     521: aload         4
     523: getfield      #875                // Field mchorse/bbs_mod/ui/utils/Area.w:I
     526: iconst_3
     527: idiv
     528: iadd
     529: i2f
     530: aload         4
     532: getfield      #1055               // Field mchorse/bbs_mod/ui/utils/Area.y:I
     535: aload         4
     537: getfield      #877                // Field mchorse/bbs_mod/ui/utils/Area.h:I
     540: iadd
     541: i2f
     542: iload         6
     544: invokevirtual #1134               // Method mchorse/bbs_mod/ui/framework/elements/utils/Batcher2D.box:(FFFFI)V
     547: aload_1
     548: getfield      #1044               // Field mchorse/bbs_mod/ui/framework/UIContext.batcher:Lmchorse/bbs_mod/ui/framework/elements/utils/Batcher2D;
     551: aload         4
     553: getfield      #1054               // Field mchorse/bbs_mod/ui/utils/Area.x:I
     556: aload         4
     558: getfield      #875                // Field mchorse/bbs_mod/ui/utils/Area.w:I
     561: iadd
     562: aload         4
     564: getfield      #875                // Field mchorse/bbs_mod/ui/utils/Area.w:I
     567: iconst_3
     568: idiv
     569: isub
     570: i2f
     571: aload         4
     573: getfield      #1055               // Field mchorse/bbs_mod/ui/utils/Area.y:I
     576: i2f
     577: aload         4
     579: getfield      #1054               // Field mchorse/bbs_mod/ui/utils/Area.x:I
     582: aload         4
     584: getfield      #875                // Field mchorse/bbs_mod/ui/utils/Area.w:I
     587: iadd
     588: aload         4
     590: getfield      #875                // Field mchorse/bbs_mod/ui/utils/Area.w:I
     593: iconst_3
     594: idiv
     595: isub
     596: iconst_1
     597: iadd
     598: i2f
     599: aload         4
     601: getfield      #1055               // Field mchorse/bbs_mod/ui/utils/Area.y:I
     604: aload         4
     606: getfield      #877                // Field mchorse/bbs_mod/ui/utils/Area.h:I
     609: iadd
     610: i2f
     611: iload         6
     613: invokevirtual #1134               // Method mchorse/bbs_mod/ui/framework/elements/utils/Batcher2D.box:(FFFFI)V
     616: aload_1
     617: getfield      #1044               // Field mchorse/bbs_mod/ui/framework/UIContext.batcher:Lmchorse/bbs_mod/ui/framework/elements/utils/Batcher2D;
     620: aload         4
     622: getfield      #1054               // Field mchorse/bbs_mod/ui/utils/Area.x:I
     625: i2f
     626: aload         4
     628: getfield      #1055               // Field mchorse/bbs_mod/ui/utils/Area.y:I
     631: aload         4
     633: getfield      #877                // Field mchorse/bbs_mod/ui/utils/Area.h:I
     636: iconst_3
     637: idiv
     638: iadd
     639: iconst_1
     640: isub
     641: i2f
     642: aload         4
     644: getfield      #1054               // Field mchorse/bbs_mod/ui/utils/Area.x:I
     647: aload         4
     649: getfield      #875                // Field mchorse/bbs_mod/ui/utils/Area.w:I
     652: iadd
     653: i2f
     654: aload         4
     656: getfield      #1055               // Field mchorse/bbs_mod/ui/utils/Area.y:I
     659: aload         4
     661: getfield      #877                // Field mchorse/bbs_mod/ui/utils/Area.h:I
     664: iconst_3
     665: idiv
     666: iadd
     667: i2f
     668: iload         6
     670: invokevirtual #1134               // Method mchorse/bbs_mod/ui/framework/elements/utils/Batcher2D.box:(FFFFI)V
     673: aload_1
     674: getfield      #1044               // Field mchorse/bbs_mod/ui/framework/UIContext.batcher:Lmchorse/bbs_mod/ui/framework/elements/utils/Batcher2D;
     677: aload         4
     679: getfield      #1054               // Field mchorse/bbs_mod/ui/utils/Area.x:I
     682: i2f
     683: aload         4
     685: getfield      #1055               // Field mchorse/bbs_mod/ui/utils/Area.y:I
     688: aload         4
     690: getfield      #877                // Field mchorse/bbs_mod/ui/utils/Area.h:I
     693: iadd
     694: aload         4
     696: getfield      #877                // Field mchorse/bbs_mod/ui/utils/Area.h:I
     699: iconst_3
     700: idiv
     701: isub
     702: iconst_1
     703: isub
     704: i2f
     705: aload         4
     707: getfield      #1054               // Field mchorse/bbs_mod/ui/utils/Area.x:I
     710: aload         4
     712: getfield      #875                // Field mchorse/bbs_mod/ui/utils/Area.w:I
     715: iadd
     716: i2f
     717: aload         4
     719: getfield      #1055               // Field mchorse/bbs_mod/ui/utils/Area.y:I
     722: aload         4
     724: getfield      #877                // Field mchorse/bbs_mod/ui/utils/Area.h:I
     727: iadd
     728: aload         4
     730: getfield      #877                // Field mchorse/bbs_mod/ui/utils/Area.h:I
     733: iconst_3
     734: idiv
     735: isub
     736: i2f
     737: iload         6
     739: invokevirtual #1134               // Method mchorse/bbs_mod/ui/framework/elements/utils/Batcher2D.box:(FFFFI)V
     742: getstatic     #1137               // Field mchorse/bbs_mod/BBSSettings.editorSafeMargins:Lmchorse/bbs_mod/settings/values/numeric/ValueBoolean;
     745: invokevirtual #774                // Method mchorse/bbs_mod/settings/values/numeric/ValueBoolean.get:()Ljava/lang/Object;
     748: checkcast     #776                // class java/lang/Boolean
     751: invokevirtual #779                // Method java/lang/Boolean.booleanValue:()Z
     754: ifeq          1119
     757: getstatic     #1140               // Field mchorse/bbs_mod/BBSSettings.editorSafeMarginsColor:Lmchorse/bbs_mod/settings/values/numeric/ValueInt;
     760: invokevirtual #859                // Method mchorse/bbs_mod/settings/values/numeric/ValueInt.get:()Ljava/lang/Object;
     763: checkcast     #861                // class java/lang/Integer
     766: invokevirtual #864                // Method java/lang/Integer.intValue:()I
     769: istore        6
     771: aload         4
     773: getfield      #875                // Field mchorse/bbs_mod/ui/utils/Area.w:I
     776: i2f
     777: ldc_w         #1141               // float 0.05f
     780: fmul
     781: invokestatic  #1145               // Method java/lang/Math.round:(F)I
     784: istore        7
     786: aload         4
     788: getfield      #877                // Field mchorse/bbs_mod/ui/utils/Area.h:I
     791: i2f
     792: ldc_w         #1141               // float 0.05f
     795: fmul
     796: invokestatic  #1145               // Method java/lang/Math.round:(F)I
     799: istore        8
     801: aload         4
     803: getfield      #1054               // Field mchorse/bbs_mod/ui/utils/Area.x:I
     806: iload         7
     808: iadd
     809: istore        9
     811: aload         4
     813: getfield      #1054               // Field mchorse/bbs_mod/ui/utils/Area.x:I
     816: aload         4
     818: getfield      #875                // Field mchorse/bbs_mod/ui/utils/Area.w:I
     821: iadd
     822: iload         7
     824: isub
     825: istore        10
     827: aload         4
     829: getfield      #1055               // Field mchorse/bbs_mod/ui/utils/Area.y:I
     832: iload         8
     834: iadd
     835: istore        11
     837: aload         4
     839: getfield      #1055               // Field mchorse/bbs_mod/ui/utils/Area.y:I
     842: aload         4
     844: getfield      #877                // Field mchorse/bbs_mod/ui/utils/Area.h:I
     847: iadd
     848: iload         8
     850: isub
     851: istore        12
     853: aload_1
     854: getfield      #1044               // Field mchorse/bbs_mod/ui/framework/UIContext.batcher:Lmchorse/bbs_mod/ui/framework/elements/utils/Batcher2D;
     857: iload         9
     859: i2f
     860: iload         11
     862: i2f
     863: iload         9
     865: iconst_1
     866: iadd
     867: i2f
     868: iload         12
     870: i2f
     871: iload         6
     873: invokevirtual #1134               // Method mchorse/bbs_mod/ui/framework/elements/utils/Batcher2D.box:(FFFFI)V
     876: aload_1
     877: getfield      #1044               // Field mchorse/bbs_mod/ui/framework/UIContext.batcher:Lmchorse/bbs_mod/ui/framework/elements/utils/Batcher2D;
     880: iload         10
     882: iconst_1
     883: isub
     884: i2f
     885: iload         11
     887: i2f
     888: iload         10
     890: i2f
     891: iload         12
     893: i2f
     894: iload         6
     896: invokevirtual #1134               // Method mchorse/bbs_mod/ui/framework/elements/utils/Batcher2D.box:(FFFFI)V
     899: aload_1
     900: getfield      #1044               // Field mchorse/bbs_mod/ui/framework/UIContext.batcher:Lmchorse/bbs_mod/ui/framework/elements/utils/Batcher2D;
     903: iload         9
     905: i2f
     906: iload         11
     908: i2f
     909: iload         10
     911: i2f
     912: iload         11
     914: iconst_1
     915: iadd
     916: i2f
     917: iload         6
     919: invokevirtual #1134               // Method mchorse/bbs_mod/ui/framework/elements/utils/Batcher2D.box:(FFFFI)V
     922: aload_1
     923: getfield      #1044               // Field mchorse/bbs_mod/ui/framework/UIContext.batcher:Lmchorse/bbs_mod/ui/framework/elements/utils/Batcher2D;
     926: iload         9
     928: i2f
     929: iload         12
     931: iconst_1
     932: isub
     933: i2f
     934: iload         10
     936: i2f
     937: iload         12
     939: i2f
     940: iload         6
     942: invokevirtual #1134               // Method mchorse/bbs_mod/ui/framework/elements/utils/Batcher2D.box:(FFFFI)V
     945: aload         4
     947: getfield      #875                // Field mchorse/bbs_mod/ui/utils/Area.w:I
     950: i2f
     951: ldc_w         #1146               // float 0.1f
     954: fmul
     955: invokestatic  #1145               // Method java/lang/Math.round:(F)I
     958: istore        13
     960: aload         4
     962: getfield      #877                // Field mchorse/bbs_mod/ui/utils/Area.h:I
     965: i2f
     966: ldc_w         #1146               // float 0.1f
     969: fmul
     970: invokestatic  #1145               // Method java/lang/Math.round:(F)I
     973: istore        14
     975: aload         4
     977: getfield      #1054               // Field mchorse/bbs_mod/ui/utils/Area.x:I
     980: iload         13
     982: iadd
     983: istore        15
     985: aload         4
     987: getfield      #1054               // Field mchorse/bbs_mod/ui/utils/Area.x:I
     990: aload         4
     992: getfield      #875                // Field mchorse/bbs_mod/ui/utils/Area.w:I
     995: iadd
     996: iload         13
     998: isub
     999: istore        16
    1001: aload         4
    1003: getfield      #1055               // Field mchorse/bbs_mod/ui/utils/Area.y:I
    1006: iload         14
    1008: iadd
    1009: istore        17
    1011: aload         4
    1013: getfield      #1055               // Field mchorse/bbs_mod/ui/utils/Area.y:I
    1016: aload         4
    1018: getfield      #877                // Field mchorse/bbs_mod/ui/utils/Area.h:I
    1021: iadd
    1022: iload         14
    1024: isub
    1025: istore        18
    1027: aload_1
    1028: getfield      #1044               // Field mchorse/bbs_mod/ui/framework/UIContext.batcher:Lmchorse/bbs_mod/ui/framework/elements/utils/Batcher2D;
    1031: iload         15
    1033: i2f
    1034: iload         17
    1036: i2f
    1037: iload         15
    1039: iconst_1
    1040: iadd
    1041: i2f
    1042: iload         18
    1044: i2f
    1045: iload         6
    1047: invokevirtual #1134               // Method mchorse/bbs_mod/ui/framework/elements/utils/Batcher2D.box:(FFFFI)V
    1050: aload_1
    1051: getfield      #1044               // Field mchorse/bbs_mod/ui/framework/UIContext.batcher:Lmchorse/bbs_mod/ui/framework/elements/utils/Batcher2D;
    1054: iload         16
    1056: iconst_1
    1057: isub
    1058: i2f
    1059: iload         17
    1061: i2f
    1062: iload         16
    1064: i2f
    1065: iload         18
    1067: i2f
    1068: iload         6
    1070: invokevirtual #1134               // Method mchorse/bbs_mod/ui/framework/elements/utils/Batcher2D.box:(FFFFI)V
    1073: aload_1
    1074: getfield      #1044               // Field mchorse/bbs_mod/ui/framework/UIContext.batcher:Lmchorse/bbs_mod/ui/framework/elements/utils/Batcher2D;
    1077: iload         15
    1079: i2f
    1080: iload         17
    1082: i2f
    1083: iload         16
    1085: i2f
    1086: iload         17
    1088: iconst_1
    1089: iadd
    1090: i2f
    1091: iload         6
    1093: invokevirtual #1134               // Method mchorse/bbs_mod/ui/framework/elements/utils/Batcher2D.box:(FFFFI)V
    1096: aload_1
    1097: getfield      #1044               // Field mchorse/bbs_mod/ui/framework/UIContext.batcher:Lmchorse/bbs_mod/ui/framework/elements/utils/Batcher2D;
    1100: iload         15
    1102: i2f
    1103: iload         18
    1105: iconst_1
    1106: isub
    1107: i2f
    1108: iload         16
    1110: i2f
    1111: iload         18
    1113: i2f
    1114: iload         6
    1116: invokevirtual #1134               // Method mchorse/bbs_mod/ui/framework/elements/utils/Batcher2D.box:(FFFFI)V
    1119: invokestatic  #1149               // Method mchorse/bbs_mod/client/video/VideoRenderer.update:()V
    1122: getstatic     #1152               // Field mchorse/bbs_mod/BBSSettings.editorCenterLines:Lmchorse/bbs_mod/settings/values/numeric/ValueBoolean;
    1125: invokevirtual #774                // Method mchorse/bbs_mod/settings/values/numeric/ValueBoolean.get:()Ljava/lang/Object;
    1128: checkcast     #776                // class java/lang/Boolean
    1131: invokevirtual #779                // Method java/lang/Boolean.booleanValue:()Z
    1134: ifeq          1223
    1137: getstatic     #1130               // Field mchorse/bbs_mod/BBSSettings.editorGuidesColor:Lmchorse/bbs_mod/settings/values/numeric/ValueInt;
    1140: invokevirtual #859                // Method mchorse/bbs_mod/settings/values/numeric/ValueInt.get:()Ljava/lang/Object;
    1143: checkcast     #861                // class java/lang/Integer
    1146: invokevirtual #864                // Method java/lang/Integer.intValue:()I
    1149: istore        6
    1151: aload         4
    1153: invokevirtual #890                // Method mchorse/bbs_mod/ui/utils/Area.mx:()I
    1156: istore        7
    1158: aload         4
    1160: invokevirtual #893                // Method mchorse/bbs_mod/ui/utils/Area.my:()I
    1163: istore        8
    1165: aload_1
    1166: getfield      #1044               // Field mchorse/bbs_mod/ui/framework/UIContext.batcher:Lmchorse/bbs_mod/ui/framework/elements/utils/Batcher2D;
    1169: aload         4
    1171: getfield      #1054               // Field mchorse/bbs_mod/ui/utils/Area.x:I
    1174: i2f
    1175: iload         8
    1177: i2f
    1178: aload         4
    1180: invokevirtual #1155               // Method mchorse/bbs_mod/ui/utils/Area.ex:()I
    1183: i2f
    1184: iload         8
    1186: iconst_1
    1187: iadd
    1188: i2f
    1189: iload         6
    1191: invokevirtual #1134               // Method mchorse/bbs_mod/ui/framework/elements/utils/Batcher2D.box:(FFFFI)V
    1194: aload_1
    1195: getfield      #1044               // Field mchorse/bbs_mod/ui/framework/UIContext.batcher:Lmchorse/bbs_mod/ui/framework/elements/utils/Batcher2D;
    1198: iload         7
    1200: i2f
    1201: aload         4
    1203: getfield      #1055               // Field mchorse/bbs_mod/ui/utils/Area.y:I
    1206: i2f
    1207: iload         7
    1209: iconst_1
    1210: iadd
    1211: i2f
    1212: aload         4
    1214: invokevirtual #1158               // Method mchorse/bbs_mod/ui/utils/Area.ey:()I
    1217: i2f
    1218: iload         6
    1220: invokevirtual #1134               // Method mchorse/bbs_mod/ui/framework/elements/utils/Batcher2D.box:(FFFFI)V
    1223: getstatic     #1161               // Field mchorse/bbs_mod/BBSSettings.editorCrosshair:Lmchorse/bbs_mod/settings/values/numeric/ValueBoolean;
    1226: invokevirtual #774                // Method mchorse/bbs_mod/settings/values/numeric/ValueBoolean.get:()Ljava/lang/Object;
    1229: checkcast     #776                // class java/lang/Boolean
    1232: invokevirtual #779                // Method java/lang/Boolean.booleanValue:()Z
    1235: ifeq          1318
    1238: aload         4
    1240: invokevirtual #890                // Method mchorse/bbs_mod/ui/utils/Area.mx:()I
    1243: iconst_1
    1244: iadd
    1245: istore        6
    1247: aload         4
    1249: invokevirtual #893                // Method mchorse/bbs_mod/ui/utils/Area.my:()I
    1252: iconst_1
    1253: iadd
    1254: istore        7
    1256: aload_1
    1257: getfield      #1044               // Field mchorse/bbs_mod/ui/framework/UIContext.batcher:Lmchorse/bbs_mod/ui/framework/elements/utils/Batcher2D;
    1260: iload         6
    1262: iconst_4
    1263: isub
    1264: i2f
    1265: iload         7
    1267: iconst_1
    1268: isub
    1269: i2f
    1270: iload         6
    1272: iconst_3
    1273: iadd
    1274: i2f
    1275: iload         7
    1277: i2f
    1278: iconst_m1
    1279: ldc           #115                // float 0.5f
    1281: invokestatic  #1167               // Method mchorse/bbs_mod/utils/colors/Colors.setA:(IF)I
    1284: invokevirtual #1134               // Method mchorse/bbs_mod/ui/framework/elements/utils/Batcher2D.box:(FFFFI)V
    1287: aload_1
    1288: getfield      #1044               // Field mchorse/bbs_mod/ui/framework/UIContext.batcher:Lmchorse/bbs_mod/ui/framework/elements/utils/Batcher2D;
    1291: iload         6
    1293: iconst_1
    1294: isub
    1295: i2f
    1296: iload         7
    1298: iconst_4
    1299: isub
    1300: i2f
    1301: iload         6
    1303: i2f
    1304: iload         7
    1306: iconst_3
    1307: iadd
    1308: i2f
    1309: iconst_m1
    1310: ldc           #115                // float 0.5f
    1312: invokestatic  #1167               // Method mchorse/bbs_mod/utils/colors/Colors.setA:(IF)I
    1315: invokevirtual #1134               // Method mchorse/bbs_mod/ui/framework/elements/utils/Batcher2D.box:(FFFFI)V
    1318: aload_0
    1319: getfield      #94                 // Field panel:Lmchorse/bbs_mod/ui/film/UIFilmPanel;
    1322: invokevirtual #480                // Method mchorse/bbs_mod/ui/film/UIFilmPanel.getController:()Lmchorse/bbs_mod/ui/film/controller/UIFilmController;
    1325: aload_1
    1326: aload         4
    1328: invokevirtual #1171               // Method mchorse/bbs_mod/ui/film/controller/UIFilmController.renderHUD:(Lmchorse/bbs_mod/ui/framework/UIContext;Lmchorse/bbs_mod/ui/utils/Area;)V
    1331: getstatic     #1174               // Field mchorse/bbs_mod/BBSSettings.editorFilmOverlayVisible:Lmchorse/bbs_mod/settings/values/numeric/ValueBoolean;
    1334: invokevirtual #774                // Method mchorse/bbs_mod/settings/values/numeric/ValueBoolean.get:()Ljava/lang/Object;
    1337: checkcast     #776                // class java/lang/Boolean
    1340: invokevirtual #779                // Method java/lang/Boolean.booleanValue:()Z
    1343: ifeq          1569
    1346: aload_0
    1347: getfield      #94                 // Field panel:Lmchorse/bbs_mod/ui/film/UIFilmPanel;
    1350: getfield      #965                // Field mchorse/bbs_mod/ui/film/UIFilmPanel.replayEditor:Lmchorse/bbs_mod/ui/film/replays/UIReplaysEditor;
    1353: invokevirtual #1177               // Method mchorse/bbs_mod/ui/film/replays/UIReplaysEditor.isVisible:()Z
    1356: ifeq          1569
    1359: aload_0
    1360: getfield      #94                 // Field panel:Lmchorse/bbs_mod/ui/film/UIFilmPanel;
    1363: invokevirtual #730                // Method mchorse/bbs_mod/ui/film/UIFilmPanel.getData:()Lmchorse/bbs_mod/settings/values/core/ValueGroup;
    1366: ifnull        1569
    1369: aload_0
    1370: getfield      #94                 // Field panel:Lmchorse/bbs_mod/ui/film/UIFilmPanel;
    1373: invokevirtual #1099               // Method mchorse/bbs_mod/ui/film/UIFilmPanel.getRunner:()Lmchorse/bbs_mod/camera/controller/RunnerCameraController;
    1376: astore        6
    1378: aload         4
    1380: getfield      #875                // Field mchorse/bbs_mod/ui/utils/Area.w:I
    1383: i2f
    1384: getstatic     #1181               // Field mchorse/bbs_mod/BBSSettings.audioWaveformWidth:Lmchorse/bbs_mod/settings/values/numeric/ValueFloat;
    1387: invokevirtual #1184               // Method mchorse/bbs_mod/settings/values/numeric/ValueFloat.get:()Ljava/lang/Object;
    1390: checkcast     #1186               // class java/lang/Float
    1393: invokevirtual #1190               // Method java/lang/Float.floatValue:()F
    1396: fmul
    1397: f2i
    1398: istore        7
    1400: aload         4
    1402: ldc           #115                // float 0.5f
    1404: iload         7
    1406: invokevirtual #1193               // Method mchorse/bbs_mod/ui/utils/Area.x:(FI)I
    1409: istore        8
    1411: aload_0
    1412: getfield      #94                 // Field panel:Lmchorse/bbs_mod/ui/film/UIFilmPanel;
    1415: invokevirtual #1092               // Method mchorse/bbs_mod/ui/film/UIFilmPanel.getCursor:()I
    1418: i2f
    1419: aload         6
    1421: invokevirtual #1104               // Method mchorse/bbs_mod/camera/controller/RunnerCameraController.isRunning:()Z
    1424: ifeq          1434
    1427: aload_1
    1428: invokevirtual #1196               // Method mchorse/bbs_mod/ui/framework/UIContext.getTransition:()F
    1431: goto          1435
    1434: fconst_0
    1435: fadd
    1436: fstore        9
    1438: aload_0
    1439: getfield      #83                 // Field clips:Ljava/util/List;
    1442: invokeinterface #673,  1          // InterfaceMethod java/util/List.clear:()V
    1447: aload_0
    1448: getfield      #94                 // Field panel:Lmchorse/bbs_mod/ui/film/UIFilmPanel;
    1451: invokevirtual #730                // Method mchorse/bbs_mod/ui/film/UIFilmPanel.getData:()Lmchorse/bbs_mod/settings/values/core/ValueGroup;
    1454: checkcast     #732                // class mchorse/bbs_mod/film/Film
    1457: getfield      #736                // Field mchorse/bbs_mod/film/Film.camera:Lmchorse/bbs_mod/utils/clips/Clips;
    1460: invokevirtual #1198               // Method mchorse/bbs_mod/utils/clips/Clips.get:()Ljava/util/List;
    1463: invokeinterface #619,  1          // InterfaceMethod java/util/List.iterator:()Ljava/util/Iterator;
    1468: astore        10
    1470: aload         10
    1472: invokeinterface #624,  1          // InterfaceMethod java/util/Iterator.hasNext:()Z
    1477: ifeq          1518
    1480: aload         10
    1482: invokeinterface #627,  1          // InterfaceMethod java/util/Iterator.next:()Ljava/lang/Object;
    1487: checkcast     #1200               // class mchorse/bbs_mod/utils/clips/Clip
    1490: astore        11
    1492: aload         11
    1494: instanceof    #738                // class mchorse/bbs_mod/camera/clips/misc/AudioClip
    1497: ifeq          1515
    1500: aload_0
    1501: getfield      #83                 // Field clips:Ljava/util/List;
    1504: aload         11
    1506: checkcast     #738                // class mchorse/bbs_mod/camera/clips/misc/AudioClip
    1509: invokeinterface #680,  2          // InterfaceMethod java/util/List.add:(Ljava/lang/Object;)Z
    1514: pop
    1515: goto          1470
    1518: aload_1
    1519: getfield      #1044               // Field mchorse/bbs_mod/ui/framework/UIContext.batcher:Lmchorse/bbs_mod/ui/framework/elements/utils/Batcher2D;
    1522: aload_0
    1523: getfield      #83                 // Field clips:Ljava/util/List;
    1526: fload         9
    1528: iload         8
    1530: aload         4
    1532: getfield      #1055               // Field mchorse/bbs_mod/ui/utils/Area.y:I
    1535: bipush        10
    1537: iadd
    1538: iload         7
    1540: getstatic     #1203               // Field mchorse/bbs_mod/BBSSettings.audioWaveformHeight:Lmchorse/bbs_mod/settings/values/numeric/ValueInt;
    1543: invokevirtual #859                // Method mchorse/bbs_mod/settings/values/numeric/ValueInt.get:()Ljava/lang/Object;
    1546: checkcast     #861                // class java/lang/Integer
    1549: invokevirtual #864                // Method java/lang/Integer.intValue:()I
    1552: aload_1
    1553: getfield      #1108               // Field mchorse/bbs_mod/ui/framework/UIContext.menu:Lmchorse/bbs_mod/ui/framework/UIBaseMenu;
    1556: getfield      #1114               // Field mchorse/bbs_mod/ui/framework/UIBaseMenu.width:I
    1559: aload_1
    1560: getfield      #1108               // Field mchorse/bbs_mod/ui/framework/UIContext.menu:Lmchorse/bbs_mod/ui/framework/UIBaseMenu;
    1563: getfield      #1115               // Field mchorse/bbs_mod/ui/framework/UIBaseMenu.height:I
    1566: invokestatic  #1207               // Method mchorse/bbs_mod/audio/AudioRenderer.renderAll:(Lmchorse/bbs_mod/ui/framework/elements/utils/Batcher2D;Ljava/util/List;FIIIIII)V
    1569: aload_0
    1570: getfield      #102                // Field icons:Lmchorse/bbs_mod/ui/framework/elements/UIElement;
    1573: getfield      #1208               // Field mchorse/bbs_mod/ui/framework/elements/UIElement.area:Lmchorse/bbs_mod/ui/utils/Area;
    1576: astore        6
    1578: aload_0
    1579: getfield      #664                // Field viewportButtonsHidden:Z
    1582: ifeq          1642
    1585: aload_0
    1586: getfield      #372                // Field hideOverlays:Lmchorse/bbs_mod/ui/framework/elements/buttons/UIIcon;
    1589: invokevirtual #1209               // Method mchorse/bbs_mod/ui/framework/elements/buttons/UIIcon.isVisible:()Z
    1592: ifeq          1677
    1595: aload_0
    1596: getfield      #372                // Field hideOverlays:Lmchorse/bbs_mod/ui/framework/elements/buttons/UIIcon;
    1599: getfield      #1210               // Field mchorse/bbs_mod/ui/framework/elements/buttons/UIIcon.area:Lmchorse/bbs_mod/ui/utils/Area;
    1602: astore        7
    1604: aload_1
    1605: getfield      #1044               // Field mchorse/bbs_mod/ui/framework/UIContext.batcher:Lmchorse/bbs_mod/ui/framework/elements/utils/Batcher2D;
    1608: aload         7
    1610: getfield      #1054               // Field mchorse/bbs_mod/ui/utils/Area.x:I
    1613: i2f
    1614: aload         7
    1616: getfield      #1055               // Field mchorse/bbs_mod/ui/utils/Area.y:I
    1619: i2f
    1620: aload         7
    1622: invokevirtual #1155               // Method mchorse/bbs_mod/ui/utils/Area.ex:()I
    1625: i2f
    1626: aload         7
    1628: invokevirtual #1158               // Method mchorse/bbs_mod/ui/utils/Area.ey:()I
    1631: i2f
    1632: iconst_0
    1633: ldc_w         #1211               // int -2013265920
    1636: invokevirtual #1215               // Method mchorse/bbs_mod/ui/framework/elements/utils/Batcher2D.gradientVBox:(FFFFII)V
    1639: goto          1677
    1642: aload_1
    1643: getfield      #1044               // Field mchorse/bbs_mod/ui/framework/UIContext.batcher:Lmchorse/bbs_mod/ui/framework/elements/utils/Batcher2D;
    1646: aload         6
    1648: getfield      #1054               // Field mchorse/bbs_mod/ui/utils/Area.x:I
    1651: i2f
    1652: aload         6
    1654: getfield      #1055               // Field mchorse/bbs_mod/ui/utils/Area.y:I
    1657: i2f
    1658: aload         6
    1660: invokevirtual #1155               // Method mchorse/bbs_mod/ui/utils/Area.ex:()I
    1663: i2f
    1664: aload         6
    1666: invokevirtual #1158               // Method mchorse/bbs_mod/ui/utils/Area.ey:()I
    1669: i2f
    1670: iconst_0
    1671: ldc_w         #1211               // int -2013265920
    1674: invokevirtual #1215               // Method mchorse/bbs_mod/ui/framework/elements/utils/Batcher2D.gradientVBox:(FFFFII)V
    1677: aload_0
    1678: getfield      #664                // Field viewportButtonsHidden:Z
    1681: ifne          1843
    1684: aload_0
    1685: getfield      #94                 // Field panel:Lmchorse/bbs_mod/ui/film/UIFilmPanel;
    1688: invokevirtual #908                // Method mchorse/bbs_mod/ui/film/UIFilmPanel.isFlying:()Z
    1691: ifeq          1711
    1694: aload_1
    1695: getfield      #1044               // Field mchorse/bbs_mod/ui/framework/UIContext.batcher:Lmchorse/bbs_mod/ui/framework/elements/utils/Batcher2D;
    1698: aload_0
    1699: getfield      #458                // Field flight:Lmchorse/bbs_mod/ui/framework/elements/buttons/UIIcon;
    1702: getfield      #1210               // Field mchorse/bbs_mod/ui/framework/elements/buttons/UIIcon.area:Lmchorse/bbs_mod/ui/utils/Area;
    1705: getstatic     #1221               // Field mchorse/bbs_mod/utils/Direction.BOTTOM:Lmchorse/bbs_mod/utils/Direction;
    1708: invokestatic  #1227               // Method mchorse/bbs_mod/ui/dashboard/panels/UIDashboardPanels.renderHighlight:(Lmchorse/bbs_mod/ui/framework/elements/utils/Batcher2D;Lmchorse/bbs_mod/ui/utils/Area;Lmchorse/bbs_mod/utils/Direction;)V
    1711: aload_0
    1712: getfield      #94                 // Field panel:Lmchorse/bbs_mod/ui/film/UIFilmPanel;
    1715: invokevirtual #480                // Method mchorse/bbs_mod/ui/film/UIFilmPanel.getController:()Lmchorse/bbs_mod/ui/film/controller/UIFilmController;
    1718: invokevirtual #1230               // Method mchorse/bbs_mod/ui/film/controller/UIFilmController.isControlling:()Z
    1721: ifeq          1741
    1724: aload_1
    1725: getfield      #1044               // Field mchorse/bbs_mod/ui/framework/UIContext.batcher:Lmchorse/bbs_mod/ui/framework/elements/utils/Batcher2D;
    1728: aload_0
    1729: getfield      #471                // Field control:Lmchorse/bbs_mod/ui/framework/elements/buttons/UIIcon;
    1732: getfield      #1210               // Field mchorse/bbs_mod/ui/framework/elements/buttons/UIIcon.area:Lmchorse/bbs_mod/ui/utils/Area;
    1735: getstatic     #1221               // Field mchorse/bbs_mod/utils/Direction.BOTTOM:Lmchorse/bbs_mod/utils/Direction;
    1738: invokestatic  #1227               // Method mchorse/bbs_mod/ui/dashboard/panels/UIDashboardPanels.renderHighlight:(Lmchorse/bbs_mod/ui/framework/elements/utils/Batcher2D;Lmchorse/bbs_mod/ui/utils/Area;Lmchorse/bbs_mod/utils/Direction;)V
    1741: aload_0
    1742: getfield      #94                 // Field panel:Lmchorse/bbs_mod/ui/film/UIFilmPanel;
    1745: invokevirtual #480                // Method mchorse/bbs_mod/ui/film/UIFilmPanel.getController:()Lmchorse/bbs_mod/ui/film/controller/UIFilmController;
    1748: invokevirtual #1233               // Method mchorse/bbs_mod/ui/film/controller/UIFilmController.isRecording:()Z
    1751: ifeq          1771
    1754: aload_1
    1755: getfield      #1044               // Field mchorse/bbs_mod/ui/framework/UIContext.batcher:Lmchorse/bbs_mod/ui/framework/elements/utils/Batcher2D;
    1758: aload_0
    1759: getfield      #512                // Field recordReplay:Lmchorse/bbs_mod/ui/framework/elements/buttons/UIIcon;
    1762: getfield      #1210               // Field mchorse/bbs_mod/ui/framework/elements/buttons/UIIcon.area:Lmchorse/bbs_mod/ui/utils/Area;
    1765: getstatic     #1221               // Field mchorse/bbs_mod/utils/Direction.BOTTOM:Lmchorse/bbs_mod/utils/Direction;
    1768: invokestatic  #1227               // Method mchorse/bbs_mod/ui/dashboard/panels/UIDashboardPanels.renderHighlight:(Lmchorse/bbs_mod/ui/framework/elements/utils/Batcher2D;Lmchorse/bbs_mod/ui/utils/Area;Lmchorse/bbs_mod/utils/Direction;)V
    1771: aload_0
    1772: getfield      #94                 // Field panel:Lmchorse/bbs_mod/ui/film/UIFilmPanel;
    1775: getfield      #1237               // Field mchorse/bbs_mod/ui/film/UIFilmPanel.recorder:Lmchorse/bbs_mod/ui/film/UIFilmRecorder;
    1778: invokevirtual #1240               // Method mchorse/bbs_mod/ui/film/UIFilmRecorder.isRecording:()Z
    1781: ifeq          1801
    1784: aload_1
    1785: getfield      #1044               // Field mchorse/bbs_mod/ui/framework/UIContext.batcher:Lmchorse/bbs_mod/ui/framework/elements/utils/Batcher2D;
    1788: aload_0
    1789: getfield      #530                // Field recordVideo:Lmchorse/bbs_mod/ui/framework/elements/buttons/UIIcon;
    1792: getfield      #1210               // Field mchorse/bbs_mod/ui/framework/elements/buttons/UIIcon.area:Lmchorse/bbs_mod/ui/utils/Area;
    1795: getstatic     #1221               // Field mchorse/bbs_mod/utils/Direction.BOTTOM:Lmchorse/bbs_mod/utils/Direction;
    1798: invokestatic  #1227               // Method mchorse/bbs_mod/ui/dashboard/panels/UIDashboardPanels.renderHighlight:(Lmchorse/bbs_mod/ui/framework/elements/utils/Batcher2D;Lmchorse/bbs_mod/ui/utils/Area;Lmchorse/bbs_mod/utils/Direction;)V
    1801: aload_0
    1802: getfield      #94                 // Field panel:Lmchorse/bbs_mod/ui/film/UIFilmPanel;
    1805: invokevirtual #480                // Method mchorse/bbs_mod/ui/film/UIFilmPanel.getController:()Lmchorse/bbs_mod/ui/film/controller/UIFilmController;
    1808: invokevirtual #710                // Method mchorse/bbs_mod/ui/film/controller/UIFilmController.getOnionSkin:()Lmchorse/bbs_mod/settings/values/ui/ValueOnionSkin;
    1811: getfield      #1244               // Field mchorse/bbs_mod/settings/values/ui/ValueOnionSkin.enabled:Lmchorse/bbs_mod/settings/values/numeric/ValueBoolean;
    1814: invokevirtual #774                // Method mchorse/bbs_mod/settings/values/numeric/ValueBoolean.get:()Ljava/lang/Object;
    1817: checkcast     #776                // class java/lang/Boolean
    1820: invokevirtual #779                // Method java/lang/Boolean.booleanValue:()Z
    1823: ifeq          1843
    1826: aload_1
    1827: getfield      #1044               // Field mchorse/bbs_mod/ui/framework/UIContext.batcher:Lmchorse/bbs_mod/ui/framework/elements/utils/Batcher2D;
    1830: aload_0
    1831: getfield      #345                // Field onionSkin:Lmchorse/bbs_mod/ui/framework/elements/buttons/UIIcon;
    1834: getfield      #1210               // Field mchorse/bbs_mod/ui/framework/elements/buttons/UIIcon.area:Lmchorse/bbs_mod/ui/utils/Area;
    1837: getstatic     #1221               // Field mchorse/bbs_mod/utils/Direction.BOTTOM:Lmchorse/bbs_mod/utils/Direction;
    1840: invokestatic  #1227               // Method mchorse/bbs_mod/ui/dashboard/panels/UIDashboardPanels.renderHighlight:(Lmchorse/bbs_mod/ui/framework/elements/utils/Batcher2D;Lmchorse/bbs_mod/ui/utils/Area;Lmchorse/bbs_mod/utils/Direction;)V
    1843: getstatic     #1174               // Field mchorse/bbs_mod/BBSSettings.editorFilmOverlayVisible:Lmchorse/bbs_mod/settings/values/numeric/ValueBoolean;
    1846: invokevirtual #774                // Method mchorse/bbs_mod/settings/values/numeric/ValueBoolean.get:()Ljava/lang/Object;
    1849: checkcast     #776                // class java/lang/Boolean
    1852: invokevirtual #779                // Method java/lang/Boolean.booleanValue:()Z
    1855: ifne          1875
    1858: aload_1
    1859: getfield      #1044               // Field mchorse/bbs_mod/ui/framework/UIContext.batcher:Lmchorse/bbs_mod/ui/framework/elements/utils/Batcher2D;
    1862: aload_0
    1863: getfield      #372                // Field hideOverlays:Lmchorse/bbs_mod/ui/framework/elements/buttons/UIIcon;
    1866: getfield      #1210               // Field mchorse/bbs_mod/ui/framework/elements/buttons/UIIcon.area:Lmchorse/bbs_mod/ui/utils/Area;
    1869: getstatic     #1221               // Field mchorse/bbs_mod/utils/Direction.BOTTOM:Lmchorse/bbs_mod/utils/Direction;
    1872: invokestatic  #1227               // Method mchorse/bbs_mod/ui/dashboard/panels/UIDashboardPanels.renderHighlight:(Lmchorse/bbs_mod/ui/framework/elements/utils/Batcher2D;Lmchorse/bbs_mod/ui/utils/Area;Lmchorse/bbs_mod/utils/Direction;)V
    1875: aload_0
    1876: getfield      #664                // Field viewportButtonsHidden:Z
    1879: ifeq          1899
    1882: aload_1
    1883: getfield      #1044               // Field mchorse/bbs_mod/ui/framework/UIContext.batcher:Lmchorse/bbs_mod/ui/framework/elements/utils/Batcher2D;
    1886: aload_0
    1887: getfield      #372                // Field hideOverlays:Lmchorse/bbs_mod/ui/framework/elements/buttons/UIIcon;
    1890: getfield      #1210               // Field mchorse/bbs_mod/ui/framework/elements/buttons/UIIcon.area:Lmchorse/bbs_mod/ui/utils/Area;
    1893: getstatic     #1221               // Field mchorse/bbs_mod/utils/Direction.BOTTOM:Lmchorse/bbs_mod/utils/Direction;
    1896: invokestatic  #1227               // Method mchorse/bbs_mod/ui/dashboard/panels/UIDashboardPanels.renderHighlight:(Lmchorse/bbs_mod/ui/framework/elements/utils/Batcher2D;Lmchorse/bbs_mod/ui/utils/Area;Lmchorse/bbs_mod/utils/Direction;)V
    1899: invokestatic  #397                // Method mchorse/bbs_mod/client/BBSRendering.isIrisLoaded:()Z
    1902: ifeq          1928
    1905: invokestatic  #1004               // Method mchorse/bbs_mod/client/BBSRendering.isIrisShadersEnabled:()Z
    1908: ifeq          1928
    1911: aload_1
    1912: getfield      #1044               // Field mchorse/bbs_mod/ui/framework/UIContext.batcher:Lmchorse/bbs_mod/ui/framework/elements/utils/Batcher2D;
    1915: aload_0
    1916: getfield      #388                // Field toggleShaders:Lmchorse/bbs_mod/ui/framework/elements/buttons/UIIcon;
    1919: getfield      #1210               // Field mchorse/bbs_mod/ui/framework/elements/buttons/UIIcon.area:Lmchorse/bbs_mod/ui/utils/Area;
    1922: getstatic     #1221               // Field mchorse/bbs_mod/utils/Direction.BOTTOM:Lmchorse/bbs_mod/utils/Direction;
    1925: invokestatic  #1227               // Method mchorse/bbs_mod/ui/dashboard/panels/UIDashboardPanels.renderHighlight:(Lmchorse/bbs_mod/ui/framework/elements/utils/Batcher2D;Lmchorse/bbs_mod/ui/utils/Area;Lmchorse/bbs_mod/utils/Direction;)V
    1928: aload_0
    1929: getfield      #664                // Field viewportButtonsHidden:Z
    1932: ifne          2033
    1935: aload_0
    1936: getfield      #94                 // Field panel:Lmchorse/bbs_mod/ui/film/UIFilmPanel;
    1939: invokevirtual #480                // Method mchorse/bbs_mod/ui/film/UIFilmPanel.getController:()Lmchorse/bbs_mod/ui/film/controller/UIFilmController;
    1942: invokevirtual #1230               // Method mchorse/bbs_mod/ui/film/controller/UIFilmController.isControlling:()Z
    1945: ifeq          2033
    1948: getstatic     #1247               // Field mchorse/bbs_mod/ui/UIKeys.FILM_CONTROLLER_CONTROL_MODE_TOOLTIP:Lmchorse/bbs_mod/l10n/keys/IKey;
    1951: iconst_1
    1952: anewarray     #1249               // class java/lang/Object
    1955: dup
    1956: iconst_0
    1957: getstatic     #1252               // Field mchorse/bbs_mod/ui/Keys.FILM_CONTROLLER_TOGGLE_CONTROL:Lmchorse/bbs_mod/ui/utils/keys/KeyCombo;
    1960: invokevirtual #1257               // Method mchorse/bbs_mod/ui/utils/keys/KeyCombo.getMainKey:()I
    1963: invokestatic  #1263               // Method mchorse/bbs_mod/ui/utils/keys/KeyCodes.getName:(I)Ljava/lang/String;
    1966: aastore
    1967: invokeinterface #1269,  2         // InterfaceMethod mchorse/bbs_mod/l10n/keys/IKey.format:([Ljava/lang/Object;)Lmchorse/bbs_mod/l10n/keys/IKey;
    1972: invokeinterface #1271,  1         // InterfaceMethod mchorse/bbs_mod/l10n/keys/IKey.get:()Ljava/lang/String;
    1977: astore        7
    1979: aload_1
    1980: getfield      #1044               // Field mchorse/bbs_mod/ui/framework/UIContext.batcher:Lmchorse/bbs_mod/ui/framework/elements/utils/Batcher2D;
    1983: invokevirtual #1275               // Method mchorse/bbs_mod/ui/framework/elements/utils/Batcher2D.getFont:()Lmchorse/bbs_mod/ui/framework/elements/utils/FontRenderer;
    1986: aload         7
    1988: invokevirtual #1281               // Method mchorse/bbs_mod/ui/framework/elements/utils/FontRenderer.getWidth:(Ljava/lang/String;)I
    1991: istore        8
    1993: aload_1
    1994: getfield      #1044               // Field mchorse/bbs_mod/ui/framework/UIContext.batcher:Lmchorse/bbs_mod/ui/framework/elements/utils/Batcher2D;
    1997: invokevirtual #1275               // Method mchorse/bbs_mod/ui/framework/elements/utils/Batcher2D.getFont:()Lmchorse/bbs_mod/ui/framework/elements/utils/FontRenderer;
    2000: invokevirtual #1284               // Method mchorse/bbs_mod/ui/framework/elements/utils/FontRenderer.getHeight:()I
    2003: istore        9
    2005: aload_1
    2006: getfield      #1044               // Field mchorse/bbs_mod/ui/framework/UIContext.batcher:Lmchorse/bbs_mod/ui/framework/elements/utils/Batcher2D;
    2009: aload         7
    2011: aload         6
    2013: iload         8
    2015: invokevirtual #1287               // Method mchorse/bbs_mod/ui/utils/Area.mx:(I)I
    2018: i2f
    2019: aload         6
    2021: getfield      #1055               // Field mchorse/bbs_mod/ui/utils/Area.y:I
    2024: iload         9
    2026: isub
    2027: iconst_5
    2028: isub
    2029: i2f
    2030: invokevirtual #1291               // Method mchorse/bbs_mod/ui/framework/elements/utils/Batcher2D.textCard:(Ljava/lang/String;FF)V
    2033: aload_1
    2034: getfield      #1044               // Field mchorse/bbs_mod/ui/framework/UIContext.batcher:Lmchorse/bbs_mod/ui/framework/elements/utils/Batcher2D;
    2037: aload_0
    2038: getfield      #871                // Field area:Lmchorse/bbs_mod/ui/utils/Area;
    2041: aload_1
    2042: invokevirtual #1295               // Method mchorse/bbs_mod/ui/framework/elements/utils/Batcher2D.clip:(Lmchorse/bbs_mod/ui/utils/Area;Lmchorse/bbs_mod/ui/framework/UIContext;)V
    2045: aload_0
    2046: aload_1
    2047: invokespecial #1297               // Method mchorse/bbs_mod/ui/framework/elements/UIElement.render:(Lmchorse/bbs_mod/ui/framework/UIContext;)V
    2050: aload_1
    2051: getfield      #1044               // Field mchorse/bbs_mod/ui/framework/UIContext.batcher:Lmchorse/bbs_mod/ui/framework/elements/utils/Batcher2D;
    2054: aload_1
    2055: invokevirtual #1300               // Method mchorse/bbs_mod/ui/framework/elements/utils/Batcher2D.unclip:(Lmchorse/bbs_mod/ui/framework/UIContext;)V
    2058: return

  private void renderCursor(mchorse.bbs_mod.ui.framework.UIContext);
    Code:
       0: invokestatic  #1331               // Method net/minecraft/class_310.method_1551:()Lnet/minecraft/class_310;
       3: getfield      #1335               // Field net/minecraft/class_310.field_1773:Lnet/minecraft/class_757;
       6: invokevirtual #1341               // Method net/minecraft/class_757.method_19418:()Lnet/minecraft/class_4184;
       9: astore_2
      10: invokestatic  #1347               // Method com/mojang/blaze3d/systems/RenderSystem.getModelViewStack:()Lorg/joml/Matrix4fStack;
      13: astore_3
      14: aload_3
      15: invokevirtual #1352               // Method org/joml/Matrix4fStack.pushMatrix:()Lorg/joml/Matrix4fStack;
      18: pop
      19: aload_3
      20: aload_1
      21: getfield      #1044               // Field mchorse/bbs_mod/ui/framework/UIContext.batcher:Lmchorse/bbs_mod/ui/framework/elements/utils/Batcher2D;
      24: invokevirtual #1083               // Method mchorse/bbs_mod/ui/framework/elements/utils/Batcher2D.getContext:()Lnet/minecraft/class_332;
      27: invokevirtual #1089               // Method net/minecraft/class_332.method_51448:()Lnet/minecraft/class_4587;
      30: invokevirtual #1356               // Method net/minecraft/class_4587.method_23760:()Lnet/minecraft/class_4587$class_4665;
      33: invokevirtual #1360               // Method net/minecraft/class_4587$class_4665.method_23761:()Lorg/joml/Matrix4f;
      36: invokevirtual #1363               // Method org/joml/Matrix4fStack.mul:(Lorg/joml/Matrix4fc;)Lorg/joml/Matrix4f;
      39: pop
      40: aload_3
      41: aload_0
      42: getfield      #871                // Field area:Lmchorse/bbs_mod/ui/utils/Area;
      45: getfield      #1054               // Field mchorse/bbs_mod/ui/utils/Area.x:I
      48: bipush        16
      50: iadd
      51: i2f
      52: aload_0
      53: getfield      #871                // Field area:Lmchorse/bbs_mod/ui/utils/Area;
      56: invokevirtual #1158               // Method mchorse/bbs_mod/ui/utils/Area.ey:()I
      59: bipush        12
      61: isub
      62: i2f
      63: fconst_0
      64: invokevirtual #1367               // Method org/joml/Matrix4fStack.translate:(FFF)Lorg/joml/Matrix4f;
      67: pop
      68: aload_3
      69: getstatic     #1373               // Field net/minecraft/class_7833.field_40713:Lnet/minecraft/class_7833;
      72: aload_2
      73: invokevirtual #1378               // Method net/minecraft/class_4184.method_19329:()F
      76: invokeinterface #1382,  2         // InterfaceMethod net/minecraft/class_7833.rotationDegrees:(F)Lorg/joml/Quaternionf;
      81: invokevirtual #1385               // Method org/joml/Matrix4fStack.rotate:(Lorg/joml/Quaternionfc;)Lorg/joml/Matrix4f;
      84: pop
      85: aload_3
      86: getstatic     #1388               // Field net/minecraft/class_7833.field_40716:Lnet/minecraft/class_7833;
      89: aload_2
      90: invokevirtual #1391               // Method net/minecraft/class_4184.method_19330:()F
      93: invokeinterface #1382,  2         // InterfaceMethod net/minecraft/class_7833.rotationDegrees:(F)Lorg/joml/Quaternionf;
      98: invokevirtual #1385               // Method org/joml/Matrix4fStack.rotate:(Lorg/joml/Quaternionfc;)Lorg/joml/Matrix4f;
     101: pop
     102: aload_3
     103: ldc_w         #1392               // float -1.0f
     106: ldc_w         #1392               // float -1.0f
     109: ldc_w         #1392               // float -1.0f
     112: invokevirtual #1394               // Method org/joml/Matrix4fStack.scale:(FFF)Lorg/joml/Matrix4f;
     115: pop
     116: invokestatic  #1397               // Method com/mojang/blaze3d/systems/RenderSystem.applyModelViewMatrix:()V
     119: bipush        10
     121: invokestatic  #1401               // Method com/mojang/blaze3d/systems/RenderSystem.renderCrosshair:(I)V
     124: aload_3
     125: invokevirtual #1404               // Method org/joml/Matrix4fStack.popMatrix:()Lorg/joml/Matrix4fStack;
     128: pop
     129: invokestatic  #1397               // Method com/mojang/blaze3d/systems/RenderSystem.applyModelViewMatrix:()V
     132: return

  public void cancelCapture();
    Code:
       0: aload_0
       1: aconst_null
       2: putfield      #1065               // Field pendingThumbnail:Ljava/io/File;
       5: aload_0
       6: aconst_null
       7: putfield      #1076               // Field pendingThumbnailCallback:Ljava/lang/Runnable;
      10: return

  public void captureThumbnail(java.io.File);
    Code:
       0: aload_0
       1: aload_1
       2: aconst_null
       3: invokevirtual #1414               // Method captureThumbnail:(Ljava/io/File;Ljava/lang/Runnable;)V
       6: return

  public void captureThumbnail(java.io.File, java.lang.Runnable);
    Code:
       0: aload_0
       1: aload_1
       2: putfield      #1065               // Field pendingThumbnail:Ljava/io/File;
       5: aload_0
       6: aload_2
       7: putfield      #1076               // Field pendingThumbnailCallback:Ljava/lang/Runnable;
      10: return

  public void captureThumbnailNow(java.io.File, java.lang.Runnable);
    Code:
       0: aload_0
       1: aconst_null
       2: putfield      #1065               // Field pendingThumbnail:Ljava/io/File;
       5: aload_0
       6: aconst_null
       7: putfield      #1076               // Field pendingThumbnailCallback:Ljava/lang/Runnable;
      10: aload_0
      11: aload_1
      12: aload_2
      13: invokevirtual #1080               // Method captureThumbnailInternal:(Ljava/io/File;Ljava/lang/Runnable;)V
      16: return

  private void captureThumbnailInternal(java.io.File, java.lang.Runnable);
    Code:
       0: aload_0
       1: invokevirtual #902                // Method getViewport:()Lmchorse/bbs_mod/ui/utils/Area;
       4: astore_3
       5: aload_0
       6: invokevirtual #704                // Method getContext:()Lmchorse/bbs_mod/ui/framework/UIContext;
       9: astore        4
      11: aload_3
      12: ifnull        142
      15: aload         4
      17: ifnull        142
      20: aload_3
      21: getfield      #875                // Field mchorse/bbs_mod/ui/utils/Area.w:I
      24: ifle          142
      27: aload_3
      28: getfield      #877                // Field mchorse/bbs_mod/ui/utils/Area.h:I
      31: ifle          142
      34: invokestatic  #1331               // Method net/minecraft/class_310.method_1551:()Lnet/minecraft/class_310;
      37: invokevirtual #1422               // Method net/minecraft/class_310.method_22683:()Lnet/minecraft/class_1041;
      40: invokevirtual #1428               // Method net/minecraft/class_1041.method_4495:()D
      43: dstore        5
      45: aload_3
      46: getfield      #875                // Field mchorse/bbs_mod/ui/utils/Area.w:I
      49: i2d
      50: dload         5
      52: dmul
      53: d2i
      54: istore        7
      56: aload_3
      57: getfield      #877                // Field mchorse/bbs_mod/ui/utils/Area.h:I
      60: i2d
      61: dload         5
      63: dmul
      64: d2i
      65: istore        8
      67: aload         4
      69: aload_3
      70: getfield      #1054               // Field mchorse/bbs_mod/ui/utils/Area.x:I
      73: invokevirtual #1431               // Method mchorse/bbs_mod/ui/framework/UIContext.globalX:(I)I
      76: i2d
      77: dload         5
      79: dmul
      80: d2i
      81: istore        9
      83: invokestatic  #1331               // Method net/minecraft/class_310.method_1551:()Lnet/minecraft/class_310;
      86: invokevirtual #1422               // Method net/minecraft/class_310.method_22683:()Lnet/minecraft/class_1041;
      89: invokevirtual #1434               // Method net/minecraft/class_1041.method_4506:()I
      92: i2d
      93: aload         4
      95: aload_3
      96: getfield      #1055               // Field mchorse/bbs_mod/ui/utils/Area.y:I
      99: invokevirtual #1437               // Method mchorse/bbs_mod/ui/framework/UIContext.globalY:(I)I
     102: i2d
     103: dload         5
     105: dmul
     106: dsub
     107: iload         8
     109: i2d
     110: dsub
     111: d2i
     112: istore        10
     114: iload         7
     116: ifle          142
     119: iload         8
     121: ifle          142
     124: aload_0
     125: aload_1
     126: aload_2
     127: iload         9
     129: iload         10
     131: iload         7
     133: iload         8
     135: invokevirtual #1441               // Method captureThumbnailFromFramebuffer:(Ljava/io/File;Ljava/lang/Runnable;IIII)Z
     138: ifeq          142
     141: return
     142: invokestatic  #1008               // Method mchorse/bbs_mod/client/BBSRendering.getTexture:()Lmchorse/bbs_mod/graphics/texture/Texture;
     145: astore        5
     147: aload         5
     149: ifnull        267
     152: aload         5
     154: invokevirtual #1444               // Method mchorse/bbs_mod/graphics/texture/Texture.isValid:()Z
     157: ifeq          267
     160: aload         5
     162: getfield      #1059               // Field mchorse/bbs_mod/graphics/texture/Texture.width:I
     165: ifle          267
     168: aload         5
     170: getfield      #1057               // Field mchorse/bbs_mod/graphics/texture/Texture.height:I
     173: ifle          267
     176: aload         5
     178: getfield      #1059               // Field mchorse/bbs_mod/graphics/texture/Texture.width:I
     181: istore        6
     183: aload         5
     185: getfield      #1057               // Field mchorse/bbs_mod/graphics/texture/Texture.height:I
     188: istore        7
     190: aload         5
     192: getfield      #1053               // Field mchorse/bbs_mod/graphics/texture/Texture.id:I
     195: iload         6
     197: iload         7
     199: aload         5
     201: invokevirtual #1448               // Method mchorse/bbs_mod/graphics/texture/Texture.getFormat:()Lmchorse/bbs_mod/graphics/texture/TextureFormat;
     204: invokestatic  #1452               // Method mchorse/bbs_mod/utils/ScreenshotRecorder.readTexturePixels:(IIILmchorse/bbs_mod/graphics/texture/TextureFormat;)[I
     207: astore        8
     209: aload         8
     211: ifnull        223
     214: aload_0
     215: aload         8
     217: invokevirtual #1456               // Method isThumbnailPixelDataValid:([I)Z
     220: ifne          234
     223: aload_2
     224: ifnull        233
     227: aload_2
     228: invokeinterface #1462,  1         // InterfaceMethod java/lang/Runnable.run:()V
     233: return
     234: aload_0
     235: aload_1
     236: aload_2
     237: iload         6
     239: iload         7
     241: aload         8
     243: invokevirtual #1466               // Method saveThumbnailPixels:(Ljava/io/File;Ljava/lang/Runnable;II[I)V
     246: goto          266
     249: astore        6
     251: aload         6
     253: invokevirtual #1469               // Method java/lang/Exception.printStackTrace:()V
     256: aload_2
     257: ifnull        266
     260: aload_2
     261: invokeinterface #1462,  1         // InterfaceMethod java/lang/Runnable.run:()V
     266: return
     267: aload_2
     268: ifnull        277
     271: aload_2
     272: invokeinterface #1462,  1         // InterfaceMethod java/lang/Runnable.run:()V
     277: return
    Exception table:
       from    to  target type
         176   233   249   Class java/lang/Exception
         234   246   249   Class java/lang/Exception

  private boolean captureThumbnailFromFramebuffer(java.io.File, java.lang.Runnable, int, int, int, int);
    Code:
       0: iload         5
       2: iload         6
       4: imul
       5: iconst_4
       6: imul
       7: invokestatic  #1480               // Method org/lwjgl/BufferUtils.createFloatBuffer:(I)Ljava/nio/FloatBuffer;
      10: astore        7
      12: iload_3
      13: iload         4
      15: iload         5
      17: iload         6
      19: sipush        6408
      22: sipush        5126
      25: aload         7
      27: invokestatic  #1486               // Method org/lwjgl/opengl/GL11.glReadPixels:(IIIIIILjava/nio/FloatBuffer;)V
      30: aload         7
      32: invokevirtual #1492               // Method java/nio/FloatBuffer.rewind:()Ljava/nio/FloatBuffer;
      35: pop
      36: aload         7
      38: iload         5
      40: iload         6
      42: iconst_4
      43: invokestatic  #1496               // Method mchorse/bbs_mod/utils/ScreenshotRecorder.convertFloatPixelsToARGB:(Ljava/nio/FloatBuffer;III)[I
      46: astore        8
      48: aload_0
      49: aload         8
      51: invokevirtual #1456               // Method isThumbnailPixelDataValid:([I)Z
      54: ifne          59
      57: iconst_0
      58: ireturn
      59: aload_0
      60: aload_1
      61: aload_2
      62: iload         5
      64: iload         6
      66: aload         8
      68: invokevirtual #1466               // Method saveThumbnailPixels:(Ljava/io/File;Ljava/lang/Runnable;II[I)V
      71: iconst_1
      72: ireturn
      73: astore        7
      75: aload         7
      77: invokevirtual #1469               // Method java/lang/Exception.printStackTrace:()V
      80: iconst_0
      81: ireturn
    Exception table:
       from    to  target type
           0    58    73   Class java/lang/Exception
          59    72    73   Class java/lang/Exception

  private void saveThumbnailPixels(java.io.File, java.lang.Runnable, int, int, int[]);
    Code:
       0: new           #1500               // class java/lang/Thread
       3: dup
       4: iload_3
       5: iload         4
       7: aload         5
       9: aload_1
      10: aload_2
      11: invokedynamic #1508,  0           // InvokeDynamic #27:run:(II[ILjava/io/File;Ljava/lang/Runnable;)Ljava/lang/Runnable;
      16: invokespecial #1511               // Method java/lang/Thread."<init>":(Ljava/lang/Runnable;)V
      19: invokevirtual #1513               // Method java/lang/Thread.start:()V
      22: return

  private boolean isThumbnailPixelDataValid(int[]);
    Code:
       0: aload_1
       1: ifnull        9
       4: aload_1
       5: arraylength
       6: ifne          11
       9: iconst_0
      10: ireturn
      11: iconst_0
      12: istore_2
      13: iconst_1
      14: aload_1
      15: arraylength
      16: bipush        64
      18: idiv
      19: invokestatic  #660                // Method java/lang/Math.max:(II)I
      22: istore_3
      23: iconst_0
      24: istore        4
      26: iload         4
      28: aload_1
      29: arraylength
      30: if_icmpge     94
      33: aload_1
      34: iload         4
      36: iaload
      37: istore        5
      39: iload         5
      41: bipush        16
      43: ishr
      44: sipush        255
      47: iand
      48: istore        6
      50: iload         5
      52: bipush        8
      54: ishr
      55: sipush        255
      58: iand
      59: istore        7
      61: iload         5
      63: sipush        255
      66: iand
      67: istore        8
      69: iload         6
      71: iload         7
      73: iadd
      74: iload         8
      76: iadd
      77: bipush        12
      79: if_icmple     85
      82: iinc          2, 1
      85: iload         4
      87: iload_3
      88: iadd
      89: istore        4
      91: goto          26
      94: iload_2
      95: iconst_3
      96: if_icmplt     103
      99: iconst_1
     100: goto          104
     103: iconst_0
     104: ireturn

  private static void lambda$saveThumbnailPixels$0(int, int, int[], java.io.File, java.lang.Runnable);
    Code:
       0: new           #21                 // class mchorse/bbs_mod/utils/ScreenshotRecorder$ScreenshotRunner
       3: dup
       4: iload_0
       5: iload_1
       6: aload_2
       7: aload_3
       8: invokespecial #1523               // Method mchorse/bbs_mod/utils/ScreenshotRecorder$ScreenshotRunner."<init>":(II[ILjava/io/File;)V
      11: astore        5
      13: aload         5
      15: iconst_0
      16: putfield      #1526               // Field mchorse/bbs_mod/utils/ScreenshotRecorder$ScreenshotRunner.playSound:Z
      19: aload         5
      21: invokevirtual #1527               // Method mchorse/bbs_mod/utils/ScreenshotRecorder$ScreenshotRunner.run:()V
      24: aload         4
      26: ifnull        37
      29: invokestatic  #1331               // Method net/minecraft/class_310.method_1551:()Lnet/minecraft/class_310;
      32: aload         4
      34: invokevirtual #1530               // Method net/minecraft/class_310.execute:(Ljava/lang/Runnable;)V
      37: return

  private static void lambda$createGizmoButton$0(mchorse.bbs_mod.ui.utils.Gizmo$Mode, mchorse.bbs_mod.ui.framework.elements.buttons.UIIcon);
    Code:
       0: getstatic     #993                // Field mchorse/bbs_mod/ui/utils/Gizmo.INSTANCE:Lmchorse/bbs_mod/ui/utils/Gizmo;
       3: aload_0
       4: invokevirtual #1535               // Method mchorse/bbs_mod/ui/utils/Gizmo.setMode:(Lmchorse/bbs_mod/ui/utils/Gizmo$Mode;)Z
       7: pop
       8: invokestatic  #1540               // Method mchorse/bbs_mod/ui/utils/UIUtils.playClick:()V
      11: return

  private void lambda$new$38(mchorse.bbs_mod.ui.framework.elements.buttons.UIButton);
    Code:
       0: aload_0
       1: getfield      #94                 // Field panel:Lmchorse/bbs_mod/ui/film/UIFilmPanel;
       4: invokevirtual #1543               // Method mchorse/bbs_mod/ui/film/UIFilmPanel.joinPendingWorld:()V
       7: return

  private void lambda$new$37(mchorse.bbs_mod.settings.values.base.BaseValue, int);
    Code:
       0: aload_0
       1: invokevirtual #572                // Method rebuildViewportToolbar:()V
       4: return

  private void lambda$new$36(mchorse.bbs_mod.ui.framework.elements.buttons.UIIcon);
    Code:
       0: aload_0
       1: getfield      #94                 // Field panel:Lmchorse/bbs_mod/ui/film/UIFilmPanel;
       4: invokevirtual #1549               // Method mchorse/bbs_mod/ui/film/UIFilmPanel.openRenderQueueOverlay:()V
       7: return

  private void lambda$new$28(mchorse.bbs_mod.ui.utils.context.ContextMenuManager);
    Code:
       0: aload_1
       1: getstatic     #1552               // Field mchorse/bbs_mod/ui/utils/icons/Icons.CAMERA:Lmchorse/bbs_mod/ui/utils/icons/Icon;
       4: getstatic     #1555               // Field mchorse/bbs_mod/ui/UIKeys.FILM_SCREENSHOT:Lmchorse/bbs_mod/l10n/keys/IKey;
       7: aload_0
       8: invokedynamic #1562,  0           // InvokeDynamic #28:run:(Lmchorse/bbs_mod/ui/film/UIFilmPreview;)Ljava/lang/Runnable;
      13: invokevirtual #1568               // Method mchorse/bbs_mod/ui/utils/context/ContextMenuManager.action:(Lmchorse/bbs_mod/ui/utils/icons/Icon;Lmchorse/bbs_mod/l10n/keys/IKey;Ljava/lang/Runnable;)Lmchorse/bbs_mod/ui/utils/context/ContextAction;
      16: pop
      17: aload_1
      18: getstatic     #1571               // Field mchorse/bbs_mod/ui/utils/icons/Icons.IMAGE:Lmchorse/bbs_mod/ui/utils/icons/Icon;
      21: getstatic     #1574               // Field mchorse/bbs_mod/ui/UIKeys.FILM_SET_THUMBNAIL:Lmchorse/bbs_mod/l10n/keys/IKey;
      24: aload_0
      25: getfield      #94                 // Field panel:Lmchorse/bbs_mod/ui/film/UIFilmPanel;
      28: dup
      29: invokestatic  #486                // Method java/util/Objects.requireNonNull:(Ljava/lang/Object;)Ljava/lang/Object;
      32: pop
      33: invokedynamic #1581,  0           // InvokeDynamic #29:run:(Lmchorse/bbs_mod/ui/film/UIFilmPanel;)Ljava/lang/Runnable;
      38: invokevirtual #1568               // Method mchorse/bbs_mod/ui/utils/context/ContextMenuManager.action:(Lmchorse/bbs_mod/ui/utils/icons/Icon;Lmchorse/bbs_mod/l10n/keys/IKey;Ljava/lang/Runnable;)Lmchorse/bbs_mod/ui/utils/context/ContextAction;
      41: pop
      42: aload_1
      43: getstatic     #1584               // Field mchorse/bbs_mod/ui/utils/icons/Icons.FOLDER:Lmchorse/bbs_mod/ui/utils/icons/Icon;
      46: getstatic     #1587               // Field mchorse/bbs_mod/ui/UIKeys.CAMERA_TOOLTIPS_OPEN_SCREENSHOTS:Lmchorse/bbs_mod/l10n/keys/IKey;
      49: invokedynamic #1592,  0           // InvokeDynamic #30:run:()Ljava/lang/Runnable;
      54: invokevirtual #1568               // Method mchorse/bbs_mod/ui/utils/context/ContextMenuManager.action:(Lmchorse/bbs_mod/ui/utils/icons/Icon;Lmchorse/bbs_mod/l10n/keys/IKey;Ljava/lang/Runnable;)Lmchorse/bbs_mod/ui/utils/context/ContextAction;
      57: pop
      58: aload_1
      59: getstatic     #541                // Field mchorse/bbs_mod/ui/utils/icons/Icons.FILM:Lmchorse/bbs_mod/ui/utils/icons/Icon;
      62: getstatic     #1595               // Field mchorse/bbs_mod/ui/UIKeys.CAMERA_TOOLTIPS_OPEN_VIDEOS:Lmchorse/bbs_mod/l10n/keys/IKey;
      65: aload_0
      66: invokedynamic #1600,  0           // InvokeDynamic #31:run:(Lmchorse/bbs_mod/ui/film/UIFilmPreview;)Ljava/lang/Runnable;
      71: invokevirtual #1568               // Method mchorse/bbs_mod/ui/utils/context/ContextMenuManager.action:(Lmchorse/bbs_mod/ui/utils/icons/Icon;Lmchorse/bbs_mod/l10n/keys/IKey;Ljava/lang/Runnable;)Lmchorse/bbs_mod/ui/utils/context/ContextAction;
      74: pop
      75: aload_1
      76: getstatic     #1603               // Field mchorse/bbs_mod/ui/utils/icons/Icons.GEAR:Lmchorse/bbs_mod/ui/utils/icons/Icon;
      79: getstatic     #1606               // Field mchorse/bbs_mod/ui/UIKeys.CAMERA_TOOLTIPS_OPEN_VIDEO_SETTINGS:Lmchorse/bbs_mod/l10n/keys/IKey;
      82: aload_0
      83: invokedynamic #1611,  0           // InvokeDynamic #32:run:(Lmchorse/bbs_mod/ui/film/UIFilmPreview;)Ljava/lang/Runnable;
      88: invokevirtual #1568               // Method mchorse/bbs_mod/ui/utils/context/ContextMenuManager.action:(Lmchorse/bbs_mod/ui/utils/icons/Icon;Lmchorse/bbs_mod/l10n/keys/IKey;Ljava/lang/Runnable;)Lmchorse/bbs_mod/ui/utils/context/ContextAction;
      91: pop
      92: aload_1
      93: getstatic     #1614               // Field mchorse/bbs_mod/ui/utils/icons/Icons.SOUND:Lmchorse/bbs_mod/ui/utils/icons/Icon;
      96: getstatic     #1617               // Field mchorse/bbs_mod/ui/UIKeys.FILM_RENDER_AUDIO:Lmchorse/bbs_mod/l10n/keys/IKey;
      99: aload_0
     100: invokedynamic #1621,  0           // InvokeDynamic #33:run:(Lmchorse/bbs_mod/ui/film/UIFilmPreview;)Ljava/lang/Runnable;
     105: invokevirtual #1568               // Method mchorse/bbs_mod/ui/utils/context/ContextMenuManager.action:(Lmchorse/bbs_mod/ui/utils/icons/Icon;Lmchorse/bbs_mod/l10n/keys/IKey;Ljava/lang/Runnable;)Lmchorse/bbs_mod/ui/utils/context/ContextAction;
     108: pop
     109: aload_1
     110: getstatic     #1624               // Field mchorse/bbs_mod/ui/utils/icons/Icons.REFRESH:Lmchorse/bbs_mod/ui/utils/icons/Icon;
     113: getstatic     #1627               // Field mchorse/bbs_mod/ui/UIKeys.FILM_RESET_REPLAYS:Lmchorse/bbs_mod/l10n/keys/IKey;
     116: aload_0
     117: getfield      #94                 // Field panel:Lmchorse/bbs_mod/ui/film/UIFilmPanel;
     120: getfield      #1237               // Field mchorse/bbs_mod/ui/film/UIFilmPanel.recorder:Lmchorse/bbs_mod/ui/film/UIFilmRecorder;
     123: getfield      #1630               // Field mchorse/bbs_mod/ui/film/UIFilmRecorder.resetReplays:Z
     126: aload_0
     127: invokedynamic #1635,  0           // InvokeDynamic #34:run:(Lmchorse/bbs_mod/ui/film/UIFilmPreview;)Ljava/lang/Runnable;
     132: invokevirtual #1638               // Method mchorse/bbs_mod/ui/utils/context/ContextMenuManager.action:(Lmchorse/bbs_mod/ui/utils/icons/Icon;Lmchorse/bbs_mod/l10n/keys/IKey;ZLjava/lang/Runnable;)Lmchorse/bbs_mod/ui/utils/context/ContextAction;
     135: pop
     136: return

  private void lambda$new$35();
    Code:
       0: aload_0
       1: getfield      #94                 // Field panel:Lmchorse/bbs_mod/ui/film/UIFilmPanel;
       4: getfield      #1237               // Field mchorse/bbs_mod/ui/film/UIFilmPanel.recorder:Lmchorse/bbs_mod/ui/film/UIFilmRecorder;
       7: aload_0
       8: getfield      #94                 // Field panel:Lmchorse/bbs_mod/ui/film/UIFilmPanel;
      11: getfield      #1237               // Field mchorse/bbs_mod/ui/film/UIFilmPanel.recorder:Lmchorse/bbs_mod/ui/film/UIFilmRecorder;
      14: getfield      #1630               // Field mchorse/bbs_mod/ui/film/UIFilmRecorder.resetReplays:Z
      17: ifne          24
      20: iconst_1
      21: goto          25
      24: iconst_0
      25: putfield      #1630               // Field mchorse/bbs_mod/ui/film/UIFilmRecorder.resetReplays:Z
      28: return

  private void lambda$new$34();
    Code:
       0: aload_0
       1: invokevirtual #704                // Method getContext:()Lmchorse/bbs_mod/ui/framework/UIContext;
       4: aload_0
       5: getfield      #94                 // Field panel:Lmchorse/bbs_mod/ui/film/UIFilmPanel;
       8: getfield      #935                // Field mchorse/bbs_mod/ui/film/UIFilmPanel.dashboard:Lmchorse/bbs_mod/ui/dashboard/UIDashboard;
      11: getfield      #1643               // Field mchorse/bbs_mod/ui/dashboard/UIDashboard.settingsPanel:Lmchorse/bbs_mod/settings/ui/UISettingsOverlayPanel;
      14: sipush        580
      17: sipush        340
      20: invokestatic  #1646               // Method mchorse/bbs_mod/ui/framework/elements/overlay/UIOverlay.addOverlay:(Lmchorse/bbs_mod/ui/framework/UIContext;Lmchorse/bbs_mod/ui/framework/elements/overlay/UIOverlayPanel;II)Lmchorse/bbs_mod/ui/framework/elements/overlay/UIOverlay;
      23: pop
      24: aload_0
      25: getfield      #94                 // Field panel:Lmchorse/bbs_mod/ui/film/UIFilmPanel;
      28: getfield      #935                // Field mchorse/bbs_mod/ui/film/UIFilmPanel.dashboard:Lmchorse/bbs_mod/ui/dashboard/UIDashboard;
      31: getfield      #1643               // Field mchorse/bbs_mod/ui/dashboard/UIDashboard.settingsPanel:Lmchorse/bbs_mod/settings/ui/UISettingsOverlayPanel;
      34: ldc_w         #1648               // String video
      37: invokevirtual #1654               // Method mchorse/bbs_mod/settings/ui/UISettingsOverlayPanel.selectCategory:(Ljava/lang/String;)V
      40: return

  private void lambda$new$33();
    Code:
       0: aload_0
       1: getfield      #94                 // Field panel:Lmchorse/bbs_mod/ui/film/UIFilmPanel;
       4: getfield      #1237               // Field mchorse/bbs_mod/ui/film/UIFilmPanel.recorder:Lmchorse/bbs_mod/ui/film/UIFilmRecorder;
       7: invokevirtual #1657               // Method mchorse/bbs_mod/ui/film/UIFilmRecorder.openMovies:()V
      10: return

  private static void lambda$new$32();
    Code:
       0: invokestatic  #1663               // Method mchorse/bbs_mod/BBSModClient.getScreenshotRecorder:()Lmchorse/bbs_mod/utils/ScreenshotRecorder;
       3: invokevirtual #1666               // Method mchorse/bbs_mod/utils/ScreenshotRecorder.getScreenshots:()Ljava/io/File;
       6: invokestatic  #1670               // Method mchorse/bbs_mod/ui/utils/UIUtils.openFolder:(Ljava/io/File;)Z
       9: pop
      10: return

  private void lambda$new$29();
    Code:
       0: invokestatic  #1663               // Method mchorse/bbs_mod/BBSModClient.getScreenshotRecorder:()Lmchorse/bbs_mod/utils/ScreenshotRecorder;
       3: astore_1
       4: invokestatic  #1008               // Method mchorse/bbs_mod/client/BBSRendering.getTexture:()Lmchorse/bbs_mod/graphics/texture/Texture;
       7: astore_2
       8: invokestatic  #1675               // Method mchorse/bbs_mod/graphics/window/Window.isAltPressed:()Z
      11: ifeq          18
      14: aconst_null
      15: goto          22
      18: aload_1
      19: invokevirtual #1678               // Method mchorse/bbs_mod/utils/ScreenshotRecorder.getScreenshotFile:()Ljava/io/File;
      22: astore_3
      23: aload_3
      24: ifnull        37
      27: aload_0
      28: aload_3
      29: invokedynamic #1685,  0           // InvokeDynamic #35:run:(Lmchorse/bbs_mod/ui/film/UIFilmPreview;Ljava/io/File;)Ljava/lang/Runnable;
      34: goto          38
      37: aconst_null
      38: astore        4
      40: aload_1
      41: aload_3
      42: aload_2
      43: aload         4
      45: invokevirtual #1689               // Method mchorse/bbs_mod/utils/ScreenshotRecorder.takeScreenshot:(Ljava/io/File;Lmchorse/bbs_mod/graphics/texture/Texture;Ljava/lang/Runnable;)V
      48: new           #812                // class mchorse/bbs_mod/ui/framework/elements/overlay/UIMessageFolderOverlayPanel
      51: dup
      52: getstatic     #1692               // Field mchorse/bbs_mod/ui/UIKeys.FILM_SCREENSHOT_TITLE:Lmchorse/bbs_mod/l10n/keys/IKey;
      55: getstatic     #1695               // Field mchorse/bbs_mod/ui/UIKeys.FILM_SCREENSHOT_DESCRIPTION:Lmchorse/bbs_mod/l10n/keys/IKey;
      58: aload_1
      59: invokevirtual #1666               // Method mchorse/bbs_mod/utils/ScreenshotRecorder.getScreenshots:()Ljava/io/File;
      62: invokespecial #821                // Method mchorse/bbs_mod/ui/framework/elements/overlay/UIMessageFolderOverlayPanel."<init>":(Lmchorse/bbs_mod/l10n/keys/IKey;Lmchorse/bbs_mod/l10n/keys/IKey;Ljava/io/File;)V
      65: astore        5
      67: aload_0
      68: invokevirtual #704                // Method getContext:()Lmchorse/bbs_mod/ui/framework/UIContext;
      71: aload         5
      73: invokestatic  #827                // Method mchorse/bbs_mod/ui/framework/elements/overlay/UIOverlay.addOverlay:(Lmchorse/bbs_mod/ui/framework/UIContext;Lmchorse/bbs_mod/ui/framework/elements/overlay/UIOverlayPanel;)Lmchorse/bbs_mod/ui/framework/elements/overlay/UIOverlay;
      76: pop
      77: return

  private void lambda$new$30(java.io.File);
    Code:
       0: invokestatic  #1331               // Method net/minecraft/class_310.method_1551:()Lnet/minecraft/class_310;
       3: aload_0
       4: aload_1
       5: invokedynamic #1704,  0           // InvokeDynamic #36:run:(Lmchorse/bbs_mod/ui/film/UIFilmPreview;Ljava/io/File;)Ljava/lang/Runnable;
      10: invokevirtual #1530               // Method net/minecraft/class_310.execute:(Ljava/lang/Runnable;)V
      13: return

  private void lambda$new$31(java.io.File);
    Code:
       0: aload_0
       1: getfield      #94                 // Field panel:Lmchorse/bbs_mod/ui/film/UIFilmPanel;
       4: aload_1
       5: invokevirtual #1707               // Method mchorse/bbs_mod/ui/film/UIFilmPanel.setFilmThumbnailFromFile:(Ljava/io/File;)V
       8: return

  private void lambda$new$26(mchorse.bbs_mod.ui.framework.elements.buttons.UIIcon);
    Code:
       0: aload_0
       1: getfield      #94                 // Field panel:Lmchorse/bbs_mod/ui/film/UIFilmPanel;
       4: invokevirtual #1710               // Method mchorse/bbs_mod/ui/film/UIFilmPanel.checkShowNoCamera:()Z
       7: ifeq          11
      10: return
      11: invokestatic  #1715               // Method mchorse/bbs_mod/utils/FFMpegUtils.checkFFMPEG:()Z
      14: ifne          76
      17: new           #829                // class mchorse/bbs_mod/ui/framework/elements/overlay/UIMessageOverlayPanel
      20: dup
      21: getstatic     #1718               // Field mchorse/bbs_mod/ui/UIKeys.GENERAL_WARNING:Lmchorse/bbs_mod/l10n/keys/IKey;
      24: getstatic     #1721               // Field mchorse/bbs_mod/ui/UIKeys.GENERAL_FFMPEG_ERROR_DESCRIPTION:Lmchorse/bbs_mod/l10n/keys/IKey;
      27: invokespecial #838                // Method mchorse/bbs_mod/ui/framework/elements/overlay/UIMessageOverlayPanel."<init>":(Lmchorse/bbs_mod/l10n/keys/IKey;Lmchorse/bbs_mod/l10n/keys/IKey;)V
      30: astore_2
      31: new           #193                // class mchorse/bbs_mod/ui/framework/elements/buttons/UIIcon
      34: dup
      35: getstatic     #1724               // Field mchorse/bbs_mod/ui/utils/icons/Icons.HELP:Lmchorse/bbs_mod/ui/utils/icons/Icon;
      38: invokedynamic #1729,  0           // InvokeDynamic #37:accept:()Ljava/util/function/Consumer;
      43: invokespecial #218                // Method mchorse/bbs_mod/ui/framework/elements/buttons/UIIcon."<init>":(Lmchorse/bbs_mod/ui/utils/icons/Icon;Ljava/util/function/Consumer;)V
      46: astore_3
      47: aload_3
      48: getstatic     #1732               // Field mchorse/bbs_mod/ui/UIKeys.GENERAL_FFMPEG_ERROR_GUIDE:Lmchorse/bbs_mod/l10n/keys/IKey;
      51: getstatic     #1735               // Field mchorse/bbs_mod/utils/Direction.LEFT:Lmchorse/bbs_mod/utils/Direction;
      54: invokevirtual #1738               // Method mchorse/bbs_mod/ui/framework/elements/buttons/UIIcon.tooltip:(Lmchorse/bbs_mod/l10n/keys/IKey;Lmchorse/bbs_mod/utils/Direction;)Lmchorse/bbs_mod/ui/framework/elements/UIElement;
      57: pop
      58: aload_2
      59: getfield      #1739               // Field mchorse/bbs_mod/ui/framework/elements/overlay/UIMessageOverlayPanel.icons:Lmchorse/bbs_mod/ui/framework/elements/UIElement;
      62: aload_3
      63: invokevirtual #648                // Method mchorse/bbs_mod/ui/framework/elements/UIElement.add:(Lmchorse/bbs_mod/ui/framework/elements/IUIElement;)V
      66: aload_0
      67: invokevirtual #704                // Method getContext:()Lmchorse/bbs_mod/ui/framework/UIContext;
      70: aload_2
      71: invokestatic  #827                // Method mchorse/bbs_mod/ui/framework/elements/overlay/UIOverlay.addOverlay:(Lmchorse/bbs_mod/ui/framework/UIContext;Lmchorse/bbs_mod/ui/framework/elements/overlay/UIOverlayPanel;)Lmchorse/bbs_mod/ui/framework/elements/overlay/UIOverlay;
      74: pop
      75: return
      76: aload_0
      77: getfield      #94                 // Field panel:Lmchorse/bbs_mod/ui/film/UIFilmPanel;
      80: invokevirtual #730                // Method mchorse/bbs_mod/ui/film/UIFilmPanel.getData:()Lmchorse/bbs_mod/settings/values/core/ValueGroup;
      83: ifnull        115
      86: aload_0
      87: getfield      #94                 // Field panel:Lmchorse/bbs_mod/ui/film/UIFilmPanel;
      90: getfield      #1237               // Field mchorse/bbs_mod/ui/film/UIFilmPanel.recorder:Lmchorse/bbs_mod/ui/film/UIFilmRecorder;
      93: aload_0
      94: getfield      #94                 // Field panel:Lmchorse/bbs_mod/ui/film/UIFilmPanel;
      97: invokevirtual #730                // Method mchorse/bbs_mod/ui/film/UIFilmPanel.getData:()Lmchorse/bbs_mod/settings/values/core/ValueGroup;
     100: checkcast     #732                // class mchorse/bbs_mod/film/Film
     103: getfield      #736                // Field mchorse/bbs_mod/film/Film.camera:Lmchorse/bbs_mod/utils/clips/Clips;
     106: invokevirtual #794                // Method mchorse/bbs_mod/utils/clips/Clips.calculateDuration:()I
     109: invokestatic  #1008               // Method mchorse/bbs_mod/client/BBSRendering.getTexture:()Lmchorse/bbs_mod/graphics/texture/Texture;
     112: invokevirtual #1743               // Method mchorse/bbs_mod/ui/film/UIFilmRecorder.startRecording:(ILmchorse/bbs_mod/graphics/texture/Texture;)V
     115: return

  private static void lambda$new$27(mchorse.bbs_mod.ui.framework.elements.buttons.UIIcon);
    Code:
       0: getstatic     #1749               // Field mchorse/bbs_mod/ui/UIKeys.GENERAL_FFMPEG_ERROR_GUIDE_LINK:Lmchorse/bbs_mod/l10n/keys/IKey;
       3: invokeinterface #1271,  1         // InterfaceMethod mchorse/bbs_mod/l10n/keys/IKey.get:()Ljava/lang/String;
       8: invokestatic  #1753               // Method mchorse/bbs_mod/ui/utils/UIUtils.openWebLink:(Ljava/lang/String;)Z
      11: pop
      12: return

  private void lambda$new$23(mchorse.bbs_mod.ui.utils.context.ContextMenuManager);
    Code:
       0: aload_1
       1: getstatic     #1756               // Field mchorse/bbs_mod/ui/utils/icons/Icons.DOWNLOAD:Lmchorse/bbs_mod/ui/utils/icons/Icon;
       4: getstatic     #1759               // Field mchorse/bbs_mod/ui/UIKeys.FILM_CONTROLLER_KEYS_TOGGLE_INSTANT_KEYFRAMES:Lmchorse/bbs_mod/l10n/keys/IKey;
       7: aload_0
       8: getfield      #94                 // Field panel:Lmchorse/bbs_mod/ui/film/UIFilmPanel;
      11: invokevirtual #480                // Method mchorse/bbs_mod/ui/film/UIFilmPanel.getController:()Lmchorse/bbs_mod/ui/film/controller/UIFilmController;
      14: invokevirtual #1762               // Method mchorse/bbs_mod/ui/film/controller/UIFilmController.isInstantKeyframes:()Z
      17: aload_0
      18: invokedynamic #1767,  0           // InvokeDynamic #38:run:(Lmchorse/bbs_mod/ui/film/UIFilmPreview;)Ljava/lang/Runnable;
      23: invokevirtual #1638               // Method mchorse/bbs_mod/ui/utils/context/ContextMenuManager.action:(Lmchorse/bbs_mod/ui/utils/icons/Icon;Lmchorse/bbs_mod/l10n/keys/IKey;ZLjava/lang/Runnable;)Lmchorse/bbs_mod/ui/utils/context/ContextAction;
      26: pop
      27: aload_1
      28: getstatic     #132                // Field mchorse/bbs_mod/ui/utils/icons/Icons.ALL_DIRECTIONS:Lmchorse/bbs_mod/ui/utils/icons/Icon;
      31: getstatic     #1770               // Field mchorse/bbs_mod/ui/UIKeys.FILM_CONTROLLER_KEYS_TOGGLE_COUNTDOWN_CONTROL:Lmchorse/bbs_mod/l10n/keys/IKey;
      34: aload_0
      35: getfield      #94                 // Field panel:Lmchorse/bbs_mod/ui/film/UIFilmPanel;
      38: invokevirtual #480                // Method mchorse/bbs_mod/ui/film/UIFilmPanel.getController:()Lmchorse/bbs_mod/ui/film/controller/UIFilmController;
      41: invokevirtual #1773               // Method mchorse/bbs_mod/ui/film/controller/UIFilmController.isCountdownControlEnabled:()Z
      44: aload_0
      45: invokedynamic #1778,  0           // InvokeDynamic #39:run:(Lmchorse/bbs_mod/ui/film/UIFilmPreview;)Ljava/lang/Runnable;
      50: invokevirtual #1638               // Method mchorse/bbs_mod/ui/utils/context/ContextMenuManager.action:(Lmchorse/bbs_mod/ui/utils/icons/Icon;Lmchorse/bbs_mod/l10n/keys/IKey;ZLjava/lang/Runnable;)Lmchorse/bbs_mod/ui/utils/context/ContextAction;
      53: pop
      54: return

  private void lambda$new$25();
    Code:
       0: aload_0
       1: getfield      #94                 // Field panel:Lmchorse/bbs_mod/ui/film/UIFilmPanel;
       4: invokevirtual #480                // Method mchorse/bbs_mod/ui/film/UIFilmPanel.getController:()Lmchorse/bbs_mod/ui/film/controller/UIFilmController;
       7: invokevirtual #1781               // Method mchorse/bbs_mod/ui/film/controller/UIFilmController.toggleCountdownControl:()V
      10: return

  private void lambda$new$24();
    Code:
       0: aload_0
       1: getfield      #94                 // Field panel:Lmchorse/bbs_mod/ui/film/UIFilmPanel;
       4: invokevirtual #480                // Method mchorse/bbs_mod/ui/film/UIFilmPanel.getController:()Lmchorse/bbs_mod/ui/film/controller/UIFilmController;
       7: invokevirtual #1784               // Method mchorse/bbs_mod/ui/film/controller/UIFilmController.toggleInstantKeyframes:()V
      10: return

  private void lambda$new$22(mchorse.bbs_mod.ui.framework.elements.buttons.UIIcon);
    Code:
       0: aload_0
       1: getfield      #94                 // Field panel:Lmchorse/bbs_mod/ui/film/UIFilmPanel;
       4: invokevirtual #480                // Method mchorse/bbs_mod/ui/film/UIFilmPanel.getController:()Lmchorse/bbs_mod/ui/film/controller/UIFilmController;
       7: invokevirtual #1787               // Method mchorse/bbs_mod/ui/film/controller/UIFilmController.pickRecording:()V
      10: return

  private void lambda$new$21(mchorse.bbs_mod.ui.framework.elements.buttons.UIIcon);
    Code:
       0: aload_0
       1: getfield      #94                 // Field panel:Lmchorse/bbs_mod/ui/film/UIFilmPanel;
       4: invokevirtual #480                // Method mchorse/bbs_mod/ui/film/UIFilmPanel.getController:()Lmchorse/bbs_mod/ui/film/controller/UIFilmController;
       7: invokevirtual #1790               // Method mchorse/bbs_mod/ui/film/controller/UIFilmController.toggleOrbitMode:()V
      10: return

  private void lambda$new$20(mchorse.bbs_mod.ui.framework.elements.buttons.UIIcon);
    Code:
       0: aload_0
       1: getfield      #94                 // Field panel:Lmchorse/bbs_mod/ui/film/UIFilmPanel;
       4: invokevirtual #480                // Method mchorse/bbs_mod/ui/film/UIFilmPanel.getController:()Lmchorse/bbs_mod/ui/film/controller/UIFilmController;
       7: invokevirtual #1793               // Method mchorse/bbs_mod/ui/film/controller/UIFilmController.toggleControl:()V
      10: return

  private void lambda$new$19(mchorse.bbs_mod.ui.framework.elements.buttons.UIIcon);
    Code:
       0: aload_0
       1: getfield      #94                 // Field panel:Lmchorse/bbs_mod/ui/film/UIFilmPanel;
       4: invokevirtual #1796               // Method mchorse/bbs_mod/ui/film/UIFilmPanel.toggleFlight:()V
       7: return

  private void lambda$new$15(mchorse.bbs_mod.ui.utils.context.ContextMenuManager);
    Code:
       0: aload_1
       1: getstatic     #433                // Field mchorse/bbs_mod/ui/utils/icons/Icons.MOVE_TO:Lmchorse/bbs_mod/ui/utils/icons/Icon;
       4: getstatic     #1799               // Field mchorse/bbs_mod/ui/UIKeys.FILM_TELEPORT_CONTEXT_PLAYER:Lmchorse/bbs_mod/l10n/keys/IKey;
       7: getstatic     #1802               // Field mchorse/bbs_mod/BBSSettings.editorCameraPreviewPlayerSync:Lmchorse/bbs_mod/settings/values/numeric/ValueBoolean;
      10: invokevirtual #774                // Method mchorse/bbs_mod/settings/values/numeric/ValueBoolean.get:()Ljava/lang/Object;
      13: checkcast     #776                // class java/lang/Boolean
      16: invokevirtual #779                // Method java/lang/Boolean.booleanValue:()Z
      19: invokedynamic #1807,  0           // InvokeDynamic #40:run:()Ljava/lang/Runnable;
      24: invokevirtual #1638               // Method mchorse/bbs_mod/ui/utils/context/ContextMenuManager.action:(Lmchorse/bbs_mod/ui/utils/icons/Icon;Lmchorse/bbs_mod/l10n/keys/IKey;ZLjava/lang/Runnable;)Lmchorse/bbs_mod/ui/utils/context/ContextAction;
      27: pop
      28: aload_1
      29: getstatic     #1810               // Field mchorse/bbs_mod/ui/utils/icons/Icons.COPY:Lmchorse/bbs_mod/ui/utils/icons/Icon;
      32: getstatic     #1813               // Field mchorse/bbs_mod/ui/UIKeys.CAMERA_PANELS_CONTEXT_COPY_POSITION:Lmchorse/bbs_mod/l10n/keys/IKey;
      35: aload_0
      36: invokedynamic #1818,  0           // InvokeDynamic #41:run:(Lmchorse/bbs_mod/ui/film/UIFilmPreview;)Ljava/lang/Runnable;
      41: invokevirtual #1568               // Method mchorse/bbs_mod/ui/utils/context/ContextMenuManager.action:(Lmchorse/bbs_mod/ui/utils/icons/Icon;Lmchorse/bbs_mod/l10n/keys/IKey;Ljava/lang/Runnable;)Lmchorse/bbs_mod/ui/utils/context/ContextAction;
      44: pop
      45: invokestatic  #1821               // Method mchorse/bbs_mod/graphics/window/Window.getClipboard:()Ljava/lang/String;
      48: invokestatic  #1827               // Method mchorse/bbs_mod/ui/film/utils/UICameraUtils.stringToMap:(Ljava/lang/String;)Ljava/util/Map;
      51: astore_2
      52: aload_2
      53: invokeinterface #1830,  1         // InterfaceMethod java/util/Map.isEmpty:()Z
      58: ifne          79
      61: aload_1
      62: getstatic     #1833               // Field mchorse/bbs_mod/ui/utils/icons/Icons.PASTE:Lmchorse/bbs_mod/ui/utils/icons/Icon;
      65: getstatic     #1836               // Field mchorse/bbs_mod/ui/UIKeys.CAMERA_PANELS_CONTEXT_PASTE_POSITION:Lmchorse/bbs_mod/l10n/keys/IKey;
      68: aload_0
      69: aload_2
      70: invokedynamic #1844,  0           // InvokeDynamic #42:run:(Lmchorse/bbs_mod/ui/film/UIFilmPreview;Ljava/util/Map;)Ljava/lang/Runnable;
      75: invokevirtual #1568               // Method mchorse/bbs_mod/ui/utils/context/ContextMenuManager.action:(Lmchorse/bbs_mod/ui/utils/icons/Icon;Lmchorse/bbs_mod/l10n/keys/IKey;Ljava/lang/Runnable;)Lmchorse/bbs_mod/ui/utils/context/ContextAction;
      78: pop
      79: return

  private void lambda$new$18(java.util.Map);
    Code:
       0: new           #1848               // class mchorse/bbs_mod/camera/data/Position
       3: dup
       4: invokespecial #1849               // Method mchorse/bbs_mod/camera/data/Position."<init>":()V
       7: astore_2
       8: aload_1
       9: invokestatic  #1853               // Method mchorse/bbs_mod/ui/film/utils/UICameraUtils.createPoint:(Ljava/util/Map;)Lmchorse/bbs_mod/camera/data/Point;
      12: astore_3
      13: aload_1
      14: invokestatic  #1857               // Method mchorse/bbs_mod/ui/film/utils/UICameraUtils.createAngle:(Ljava/util/Map;)Lmchorse/bbs_mod/camera/data/Angle;
      17: astore        4
      19: aload_3
      20: ifnull        45
      23: aload         4
      25: ifnull        45
      28: aload_2
      29: getfield      #1861               // Field mchorse/bbs_mod/camera/data/Position.point:Lmchorse/bbs_mod/camera/data/Point;
      32: aload_3
      33: invokevirtual #1866               // Method mchorse/bbs_mod/camera/data/Point.set:(Lmchorse/bbs_mod/camera/data/Point;)V
      36: aload_2
      37: getfield      #1870               // Field mchorse/bbs_mod/camera/data/Position.angle:Lmchorse/bbs_mod/camera/data/Angle;
      40: aload         4
      42: invokevirtual #1875               // Method mchorse/bbs_mod/camera/data/Angle.set:(Lmchorse/bbs_mod/camera/data/Angle;)V
      45: aload_0
      46: getfield      #94                 // Field panel:Lmchorse/bbs_mod/ui/film/UIFilmPanel;
      49: getfield      #1879               // Field mchorse/bbs_mod/ui/film/UIFilmPanel.cameraEditor:Lmchorse/bbs_mod/ui/film/UIClipsPanel;
      52: aload_2
      53: invokevirtual #1885               // Method mchorse/bbs_mod/ui/film/UIClipsPanel.editClip:(Lmchorse/bbs_mod/camera/data/Position;)V
      56: return

  private void lambda$new$17();
    Code:
       0: new           #1848               // class mchorse/bbs_mod/camera/data/Position
       3: dup
       4: aload_0
       5: getfield      #94                 // Field panel:Lmchorse/bbs_mod/ui/film/UIFilmPanel;
       8: invokevirtual #1012               // Method mchorse/bbs_mod/ui/film/UIFilmPanel.getCamera:()Lmchorse/bbs_mod/camera/Camera;
      11: invokespecial #1889               // Method mchorse/bbs_mod/camera/data/Position."<init>":(Lmchorse/bbs_mod/camera/Camera;)V
      14: astore_1
      15: new           #1891               // class java/util/LinkedHashMap
      18: dup
      19: invokespecial #1892               // Method java/util/LinkedHashMap."<init>":()V
      22: astore_2
      23: aload_2
      24: aload_1
      25: getfield      #1861               // Field mchorse/bbs_mod/camera/data/Position.point:Lmchorse/bbs_mod/camera/data/Point;
      28: invokestatic  #1896               // Method mchorse/bbs_mod/ui/film/utils/UICameraUtils.copyPoint:(Ljava/util/Map;Lmchorse/bbs_mod/camera/data/Point;)V
      31: aload_2
      32: aload_1
      33: getfield      #1870               // Field mchorse/bbs_mod/camera/data/Position.angle:Lmchorse/bbs_mod/camera/data/Angle;
      36: invokestatic  #1900               // Method mchorse/bbs_mod/ui/film/utils/UICameraUtils.copyAngle:(Ljava/util/Map;Lmchorse/bbs_mod/camera/data/Angle;)V
      39: aload_2
      40: invokestatic  #1904               // Method mchorse/bbs_mod/ui/film/utils/UICameraUtils.mapToString:(Ljava/util/Map;)Ljava/lang/String;
      43: invokestatic  #1907               // Method mchorse/bbs_mod/graphics/window/Window.setClipboard:(Ljava/lang/String;)V
      46: return

  private static void lambda$new$16();
    Code:
       0: getstatic     #1802               // Field mchorse/bbs_mod/BBSSettings.editorCameraPreviewPlayerSync:Lmchorse/bbs_mod/settings/values/numeric/ValueBoolean;
       3: getstatic     #1802               // Field mchorse/bbs_mod/BBSSettings.editorCameraPreviewPlayerSync:Lmchorse/bbs_mod/settings/values/numeric/ValueBoolean;
       6: invokevirtual #774                // Method mchorse/bbs_mod/settings/values/numeric/ValueBoolean.get:()Ljava/lang/Object;
       9: checkcast     #776                // class java/lang/Boolean
      12: invokevirtual #779                // Method java/lang/Boolean.booleanValue:()Z
      15: ifne          22
      18: iconst_1
      19: goto          23
      22: iconst_0
      23: invokestatic  #1072               // Method java/lang/Boolean.valueOf:(Z)Ljava/lang/Boolean;
      26: invokevirtual #1074               // Method mchorse/bbs_mod/settings/values/numeric/ValueBoolean.set:(Ljava/lang/Object;)V
      29: return

  private void lambda$new$14(mchorse.bbs_mod.ui.framework.elements.buttons.UIIcon);
    Code:
       0: aload_0
       1: getfield      #94                 // Field panel:Lmchorse/bbs_mod/ui/film/UIFilmPanel;
       4: invokevirtual #1911               // Method mchorse/bbs_mod/ui/film/UIFilmPanel.teleportToCamera:()V
       7: return

  private void lambda$new$11(mchorse.bbs_mod.ui.utils.context.ContextMenuManager);
    Code:
       0: aload_1
       1: getstatic     #1914               // Field mchorse/bbs_mod/ui/utils/icons/Icons.PLAY:Lmchorse/bbs_mod/ui/utils/icons/Icon;
       4: getstatic     #1917               // Field mchorse/bbs_mod/ui/UIKeys.CAMERA_EDITOR_KEYS_EDITOR_PLAY_FILM:Lmchorse/bbs_mod/l10n/keys/IKey;
       7: aload_0
       8: invokedynamic #1922,  0           // InvokeDynamic #43:run:(Lmchorse/bbs_mod/ui/film/UIFilmPreview;)Ljava/lang/Runnable;
      13: invokevirtual #1568               // Method mchorse/bbs_mod/ui/utils/context/ContextMenuManager.action:(Lmchorse/bbs_mod/ui/utils/icons/Icon;Lmchorse/bbs_mod/l10n/keys/IKey;Ljava/lang/Runnable;)Lmchorse/bbs_mod/ui/utils/context/ContextAction;
      16: pop
      17: aload_1
      18: getstatic     #1925               // Field mchorse/bbs_mod/ui/utils/icons/Icons.PAUSE:Lmchorse/bbs_mod/ui/utils/icons/Icon;
      21: getstatic     #1928               // Field mchorse/bbs_mod/ui/UIKeys.CAMERA_EDITOR_KEYS_EDITOR_FREEZE_PAUSED:Lmchorse/bbs_mod/l10n/keys/IKey;
      24: aload_0
      25: getfield      #94                 // Field panel:Lmchorse/bbs_mod/ui/film/UIFilmPanel;
      28: invokevirtual #480                // Method mchorse/bbs_mod/ui/film/UIFilmPanel.getController:()Lmchorse/bbs_mod/ui/film/controller/UIFilmController;
      31: invokevirtual #1931               // Method mchorse/bbs_mod/ui/film/controller/UIFilmController.isPaused:()Z
      34: ifne          41
      37: iconst_1
      38: goto          42
      41: iconst_0
      42: aload_0
      43: invokedynamic #1938,  0           // InvokeDynamic #44:run:(Lmchorse/bbs_mod/ui/film/UIFilmPreview;)Ljava/lang/Runnable;
      48: invokevirtual #1638               // Method mchorse/bbs_mod/ui/utils/context/ContextMenuManager.action:(Lmchorse/bbs_mod/ui/utils/icons/Icon;Lmchorse/bbs_mod/l10n/keys/IKey;ZLjava/lang/Runnable;)Lmchorse/bbs_mod/ui/utils/context/ContextAction;
      51: pop
      52: return

  private void lambda$new$13();
    Code:
       0: aload_0
       1: getfield      #94                 // Field panel:Lmchorse/bbs_mod/ui/film/UIFilmPanel;
       4: invokevirtual #480                // Method mchorse/bbs_mod/ui/film/UIFilmPanel.getController:()Lmchorse/bbs_mod/ui/film/controller/UIFilmController;
       7: aload_0
       8: getfield      #94                 // Field panel:Lmchorse/bbs_mod/ui/film/UIFilmPanel;
      11: invokevirtual #480                // Method mchorse/bbs_mod/ui/film/UIFilmPanel.getController:()Lmchorse/bbs_mod/ui/film/controller/UIFilmController;
      14: invokevirtual #1931               // Method mchorse/bbs_mod/ui/film/controller/UIFilmController.isPaused:()Z
      17: ifne          24
      20: iconst_1
      21: goto          25
      24: iconst_0
      25: invokevirtual #1941               // Method mchorse/bbs_mod/ui/film/controller/UIFilmController.setPaused:(Z)V
      28: return

  private void lambda$new$12();
    Code:
       0: aload_0
       1: getfield      #94                 // Field panel:Lmchorse/bbs_mod/ui/film/UIFilmPanel;
       4: invokevirtual #1710               // Method mchorse/bbs_mod/ui/film/UIFilmPanel.checkShowNoCamera:()Z
       7: ifne          47
      10: aload_0
      11: getfield      #94                 // Field panel:Lmchorse/bbs_mod/ui/film/UIFilmPanel;
      14: getfield      #935                // Field mchorse/bbs_mod/ui/film/UIFilmPanel.dashboard:Lmchorse/bbs_mod/ui/dashboard/UIDashboard;
      17: invokevirtual #1944               // Method mchorse/bbs_mod/ui/dashboard/UIDashboard.closeThisMenu:()V
      20: aload_0
      21: getfield      #94                 // Field panel:Lmchorse/bbs_mod/ui/film/UIFilmPanel;
      24: invokevirtual #730                // Method mchorse/bbs_mod/ui/film/UIFilmPanel.getData:()Lmchorse/bbs_mod/settings/values/core/ValueGroup;
      27: ifnull        47
      30: aload_0
      31: getfield      #94                 // Field panel:Lmchorse/bbs_mod/ui/film/UIFilmPanel;
      34: invokevirtual #730                // Method mchorse/bbs_mod/ui/film/UIFilmPanel.getData:()Lmchorse/bbs_mod/settings/values/core/ValueGroup;
      37: checkcast     #732                // class mchorse/bbs_mod/film/Film
      40: invokevirtual #1947               // Method mchorse/bbs_mod/film/Film.getId:()Ljava/lang/String;
      43: iconst_1
      44: invokestatic  #1953               // Method mchorse/bbs_mod/film/Films.playFilm:(Ljava/lang/String;Z)V
      47: return

  private void lambda$new$10(mchorse.bbs_mod.ui.framework.elements.buttons.UIIcon);
    Code:
       0: aload_0
       1: getfield      #94                 // Field panel:Lmchorse/bbs_mod/ui/film/UIFilmPanel;
       4: invokevirtual #1956               // Method mchorse/bbs_mod/ui/film/UIFilmPanel.togglePlayback:()V
       7: return

  private mchorse.bbs_mod.ui.utils.icons.Icon lambda$new$9();
    Code:
       0: aload_0
       1: getfield      #94                 // Field panel:Lmchorse/bbs_mod/ui/film/UIFilmPanel;
       4: invokevirtual #1957               // Method mchorse/bbs_mod/ui/film/UIFilmPanel.isRunning:()Z
       7: ifeq          16
      10: getstatic     #1925               // Field mchorse/bbs_mod/ui/utils/icons/Icons.PAUSE:Lmchorse/bbs_mod/ui/utils/icons/Icon;
      13: goto          19
      16: getstatic     #1914               // Field mchorse/bbs_mod/ui/utils/icons/Icons.PLAY:Lmchorse/bbs_mod/ui/utils/icons/Icon;
      19: areturn

  private static void lambda$new$8(mchorse.bbs_mod.ui.framework.elements.buttons.UIIcon);
    Code:
       0: invokestatic  #1959               // Method mchorse/bbs_mod/client/BBSRendering.toggleShaders:()V
       3: return

  private static void lambda$new$7(mchorse.bbs_mod.ui.framework.elements.buttons.UIIcon);
    Code:
       0: getstatic     #1174               // Field mchorse/bbs_mod/BBSSettings.editorFilmOverlayVisible:Lmchorse/bbs_mod/settings/values/numeric/ValueBoolean;
       3: getstatic     #1174               // Field mchorse/bbs_mod/BBSSettings.editorFilmOverlayVisible:Lmchorse/bbs_mod/settings/values/numeric/ValueBoolean;
       6: invokevirtual #774                // Method mchorse/bbs_mod/settings/values/numeric/ValueBoolean.get:()Ljava/lang/Object;
       9: checkcast     #776                // class java/lang/Boolean
      12: invokevirtual #779                // Method java/lang/Boolean.booleanValue:()Z
      15: ifne          22
      18: iconst_1
      19: goto          23
      22: iconst_0
      23: invokestatic  #1072               // Method java/lang/Boolean.valueOf:(Z)Ljava/lang/Boolean;
      26: invokevirtual #1074               // Method mchorse/bbs_mod/settings/values/numeric/ValueBoolean.set:(Ljava/lang/Object;)V
      29: return

  private mchorse.bbs_mod.ui.utils.icons.Icon lambda$new$6();
    Code:
       0: getstatic     #1174               // Field mchorse/bbs_mod/BBSSettings.editorFilmOverlayVisible:Lmchorse/bbs_mod/settings/values/numeric/ValueBoolean;
       3: invokevirtual #774                // Method mchorse/bbs_mod/settings/values/numeric/ValueBoolean.get:()Ljava/lang/Object;
       6: checkcast     #776                // class java/lang/Boolean
       9: invokevirtual #779                // Method java/lang/Boolean.booleanValue:()Z
      12: ifeq          28
      15: aload_0
      16: getfield      #664                // Field viewportButtonsHidden:Z
      19: ifne          28
      22: getstatic     #1962               // Field mchorse/bbs_mod/ui/utils/icons/Icons.VISIBLE:Lmchorse/bbs_mod/ui/utils/icons/Icon;
      25: goto          31
      28: getstatic     #1965               // Field mchorse/bbs_mod/ui/utils/icons/Icons.INVISIBLE:Lmchorse/bbs_mod/ui/utils/icons/Icon;
      31: areturn

  private void lambda$new$5(mchorse.bbs_mod.ui.framework.elements.buttons.UIIcon);
    Code:
       0: aload_0
       1: invokevirtual #1967               // Method openOnionSkin:()V
       4: return

  private static void lambda$new$4();
    Code:
       0: getstatic     #993                // Field mchorse/bbs_mod/ui/utils/Gizmo.INSTANCE:Lmchorse/bbs_mod/ui/utils/Gizmo;
       3: getstatic     #186                // Field mchorse/bbs_mod/ui/utils/Gizmo$Mode.TOP:Lmchorse/bbs_mod/ui/utils/Gizmo$Mode;
       6: invokevirtual #1535               // Method mchorse/bbs_mod/ui/utils/Gizmo.setMode:(Lmchorse/bbs_mod/ui/utils/Gizmo$Mode;)Z
       9: pop
      10: invokestatic  #1540               // Method mchorse/bbs_mod/ui/utils/UIUtils.playClick:()V
      13: return

  private static void lambda$new$3();
    Code:
       0: getstatic     #993                // Field mchorse/bbs_mod/ui/utils/Gizmo.INSTANCE:Lmchorse/bbs_mod/ui/utils/Gizmo;
       3: getstatic     #175                // Field mchorse/bbs_mod/ui/utils/Gizmo$Mode.COMBINED:Lmchorse/bbs_mod/ui/utils/Gizmo$Mode;
       6: invokevirtual #1535               // Method mchorse/bbs_mod/ui/utils/Gizmo.setMode:(Lmchorse/bbs_mod/ui/utils/Gizmo$Mode;)Z
       9: pop
      10: invokestatic  #1540               // Method mchorse/bbs_mod/ui/utils/UIUtils.playClick:()V
      13: return

  private void lambda$new$2(mchorse.bbs_mod.settings.values.base.BaseValue, int);
    Code:
       0: aload_0
       1: invokevirtual #277                // Method rebuildGizmoToolbar:()V
       4: return

  private void lambda$new$1(mchorse.bbs_mod.ui.framework.elements.buttons.UIIcon);
    Code:
       0: aload_0
       1: invokevirtual #704                // Method getContext:()Lmchorse/bbs_mod/ui/framework/UIContext;
       4: new           #1969               // class mchorse/bbs_mod/ui/film/controller/UIGizmoTranslateSpeedContextMenu
       7: dup
       8: invokespecial #1970               // Method mchorse/bbs_mod/ui/film/controller/UIGizmoTranslateSpeedContextMenu."<init>":()V
      11: invokevirtual #719                // Method mchorse/bbs_mod/ui/framework/UIContext.replaceContextMenu:(Lmchorse/bbs_mod/ui/framework/elements/context/UIContextMenu;)V
      14: return

  private void lambda$new$0(mchorse.bbs_mod.ui.framework.elements.buttons.UIIcon);
    Code:
       0: aload_0
       1: invokevirtual #704                // Method getContext:()Lmchorse/bbs_mod/ui/framework/UIContext;
       4: new           #1972               // class mchorse/bbs_mod/ui/film/controller/UIGizmoSizeContextMenu
       7: dup
       8: invokespecial #1973               // Method mchorse/bbs_mod/ui/film/controller/UIGizmoSizeContextMenu."<init>":()V
      11: invokevirtual #719                // Method mchorse/bbs_mod/ui/framework/UIContext.replaceContextMenu:(Lmchorse/bbs_mod/ui/framework/elements/context/UIContextMenu;)V
      14: return

  static {};
    Code:
       0: new           #80                 // class java/util/ArrayList
       3: dup
       4: invokespecial #81                 // Method java/util/ArrayList."<init>":()V
       7: putstatic     #613                // Field extensions:Ljava/util/List;
      10: return
}
