Compiled from "UIKeyframes.java"
public class mchorse.bbs_mod.ui.framework.elements.input.keyframes.UIKeyframes extends mchorse.bbs_mod.ui.framework.elements.UIElement {
  private static final int RULER_HEIGHT;

  private boolean selecting;

  private boolean navigating;

  private int dragging;

  private mchorse.bbs_mod.utils.Pair<mchorse.bbs_mod.utils.keyframes.Keyframe, mchorse.bbs_mod.ui.framework.elements.input.keyframes.graphs.KeyframeType> draggingData;

  private boolean scaling;

  private float scalingAnchor;

  private java.util.Map<mchorse.bbs_mod.utils.keyframes.Keyframe, java.lang.Float> scaleTicks;

  private boolean single;

  private boolean stacking;

  private float stackOffset;

  private int lastX;

  private int lastY;

  private int originalX;

  private int originalY;

  private float originalT;

  private java.lang.Object originalV;

  private java.lang.Runnable changeCallback;

  protected final mchorse.bbs_mod.ui.framework.elements.input.keyframes.graphs.UIKeyframeDopeSheet dopeSheet;

  protected mchorse.bbs_mod.ui.framework.elements.input.keyframes.graphs.IUIKeyframeGraph currentGraph;

  private final mchorse.bbs_mod.ui.utils.Scale xAxis;

  private final java.util.function.Consumer<mchorse.bbs_mod.utils.keyframes.Keyframe> callback;

  private java.util.function.Consumer<mchorse.bbs_mod.ui.framework.UIContext> backgroundRender;

  private java.util.function.Supplier<java.lang.Integer> duration;

  private mchorse.bbs_mod.ui.framework.elements.input.keyframes.UIKeyframes$SheetCache cache;

  private mchorse.bbs_mod.ui.utils.presets.UICopyPasteController copyPasteController;

  private mchorse.bbs_mod.ui.framework.elements.utils.UIDraggable sidebarResizer;

  public mchorse.bbs_mod.ui.framework.elements.input.keyframes.UIKeyframes(java.util.function.Consumer<mchorse.bbs_mod.utils.keyframes.Keyframe>);
    Code:
       0: aload_0
       1: invokespecial #85                 // Method mchorse/bbs_mod/ui/framework/elements/UIElement."<init>":()V
       4: aload_0
       5: iconst_m1
       6: putfield      #87                 // Field dragging:I
       9: aload_0
      10: new           #89                 // class java/util/HashMap
      13: dup
      14: invokespecial #90                 // Method java/util/HashMap."<init>":()V
      17: putfield      #92                 // Field scaleTicks:Ljava/util/Map;
      20: aload_0
      21: new           #94                 // class mchorse/bbs_mod/ui/framework/elements/input/keyframes/graphs/UIKeyframeDopeSheet
      24: dup
      25: aload_0
      26: invokespecial #97                 // Method mchorse/bbs_mod/ui/framework/elements/input/keyframes/graphs/UIKeyframeDopeSheet."<init>":(Lmchorse/bbs_mod/ui/framework/elements/input/keyframes/UIKeyframes;)V
      29: putfield      #99                 // Field dopeSheet:Lmchorse/bbs_mod/ui/framework/elements/input/keyframes/graphs/UIKeyframeDopeSheet;
      32: aload_0
      33: aload_0
      34: getfield      #99                 // Field dopeSheet:Lmchorse/bbs_mod/ui/framework/elements/input/keyframes/graphs/UIKeyframeDopeSheet;
      37: putfield      #101                // Field currentGraph:Lmchorse/bbs_mod/ui/framework/elements/input/keyframes/graphs/IUIKeyframeGraph;
      40: aload_0
      41: new           #103                // class mchorse/bbs_mod/ui/utils/Scale
      44: dup
      45: aload_0
      46: getfield      #107                // Field area:Lmchorse/bbs_mod/ui/utils/Area;
      49: getstatic     #113                // Field mchorse/bbs_mod/ui/utils/ScrollDirection.HORIZONTAL:Lmchorse/bbs_mod/ui/utils/ScrollDirection;
      52: invokespecial #116                // Method mchorse/bbs_mod/ui/utils/Scale."<init>":(Lmchorse/bbs_mod/ui/utils/Area;Lmchorse/bbs_mod/ui/utils/ScrollDirection;)V
      55: putfield      #118                // Field xAxis:Lmchorse/bbs_mod/ui/utils/Scale;
      58: aload_0
      59: aload_1
      60: putfield      #120                // Field callback:Ljava/util/function/Consumer;
      63: aload_0
      64: new           #15                 // class mchorse/bbs_mod/ui/utils/presets/UICopyPasteController
      67: dup
      68: getstatic     #126                // Field mchorse/bbs_mod/utils/presets/PresetManager.KEYFRAMES:Lmchorse/bbs_mod/utils/presets/PresetManager;
      71: ldc           #128                // String _CopyKeyframes
      73: invokespecial #131                // Method mchorse/bbs_mod/ui/utils/presets/UICopyPasteController."<init>":(Lmchorse/bbs_mod/utils/presets/PresetManager;Ljava/lang/String;)V
      76: aload_0
      77: invokedynamic #150,  0            // InvokeDynamic #0:get:(Lmchorse/bbs_mod/ui/framework/elements/input/keyframes/UIKeyframes;)Ljava/util/function/Supplier;
      82: invokevirtual #154                // Method mchorse/bbs_mod/ui/utils/presets/UICopyPasteController.supplier:(Ljava/util/function/Supplier;)Lmchorse/bbs_mod/ui/utils/presets/UICopyPasteController;
      85: aload_0
      86: invokedynamic #164,  0            // InvokeDynamic #1:paste:(Lmchorse/bbs_mod/ui/framework/elements/input/keyframes/UIKeyframes;)Lmchorse/bbs_mod/ui/utils/presets/UICopyPasteController$IPaste;
      91: invokevirtual #168                // Method mchorse/bbs_mod/ui/utils/presets/UICopyPasteController.consumer:(Lmchorse/bbs_mod/ui/utils/presets/UICopyPasteController$IPaste;)Lmchorse/bbs_mod/ui/utils/presets/UICopyPasteController;
      94: aload_0
      95: invokedynamic #175,  0            // InvokeDynamic #2:get:(Lmchorse/bbs_mod/ui/framework/elements/input/keyframes/UIKeyframes;)Ljava/util/function/Supplier;
     100: invokevirtual #178                // Method mchorse/bbs_mod/ui/utils/presets/UICopyPasteController.canCopy:(Ljava/util/function/Supplier;)Lmchorse/bbs_mod/ui/utils/presets/UICopyPasteController;
     103: putfield      #180                // Field copyPasteController:Lmchorse/bbs_mod/ui/utils/presets/UICopyPasteController;
     106: aload_0
     107: aload_0
     108: invokedynamic #192,  0            // InvokeDynamic #3:accept:(Lmchorse/bbs_mod/ui/framework/elements/input/keyframes/UIKeyframes;)Ljava/util/function/Consumer;
     113: invokevirtual #196                // Method context:(Ljava/util/function/Consumer;)Lmchorse/bbs_mod/ui/framework/elements/UIElement;
     116: pop
     117: getstatic     #202                // Field mchorse/bbs_mod/ui/UIKeys.KEYFRAMES_KEYS_CATEGORY:Lmchorse/bbs_mod/l10n/keys/IKey;
     120: astore_2
     121: aload_0
     122: invokedynamic #207,  0            // InvokeDynamic #4:get:(Lmchorse/bbs_mod/ui/framework/elements/input/keyframes/UIKeyframes;)Ljava/util/function/Supplier;
     127: astore_3
     128: aload_0
     129: invokevirtual #211                // Method keys:()Lmchorse/bbs_mod/ui/utils/keys/KeybindManager;
     132: getstatic     #217                // Field mchorse/bbs_mod/ui/Keys.KEYFRAMES_MAXIMIZE:Lmchorse/bbs_mod/ui/utils/keys/KeyCombo;
     135: aload_0
     136: invokedynamic #226,  0            // InvokeDynamic #5:run:(Lmchorse/bbs_mod/ui/framework/elements/input/keyframes/UIKeyframes;)Ljava/lang/Runnable;
     141: invokevirtual #232                // Method mchorse/bbs_mod/ui/utils/keys/KeybindManager.register:(Lmchorse/bbs_mod/ui/utils/keys/KeyCombo;Ljava/lang/Runnable;)Lmchorse/bbs_mod/ui/utils/keys/Keybind;
     144: invokevirtual #238                // Method mchorse/bbs_mod/ui/utils/keys/Keybind.inside:()Lmchorse/bbs_mod/ui/utils/keys/Keybind;
     147: aload_2
     148: invokevirtual #242                // Method mchorse/bbs_mod/ui/utils/keys/Keybind.category:(Lmchorse/bbs_mod/l10n/keys/IKey;)Lmchorse/bbs_mod/ui/utils/keys/Keybind;
     151: pop
     152: aload_0
     153: invokevirtual #211                // Method keys:()Lmchorse/bbs_mod/ui/utils/keys/KeybindManager;
     156: getstatic     #245                // Field mchorse/bbs_mod/ui/Keys.KEYFRAMES_SELECT_ALL:Lmchorse/bbs_mod/ui/utils/keys/KeyCombo;
     159: aload_0
     160: invokedynamic #250,  0            // InvokeDynamic #6:run:(Lmchorse/bbs_mod/ui/framework/elements/input/keyframes/UIKeyframes;)Ljava/lang/Runnable;
     165: invokevirtual #232                // Method mchorse/bbs_mod/ui/utils/keys/KeybindManager.register:(Lmchorse/bbs_mod/ui/utils/keys/KeyCombo;Ljava/lang/Runnable;)Lmchorse/bbs_mod/ui/utils/keys/Keybind;
     168: invokevirtual #238                // Method mchorse/bbs_mod/ui/utils/keys/Keybind.inside:()Lmchorse/bbs_mod/ui/utils/keys/Keybind;
     171: aload_2
     172: invokevirtual #242                // Method mchorse/bbs_mod/ui/utils/keys/Keybind.category:(Lmchorse/bbs_mod/l10n/keys/IKey;)Lmchorse/bbs_mod/ui/utils/keys/Keybind;
     175: aload_3
     176: invokevirtual #254                // Method mchorse/bbs_mod/ui/utils/keys/Keybind.active:(Ljava/util/function/Supplier;)Lmchorse/bbs_mod/ui/utils/keys/Keybind;
     179: pop
     180: aload_0
     181: invokevirtual #211                // Method keys:()Lmchorse/bbs_mod/ui/utils/keys/KeybindManager;
     184: getstatic     #257                // Field mchorse/bbs_mod/ui/Keys.COPY:Lmchorse/bbs_mod/ui/utils/keys/KeyCombo;
     187: aload_0
     188: invokedynamic #262,  0            // InvokeDynamic #7:run:(Lmchorse/bbs_mod/ui/framework/elements/input/keyframes/UIKeyframes;)Ljava/lang/Runnable;
     193: invokevirtual #232                // Method mchorse/bbs_mod/ui/utils/keys/KeybindManager.register:(Lmchorse/bbs_mod/ui/utils/keys/KeyCombo;Ljava/lang/Runnable;)Lmchorse/bbs_mod/ui/utils/keys/Keybind;
     196: invokevirtual #238                // Method mchorse/bbs_mod/ui/utils/keys/Keybind.inside:()Lmchorse/bbs_mod/ui/utils/keys/Keybind;
     199: aload_2
     200: invokevirtual #242                // Method mchorse/bbs_mod/ui/utils/keys/Keybind.category:(Lmchorse/bbs_mod/l10n/keys/IKey;)Lmchorse/bbs_mod/ui/utils/keys/Keybind;
     203: pop
     204: aload_0
     205: invokevirtual #211                // Method keys:()Lmchorse/bbs_mod/ui/utils/keys/KeybindManager;
     208: getstatic     #265                // Field mchorse/bbs_mod/ui/Keys.CUT:Lmchorse/bbs_mod/ui/utils/keys/KeyCombo;
     211: aload_0
     212: invokedynamic #270,  0            // InvokeDynamic #8:run:(Lmchorse/bbs_mod/ui/framework/elements/input/keyframes/UIKeyframes;)Ljava/lang/Runnable;
     217: invokevirtual #232                // Method mchorse/bbs_mod/ui/utils/keys/KeybindManager.register:(Lmchorse/bbs_mod/ui/utils/keys/KeyCombo;Ljava/lang/Runnable;)Lmchorse/bbs_mod/ui/utils/keys/Keybind;
     220: invokevirtual #238                // Method mchorse/bbs_mod/ui/utils/keys/Keybind.inside:()Lmchorse/bbs_mod/ui/utils/keys/Keybind;
     223: aload_2
     224: invokevirtual #242                // Method mchorse/bbs_mod/ui/utils/keys/Keybind.category:(Lmchorse/bbs_mod/l10n/keys/IKey;)Lmchorse/bbs_mod/ui/utils/keys/Keybind;
     227: aload_3
     228: invokevirtual #254                // Method mchorse/bbs_mod/ui/utils/keys/Keybind.active:(Ljava/util/function/Supplier;)Lmchorse/bbs_mod/ui/utils/keys/Keybind;
     231: pop
     232: aload_0
     233: invokevirtual #211                // Method keys:()Lmchorse/bbs_mod/ui/utils/keys/KeybindManager;
     236: getstatic     #273                // Field mchorse/bbs_mod/ui/Keys.PASTE:Lmchorse/bbs_mod/ui/utils/keys/KeyCombo;
     239: aload_0
     240: invokedynamic #278,  0            // InvokeDynamic #9:run:(Lmchorse/bbs_mod/ui/framework/elements/input/keyframes/UIKeyframes;)Ljava/lang/Runnable;
     245: invokevirtual #232                // Method mchorse/bbs_mod/ui/utils/keys/KeybindManager.register:(Lmchorse/bbs_mod/ui/utils/keys/KeyCombo;Ljava/lang/Runnable;)Lmchorse/bbs_mod/ui/utils/keys/Keybind;
     248: invokevirtual #238                // Method mchorse/bbs_mod/ui/utils/keys/Keybind.inside:()Lmchorse/bbs_mod/ui/utils/keys/Keybind;
     251: aload_2
     252: invokevirtual #242                // Method mchorse/bbs_mod/ui/utils/keys/Keybind.category:(Lmchorse/bbs_mod/l10n/keys/IKey;)Lmchorse/bbs_mod/ui/utils/keys/Keybind;
     255: aload_3
     256: invokevirtual #254                // Method mchorse/bbs_mod/ui/utils/keys/Keybind.active:(Ljava/util/function/Supplier;)Lmchorse/bbs_mod/ui/utils/keys/Keybind;
     259: pop
     260: aload_0
     261: invokevirtual #211                // Method keys:()Lmchorse/bbs_mod/ui/utils/keys/KeybindManager;
     264: getstatic     #281                // Field mchorse/bbs_mod/ui/Keys.PRESETS:Lmchorse/bbs_mod/ui/utils/keys/KeyCombo;
     267: aload_0
     268: invokedynamic #286,  0            // InvokeDynamic #10:run:(Lmchorse/bbs_mod/ui/framework/elements/input/keyframes/UIKeyframes;)Ljava/lang/Runnable;
     273: invokevirtual #232                // Method mchorse/bbs_mod/ui/utils/keys/KeybindManager.register:(Lmchorse/bbs_mod/ui/utils/keys/KeyCombo;Ljava/lang/Runnable;)Lmchorse/bbs_mod/ui/utils/keys/Keybind;
     276: aload_2
     277: invokevirtual #242                // Method mchorse/bbs_mod/ui/utils/keys/Keybind.category:(Lmchorse/bbs_mod/l10n/keys/IKey;)Lmchorse/bbs_mod/ui/utils/keys/Keybind;
     280: aload_3
     281: invokevirtual #254                // Method mchorse/bbs_mod/ui/utils/keys/Keybind.active:(Ljava/util/function/Supplier;)Lmchorse/bbs_mod/ui/utils/keys/Keybind;
     284: pop
     285: aload_0
     286: invokevirtual #211                // Method keys:()Lmchorse/bbs_mod/ui/utils/keys/KeybindManager;
     289: getstatic     #289                // Field mchorse/bbs_mod/ui/Keys.DELETE:Lmchorse/bbs_mod/ui/utils/keys/KeyCombo;
     292: aload_0
     293: invokedynamic #294,  0            // InvokeDynamic #11:run:(Lmchorse/bbs_mod/ui/framework/elements/input/keyframes/UIKeyframes;)Ljava/lang/Runnable;
     298: invokevirtual #232                // Method mchorse/bbs_mod/ui/utils/keys/KeybindManager.register:(Lmchorse/bbs_mod/ui/utils/keys/KeyCombo;Ljava/lang/Runnable;)Lmchorse/bbs_mod/ui/utils/keys/Keybind;
     301: invokevirtual #238                // Method mchorse/bbs_mod/ui/utils/keys/Keybind.inside:()Lmchorse/bbs_mod/ui/utils/keys/Keybind;
     304: aload_2
     305: invokevirtual #242                // Method mchorse/bbs_mod/ui/utils/keys/Keybind.category:(Lmchorse/bbs_mod/l10n/keys/IKey;)Lmchorse/bbs_mod/ui/utils/keys/Keybind;
     308: aload_3
     309: invokevirtual #254                // Method mchorse/bbs_mod/ui/utils/keys/Keybind.active:(Ljava/util/function/Supplier;)Lmchorse/bbs_mod/ui/utils/keys/Keybind;
     312: pop
     313: aload_0
     314: invokevirtual #211                // Method keys:()Lmchorse/bbs_mod/ui/utils/keys/KeybindManager;
     317: getstatic     #297                // Field mchorse/bbs_mod/ui/Keys.KEYFRAMES_SELECT_LEFT:Lmchorse/bbs_mod/ui/utils/keys/KeyCombo;
     320: aload_0
     321: invokedynamic #302,  0            // InvokeDynamic #12:run:(Lmchorse/bbs_mod/ui/framework/elements/input/keyframes/UIKeyframes;)Ljava/lang/Runnable;
     326: invokevirtual #232                // Method mchorse/bbs_mod/ui/utils/keys/KeybindManager.register:(Lmchorse/bbs_mod/ui/utils/keys/KeyCombo;Ljava/lang/Runnable;)Lmchorse/bbs_mod/ui/utils/keys/Keybind;
     329: aload_2
     330: invokevirtual #242                // Method mchorse/bbs_mod/ui/utils/keys/Keybind.category:(Lmchorse/bbs_mod/l10n/keys/IKey;)Lmchorse/bbs_mod/ui/utils/keys/Keybind;
     333: aload_3
     334: invokevirtual #254                // Method mchorse/bbs_mod/ui/utils/keys/Keybind.active:(Ljava/util/function/Supplier;)Lmchorse/bbs_mod/ui/utils/keys/Keybind;
     337: pop
     338: aload_0
     339: invokevirtual #211                // Method keys:()Lmchorse/bbs_mod/ui/utils/keys/KeybindManager;
     342: getstatic     #305                // Field mchorse/bbs_mod/ui/Keys.KEYFRAMES_SELECT_RIGHT:Lmchorse/bbs_mod/ui/utils/keys/KeyCombo;
     345: aload_0
     346: invokedynamic #310,  0            // InvokeDynamic #13:run:(Lmchorse/bbs_mod/ui/framework/elements/input/keyframes/UIKeyframes;)Ljava/lang/Runnable;
     351: invokevirtual #232                // Method mchorse/bbs_mod/ui/utils/keys/KeybindManager.register:(Lmchorse/bbs_mod/ui/utils/keys/KeyCombo;Ljava/lang/Runnable;)Lmchorse/bbs_mod/ui/utils/keys/Keybind;
     354: aload_2
     355: invokevirtual #242                // Method mchorse/bbs_mod/ui/utils/keys/Keybind.category:(Lmchorse/bbs_mod/l10n/keys/IKey;)Lmchorse/bbs_mod/ui/utils/keys/Keybind;
     358: aload_3
     359: invokevirtual #254                // Method mchorse/bbs_mod/ui/utils/keys/Keybind.active:(Ljava/util/function/Supplier;)Lmchorse/bbs_mod/ui/utils/keys/Keybind;
     362: pop
     363: aload_0
     364: invokevirtual #211                // Method keys:()Lmchorse/bbs_mod/ui/utils/keys/KeybindManager;
     367: getstatic     #313                // Field mchorse/bbs_mod/ui/Keys.KEYFRAMES_SELECT_SAME:Lmchorse/bbs_mod/ui/utils/keys/KeyCombo;
     370: aload_0
     371: invokedynamic #318,  0            // InvokeDynamic #14:run:(Lmchorse/bbs_mod/ui/framework/elements/input/keyframes/UIKeyframes;)Ljava/lang/Runnable;
     376: invokevirtual #232                // Method mchorse/bbs_mod/ui/utils/keys/KeybindManager.register:(Lmchorse/bbs_mod/ui/utils/keys/KeyCombo;Ljava/lang/Runnable;)Lmchorse/bbs_mod/ui/utils/keys/Keybind;
     379: invokevirtual #238                // Method mchorse/bbs_mod/ui/utils/keys/Keybind.inside:()Lmchorse/bbs_mod/ui/utils/keys/Keybind;
     382: aload_2
     383: invokevirtual #242                // Method mchorse/bbs_mod/ui/utils/keys/Keybind.category:(Lmchorse/bbs_mod/l10n/keys/IKey;)Lmchorse/bbs_mod/ui/utils/keys/Keybind;
     386: aload_3
     387: invokevirtual #254                // Method mchorse/bbs_mod/ui/utils/keys/Keybind.active:(Ljava/util/function/Supplier;)Lmchorse/bbs_mod/ui/utils/keys/Keybind;
     390: pop
     391: aload_0
     392: invokevirtual #211                // Method keys:()Lmchorse/bbs_mod/ui/utils/keys/KeybindManager;
     395: getstatic     #321                // Field mchorse/bbs_mod/ui/Keys.KEYFRAMES_SCALE_TIME:Lmchorse/bbs_mod/ui/utils/keys/KeyCombo;
     398: aload_0
     399: invokedynamic #326,  0            // InvokeDynamic #15:run:(Lmchorse/bbs_mod/ui/framework/elements/input/keyframes/UIKeyframes;)Ljava/lang/Runnable;
     404: invokevirtual #232                // Method mchorse/bbs_mod/ui/utils/keys/KeybindManager.register:(Lmchorse/bbs_mod/ui/utils/keys/KeyCombo;Ljava/lang/Runnable;)Lmchorse/bbs_mod/ui/utils/keys/Keybind;
     407: invokevirtual #238                // Method mchorse/bbs_mod/ui/utils/keys/Keybind.inside:()Lmchorse/bbs_mod/ui/utils/keys/Keybind;
     410: aload_2
     411: invokevirtual #242                // Method mchorse/bbs_mod/ui/utils/keys/Keybind.category:(Lmchorse/bbs_mod/l10n/keys/IKey;)Lmchorse/bbs_mod/ui/utils/keys/Keybind;
     414: pop
     415: aload_0
     416: invokevirtual #211                // Method keys:()Lmchorse/bbs_mod/ui/utils/keys/KeybindManager;
     419: getstatic     #329                // Field mchorse/bbs_mod/ui/Keys.KEYFRAMES_STACK_KEYFRAMES:Lmchorse/bbs_mod/ui/utils/keys/KeyCombo;
     422: aload_0
     423: invokedynamic #334,  0            // InvokeDynamic #16:run:(Lmchorse/bbs_mod/ui/framework/elements/input/keyframes/UIKeyframes;)Ljava/lang/Runnable;
     428: invokevirtual #232                // Method mchorse/bbs_mod/ui/utils/keys/KeybindManager.register:(Lmchorse/bbs_mod/ui/utils/keys/KeyCombo;Ljava/lang/Runnable;)Lmchorse/bbs_mod/ui/utils/keys/Keybind;
     431: invokevirtual #238                // Method mchorse/bbs_mod/ui/utils/keys/Keybind.inside:()Lmchorse/bbs_mod/ui/utils/keys/Keybind;
     434: aload_2
     435: invokevirtual #242                // Method mchorse/bbs_mod/ui/utils/keys/Keybind.category:(Lmchorse/bbs_mod/l10n/keys/IKey;)Lmchorse/bbs_mod/ui/utils/keys/Keybind;
     438: pop
     439: aload_0
     440: invokevirtual #211                // Method keys:()Lmchorse/bbs_mod/ui/utils/keys/KeybindManager;
     443: getstatic     #337                // Field mchorse/bbs_mod/ui/Keys.KEYFRAMES_SELECT_PREV:Lmchorse/bbs_mod/ui/utils/keys/KeyCombo;
     446: aload_0
     447: invokedynamic #342,  0            // InvokeDynamic #17:run:(Lmchorse/bbs_mod/ui/framework/elements/input/keyframes/UIKeyframes;)Ljava/lang/Runnable;
     452: invokevirtual #232                // Method mchorse/bbs_mod/ui/utils/keys/KeybindManager.register:(Lmchorse/bbs_mod/ui/utils/keys/KeyCombo;Ljava/lang/Runnable;)Lmchorse/bbs_mod/ui/utils/keys/Keybind;
     455: invokevirtual #238                // Method mchorse/bbs_mod/ui/utils/keys/Keybind.inside:()Lmchorse/bbs_mod/ui/utils/keys/Keybind;
     458: aload_2
     459: invokevirtual #242                // Method mchorse/bbs_mod/ui/utils/keys/Keybind.category:(Lmchorse/bbs_mod/l10n/keys/IKey;)Lmchorse/bbs_mod/ui/utils/keys/Keybind;
     462: pop
     463: aload_0
     464: invokevirtual #211                // Method keys:()Lmchorse/bbs_mod/ui/utils/keys/KeybindManager;
     467: getstatic     #345                // Field mchorse/bbs_mod/ui/Keys.KEYFRAMES_SELECT_NEXT:Lmchorse/bbs_mod/ui/utils/keys/KeyCombo;
     470: aload_0
     471: invokedynamic #350,  0            // InvokeDynamic #18:run:(Lmchorse/bbs_mod/ui/framework/elements/input/keyframes/UIKeyframes;)Ljava/lang/Runnable;
     476: invokevirtual #232                // Method mchorse/bbs_mod/ui/utils/keys/KeybindManager.register:(Lmchorse/bbs_mod/ui/utils/keys/KeyCombo;Ljava/lang/Runnable;)Lmchorse/bbs_mod/ui/utils/keys/Keybind;
     479: invokevirtual #238                // Method mchorse/bbs_mod/ui/utils/keys/Keybind.inside:()Lmchorse/bbs_mod/ui/utils/keys/Keybind;
     482: aload_2
     483: invokevirtual #242                // Method mchorse/bbs_mod/ui/utils/keys/Keybind.category:(Lmchorse/bbs_mod/l10n/keys/IKey;)Lmchorse/bbs_mod/ui/utils/keys/Keybind;
     486: pop
     487: aload_0
     488: invokevirtual #211                // Method keys:()Lmchorse/bbs_mod/ui/utils/keys/KeybindManager;
     491: getstatic     #353                // Field mchorse/bbs_mod/ui/Keys.KEYFRAMES_SPREAD:Lmchorse/bbs_mod/ui/utils/keys/KeyCombo;
     494: aload_0
     495: invokedynamic #358,  0            // InvokeDynamic #19:run:(Lmchorse/bbs_mod/ui/framework/elements/input/keyframes/UIKeyframes;)Ljava/lang/Runnable;
     500: invokevirtual #232                // Method mchorse/bbs_mod/ui/utils/keys/KeybindManager.register:(Lmchorse/bbs_mod/ui/utils/keys/KeyCombo;Ljava/lang/Runnable;)Lmchorse/bbs_mod/ui/utils/keys/Keybind;
     503: aload_2
     504: invokevirtual #242                // Method mchorse/bbs_mod/ui/utils/keys/Keybind.category:(Lmchorse/bbs_mod/l10n/keys/IKey;)Lmchorse/bbs_mod/ui/utils/keys/Keybind;
     507: pop
     508: aload_0
     509: invokevirtual #211                // Method keys:()Lmchorse/bbs_mod/ui/utils/keys/KeybindManager;
     512: getstatic     #361                // Field mchorse/bbs_mod/ui/Keys.KEYFRAMES_ADJUST_VALUES:Lmchorse/bbs_mod/ui/utils/keys/KeyCombo;
     515: aload_0
     516: invokedynamic #366,  0            // InvokeDynamic #20:run:(Lmchorse/bbs_mod/ui/framework/elements/input/keyframes/UIKeyframes;)Ljava/lang/Runnable;
     521: invokevirtual #232                // Method mchorse/bbs_mod/ui/utils/keys/KeybindManager.register:(Lmchorse/bbs_mod/ui/utils/keys/KeyCombo;Ljava/lang/Runnable;)Lmchorse/bbs_mod/ui/utils/keys/Keybind;
     524: aload_2
     525: invokevirtual #242                // Method mchorse/bbs_mod/ui/utils/keys/Keybind.category:(Lmchorse/bbs_mod/l10n/keys/IKey;)Lmchorse/bbs_mod/ui/utils/keys/Keybind;
     528: pop
     529: aload_0
     530: invokedynamic #372,  0            // InvokeDynamic #21:get:(Lmchorse/bbs_mod/ui/framework/elements/input/keyframes/UIKeyframes;)Ljava/util/function/Supplier;
     535: astore        4
     537: aload_0
     538: invokevirtual #211                // Method keys:()Lmchorse/bbs_mod/ui/utils/keys/KeybindManager;
     541: getstatic     #375                // Field mchorse/bbs_mod/ui/Keys.POSE_LIMB_KEYFRAME:Lmchorse/bbs_mod/ui/utils/keys/KeyCombo;
     544: aload_0
     545: invokedynamic #380,  0            // InvokeDynamic #22:run:(Lmchorse/bbs_mod/ui/framework/elements/input/keyframes/UIKeyframes;)Ljava/lang/Runnable;
     550: invokevirtual #232                // Method mchorse/bbs_mod/ui/utils/keys/KeybindManager.register:(Lmchorse/bbs_mod/ui/utils/keys/KeyCombo;Ljava/lang/Runnable;)Lmchorse/bbs_mod/ui/utils/keys/Keybind;
     553: invokevirtual #238                // Method mchorse/bbs_mod/ui/utils/keys/Keybind.inside:()Lmchorse/bbs_mod/ui/utils/keys/Keybind;
     556: getstatic     #383                // Field mchorse/bbs_mod/ui/UIKeys.POSE_LIMB_KEYS_CATEGORY:Lmchorse/bbs_mod/l10n/keys/IKey;
     559: invokevirtual #242                // Method mchorse/bbs_mod/ui/utils/keys/Keybind.category:(Lmchorse/bbs_mod/l10n/keys/IKey;)Lmchorse/bbs_mod/ui/utils/keys/Keybind;
     562: aload         4
     564: invokevirtual #254                // Method mchorse/bbs_mod/ui/utils/keys/Keybind.active:(Ljava/util/function/Supplier;)Lmchorse/bbs_mod/ui/utils/keys/Keybind;
     567: pop
     568: aload_0
     569: invokevirtual #211                // Method keys:()Lmchorse/bbs_mod/ui/utils/keys/KeybindManager;
     572: getstatic     #386                // Field mchorse/bbs_mod/ui/Keys.POSE_LIMB_KEYFRAME_DEFAULT:Lmchorse/bbs_mod/ui/utils/keys/KeyCombo;
     575: aload_0
     576: invokedynamic #391,  0            // InvokeDynamic #23:run:(Lmchorse/bbs_mod/ui/framework/elements/input/keyframes/UIKeyframes;)Ljava/lang/Runnable;
     581: invokevirtual #232                // Method mchorse/bbs_mod/ui/utils/keys/KeybindManager.register:(Lmchorse/bbs_mod/ui/utils/keys/KeyCombo;Ljava/lang/Runnable;)Lmchorse/bbs_mod/ui/utils/keys/Keybind;
     584: invokevirtual #238                // Method mchorse/bbs_mod/ui/utils/keys/Keybind.inside:()Lmchorse/bbs_mod/ui/utils/keys/Keybind;
     587: getstatic     #383                // Field mchorse/bbs_mod/ui/UIKeys.POSE_LIMB_KEYS_CATEGORY:Lmchorse/bbs_mod/l10n/keys/IKey;
     590: invokevirtual #242                // Method mchorse/bbs_mod/ui/utils/keys/Keybind.category:(Lmchorse/bbs_mod/l10n/keys/IKey;)Lmchorse/bbs_mod/ui/utils/keys/Keybind;
     593: aload         4
     595: invokevirtual #254                // Method mchorse/bbs_mod/ui/utils/keys/Keybind.active:(Ljava/util/function/Supplier;)Lmchorse/bbs_mod/ui/utils/keys/Keybind;
     598: pop
     599: aload_0
     600: new           #11                 // class mchorse/bbs_mod/ui/framework/elements/input/keyframes/UIKeyframes$1
     603: dup
     604: aload_0
     605: aload_0
     606: invokedynamic #398,  0            // InvokeDynamic #24:accept:(Lmchorse/bbs_mod/ui/framework/elements/input/keyframes/UIKeyframes;)Ljava/util/function/Consumer;
     611: invokespecial #401                // Method mchorse/bbs_mod/ui/framework/elements/input/keyframes/UIKeyframes$1."<init>":(Lmchorse/bbs_mod/ui/framework/elements/input/keyframes/UIKeyframes;Ljava/util/function/Consumer;)V
     614: aload_0
     615: invokedynamic #406,  0            // InvokeDynamic #25:accept:(Lmchorse/bbs_mod/ui/framework/elements/input/keyframes/UIKeyframes;)Ljava/util/function/Consumer;
     620: invokevirtual #410                // Method mchorse/bbs_mod/ui/framework/elements/input/keyframes/UIKeyframes$1.rendering:(Ljava/util/function/Consumer;)Lmchorse/bbs_mod/ui/framework/elements/utils/UIDraggable;
     623: putfield      #412                // Field sidebarResizer:Lmchorse/bbs_mod/ui/framework/elements/utils/UIDraggable;
     626: aload_0
     627: aload_0
     628: getfield      #412                // Field sidebarResizer:Lmchorse/bbs_mod/ui/framework/elements/utils/UIDraggable;
     631: invokevirtual #416                // Method add:(Lmchorse/bbs_mod/ui/framework/elements/IUIElement;)V
     634: aload_0
     635: invokevirtual #419                // Method updateSidebarResizerState:()V
     638: return

  public mchorse.bbs_mod.ui.framework.elements.input.keyframes.UIKeyframes single();
    Code:
       0: aload_0
       1: iconst_1
       2: putfield      #427                // Field single:Z
       5: aload_0
       6: areturn

  private void adjustValues();
    Code:
       0: aload_0
       1: invokevirtual #431                // Method getContext:()Lmchorse/bbs_mod/ui/framework/UIContext;
       4: aload_0
       5: invokedynamic #436,  0            // InvokeDynamic #26:accept:(Lmchorse/bbs_mod/ui/framework/elements/input/keyframes/UIKeyframes;)Ljava/util/function/Consumer;
      10: invokevirtual #441                // Method mchorse/bbs_mod/ui/framework/UIContext.replaceContextMenu:(Ljava/util/function/Consumer;)V
      13: return

  private void interpolationMenu();
    Code:
       0: aload_0
       1: invokevirtual #431                // Method getContext:()Lmchorse/bbs_mod/ui/framework/UIContext;
       4: aload_0
       5: invokedynamic #447,  0            // InvokeDynamic #27:accept:(Lmchorse/bbs_mod/ui/framework/elements/input/keyframes/UIKeyframes;)Ljava/util/function/Consumer;
      10: invokevirtual #441                // Method mchorse/bbs_mod/ui/framework/UIContext.replaceContextMenu:(Ljava/util/function/Consumer;)V
      13: return

  private void setInterpolation(mchorse.bbs_mod.utils.interps.IInterp);
    Code:
       0: aload_0
       1: invokevirtual #454                // Method getGraph:()Lmchorse/bbs_mod/ui/framework/elements/input/keyframes/graphs/IUIKeyframeGraph;
       4: invokeinterface #460,  1          // InterfaceMethod mchorse/bbs_mod/ui/framework/elements/input/keyframes/graphs/IUIKeyframeGraph.getSheets:()Ljava/util/List;
       9: invokeinterface #466,  1          // InterfaceMethod java/util/List.iterator:()Ljava/util/Iterator;
      14: astore_2
      15: aload_2
      16: invokeinterface #471,  1          // InterfaceMethod java/util/Iterator.hasNext:()Z
      21: ifeq          116
      24: aload_2
      25: invokeinterface #474,  1          // InterfaceMethod java/util/Iterator.next:()Ljava/lang/Object;
      30: checkcast     #476                // class mchorse/bbs_mod/ui/framework/elements/input/keyframes/UIKeyframeSheet
      33: astore_3
      34: aload_3
      35: getfield      #480                // Field mchorse/bbs_mod/ui/framework/elements/input/keyframes/UIKeyframeSheet.selection:Lmchorse/bbs_mod/ui/framework/elements/input/keyframes/KeyframeSelection;
      38: invokevirtual #485                // Method mchorse/bbs_mod/ui/framework/elements/input/keyframes/KeyframeSelection.getSelected:()Ljava/util/List;
      41: astore        4
      43: aload         4
      45: invokeinterface #488,  1          // InterfaceMethod java/util/List.isEmpty:()Z
      50: ifeq          56
      53: goto          15
      56: aload_3
      57: getfield      #492                // Field mchorse/bbs_mod/ui/framework/elements/input/keyframes/UIKeyframeSheet.channel:Lmchorse/bbs_mod/utils/keyframes/KeyframeChannel;
      60: invokevirtual #497                // Method mchorse/bbs_mod/utils/keyframes/KeyframeChannel.preNotify:()V
      63: aload         4
      65: invokeinterface #466,  1          // InterfaceMethod java/util/List.iterator:()Ljava/util/Iterator;
      70: astore        5
      72: aload         5
      74: invokeinterface #471,  1          // InterfaceMethod java/util/Iterator.hasNext:()Z
      79: ifeq          106
      82: aload         5
      84: invokeinterface #474,  1          // InterfaceMethod java/util/Iterator.next:()Ljava/lang/Object;
      89: checkcast     #499                // class mchorse/bbs_mod/utils/keyframes/Keyframe
      92: astore        6
      94: aload         6
      96: invokevirtual #503                // Method mchorse/bbs_mod/utils/keyframes/Keyframe.getInterpolation:()Lmchorse/bbs_mod/utils/interps/Interpolation;
      99: aload_1
     100: invokevirtual #508                // Method mchorse/bbs_mod/utils/interps/Interpolation.setInterp:(Lmchorse/bbs_mod/utils/interps/IInterp;)V
     103: goto          72
     106: aload_3
     107: getfield      #492                // Field mchorse/bbs_mod/ui/framework/elements/input/keyframes/UIKeyframeSheet.channel:Lmchorse/bbs_mod/utils/keyframes/KeyframeChannel;
     110: invokevirtual #511                // Method mchorse/bbs_mod/utils/keyframes/KeyframeChannel.postNotify:()V
     113: goto          15
     116: return

  private void adjustValues(boolean);
    Code:
       0: aload_0
       1: invokevirtual #454                // Method getGraph:()Lmchorse/bbs_mod/ui/framework/elements/input/keyframes/graphs/IUIKeyframeGraph;
       4: invokeinterface #460,  1          // InterfaceMethod mchorse/bbs_mod/ui/framework/elements/input/keyframes/graphs/IUIKeyframeGraph.getSheets:()Ljava/util/List;
       9: invokeinterface #466,  1          // InterfaceMethod java/util/List.iterator:()Ljava/util/Iterator;
      14: astore_2
      15: aload_2
      16: invokeinterface #471,  1          // InterfaceMethod java/util/Iterator.hasNext:()Z
      21: ifeq          255
      24: aload_2
      25: invokeinterface #474,  1          // InterfaceMethod java/util/Iterator.next:()Ljava/lang/Object;
      30: checkcast     #476                // class mchorse/bbs_mod/ui/framework/elements/input/keyframes/UIKeyframeSheet
      33: astore_3
      34: aload_3
      35: getfield      #480                // Field mchorse/bbs_mod/ui/framework/elements/input/keyframes/UIKeyframeSheet.selection:Lmchorse/bbs_mod/ui/framework/elements/input/keyframes/KeyframeSelection;
      38: invokevirtual #485                // Method mchorse/bbs_mod/ui/framework/elements/input/keyframes/KeyframeSelection.getSelected:()Ljava/util/List;
      41: astore        4
      43: aload_3
      44: getfield      #492                // Field mchorse/bbs_mod/ui/framework/elements/input/keyframes/UIKeyframeSheet.channel:Lmchorse/bbs_mod/utils/keyframes/KeyframeChannel;
      47: invokevirtual #525                // Method mchorse/bbs_mod/utils/keyframes/KeyframeChannel.getFactory:()Lmchorse/bbs_mod/utils/keyframes/factories/IKeyframeFactory;
      50: astore        5
      52: aload         4
      54: invokeinterface #529,  1          // InterfaceMethod java/util/List.size:()I
      59: iconst_2
      60: if_icmplt     15
      63: aload         5
      65: invokestatic  #535                // Method mchorse/bbs_mod/utils/keyframes/factories/KeyframeFactories.isNumeric:(Lmchorse/bbs_mod/utils/keyframes/factories/IKeyframeFactory;)Z
      68: ifne          74
      71: goto          15
      74: aload_3
      75: getfield      #492                // Field mchorse/bbs_mod/ui/framework/elements/input/keyframes/UIKeyframeSheet.channel:Lmchorse/bbs_mod/utils/keyframes/KeyframeChannel;
      78: invokevirtual #497                // Method mchorse/bbs_mod/utils/keyframes/KeyframeChannel.preNotify:()V
      81: iload_1
      82: ifeq          97
      85: aload         4
      87: invokeinterface #529,  1          // InterfaceMethod java/util/List.size:()I
      92: iconst_1
      93: isub
      94: goto          98
      97: iconst_0
      98: istore        6
     100: iload_1
     101: ifeq          116
     104: aload         4
     106: invokeinterface #529,  1          // InterfaceMethod java/util/List.size:()I
     111: iconst_2
     112: isub
     113: goto          117
     116: iconst_1
     117: istore        7
     119: aload         4
     121: iload         6
     123: invokeinterface #540,  2          // InterfaceMethod java/util/List.get:(I)Ljava/lang/Object;
     128: checkcast     #499                // class mchorse/bbs_mod/utils/keyframes/Keyframe
     131: astore        8
     133: aload         4
     135: iload         7
     137: invokeinterface #540,  2          // InterfaceMethod java/util/List.get:(I)Ljava/lang/Object;
     142: checkcast     #499                // class mchorse/bbs_mod/utils/keyframes/Keyframe
     145: astore        9
     147: aload         5
     149: aload         8
     151: invokevirtual #543                // Method mchorse/bbs_mod/utils/keyframes/Keyframe.getValue:()Ljava/lang/Object;
     154: invokeinterface #547,  2          // InterfaceMethod mchorse/bbs_mod/utils/keyframes/factories/IKeyframeFactory.getY:(Ljava/lang/Object;)D
     159: aload         5
     161: aload         9
     163: invokevirtual #543                // Method mchorse/bbs_mod/utils/keyframes/Keyframe.getValue:()Ljava/lang/Object;
     166: invokeinterface #547,  2          // InterfaceMethod mchorse/bbs_mod/utils/keyframes/factories/IKeyframeFactory.getY:(Ljava/lang/Object;)D
     171: dsub
     172: dstore        10
     174: aload         4
     176: iload         6
     178: invokeinterface #550,  2          // InterfaceMethod java/util/List.remove:(I)Ljava/lang/Object;
     183: pop
     184: aload         4
     186: invokeinterface #466,  1          // InterfaceMethod java/util/List.iterator:()Ljava/util/Iterator;
     191: astore        12
     193: aload         12
     195: invokeinterface #471,  1          // InterfaceMethod java/util/Iterator.hasNext:()Z
     200: ifeq          245
     203: aload         12
     205: invokeinterface #474,  1          // InterfaceMethod java/util/Iterator.next:()Ljava/lang/Object;
     210: checkcast     #499                // class mchorse/bbs_mod/utils/keyframes/Keyframe
     213: astore        13
     215: aload         13
     217: aload         5
     219: aload         5
     221: aload         13
     223: invokevirtual #543                // Method mchorse/bbs_mod/utils/keyframes/Keyframe.getValue:()Ljava/lang/Object;
     226: invokeinterface #547,  2          // InterfaceMethod mchorse/bbs_mod/utils/keyframes/factories/IKeyframeFactory.getY:(Ljava/lang/Object;)D
     231: dload         10
     233: dadd
     234: invokeinterface #554,  3          // InterfaceMethod mchorse/bbs_mod/utils/keyframes/factories/IKeyframeFactory.yToValue:(D)Ljava/lang/Object;
     239: invokevirtual #557                // Method mchorse/bbs_mod/utils/keyframes/Keyframe.setValue:(Ljava/lang/Object;)V
     242: goto          193
     245: aload_3
     246: getfield      #492                // Field mchorse/bbs_mod/ui/framework/elements/input/keyframes/UIKeyframeSheet.channel:Lmchorse/bbs_mod/utils/keyframes/KeyframeChannel;
     249: invokevirtual #511                // Method mchorse/bbs_mod/utils/keyframes/KeyframeChannel.postNotify:()V
     252: goto          15
     255: return

  public mchorse.bbs_mod.ui.framework.elements.input.keyframes.UIKeyframes changed(java.lang.Runnable);
    Code:
       0: aload_0
       1: aload_1
       2: putfield      #570                // Field changeCallback:Ljava/lang/Runnable;
       5: aload_0
       6: areturn

  public void triggerChange();
    Code:
       0: aload_0
       1: getfield      #570                // Field changeCallback:Ljava/lang/Runnable;
       4: ifnull        16
       7: aload_0
       8: getfield      #570                // Field changeCallback:Ljava/lang/Runnable;
      11: invokeinterface #575,  1          // InterfaceMethod java/lang/Runnable.run:()V
      16: return

  public mchorse.bbs_mod.ui.framework.elements.input.keyframes.graphs.UIKeyframeDopeSheet getDopeSheet();
    Code:
       0: aload_0
       1: getfield      #99                 // Field dopeSheet:Lmchorse/bbs_mod/ui/framework/elements/input/keyframes/graphs/UIKeyframeDopeSheet;
       4: areturn

  protected void selectNextKeyframe(int);
    Code:
       0: aload_0
       1: invokevirtual #454                // Method getGraph:()Lmchorse/bbs_mod/ui/framework/elements/input/keyframes/graphs/IUIKeyframeGraph;
       4: astore_2
       5: aload_2
       6: invokeinterface #583,  1          // InterfaceMethod mchorse/bbs_mod/ui/framework/elements/input/keyframes/graphs/IUIKeyframeGraph.getSelected:()Lmchorse/bbs_mod/utils/keyframes/Keyframe;
      11: astore_3
      12: aload_3
      13: ifnonnull     95
      16: aload_0
      17: invokevirtual #431                // Method getContext:()Lmchorse/bbs_mod/ui/framework/UIContext;
      20: astore        4
      22: aload_0
      23: invokevirtual #454                // Method getGraph:()Lmchorse/bbs_mod/ui/framework/elements/input/keyframes/graphs/IUIKeyframeGraph;
      26: aload         4
      28: getfield      #586                // Field mchorse/bbs_mod/ui/framework/UIContext.mouseY:I
      31: invokeinterface #590,  2          // InterfaceMethod mchorse/bbs_mod/ui/framework/elements/input/keyframes/graphs/IUIKeyframeGraph.getSheet:(I)Lmchorse/bbs_mod/ui/framework/elements/input/keyframes/UIKeyframeSheet;
      36: astore        5
      38: aload         5
      40: getfield      #492                // Field mchorse/bbs_mod/ui/framework/elements/input/keyframes/UIKeyframeSheet.channel:Lmchorse/bbs_mod/utils/keyframes/KeyframeChannel;
      43: aload_0
      44: aload         4
      46: getfield      #593                // Field mchorse/bbs_mod/ui/framework/UIContext.mouseX:I
      49: invokevirtual #597                // Method fromGraphX:(I)D
      52: d2f
      53: invokevirtual #601                // Method mchorse/bbs_mod/utils/keyframes/KeyframeChannel.find:(F)Lmchorse/bbs_mod/utils/keyframes/KeyframeSegment;
      56: astore        6
      58: aload         6
      60: ifnull        95
      63: iload_1
      64: ifge          75
      67: aload         6
      69: getfield      #606                // Field mchorse/bbs_mod/utils/keyframes/KeyframeSegment.a:Lmchorse/bbs_mod/utils/keyframes/Keyframe;
      72: goto          80
      75: aload         6
      77: getfield      #609                // Field mchorse/bbs_mod/utils/keyframes/KeyframeSegment.b:Lmchorse/bbs_mod/utils/keyframes/Keyframe;
      80: astore_3
      81: aload_2
      82: invokeinterface #612,  1          // InterfaceMethod mchorse/bbs_mod/ui/framework/elements/input/keyframes/graphs/IUIKeyframeGraph.clearSelection:()V
      87: aload_2
      88: aload_3
      89: invokeinterface #616,  2          // InterfaceMethod mchorse/bbs_mod/ui/framework/elements/input/keyframes/graphs/IUIKeyframeGraph.selectKeyframe:(Lmchorse/bbs_mod/utils/keyframes/Keyframe;)V
      94: return
      95: aload_3
      96: ifnull        158
      99: aload_3
     100: invokevirtual #620                // Method mchorse/bbs_mod/utils/keyframes/Keyframe.getParent:()Lmchorse/bbs_mod/settings/values/base/BaseValue;
     103: checkcast     #494                // class mchorse/bbs_mod/utils/keyframes/KeyframeChannel
     106: astore        4
     108: aload         4
     110: invokevirtual #623                // Method mchorse/bbs_mod/utils/keyframes/KeyframeChannel.getKeyframes:()Ljava/util/List;
     113: aload_3
     114: invokeinterface #627,  2          // InterfaceMethod java/util/List.indexOf:(Ljava/lang/Object;)I
     119: istore        5
     121: iload         5
     123: iload_1
     124: iadd
     125: aload         4
     127: invokevirtual #630                // Method mchorse/bbs_mod/utils/keyframes/KeyframeChannel.getAll:()Ljava/util/List;
     130: invokestatic  #636                // Method mchorse/bbs_mod/utils/MathUtils.cycler:(ILjava/util/Collection;)I
     133: istore        6
     135: aload         4
     137: iload         6
     139: invokevirtual #639                // Method mchorse/bbs_mod/utils/keyframes/KeyframeChannel.get:(I)Lmchorse/bbs_mod/utils/keyframes/Keyframe;
     142: astore        7
     144: aload_2
     145: invokeinterface #612,  1          // InterfaceMethod mchorse/bbs_mod/ui/framework/elements/input/keyframes/graphs/IUIKeyframeGraph.clearSelection:()V
     150: aload_2
     151: aload         7
     153: invokeinterface #616,  2          // InterfaceMethod mchorse/bbs_mod/ui/framework/elements/input/keyframes/graphs/IUIKeyframeGraph.selectKeyframe:(Lmchorse/bbs_mod/utils/keyframes/Keyframe;)V
     158: return

  private void selectAfter(int, int, int);
    Code:
       0: aload_0
       1: iload_1
       2: invokevirtual #597                // Method fromGraphX:(I)D
       5: d2f
       6: fstore        4
       8: invokestatic  #652                // Method mchorse/bbs_mod/graphics/window/Window.isShiftPressed:()Z
      11: ifne          29
      14: aload_0
      15: getfield      #101                // Field currentGraph:Lmchorse/bbs_mod/ui/framework/elements/input/keyframes/graphs/IUIKeyframeGraph;
      18: fload         4
      20: iload_3
      21: invokeinterface #655,  3          // InterfaceMethod mchorse/bbs_mod/ui/framework/elements/input/keyframes/graphs/IUIKeyframeGraph.selectAfter:(FI)V
      26: goto          57
      29: aload_0
      30: getfield      #101                // Field currentGraph:Lmchorse/bbs_mod/ui/framework/elements/input/keyframes/graphs/IUIKeyframeGraph;
      33: iload_2
      34: invokeinterface #590,  2          // InterfaceMethod mchorse/bbs_mod/ui/framework/elements/input/keyframes/graphs/IUIKeyframeGraph.getSheet:(I)Lmchorse/bbs_mod/ui/framework/elements/input/keyframes/UIKeyframeSheet;
      39: getfield      #480                // Field mchorse/bbs_mod/ui/framework/elements/input/keyframes/UIKeyframeSheet.selection:Lmchorse/bbs_mod/ui/framework/elements/input/keyframes/KeyframeSelection;
      42: fload         4
      44: iload_3
      45: invokevirtual #658                // Method mchorse/bbs_mod/ui/framework/elements/input/keyframes/KeyframeSelection.after:(FI)V
      48: aload_0
      49: getfield      #101                // Field currentGraph:Lmchorse/bbs_mod/ui/framework/elements/input/keyframes/graphs/IUIKeyframeGraph;
      52: invokeinterface #661,  1          // InterfaceMethod mchorse/bbs_mod/ui/framework/elements/input/keyframes/graphs/IUIKeyframeGraph.pickSelected:()V
      57: return

  private void selectSame();
    Code:
       0: aload_0
       1: invokevirtual #431                // Method getContext:()Lmchorse/bbs_mod/ui/framework/UIContext;
       4: astore_1
       5: aload_0
       6: getfield      #101                // Field currentGraph:Lmchorse/bbs_mod/ui/framework/elements/input/keyframes/graphs/IUIKeyframeGraph;
       9: aload_1
      10: getfield      #593                // Field mchorse/bbs_mod/ui/framework/UIContext.mouseX:I
      13: aload_1
      14: getfield      #586                // Field mchorse/bbs_mod/ui/framework/UIContext.mouseY:I
      17: invokeinterface #666,  3          // InterfaceMethod mchorse/bbs_mod/ui/framework/elements/input/keyframes/graphs/IUIKeyframeGraph.findKeyframe:(II)Lmchorse/bbs_mod/utils/Pair;
      22: astore_2
      23: aload_2
      24: ifnull        172
      27: invokestatic  #652                // Method mchorse/bbs_mod/graphics/window/Window.isShiftPressed:()Z
      30: ifne          42
      33: aload_0
      34: getfield      #101                // Field currentGraph:Lmchorse/bbs_mod/ui/framework/elements/input/keyframes/graphs/IUIKeyframeGraph;
      37: invokeinterface #612,  1          // InterfaceMethod mchorse/bbs_mod/ui/framework/elements/input/keyframes/graphs/IUIKeyframeGraph.clearSelection:()V
      42: aload_0
      43: getfield      #101                // Field currentGraph:Lmchorse/bbs_mod/ui/framework/elements/input/keyframes/graphs/IUIKeyframeGraph;
      46: invokeinterface #460,  1          // InterfaceMethod mchorse/bbs_mod/ui/framework/elements/input/keyframes/graphs/IUIKeyframeGraph.getSheets:()Ljava/util/List;
      51: invokeinterface #466,  1          // InterfaceMethod java/util/List.iterator:()Ljava/util/Iterator;
      56: astore_3
      57: aload_3
      58: invokeinterface #471,  1          // InterfaceMethod java/util/Iterator.hasNext:()Z
      63: ifeq          163
      66: aload_3
      67: invokeinterface #474,  1          // InterfaceMethod java/util/Iterator.next:()Ljava/lang/Object;
      72: checkcast     #476                // class mchorse/bbs_mod/ui/framework/elements/input/keyframes/UIKeyframeSheet
      75: astore        4
      77: aload         4
      79: getfield      #492                // Field mchorse/bbs_mod/ui/framework/elements/input/keyframes/UIKeyframeSheet.channel:Lmchorse/bbs_mod/utils/keyframes/KeyframeChannel;
      82: invokevirtual #671                // Method mchorse/bbs_mod/utils/keyframes/KeyframeChannel.getList:()Ljava/util/List;
      85: astore        5
      87: iconst_0
      88: istore        6
      90: iload         6
      92: aload         5
      94: invokeinterface #529,  1          // InterfaceMethod java/util/List.size:()I
      99: if_icmpge     160
     102: aload         5
     104: iload         6
     106: invokeinterface #540,  2          // InterfaceMethod java/util/List.get:(I)Ljava/lang/Object;
     111: checkcast     #499                // class mchorse/bbs_mod/utils/keyframes/Keyframe
     114: astore        7
     116: aload         7
     118: invokevirtual #672                // Method mchorse/bbs_mod/utils/keyframes/Keyframe.getFactory:()Lmchorse/bbs_mod/utils/keyframes/factories/IKeyframeFactory;
     121: aload_2
     122: getfield      #674                // Field mchorse/bbs_mod/utils/Pair.a:Ljava/lang/Object;
     125: checkcast     #499                // class mchorse/bbs_mod/utils/keyframes/Keyframe
     128: invokevirtual #543                // Method mchorse/bbs_mod/utils/keyframes/Keyframe.getValue:()Ljava/lang/Object;
     131: aload         7
     133: invokevirtual #543                // Method mchorse/bbs_mod/utils/keyframes/Keyframe.getValue:()Ljava/lang/Object;
     136: invokeinterface #678,  3          // InterfaceMethod mchorse/bbs_mod/utils/keyframes/factories/IKeyframeFactory.compare:(Ljava/lang/Object;Ljava/lang/Object;)Z
     141: ifeq          154
     144: aload         4
     146: getfield      #480                // Field mchorse/bbs_mod/ui/framework/elements/input/keyframes/UIKeyframeSheet.selection:Lmchorse/bbs_mod/ui/framework/elements/input/keyframes/KeyframeSelection;
     149: iload         6
     151: invokevirtual #680                // Method mchorse/bbs_mod/ui/framework/elements/input/keyframes/KeyframeSelection.add:(I)V
     154: iinc          6, 1
     157: goto          90
     160: goto          57
     163: aload_0
     164: getfield      #101                // Field currentGraph:Lmchorse/bbs_mod/ui/framework/elements/input/keyframes/graphs/IUIKeyframeGraph;
     167: invokeinterface #661,  1          // InterfaceMethod mchorse/bbs_mod/ui/framework/elements/input/keyframes/graphs/IUIKeyframeGraph.pickSelected:()V
     172: return

  private void scaleTime();
    Code:
       0: aload_0
       1: getfield      #684                // Field scaling:Z
       4: ifeq          13
       7: aload_0
       8: iconst_0
       9: putfield      #684                // Field scaling:Z
      12: return
      13: aload_0
      14: invokevirtual #431                // Method getContext:()Lmchorse/bbs_mod/ui/framework/UIContext;
      17: astore_1
      18: aload_0
      19: iconst_1
      20: putfield      #684                // Field scaling:Z
      23: aload_0
      24: getfield      #92                 // Field scaleTicks:Ljava/util/Map;
      27: invokeinterface #687,  1          // InterfaceMethod java/util/Map.clear:()V
      32: aload_0
      33: ldc_w         #688                // float 2.1474836E9f
      36: putfield      #690                // Field scalingAnchor:F
      39: aload_0
      40: aload_1
      41: getfield      #593                // Field mchorse/bbs_mod/ui/framework/UIContext.mouseX:I
      44: putfield      #692                // Field originalX:I
      47: aload_0
      48: aload_1
      49: getfield      #586                // Field mchorse/bbs_mod/ui/framework/UIContext.mouseY:I
      52: putfield      #694                // Field originalY:I
      55: aload_0
      56: getfield      #101                // Field currentGraph:Lmchorse/bbs_mod/ui/framework/elements/input/keyframes/graphs/IUIKeyframeGraph;
      59: invokeinterface #460,  1          // InterfaceMethod mchorse/bbs_mod/ui/framework/elements/input/keyframes/graphs/IUIKeyframeGraph.getSheets:()Ljava/util/List;
      64: invokeinterface #466,  1          // InterfaceMethod java/util/List.iterator:()Ljava/util/Iterator;
      69: astore_2
      70: aload_2
      71: invokeinterface #471,  1          // InterfaceMethod java/util/Iterator.hasNext:()Z
      76: ifeq          167
      79: aload_2
      80: invokeinterface #474,  1          // InterfaceMethod java/util/Iterator.next:()Ljava/lang/Object;
      85: checkcast     #476                // class mchorse/bbs_mod/ui/framework/elements/input/keyframes/UIKeyframeSheet
      88: astore_3
      89: aload_3
      90: getfield      #480                // Field mchorse/bbs_mod/ui/framework/elements/input/keyframes/UIKeyframeSheet.selection:Lmchorse/bbs_mod/ui/framework/elements/input/keyframes/KeyframeSelection;
      93: invokevirtual #485                // Method mchorse/bbs_mod/ui/framework/elements/input/keyframes/KeyframeSelection.getSelected:()Ljava/util/List;
      96: invokeinterface #466,  1          // InterfaceMethod java/util/List.iterator:()Ljava/util/Iterator;
     101: astore        4
     103: aload         4
     105: invokeinterface #471,  1          // InterfaceMethod java/util/Iterator.hasNext:()Z
     110: ifeq          164
     113: aload         4
     115: invokeinterface #474,  1          // InterfaceMethod java/util/Iterator.next:()Ljava/lang/Object;
     120: checkcast     #499                // class mchorse/bbs_mod/utils/keyframes/Keyframe
     123: astore        5
     125: aload_0
     126: getfield      #92                 // Field scaleTicks:Ljava/util/Map;
     129: aload         5
     131: aload         5
     133: invokevirtual #698                // Method mchorse/bbs_mod/utils/keyframes/Keyframe.getTick:()F
     136: invokestatic  #704                // Method java/lang/Float.valueOf:(F)Ljava/lang/Float;
     139: invokeinterface #708,  3          // InterfaceMethod java/util/Map.put:(Ljava/lang/Object;Ljava/lang/Object;)Ljava/lang/Object;
     144: pop
     145: aload_0
     146: aload_0
     147: getfield      #690                // Field scalingAnchor:F
     150: aload         5
     152: invokevirtual #698                // Method mchorse/bbs_mod/utils/keyframes/Keyframe.getTick:()F
     155: invokestatic  #714                // Method java/lang/Math.min:(FF)F
     158: putfield      #690                // Field scalingAnchor:F
     161: goto          103
     164: goto          70
     167: return

  private void stackKeyframes(boolean);
    Code:
       0: aload_0
       1: getfield      #718                // Field stacking:Z
       4: ifeq          396
       7: aload_0
       8: iconst_0
       9: putfield      #718                // Field stacking:Z
      12: iload_1
      13: ifne          395
      16: aload_0
      17: invokevirtual #431                // Method getContext:()Lmchorse/bbs_mod/ui/framework/UIContext;
      20: astore_2
      21: new           #720                // class java/util/ArrayList
      24: dup
      25: invokespecial #721                // Method java/util/ArrayList."<init>":()V
      28: astore_3
      29: aload_0
      30: aload_2
      31: getfield      #593                // Field mchorse/bbs_mod/ui/framework/UIContext.mouseX:I
      34: invokevirtual #597                // Method fromGraphX:(I)D
      37: d2f
      38: fstore        4
      40: aload_0
      41: invokevirtual #454                // Method getGraph:()Lmchorse/bbs_mod/ui/framework/elements/input/keyframes/graphs/IUIKeyframeGraph;
      44: invokeinterface #460,  1          // InterfaceMethod mchorse/bbs_mod/ui/framework/elements/input/keyframes/graphs/IUIKeyframeGraph.getSheets:()Ljava/util/List;
      49: invokeinterface #466,  1          // InterfaceMethod java/util/List.iterator:()Ljava/util/Iterator;
      54: astore        5
      56: aload         5
      58: invokeinterface #471,  1          // InterfaceMethod java/util/Iterator.hasNext:()Z
      63: ifeq          101
      66: aload         5
      68: invokeinterface #474,  1          // InterfaceMethod java/util/Iterator.next:()Ljava/lang/Object;
      73: checkcast     #476                // class mchorse/bbs_mod/ui/framework/elements/input/keyframes/UIKeyframeSheet
      76: astore        6
      78: aload         6
      80: getfield      #480                // Field mchorse/bbs_mod/ui/framework/elements/input/keyframes/UIKeyframeSheet.selection:Lmchorse/bbs_mod/ui/framework/elements/input/keyframes/KeyframeSelection;
      83: invokevirtual #724                // Method mchorse/bbs_mod/ui/framework/elements/input/keyframes/KeyframeSelection.hasAny:()Z
      86: ifeq          98
      89: aload_3
      90: aload         6
      92: invokeinterface #727,  2          // InterfaceMethod java/util/List.add:(Ljava/lang/Object;)Z
      97: pop
      98: goto          56
     101: aload_3
     102: invokeinterface #466,  1          // InterfaceMethod java/util/List.iterator:()Ljava/util/Iterator;
     107: astore        5
     109: aload         5
     111: invokeinterface #471,  1          // InterfaceMethod java/util/Iterator.hasNext:()Z
     116: ifeq          395
     119: aload         5
     121: invokeinterface #474,  1          // InterfaceMethod java/util/Iterator.next:()Ljava/lang/Object;
     126: checkcast     #476                // class mchorse/bbs_mod/ui/framework/elements/input/keyframes/UIKeyframeSheet
     129: astore        6
     131: aload         6
     133: getfield      #480                // Field mchorse/bbs_mod/ui/framework/elements/input/keyframes/UIKeyframeSheet.selection:Lmchorse/bbs_mod/ui/framework/elements/input/keyframes/KeyframeSelection;
     136: invokevirtual #485                // Method mchorse/bbs_mod/ui/framework/elements/input/keyframes/KeyframeSelection.getSelected:()Ljava/util/List;
     139: astore        7
     141: ldc_w         #688                // float 2.1474836E9f
     144: fstore        8
     146: ldc_w         #728                // float -2.1474836E9f
     149: fstore        9
     151: aload         7
     153: invokeinterface #466,  1          // InterfaceMethod java/util/List.iterator:()Ljava/util/Iterator;
     158: astore        10
     160: aload         10
     162: invokeinterface #471,  1          // InterfaceMethod java/util/Iterator.hasNext:()Z
     167: ifeq          209
     170: aload         10
     172: invokeinterface #474,  1          // InterfaceMethod java/util/Iterator.next:()Ljava/lang/Object;
     177: checkcast     #499                // class mchorse/bbs_mod/utils/keyframes/Keyframe
     180: astore        11
     182: aload         11
     184: invokevirtual #698                // Method mchorse/bbs_mod/utils/keyframes/Keyframe.getTick:()F
     187: fload         8
     189: invokestatic  #714                // Method java/lang/Math.min:(FF)F
     192: fstore        8
     194: aload         11
     196: invokevirtual #698                // Method mchorse/bbs_mod/utils/keyframes/Keyframe.getTick:()F
     199: fload         9
     201: invokestatic  #731                // Method java/lang/Math.max:(FF)F
     204: fstore        9
     206: goto          160
     209: fload         9
     211: fload         8
     213: fsub
     214: aload_0
     215: invokevirtual #734                // Method getStackOffset:()F
     218: fadd
     219: fstore        10
     221: dconst_1
     222: fload         4
     224: fload         9
     226: fsub
     227: fload         10
     229: fdiv
     230: f2d
     231: invokestatic  #738                // Method java/lang/Math.ceil:(D)D
     234: invokestatic  #741                // Method java/lang/Math.max:(DD)D
     237: d2i
     238: istore        11
     240: fconst_0
     241: fstore        12
     243: aload         6
     245: getfield      #480                // Field mchorse/bbs_mod/ui/framework/elements/input/keyframes/UIKeyframeSheet.selection:Lmchorse/bbs_mod/ui/framework/elements/input/keyframes/KeyframeSelection;
     248: invokevirtual #742                // Method mchorse/bbs_mod/ui/framework/elements/input/keyframes/KeyframeSelection.clear:()V
     251: iconst_0
     252: istore        13
     254: iload         13
     256: iload         11
     258: if_icmpge     392
     261: aload         7
     263: invokeinterface #466,  1          // InterfaceMethod java/util/List.iterator:()Ljava/util/Iterator;
     268: astore        14
     270: aload         14
     272: invokeinterface #471,  1          // InterfaceMethod java/util/Iterator.hasNext:()Z
     277: ifeq          379
     280: aload         14
     282: invokeinterface #474,  1          // InterfaceMethod java/util/Iterator.next:()Ljava/lang/Object;
     287: checkcast     #499                // class mchorse/bbs_mod/utils/keyframes/Keyframe
     290: astore        15
     292: fload         9
     294: aload_0
     295: invokevirtual #734                // Method getStackOffset:()F
     298: fadd
     299: aload         15
     301: invokevirtual #698                // Method mchorse/bbs_mod/utils/keyframes/Keyframe.getTick:()F
     304: fload         8
     306: fsub
     307: fadd
     308: fload         12
     310: fadd
     311: fstore        16
     313: aload         6
     315: getfield      #492                // Field mchorse/bbs_mod/ui/framework/elements/input/keyframes/UIKeyframeSheet.channel:Lmchorse/bbs_mod/utils/keyframes/KeyframeChannel;
     318: fload         16
     320: aload         15
     322: invokevirtual #672                // Method mchorse/bbs_mod/utils/keyframes/Keyframe.getFactory:()Lmchorse/bbs_mod/utils/keyframes/factories/IKeyframeFactory;
     325: aload         15
     327: invokevirtual #543                // Method mchorse/bbs_mod/utils/keyframes/Keyframe.getValue:()Ljava/lang/Object;
     330: invokeinterface #746,  2          // InterfaceMethod mchorse/bbs_mod/utils/keyframes/factories/IKeyframeFactory.copy:(Ljava/lang/Object;)Ljava/lang/Object;
     335: invokevirtual #750                // Method mchorse/bbs_mod/utils/keyframes/KeyframeChannel.insert:(FLjava/lang/Object;)I
     338: istore        17
     340: aload         6
     342: getfield      #492                // Field mchorse/bbs_mod/ui/framework/elements/input/keyframes/UIKeyframeSheet.channel:Lmchorse/bbs_mod/utils/keyframes/KeyframeChannel;
     345: iload         17
     347: invokevirtual #639                // Method mchorse/bbs_mod/utils/keyframes/KeyframeChannel.get:(I)Lmchorse/bbs_mod/utils/keyframes/Keyframe;
     350: astore        18
     352: aload         18
     354: aload         15
     356: invokevirtual #752                // Method mchorse/bbs_mod/utils/keyframes/Keyframe.copy:(Lmchorse/bbs_mod/utils/keyframes/Keyframe;)V
     359: aload         18
     361: fload         16
     363: invokevirtual #756                // Method mchorse/bbs_mod/utils/keyframes/Keyframe.setTick:(F)V
     366: aload         6
     368: getfield      #480                // Field mchorse/bbs_mod/ui/framework/elements/input/keyframes/UIKeyframeSheet.selection:Lmchorse/bbs_mod/ui/framework/elements/input/keyframes/KeyframeSelection;
     371: iload         17
     373: invokevirtual #680                // Method mchorse/bbs_mod/ui/framework/elements/input/keyframes/KeyframeSelection.add:(I)V
     376: goto          270
     379: fload         12
     381: fload         10
     383: fadd
     384: fstore        12
     386: iinc          13, 1
     389: goto          254
     392: goto          109
     395: return
     396: aload_0
     397: iconst_1
     398: putfield      #718                // Field stacking:Z
     401: aload_0
     402: fconst_1
     403: putfield      #758                // Field stackOffset:F
     406: return

  public boolean isStacking();
    Code:
       0: aload_0
       1: getfield      #718                // Field stacking:Z
       4: ireturn

  public float getStackOffset();
    Code:
       0: aload_0
       1: getfield      #758                // Field stackOffset:F
       4: freturn

  private void spreadKeyframes();
    Code:
       0: aload_0
       1: invokevirtual #454                // Method getGraph:()Lmchorse/bbs_mod/ui/framework/elements/input/keyframes/graphs/IUIKeyframeGraph;
       4: invokeinterface #460,  1          // InterfaceMethod mchorse/bbs_mod/ui/framework/elements/input/keyframes/graphs/IUIKeyframeGraph.getSheets:()Ljava/util/List;
       9: invokeinterface #466,  1          // InterfaceMethod java/util/List.iterator:()Ljava/util/Iterator;
      14: astore_1
      15: aload_1
      16: invokeinterface #471,  1          // InterfaceMethod java/util/Iterator.hasNext:()Z
      21: ifeq          278
      24: aload_1
      25: invokeinterface #474,  1          // InterfaceMethod java/util/Iterator.next:()Ljava/lang/Object;
      30: checkcast     #476                // class mchorse/bbs_mod/ui/framework/elements/input/keyframes/UIKeyframeSheet
      33: astore_2
      34: aload_2
      35: getfield      #480                // Field mchorse/bbs_mod/ui/framework/elements/input/keyframes/UIKeyframeSheet.selection:Lmchorse/bbs_mod/ui/framework/elements/input/keyframes/KeyframeSelection;
      38: invokevirtual #485                // Method mchorse/bbs_mod/ui/framework/elements/input/keyframes/KeyframeSelection.getSelected:()Ljava/util/List;
      41: astore_3
      42: aload_3
      43: invokeinterface #488,  1          // InterfaceMethod java/util/List.isEmpty:()Z
      48: ifeq          54
      51: goto          15
      54: ldc_w         #769                // int 2147483647
      57: istore        4
      59: ldc_w         #770                // int -2147483648
      62: istore        5
      64: aload_3
      65: invokeinterface #466,  1          // InterfaceMethod java/util/List.iterator:()Ljava/util/Iterator;
      70: astore        6
      72: aload         6
      74: invokeinterface #471,  1          // InterfaceMethod java/util/Iterator.hasNext:()Z
      79: ifeq          131
      82: aload         6
      84: invokeinterface #474,  1          // InterfaceMethod java/util/Iterator.next:()Ljava/lang/Object;
      89: checkcast     #499                // class mchorse/bbs_mod/utils/keyframes/Keyframe
      92: astore        7
      94: aload_2
      95: getfield      #492                // Field mchorse/bbs_mod/ui/framework/elements/input/keyframes/UIKeyframeSheet.channel:Lmchorse/bbs_mod/utils/keyframes/KeyframeChannel;
      98: invokevirtual #623                // Method mchorse/bbs_mod/utils/keyframes/KeyframeChannel.getKeyframes:()Ljava/util/List;
     101: aload         7
     103: invokeinterface #627,  2          // InterfaceMethod java/util/List.indexOf:(Ljava/lang/Object;)I
     108: istore        8
     110: iload         4
     112: iload         8
     114: invokestatic  #773                // Method java/lang/Math.min:(II)I
     117: istore        4
     119: iload         5
     121: iload         8
     123: invokestatic  #775                // Method java/lang/Math.max:(II)I
     126: istore        5
     128: goto          72
     131: aload_2
     132: getfield      #492                // Field mchorse/bbs_mod/ui/framework/elements/input/keyframes/UIKeyframeSheet.channel:Lmchorse/bbs_mod/utils/keyframes/KeyframeChannel;
     135: iload         4
     137: invokevirtual #639                // Method mchorse/bbs_mod/utils/keyframes/KeyframeChannel.get:(I)Lmchorse/bbs_mod/utils/keyframes/Keyframe;
     140: astore        6
     142: aload_2
     143: getfield      #492                // Field mchorse/bbs_mod/ui/framework/elements/input/keyframes/UIKeyframeSheet.channel:Lmchorse/bbs_mod/utils/keyframes/KeyframeChannel;
     146: iload         5
     148: invokevirtual #639                // Method mchorse/bbs_mod/utils/keyframes/KeyframeChannel.get:(I)Lmchorse/bbs_mod/utils/keyframes/Keyframe;
     151: astore        7
     153: iload         5
     155: iload         4
     157: isub
     158: istore        8
     160: aload         7
     162: invokevirtual #698                // Method mchorse/bbs_mod/utils/keyframes/Keyframe.getTick:()F
     165: aload         6
     167: invokevirtual #698                // Method mchorse/bbs_mod/utils/keyframes/Keyframe.getTick:()F
     170: fsub
     171: iload         8
     173: i2f
     174: fdiv
     175: fstore        9
     177: aload_2
     178: getfield      #492                // Field mchorse/bbs_mod/ui/framework/elements/input/keyframes/UIKeyframeSheet.channel:Lmchorse/bbs_mod/utils/keyframes/KeyframeChannel;
     181: invokevirtual #497                // Method mchorse/bbs_mod/utils/keyframes/KeyframeChannel.preNotify:()V
     184: iconst_1
     185: istore        10
     187: iload         10
     189: iload         8
     191: if_icmpge     235
     194: iload         10
     196: iload         4
     198: iadd
     199: istore        11
     201: aload_2
     202: getfield      #492                // Field mchorse/bbs_mod/ui/framework/elements/input/keyframes/UIKeyframeSheet.channel:Lmchorse/bbs_mod/utils/keyframes/KeyframeChannel;
     205: iload         11
     207: invokevirtual #639                // Method mchorse/bbs_mod/utils/keyframes/KeyframeChannel.get:(I)Lmchorse/bbs_mod/utils/keyframes/Keyframe;
     210: astore        12
     212: aload         12
     214: aload         6
     216: invokevirtual #698                // Method mchorse/bbs_mod/utils/keyframes/Keyframe.getTick:()F
     219: iload         10
     221: i2f
     222: fload         9
     224: fmul
     225: fadd
     226: invokevirtual #756                // Method mchorse/bbs_mod/utils/keyframes/Keyframe.setTick:(F)V
     229: iinc          10, 1
     232: goto          187
     235: aload_2
     236: getfield      #492                // Field mchorse/bbs_mod/ui/framework/elements/input/keyframes/UIKeyframeSheet.channel:Lmchorse/bbs_mod/utils/keyframes/KeyframeChannel;
     239: invokevirtual #511                // Method mchorse/bbs_mod/utils/keyframes/KeyframeChannel.postNotify:()V
     242: aload_2
     243: getfield      #480                // Field mchorse/bbs_mod/ui/framework/elements/input/keyframes/UIKeyframeSheet.selection:Lmchorse/bbs_mod/ui/framework/elements/input/keyframes/KeyframeSelection;
     246: invokevirtual #742                // Method mchorse/bbs_mod/ui/framework/elements/input/keyframes/KeyframeSelection.clear:()V
     249: iload         4
     251: istore        10
     253: iload         10
     255: iload         5
     257: if_icmpgt     275
     260: aload_2
     261: getfield      #480                // Field mchorse/bbs_mod/ui/framework/elements/input/keyframes/UIKeyframeSheet.selection:Lmchorse/bbs_mod/ui/framework/elements/input/keyframes/KeyframeSelection;
     264: iload         10
     266: invokevirtual #680                // Method mchorse/bbs_mod/ui/framework/elements/input/keyframes/KeyframeSelection.add:(I)V
     269: iinc          10, 1
     272: goto          253
     275: goto          15
     278: aload_0
     279: invokevirtual #454                // Method getGraph:()Lmchorse/bbs_mod/ui/framework/elements/input/keyframes/graphs/IUIKeyframeGraph;
     282: invokeinterface #661,  1          // InterfaceMethod mchorse/bbs_mod/ui/framework/elements/input/keyframes/graphs/IUIKeyframeGraph.pickSelected:()V
     287: return

  public boolean isEditing();
    Code:
       0: aload_0
       1: getfield      #101                // Field currentGraph:Lmchorse/bbs_mod/ui/framework/elements/input/keyframes/graphs/IUIKeyframeGraph;
       4: aload_0
       5: getfield      #99                 // Field dopeSheet:Lmchorse/bbs_mod/ui/framework/elements/input/keyframes/graphs/UIKeyframeDopeSheet;
       8: if_acmpeq     15
      11: iconst_1
      12: goto          16
      15: iconst_0
      16: ireturn

  public void editSheet(mchorse.bbs_mod.ui.framework.elements.input.keyframes.UIKeyframeSheet);
    Code:
       0: aload_1
       1: ifnonnull     15
       4: aload_0
       5: aload_0
       6: getfield      #99                 // Field dopeSheet:Lmchorse/bbs_mod/ui/framework/elements/input/keyframes/graphs/UIKeyframeDopeSheet;
       9: putfield      #101                // Field currentGraph:Lmchorse/bbs_mod/ui/framework/elements/input/keyframes/graphs/IUIKeyframeGraph;
      12: goto          46
      15: aload_0
      16: getfield      #99                 // Field dopeSheet:Lmchorse/bbs_mod/ui/framework/elements/input/keyframes/graphs/UIKeyframeDopeSheet;
      19: invokevirtual #783                // Method mchorse/bbs_mod/ui/framework/elements/input/keyframes/graphs/UIKeyframeDopeSheet.clearSelection:()V
      22: aload_0
      23: getfield      #99                 // Field dopeSheet:Lmchorse/bbs_mod/ui/framework/elements/input/keyframes/graphs/UIKeyframeDopeSheet;
      26: invokevirtual #784                // Method mchorse/bbs_mod/ui/framework/elements/input/keyframes/graphs/UIKeyframeDopeSheet.pickSelected:()V
      29: aload_0
      30: new           #786                // class mchorse/bbs_mod/ui/framework/elements/input/keyframes/graphs/UIKeyframeGraph
      33: dup
      34: aload_0
      35: aload_1
      36: invokespecial #789                // Method mchorse/bbs_mod/ui/framework/elements/input/keyframes/graphs/UIKeyframeGraph."<init>":(Lmchorse/bbs_mod/ui/framework/elements/input/keyframes/UIKeyframes;Lmchorse/bbs_mod/ui/framework/elements/input/keyframes/UIKeyframeSheet;)V
      39: putfield      #101                // Field currentGraph:Lmchorse/bbs_mod/ui/framework/elements/input/keyframes/graphs/IUIKeyframeGraph;
      42: aload_0
      43: invokevirtual #221                // Method resetView:()V
      46: return

  public void cacheKeyframes();
    Code:
       0: aload_0
       1: new           #7                  // class mchorse/bbs_mod/ui/framework/elements/input/keyframes/UIKeyframes$SheetCache
       4: dup
       5: aload_0
       6: getfield      #101                // Field currentGraph:Lmchorse/bbs_mod/ui/framework/elements/input/keyframes/graphs/IUIKeyframeGraph;
       9: invokeinterface #460,  1          // InterfaceMethod mchorse/bbs_mod/ui/framework/elements/input/keyframes/graphs/IUIKeyframeGraph.getSheets:()Ljava/util/List;
      14: invokespecial #793                // Method mchorse/bbs_mod/ui/framework/elements/input/keyframes/UIKeyframes$SheetCache."<init>":(Ljava/util/Collection;)V
      17: putfield      #795                // Field cache:Lmchorse/bbs_mod/ui/framework/elements/input/keyframes/UIKeyframes$SheetCache;
      20: return

  public void submitKeyframes();
    Code:
       0: new           #89                 // class java/util/HashMap
       3: dup
       4: invokespecial #90                 // Method java/util/HashMap."<init>":()V
       7: astore_1
       8: aload_0
       9: getfield      #101                // Field currentGraph:Lmchorse/bbs_mod/ui/framework/elements/input/keyframes/graphs/IUIKeyframeGraph;
      12: invokeinterface #460,  1          // InterfaceMethod mchorse/bbs_mod/ui/framework/elements/input/keyframes/graphs/IUIKeyframeGraph.getSheets:()Ljava/util/List;
      17: invokeinterface #466,  1          // InterfaceMethod java/util/List.iterator:()Ljava/util/Iterator;
      22: astore_2
      23: aload_2
      24: invokeinterface #471,  1          // InterfaceMethod java/util/Iterator.hasNext:()Z
      29: ifeq          82
      32: aload_2
      33: invokeinterface #474,  1          // InterfaceMethod java/util/Iterator.next:()Ljava/lang/Object;
      38: checkcast     #476                // class mchorse/bbs_mod/ui/framework/elements/input/keyframes/UIKeyframeSheet
      41: astore_3
      42: aload_3
      43: invokevirtual #799                // Method mchorse/bbs_mod/ui/framework/elements/input/keyframes/UIKeyframeSheet.sort:()Ljava/util/List;
      46: astore        4
      48: aload_1
      49: aload_3
      50: new           #668                // class mchorse/bbs_mod/utils/Pair
      53: dup
      54: aload         4
      56: new           #720                // class java/util/ArrayList
      59: dup
      60: aload_3
      61: getfield      #480                // Field mchorse/bbs_mod/ui/framework/elements/input/keyframes/UIKeyframeSheet.selection:Lmchorse/bbs_mod/ui/framework/elements/input/keyframes/KeyframeSelection;
      64: invokevirtual #803                // Method mchorse/bbs_mod/ui/framework/elements/input/keyframes/KeyframeSelection.getIndices:()Ljava/util/Collection;
      67: invokespecial #804                // Method java/util/ArrayList."<init>":(Ljava/util/Collection;)V
      70: invokespecial #807                // Method mchorse/bbs_mod/utils/Pair."<init>":(Ljava/lang/Object;Ljava/lang/Object;)V
      73: invokeinterface #708,  3          // InterfaceMethod java/util/Map.put:(Ljava/lang/Object;Ljava/lang/Object;)Ljava/lang/Object;
      78: pop
      79: goto          23
      82: new           #7                  // class mchorse/bbs_mod/ui/framework/elements/input/keyframes/UIKeyframes$SheetCache
      85: dup
      86: aload_0
      87: getfield      #101                // Field currentGraph:Lmchorse/bbs_mod/ui/framework/elements/input/keyframes/graphs/IUIKeyframeGraph;
      90: invokeinterface #460,  1          // InterfaceMethod mchorse/bbs_mod/ui/framework/elements/input/keyframes/graphs/IUIKeyframeGraph.getSheets:()Ljava/util/List;
      95: invokespecial #793                // Method mchorse/bbs_mod/ui/framework/elements/input/keyframes/UIKeyframes$SheetCache."<init>":(Ljava/util/Collection;)V
      98: astore_2
      99: aload_0
     100: getfield      #795                // Field cache:Lmchorse/bbs_mod/ui/framework/elements/input/keyframes/UIKeyframes$SheetCache;
     103: getfield      #810                // Field mchorse/bbs_mod/ui/framework/elements/input/keyframes/UIKeyframes$SheetCache.data:Ljava/util/List;
     106: invokeinterface #466,  1          // InterfaceMethod java/util/List.iterator:()Ljava/util/Iterator;
     111: astore_3
     112: aload_3
     113: invokeinterface #471,  1          // InterfaceMethod java/util/Iterator.hasNext:()Z
     118: ifeq          234
     121: aload_3
     122: invokeinterface #474,  1          // InterfaceMethod java/util/Iterator.next:()Ljava/lang/Object;
     127: checkcast     #668                // class mchorse/bbs_mod/utils/Pair
     130: astore        4
     132: aload         4
     134: getfield      #812                // Field mchorse/bbs_mod/utils/Pair.b:Ljava/lang/Object;
     137: checkcast     #476                // class mchorse/bbs_mod/ui/framework/elements/input/keyframes/UIKeyframeSheet
     140: getfield      #492                // Field mchorse/bbs_mod/ui/framework/elements/input/keyframes/UIKeyframeSheet.channel:Lmchorse/bbs_mod/utils/keyframes/KeyframeChannel;
     143: aload         4
     145: getfield      #674                // Field mchorse/bbs_mod/utils/Pair.a:Ljava/lang/Object;
     148: checkcast     #494                // class mchorse/bbs_mod/utils/keyframes/KeyframeChannel
     151: invokevirtual #816                // Method mchorse/bbs_mod/utils/keyframes/KeyframeChannel.copyKeyframes:(Lmchorse/bbs_mod/utils/keyframes/KeyframeChannel;)V
     154: aload         4
     156: getfield      #812                // Field mchorse/bbs_mod/utils/Pair.b:Ljava/lang/Object;
     159: checkcast     #476                // class mchorse/bbs_mod/ui/framework/elements/input/keyframes/UIKeyframeSheet
     162: getfield      #480                // Field mchorse/bbs_mod/ui/framework/elements/input/keyframes/UIKeyframeSheet.selection:Lmchorse/bbs_mod/ui/framework/elements/input/keyframes/KeyframeSelection;
     165: invokevirtual #742                // Method mchorse/bbs_mod/ui/framework/elements/input/keyframes/KeyframeSelection.clear:()V
     168: aload_1
     169: aload         4
     171: getfield      #812                // Field mchorse/bbs_mod/utils/Pair.b:Ljava/lang/Object;
     174: invokeinterface #819,  2          // InterfaceMethod java/util/Map.containsKey:(Ljava/lang/Object;)Z
     179: ifeq          216
     182: aload         4
     184: getfield      #812                // Field mchorse/bbs_mod/utils/Pair.b:Ljava/lang/Object;
     187: checkcast     #476                // class mchorse/bbs_mod/ui/framework/elements/input/keyframes/UIKeyframeSheet
     190: getfield      #480                // Field mchorse/bbs_mod/ui/framework/elements/input/keyframes/UIKeyframeSheet.selection:Lmchorse/bbs_mod/ui/framework/elements/input/keyframes/KeyframeSelection;
     193: aload_1
     194: aload         4
     196: getfield      #812                // Field mchorse/bbs_mod/utils/Pair.b:Ljava/lang/Object;
     199: invokeinterface #821,  2          // InterfaceMethod java/util/Map.get:(Ljava/lang/Object;)Ljava/lang/Object;
     204: checkcast     #668                // class mchorse/bbs_mod/utils/Pair
     207: getfield      #674                // Field mchorse/bbs_mod/utils/Pair.a:Ljava/lang/Object;
     210: checkcast     #823                // class java/util/Collection
     213: invokevirtual #826                // Method mchorse/bbs_mod/ui/framework/elements/input/keyframes/KeyframeSelection.addAll:(Ljava/util/Collection;)V
     216: aload         4
     218: getfield      #812                // Field mchorse/bbs_mod/utils/Pair.b:Ljava/lang/Object;
     221: checkcast     #476                // class mchorse/bbs_mod/ui/framework/elements/input/keyframes/UIKeyframeSheet
     224: getfield      #492                // Field mchorse/bbs_mod/ui/framework/elements/input/keyframes/UIKeyframeSheet.channel:Lmchorse/bbs_mod/utils/keyframes/KeyframeChannel;
     227: iconst_1
     228: invokevirtual #828                // Method mchorse/bbs_mod/utils/keyframes/KeyframeChannel.preNotify:(I)V
     231: goto          112
     234: aload_2
     235: getfield      #810                // Field mchorse/bbs_mod/ui/framework/elements/input/keyframes/UIKeyframes$SheetCache.data:Ljava/util/List;
     238: invokeinterface #466,  1          // InterfaceMethod java/util/List.iterator:()Ljava/util/Iterator;
     243: astore_3
     244: aload_3
     245: invokeinterface #471,  1          // InterfaceMethod java/util/Iterator.hasNext:()Z
     250: ifeq          366
     253: aload_3
     254: invokeinterface #474,  1          // InterfaceMethod java/util/Iterator.next:()Ljava/lang/Object;
     259: checkcast     #668                // class mchorse/bbs_mod/utils/Pair
     262: astore        4
     264: aload         4
     266: getfield      #812                // Field mchorse/bbs_mod/utils/Pair.b:Ljava/lang/Object;
     269: checkcast     #476                // class mchorse/bbs_mod/ui/framework/elements/input/keyframes/UIKeyframeSheet
     272: getfield      #492                // Field mchorse/bbs_mod/ui/framework/elements/input/keyframes/UIKeyframeSheet.channel:Lmchorse/bbs_mod/utils/keyframes/KeyframeChannel;
     275: aload         4
     277: getfield      #674                // Field mchorse/bbs_mod/utils/Pair.a:Ljava/lang/Object;
     280: checkcast     #494                // class mchorse/bbs_mod/utils/keyframes/KeyframeChannel
     283: invokevirtual #816                // Method mchorse/bbs_mod/utils/keyframes/KeyframeChannel.copyKeyframes:(Lmchorse/bbs_mod/utils/keyframes/KeyframeChannel;)V
     286: aload         4
     288: getfield      #812                // Field mchorse/bbs_mod/utils/Pair.b:Ljava/lang/Object;
     291: checkcast     #476                // class mchorse/bbs_mod/ui/framework/elements/input/keyframes/UIKeyframeSheet
     294: getfield      #480                // Field mchorse/bbs_mod/ui/framework/elements/input/keyframes/UIKeyframeSheet.selection:Lmchorse/bbs_mod/ui/framework/elements/input/keyframes/KeyframeSelection;
     297: invokevirtual #742                // Method mchorse/bbs_mod/ui/framework/elements/input/keyframes/KeyframeSelection.clear:()V
     300: aload_1
     301: aload         4
     303: getfield      #812                // Field mchorse/bbs_mod/utils/Pair.b:Ljava/lang/Object;
     306: invokeinterface #819,  2          // InterfaceMethod java/util/Map.containsKey:(Ljava/lang/Object;)Z
     311: ifeq          348
     314: aload         4
     316: getfield      #812                // Field mchorse/bbs_mod/utils/Pair.b:Ljava/lang/Object;
     319: checkcast     #476                // class mchorse/bbs_mod/ui/framework/elements/input/keyframes/UIKeyframeSheet
     322: getfield      #480                // Field mchorse/bbs_mod/ui/framework/elements/input/keyframes/UIKeyframeSheet.selection:Lmchorse/bbs_mod/ui/framework/elements/input/keyframes/KeyframeSelection;
     325: aload_1
     326: aload         4
     328: getfield      #812                // Field mchorse/bbs_mod/utils/Pair.b:Ljava/lang/Object;
     331: invokeinterface #821,  2          // InterfaceMethod java/util/Map.get:(Ljava/lang/Object;)Ljava/lang/Object;
     336: checkcast     #668                // class mchorse/bbs_mod/utils/Pair
     339: getfield      #812                // Field mchorse/bbs_mod/utils/Pair.b:Ljava/lang/Object;
     342: checkcast     #823                // class java/util/Collection
     345: invokevirtual #826                // Method mchorse/bbs_mod/ui/framework/elements/input/keyframes/KeyframeSelection.addAll:(Ljava/util/Collection;)V
     348: aload         4
     350: getfield      #812                // Field mchorse/bbs_mod/utils/Pair.b:Ljava/lang/Object;
     353: checkcast     #476                // class mchorse/bbs_mod/ui/framework/elements/input/keyframes/UIKeyframeSheet
     356: getfield      #492                // Field mchorse/bbs_mod/ui/framework/elements/input/keyframes/UIKeyframeSheet.channel:Lmchorse/bbs_mod/utils/keyframes/KeyframeChannel;
     359: iconst_1
     360: invokevirtual #830                // Method mchorse/bbs_mod/utils/keyframes/KeyframeChannel.postNotify:(I)V
     363: goto          244
     366: aload_0
     367: aconst_null
     368: putfield      #795                // Field cache:Lmchorse/bbs_mod/ui/framework/elements/input/keyframes/UIKeyframes$SheetCache;
     371: return

  public static java.util.Map<java.lang.String, mchorse.bbs_mod.ui.framework.elements.input.keyframes.UIKeyframes$PastedKeyframes> parseKeyframes(mchorse.bbs_mod.data.types.MapType);
    Code:
       0: aload_0
       1: ifnonnull     8
       4: invokestatic  #843                // Method java/util/Collections.emptyMap:()Ljava/util/Map;
       7: areturn
       8: new           #89                 // class java/util/HashMap
      11: dup
      12: invokespecial #90                 // Method java/util/HashMap."<init>":()V
      15: astore_1
      16: aload_0
      17: invokevirtual #848                // Method mchorse/bbs_mod/data/types/MapType.keys:()Ljava/util/Set;
      20: invokeinterface #851,  1          // InterfaceMethod java/util/Set.iterator:()Ljava/util/Iterator;
      25: astore_2
      26: aload_2
      27: invokeinterface #471,  1          // InterfaceMethod java/util/Iterator.hasNext:()Z
      32: ifeq          167
      35: aload_2
      36: invokeinterface #474,  1          // InterfaceMethod java/util/Iterator.next:()Ljava/lang/Object;
      41: checkcast     #853                // class java/lang/String
      44: astore_3
      45: aload_0
      46: aload_3
      47: invokevirtual #857                // Method mchorse/bbs_mod/data/types/MapType.getMap:(Ljava/lang/String;)Lmchorse/bbs_mod/data/types/MapType;
      50: astore        4
      52: aload         4
      54: ldc_w         #859                // String keyframes
      57: invokevirtual #862                // Method mchorse/bbs_mod/data/types/MapType.getList:(Ljava/lang/String;)Lmchorse/bbs_mod/data/types/ListType;
      60: astore        5
      62: getstatic     #865                // Field mchorse/bbs_mod/utils/keyframes/factories/KeyframeFactories.FACTORIES:Ljava/util/Map;
      65: aload         4
      67: ldc_w         #867                // String type
      70: invokevirtual #871                // Method mchorse/bbs_mod/data/types/MapType.getString:(Ljava/lang/String;)Ljava/lang/String;
      73: invokeinterface #821,  2          // InterfaceMethod java/util/Map.get:(Ljava/lang/Object;)Ljava/lang/Object;
      78: checkcast     #537                // class mchorse/bbs_mod/utils/keyframes/factories/IKeyframeFactory
      81: astore        6
      83: iconst_0
      84: istore        7
      86: aload         5
      88: invokevirtual #874                // Method mchorse/bbs_mod/data/types/ListType.size:()I
      91: istore        8
      93: iload         7
      95: iload         8
      97: if_icmpge     164
     100: aload_1
     101: aload_3
     102: aload         6
     104: invokedynamic #886,  0            // InvokeDynamic #28:apply:(Lmchorse/bbs_mod/utils/keyframes/factories/IKeyframeFactory;)Ljava/util/function/Function;
     109: invokeinterface #890,  3          // InterfaceMethod java/util/Map.computeIfAbsent:(Ljava/lang/Object;Ljava/util/function/Function;)Ljava/lang/Object;
     114: checkcast     #9                  // class mchorse/bbs_mod/ui/framework/elements/input/keyframes/UIKeyframes$PastedKeyframes
     117: astore        9
     119: new           #499                // class mchorse/bbs_mod/utils/keyframes/Keyframe
     122: dup
     123: ldc_w         #892                // String
     126: aload         6
     128: invokespecial #895                // Method mchorse/bbs_mod/utils/keyframes/Keyframe."<init>":(Ljava/lang/String;Lmchorse/bbs_mod/utils/keyframes/factories/IKeyframeFactory;)V
     131: astore        10
     133: aload         10
     135: aload         5
     137: iload         7
     139: invokevirtual #898                // Method mchorse/bbs_mod/data/types/ListType.getMap:(I)Lmchorse/bbs_mod/data/types/MapType;
     142: invokevirtual #902                // Method mchorse/bbs_mod/utils/keyframes/Keyframe.fromData:(Lmchorse/bbs_mod/data/types/BaseType;)V
     145: aload         9
     147: getfield      #904                // Field mchorse/bbs_mod/ui/framework/elements/input/keyframes/UIKeyframes$PastedKeyframes.keyframes:Ljava/util/List;
     150: aload         10
     152: invokeinterface #727,  2          // InterfaceMethod java/util/List.add:(Ljava/lang/Object;)Z
     157: pop
     158: iinc          7, 1
     161: goto          93
     164: goto          26
     167: aload_1
     168: areturn

  private mchorse.bbs_mod.data.types.MapType serializeKeyframes();
    Code:
       0: aload_0
       1: iconst_0
       2: anewarray     #537                // class mchorse/bbs_mod/utils/keyframes/factories/IKeyframeFactory
       5: invokevirtual #919                // Method serializeKeyframesByFactories:([Lmchorse/bbs_mod/utils/keyframes/factories/IKeyframeFactory;)Lmchorse/bbs_mod/data/types/MapType;
       8: areturn

  public mchorse.bbs_mod.data.types.MapType serializeKeyframesByFactories(mchorse.bbs_mod.utils.keyframes.factories.IKeyframeFactory...);
    Code:
       0: new           #922                // class java/util/HashSet
       3: dup
       4: invokespecial #923                // Method java/util/HashSet."<init>":()V
       7: astore_2
       8: aload_1
       9: ifnull        28
      12: aload_1
      13: arraylength
      14: ifle          28
      17: aload_2
      18: aload_1
      19: invokestatic  #929                // Method java/util/Arrays.asList:([Ljava/lang/Object;)Ljava/util/List;
      22: invokeinterface #932,  2          // InterfaceMethod java/util/Set.addAll:(Ljava/util/Collection;)Z
      27: pop
      28: new           #845                // class mchorse/bbs_mod/data/types/MapType
      31: dup
      32: invokespecial #933                // Method mchorse/bbs_mod/data/types/MapType."<init>":()V
      35: astore_3
      36: aload_0
      37: getfield      #101                // Field currentGraph:Lmchorse/bbs_mod/ui/framework/elements/input/keyframes/graphs/IUIKeyframeGraph;
      40: invokeinterface #460,  1          // InterfaceMethod mchorse/bbs_mod/ui/framework/elements/input/keyframes/graphs/IUIKeyframeGraph.getSheets:()Ljava/util/List;
      45: invokeinterface #466,  1          // InterfaceMethod java/util/List.iterator:()Ljava/util/Iterator;
      50: astore        4
      52: aload         4
      54: invokeinterface #471,  1          // InterfaceMethod java/util/Iterator.hasNext:()Z
      59: ifeq          245
      62: aload         4
      64: invokeinterface #474,  1          // InterfaceMethod java/util/Iterator.next:()Ljava/lang/Object;
      69: checkcast     #476                // class mchorse/bbs_mod/ui/framework/elements/input/keyframes/UIKeyframeSheet
      72: astore        5
      74: aload         5
      76: getfield      #480                // Field mchorse/bbs_mod/ui/framework/elements/input/keyframes/UIKeyframeSheet.selection:Lmchorse/bbs_mod/ui/framework/elements/input/keyframes/KeyframeSelection;
      79: invokevirtual #485                // Method mchorse/bbs_mod/ui/framework/elements/input/keyframes/KeyframeSelection.getSelected:()Ljava/util/List;
      82: astore        6
      84: aload         6
      86: invokeinterface #488,  1          // InterfaceMethod java/util/List.isEmpty:()Z
      91: ifeq          97
      94: goto          52
      97: aload_2
      98: invokeinterface #934,  1          // InterfaceMethod java/util/Set.isEmpty:()Z
     103: ifne          126
     106: aload_2
     107: aload         5
     109: getfield      #492                // Field mchorse/bbs_mod/ui/framework/elements/input/keyframes/UIKeyframeSheet.channel:Lmchorse/bbs_mod/utils/keyframes/KeyframeChannel;
     112: invokevirtual #525                // Method mchorse/bbs_mod/utils/keyframes/KeyframeChannel.getFactory:()Lmchorse/bbs_mod/utils/keyframes/factories/IKeyframeFactory;
     115: invokeinterface #937,  2          // InterfaceMethod java/util/Set.contains:(Ljava/lang/Object;)Z
     120: ifne          126
     123: goto          52
     126: new           #845                // class mchorse/bbs_mod/data/types/MapType
     129: dup
     130: invokespecial #933                // Method mchorse/bbs_mod/data/types/MapType."<init>":()V
     133: astore        7
     135: new           #873                // class mchorse/bbs_mod/data/types/ListType
     138: dup
     139: invokespecial #938                // Method mchorse/bbs_mod/data/types/ListType."<init>":()V
     142: astore        8
     144: aload         7
     146: ldc_w         #867                // String type
     149: getstatic     #865                // Field mchorse/bbs_mod/utils/keyframes/factories/KeyframeFactories.FACTORIES:Ljava/util/Map;
     152: aload         5
     154: getfield      #492                // Field mchorse/bbs_mod/ui/framework/elements/input/keyframes/UIKeyframeSheet.channel:Lmchorse/bbs_mod/utils/keyframes/KeyframeChannel;
     157: invokevirtual #525                // Method mchorse/bbs_mod/utils/keyframes/KeyframeChannel.getFactory:()Lmchorse/bbs_mod/utils/keyframes/factories/IKeyframeFactory;
     160: invokestatic  #944                // Method mchorse/bbs_mod/utils/CollectionUtils.getKey:(Ljava/util/Map;Ljava/lang/Object;)Ljava/lang/Object;
     163: checkcast     #853                // class java/lang/String
     166: invokevirtual #948                // Method mchorse/bbs_mod/data/types/MapType.putString:(Ljava/lang/String;Ljava/lang/String;)V
     169: aload         7
     171: ldc_w         #859                // String keyframes
     174: aload         8
     176: invokevirtual #951                // Method mchorse/bbs_mod/data/types/MapType.put:(Ljava/lang/String;Lmchorse/bbs_mod/data/types/BaseType;)V
     179: aload         6
     181: invokeinterface #466,  1          // InterfaceMethod java/util/List.iterator:()Ljava/util/Iterator;
     186: astore        9
     188: aload         9
     190: invokeinterface #471,  1          // InterfaceMethod java/util/Iterator.hasNext:()Z
     195: ifeq          223
     198: aload         9
     200: invokeinterface #474,  1          // InterfaceMethod java/util/Iterator.next:()Ljava/lang/Object;
     205: checkcast     #499                // class mchorse/bbs_mod/utils/keyframes/Keyframe
     208: astore        10
     210: aload         8
     212: aload         10
     214: invokevirtual #955                // Method mchorse/bbs_mod/utils/keyframes/Keyframe.toData:()Lmchorse/bbs_mod/data/types/BaseType;
     217: invokevirtual #957                // Method mchorse/bbs_mod/data/types/ListType.add:(Lmchorse/bbs_mod/data/types/BaseType;)V
     220: goto          188
     223: aload         8
     225: invokevirtual #958                // Method mchorse/bbs_mod/data/types/ListType.isEmpty:()Z
     228: ifne          242
     231: aload_3
     232: aload         5
     234: getfield      #961                // Field mchorse/bbs_mod/ui/framework/elements/input/keyframes/UIKeyframeSheet.id:Ljava/lang/String;
     237: aload         7
     239: invokevirtual #951                // Method mchorse/bbs_mod/data/types/MapType.put:(Ljava/lang/String;Lmchorse/bbs_mod/data/types/BaseType;)V
     242: goto          52
     245: aload_3
     246: areturn

  public mchorse.bbs_mod.data.types.MapType serializeKeyframesByPropertySuffixes(java.lang.String...);
    Code:
       0: new           #922                // class java/util/HashSet
       3: dup
       4: invokespecial #923                // Method java/util/HashSet."<init>":()V
       7: astore_2
       8: aload_1
       9: ifnull        28
      12: aload_1
      13: arraylength
      14: ifle          28
      17: aload_2
      18: aload_1
      19: invokestatic  #929                // Method java/util/Arrays.asList:([Ljava/lang/Object;)Ljava/util/List;
      22: invokeinterface #932,  2          // InterfaceMethod java/util/Set.addAll:(Ljava/util/Collection;)Z
      27: pop
      28: new           #845                // class mchorse/bbs_mod/data/types/MapType
      31: dup
      32: invokespecial #933                // Method mchorse/bbs_mod/data/types/MapType."<init>":()V
      35: astore_3
      36: aload_0
      37: getfield      #101                // Field currentGraph:Lmchorse/bbs_mod/ui/framework/elements/input/keyframes/graphs/IUIKeyframeGraph;
      40: invokeinterface #460,  1          // InterfaceMethod mchorse/bbs_mod/ui/framework/elements/input/keyframes/graphs/IUIKeyframeGraph.getSheets:()Ljava/util/List;
      45: invokeinterface #466,  1          // InterfaceMethod java/util/List.iterator:()Ljava/util/Iterator;
      50: astore        4
      52: aload         4
      54: invokeinterface #471,  1          // InterfaceMethod java/util/Iterator.hasNext:()Z
      59: ifeq          241
      62: aload         4
      64: invokeinterface #474,  1          // InterfaceMethod java/util/Iterator.next:()Ljava/lang/Object;
      69: checkcast     #476                // class mchorse/bbs_mod/ui/framework/elements/input/keyframes/UIKeyframeSheet
      72: astore        5
      74: aload         5
      76: getfield      #480                // Field mchorse/bbs_mod/ui/framework/elements/input/keyframes/UIKeyframeSheet.selection:Lmchorse/bbs_mod/ui/framework/elements/input/keyframes/KeyframeSelection;
      79: invokevirtual #485                // Method mchorse/bbs_mod/ui/framework/elements/input/keyframes/KeyframeSelection.getSelected:()Ljava/util/List;
      82: astore        6
      84: aload         6
      86: invokeinterface #488,  1          // InterfaceMethod java/util/List.isEmpty:()Z
      91: ifeq          97
      94: goto          52
      97: aload_2
      98: invokeinterface #934,  1          // InterfaceMethod java/util/Set.isEmpty:()Z
     103: ifne          122
     106: aload_0
     107: aload         5
     109: getfield      #961                // Field mchorse/bbs_mod/ui/framework/elements/input/keyframes/UIKeyframeSheet.id:Ljava/lang/String;
     112: aload_2
     113: invokevirtual #974                // Method matchesPropertySuffix:(Ljava/lang/String;Ljava/util/Set;)Z
     116: ifne          122
     119: goto          52
     122: new           #845                // class mchorse/bbs_mod/data/types/MapType
     125: dup
     126: invokespecial #933                // Method mchorse/bbs_mod/data/types/MapType."<init>":()V
     129: astore        7
     131: new           #873                // class mchorse/bbs_mod/data/types/ListType
     134: dup
     135: invokespecial #938                // Method mchorse/bbs_mod/data/types/ListType."<init>":()V
     138: astore        8
     140: aload         7
     142: ldc_w         #867                // String type
     145: getstatic     #865                // Field mchorse/bbs_mod/utils/keyframes/factories/KeyframeFactories.FACTORIES:Ljava/util/Map;
     148: aload         5
     150: getfield      #492                // Field mchorse/bbs_mod/ui/framework/elements/input/keyframes/UIKeyframeSheet.channel:Lmchorse/bbs_mod/utils/keyframes/KeyframeChannel;
     153: invokevirtual #525                // Method mchorse/bbs_mod/utils/keyframes/KeyframeChannel.getFactory:()Lmchorse/bbs_mod/utils/keyframes/factories/IKeyframeFactory;
     156: invokestatic  #944                // Method mchorse/bbs_mod/utils/CollectionUtils.getKey:(Ljava/util/Map;Ljava/lang/Object;)Ljava/lang/Object;
     159: checkcast     #853                // class java/lang/String
     162: invokevirtual #948                // Method mchorse/bbs_mod/data/types/MapType.putString:(Ljava/lang/String;Ljava/lang/String;)V
     165: aload         7
     167: ldc_w         #859                // String keyframes
     170: aload         8
     172: invokevirtual #951                // Method mchorse/bbs_mod/data/types/MapType.put:(Ljava/lang/String;Lmchorse/bbs_mod/data/types/BaseType;)V
     175: aload         6
     177: invokeinterface #466,  1          // InterfaceMethod java/util/List.iterator:()Ljava/util/Iterator;
     182: astore        9
     184: aload         9
     186: invokeinterface #471,  1          // InterfaceMethod java/util/Iterator.hasNext:()Z
     191: ifeq          219
     194: aload         9
     196: invokeinterface #474,  1          // InterfaceMethod java/util/Iterator.next:()Ljava/lang/Object;
     201: checkcast     #499                // class mchorse/bbs_mod/utils/keyframes/Keyframe
     204: astore        10
     206: aload         8
     208: aload         10
     210: invokevirtual #955                // Method mchorse/bbs_mod/utils/keyframes/Keyframe.toData:()Lmchorse/bbs_mod/data/types/BaseType;
     213: invokevirtual #957                // Method mchorse/bbs_mod/data/types/ListType.add:(Lmchorse/bbs_mod/data/types/BaseType;)V
     216: goto          184
     219: aload         8
     221: invokevirtual #958                // Method mchorse/bbs_mod/data/types/ListType.isEmpty:()Z
     224: ifne          238
     227: aload_3
     228: aload         5
     230: getfield      #961                // Field mchorse/bbs_mod/ui/framework/elements/input/keyframes/UIKeyframeSheet.id:Ljava/lang/String;
     233: aload         7
     235: invokevirtual #951                // Method mchorse/bbs_mod/data/types/MapType.put:(Ljava/lang/String;Lmchorse/bbs_mod/data/types/BaseType;)V
     238: goto          52
     241: aload_3
     242: areturn

  private boolean matchesPropertySuffix(java.lang.String, java.util.Set<java.lang.String>);
    Code:
       0: aload_2
       1: invokeinterface #851,  1          // InterfaceMethod java/util/Set.iterator:()Ljava/util/Iterator;
       6: astore_3
       7: aload_3
       8: invokeinterface #471,  1          // InterfaceMethod java/util/Iterator.hasNext:()Z
      13: ifeq          55
      16: aload_3
      17: invokeinterface #474,  1          // InterfaceMethod java/util/Iterator.next:()Ljava/lang/Object;
      22: checkcast     #853                // class java/lang/String
      25: astore        4
      27: aload_1
      28: aload         4
      30: invokevirtual #981                // Method java/lang/String.equals:(Ljava/lang/Object;)Z
      33: ifne          50
      36: aload_1
      37: aload         4
      39: invokedynamic #992,  0            // InvokeDynamic #29:makeConcatWithConstants:(Ljava/lang/String;)Ljava/lang/String;
      44: invokevirtual #996                // Method java/lang/String.endsWith:(Ljava/lang/String;)Z
      47: ifeq          52
      50: iconst_1
      51: ireturn
      52: goto          7
      55: iconst_0
      56: ireturn

  protected void pasteKeyframes(java.util.Map<java.lang.String, mchorse.bbs_mod.ui.framework.elements.input.keyframes.UIKeyframes$PastedKeyframes>, float, int);
    Code:
       0: aload_0
       1: getfield      #101                // Field currentGraph:Lmchorse/bbs_mod/ui/framework/elements/input/keyframes/graphs/IUIKeyframeGraph;
       4: invokeinterface #460,  1          // InterfaceMethod mchorse/bbs_mod/ui/framework/elements/input/keyframes/graphs/IUIKeyframeGraph.getSheets:()Ljava/util/List;
       9: astore        4
      11: aload_0
      12: getfield      #101                // Field currentGraph:Lmchorse/bbs_mod/ui/framework/elements/input/keyframes/graphs/IUIKeyframeGraph;
      15: invokeinterface #612,  1          // InterfaceMethod mchorse/bbs_mod/ui/framework/elements/input/keyframes/graphs/IUIKeyframeGraph.clearSelection:()V
      20: aload_1
      21: invokeinterface #1002,  1         // InterfaceMethod java/util/Map.size:()I
      26: iconst_1
      27: if_icmpne     95
      30: aload_0
      31: getfield      #101                // Field currentGraph:Lmchorse/bbs_mod/ui/framework/elements/input/keyframes/graphs/IUIKeyframeGraph;
      34: iload_3
      35: invokeinterface #590,  2          // InterfaceMethod mchorse/bbs_mod/ui/framework/elements/input/keyframes/graphs/IUIKeyframeGraph.getSheet:(I)Lmchorse/bbs_mod/ui/framework/elements/input/keyframes/UIKeyframeSheet;
      40: astore        5
      42: aload         5
      44: ifnonnull     60
      47: aload         4
      49: iconst_0
      50: invokeinterface #540,  2          // InterfaceMethod java/util/List.get:(I)Ljava/lang/Object;
      55: checkcast     #476                // class mchorse/bbs_mod/ui/framework/elements/input/keyframes/UIKeyframeSheet
      58: astore        5
      60: aload_0
      61: aload         5
      63: aload_1
      64: aload_1
      65: invokeinterface #1005,  1         // InterfaceMethod java/util/Map.keySet:()Ljava/util/Set;
      70: invokeinterface #851,  1          // InterfaceMethod java/util/Set.iterator:()Ljava/util/Iterator;
      75: invokeinterface #474,  1          // InterfaceMethod java/util/Iterator.next:()Ljava/lang/Object;
      80: invokeinterface #821,  2          // InterfaceMethod java/util/Map.get:(Ljava/lang/Object;)Ljava/lang/Object;
      85: checkcast     #9                  // class mchorse/bbs_mod/ui/framework/elements/input/keyframes/UIKeyframes$PastedKeyframes
      88: fload_2
      89: invokevirtual #1009               // Method pasteKeyframesTo:(Lmchorse/bbs_mod/ui/framework/elements/input/keyframes/UIKeyframeSheet;Lmchorse/bbs_mod/ui/framework/elements/input/keyframes/UIKeyframes$PastedKeyframes;F)V
      92: goto          377
      95: ldc_w         #1010               // float 3.4028235E38f
      98: fstore        5
     100: aload_1
     101: invokeinterface #1013,  1         // InterfaceMethod java/util/Map.entrySet:()Ljava/util/Set;
     106: invokeinterface #851,  1          // InterfaceMethod java/util/Set.iterator:()Ljava/util/Iterator;
     111: astore        6
     113: aload         6
     115: invokeinterface #471,  1          // InterfaceMethod java/util/Iterator.hasNext:()Z
     120: ifeq          217
     123: aload         6
     125: invokeinterface #474,  1          // InterfaceMethod java/util/Iterator.next:()Ljava/lang/Object;
     130: checkcast     #20                 // class java/util/Map$Entry
     133: astore        7
     135: aload         7
     137: invokeinterface #1014,  1         // InterfaceMethod java/util/Map$Entry.getValue:()Ljava/lang/Object;
     142: checkcast     #9                  // class mchorse/bbs_mod/ui/framework/elements/input/keyframes/UIKeyframes$PastedKeyframes
     145: getfield      #904                // Field mchorse/bbs_mod/ui/framework/elements/input/keyframes/UIKeyframes$PastedKeyframes.keyframes:Ljava/util/List;
     148: invokeinterface #488,  1          // InterfaceMethod java/util/List.isEmpty:()Z
     153: ifeq          159
     156: goto          113
     159: aload         7
     161: invokeinterface #1014,  1         // InterfaceMethod java/util/Map$Entry.getValue:()Ljava/lang/Object;
     166: checkcast     #9                  // class mchorse/bbs_mod/ui/framework/elements/input/keyframes/UIKeyframes$PastedKeyframes
     169: getfield      #904                // Field mchorse/bbs_mod/ui/framework/elements/input/keyframes/UIKeyframes$PastedKeyframes.keyframes:Ljava/util/List;
     172: invokedynamic #1025,  0           // InvokeDynamic #30:compare:()Ljava/util/Comparator;
     177: invokeinterface #1028,  2         // InterfaceMethod java/util/List.sort:(Ljava/util/Comparator;)V
     182: fload         5
     184: aload         7
     186: invokeinterface #1014,  1         // InterfaceMethod java/util/Map$Entry.getValue:()Ljava/lang/Object;
     191: checkcast     #9                  // class mchorse/bbs_mod/ui/framework/elements/input/keyframes/UIKeyframes$PastedKeyframes
     194: getfield      #904                // Field mchorse/bbs_mod/ui/framework/elements/input/keyframes/UIKeyframes$PastedKeyframes.keyframes:Ljava/util/List;
     197: iconst_0
     198: invokeinterface #540,  2          // InterfaceMethod java/util/List.get:(I)Ljava/lang/Object;
     203: checkcast     #499                // class mchorse/bbs_mod/utils/keyframes/Keyframe
     206: invokevirtual #698                // Method mchorse/bbs_mod/utils/keyframes/Keyframe.getTick:()F
     209: invokestatic  #714                // Method java/lang/Math.min:(FF)F
     212: fstore        5
     214: goto          113
     217: aload_1
     218: invokeinterface #1013,  1         // InterfaceMethod java/util/Map.entrySet:()Ljava/util/Set;
     223: invokeinterface #851,  1          // InterfaceMethod java/util/Set.iterator:()Ljava/util/Iterator;
     228: astore        6
     230: aload         6
     232: invokeinterface #471,  1          // InterfaceMethod java/util/Iterator.hasNext:()Z
     237: ifeq          377
     240: aload         6
     242: invokeinterface #474,  1          // InterfaceMethod java/util/Iterator.next:()Ljava/lang/Object;
     247: checkcast     #20                 // class java/util/Map$Entry
     250: astore        7
     252: aload         7
     254: invokeinterface #1014,  1         // InterfaceMethod java/util/Map$Entry.getValue:()Ljava/lang/Object;
     259: checkcast     #9                  // class mchorse/bbs_mod/ui/framework/elements/input/keyframes/UIKeyframes$PastedKeyframes
     262: getfield      #904                // Field mchorse/bbs_mod/ui/framework/elements/input/keyframes/UIKeyframes$PastedKeyframes.keyframes:Ljava/util/List;
     265: iconst_0
     266: invokeinterface #540,  2          // InterfaceMethod java/util/List.get:(I)Ljava/lang/Object;
     271: checkcast     #499                // class mchorse/bbs_mod/utils/keyframes/Keyframe
     274: invokevirtual #698                // Method mchorse/bbs_mod/utils/keyframes/Keyframe.getTick:()F
     277: fstore        8
     279: aload         4
     281: invokeinterface #466,  1          // InterfaceMethod java/util/List.iterator:()Ljava/util/Iterator;
     286: astore        9
     288: aload         9
     290: invokeinterface #471,  1          // InterfaceMethod java/util/Iterator.hasNext:()Z
     295: ifeq          374
     298: aload         9
     300: invokeinterface #474,  1          // InterfaceMethod java/util/Iterator.next:()Ljava/lang/Object;
     305: checkcast     #476                // class mchorse/bbs_mod/ui/framework/elements/input/keyframes/UIKeyframeSheet
     308: astore        10
     310: aload         10
     312: getfield      #961                // Field mchorse/bbs_mod/ui/framework/elements/input/keyframes/UIKeyframeSheet.id:Ljava/lang/String;
     315: aload         7
     317: invokeinterface #1030,  1         // InterfaceMethod java/util/Map$Entry.getKey:()Ljava/lang/Object;
     322: invokevirtual #981                // Method java/lang/String.equals:(Ljava/lang/Object;)Z
     325: ifne          331
     328: goto          288
     331: fload         5
     333: ldc_w         #1010               // float 3.4028235E38f
     336: fcmpl
     337: ifne          344
     340: fconst_0
     341: goto          349
     344: fload         8
     346: fload         5
     348: fsub
     349: fstore        11
     351: aload_0
     352: aload         10
     354: aload         7
     356: invokeinterface #1014,  1         // InterfaceMethod java/util/Map$Entry.getValue:()Ljava/lang/Object;
     361: checkcast     #9                  // class mchorse/bbs_mod/ui/framework/elements/input/keyframes/UIKeyframes$PastedKeyframes
     364: fload_2
     365: fload         11
     367: fadd
     368: invokevirtual #1009               // Method pasteKeyframesTo:(Lmchorse/bbs_mod/ui/framework/elements/input/keyframes/UIKeyframeSheet;Lmchorse/bbs_mod/ui/framework/elements/input/keyframes/UIKeyframes$PastedKeyframes;F)V
     371: goto          288
     374: goto          230
     377: aload_0
     378: getfield      #101                // Field currentGraph:Lmchorse/bbs_mod/ui/framework/elements/input/keyframes/graphs/IUIKeyframeGraph;
     381: invokeinterface #661,  1          // InterfaceMethod mchorse/bbs_mod/ui/framework/elements/input/keyframes/graphs/IUIKeyframeGraph.pickSelected:()V
     386: return

  private void pasteKeyframesTo(mchorse.bbs_mod.ui.framework.elements.input.keyframes.UIKeyframeSheet, mchorse.bbs_mod.ui.framework.elements.input.keyframes.UIKeyframes$PastedKeyframes, float);
    Code:
       0: aload_1
       1: getfield      #492                // Field mchorse/bbs_mod/ui/framework/elements/input/keyframes/UIKeyframeSheet.channel:Lmchorse/bbs_mod/utils/keyframes/KeyframeChannel;
       4: invokevirtual #525                // Method mchorse/bbs_mod/utils/keyframes/KeyframeChannel.getFactory:()Lmchorse/bbs_mod/utils/keyframes/factories/IKeyframeFactory;
       7: aload_2
       8: getfield      #1037               // Field mchorse/bbs_mod/ui/framework/elements/input/keyframes/UIKeyframes$PastedKeyframes.factory:Lmchorse/bbs_mod/utils/keyframes/factories/IKeyframeFactory;
      11: if_acmpeq     15
      14: return
      15: aload_2
      16: getfield      #904                // Field mchorse/bbs_mod/ui/framework/elements/input/keyframes/UIKeyframes$PastedKeyframes.keyframes:Ljava/util/List;
      19: iconst_0
      20: invokeinterface #540,  2          // InterfaceMethod java/util/List.get:(I)Ljava/lang/Object;
      25: checkcast     #499                // class mchorse/bbs_mod/utils/keyframes/Keyframe
      28: invokevirtual #698                // Method mchorse/bbs_mod/utils/keyframes/Keyframe.getTick:()F
      31: fstore        4
      33: new           #720                // class java/util/ArrayList
      36: dup
      37: invokespecial #721                // Method java/util/ArrayList."<init>":()V
      40: astore        5
      42: aload_2
      43: getfield      #904                // Field mchorse/bbs_mod/ui/framework/elements/input/keyframes/UIKeyframes$PastedKeyframes.keyframes:Ljava/util/List;
      46: invokeinterface #466,  1          // InterfaceMethod java/util/List.iterator:()Ljava/util/Iterator;
      51: astore        6
      53: aload         6
      55: invokeinterface #471,  1          // InterfaceMethod java/util/Iterator.hasNext:()Z
      60: ifeq          140
      63: aload         6
      65: invokeinterface #474,  1          // InterfaceMethod java/util/Iterator.next:()Ljava/lang/Object;
      70: checkcast     #499                // class mchorse/bbs_mod/utils/keyframes/Keyframe
      73: astore        7
      75: aload         7
      77: aload         7
      79: invokevirtual #698                // Method mchorse/bbs_mod/utils/keyframes/Keyframe.getTick:()F
      82: fload         4
      84: fsub
      85: fload_3
      86: fadd
      87: invokevirtual #756                // Method mchorse/bbs_mod/utils/keyframes/Keyframe.setTick:(F)V
      90: aload_1
      91: getfield      #492                // Field mchorse/bbs_mod/ui/framework/elements/input/keyframes/UIKeyframeSheet.channel:Lmchorse/bbs_mod/utils/keyframes/KeyframeChannel;
      94: aload         7
      96: invokevirtual #698                // Method mchorse/bbs_mod/utils/keyframes/Keyframe.getTick:()F
      99: aload         7
     101: invokevirtual #543                // Method mchorse/bbs_mod/utils/keyframes/Keyframe.getValue:()Ljava/lang/Object;
     104: invokevirtual #750                // Method mchorse/bbs_mod/utils/keyframes/KeyframeChannel.insert:(FLjava/lang/Object;)I
     107: istore        8
     109: aload_1
     110: getfield      #492                // Field mchorse/bbs_mod/ui/framework/elements/input/keyframes/UIKeyframeSheet.channel:Lmchorse/bbs_mod/utils/keyframes/KeyframeChannel;
     113: iload         8
     115: invokevirtual #639                // Method mchorse/bbs_mod/utils/keyframes/KeyframeChannel.get:(I)Lmchorse/bbs_mod/utils/keyframes/Keyframe;
     118: astore        9
     120: aload         9
     122: aload         7
     124: invokevirtual #752                // Method mchorse/bbs_mod/utils/keyframes/Keyframe.copy:(Lmchorse/bbs_mod/utils/keyframes/Keyframe;)V
     127: aload         5
     129: aload         9
     131: invokeinterface #727,  2          // InterfaceMethod java/util/List.add:(Ljava/lang/Object;)Z
     136: pop
     137: goto          53
     140: aload         5
     142: invokeinterface #466,  1          // InterfaceMethod java/util/List.iterator:()Ljava/util/Iterator;
     147: astore        6
     149: aload         6
     151: invokeinterface #471,  1          // InterfaceMethod java/util/Iterator.hasNext:()Z
     156: ifeq          195
     159: aload         6
     161: invokeinterface #474,  1          // InterfaceMethod java/util/Iterator.next:()Ljava/lang/Object;
     166: checkcast     #499                // class mchorse/bbs_mod/utils/keyframes/Keyframe
     169: astore        7
     171: aload_1
     172: getfield      #480                // Field mchorse/bbs_mod/ui/framework/elements/input/keyframes/UIKeyframeSheet.selection:Lmchorse/bbs_mod/ui/framework/elements/input/keyframes/KeyframeSelection;
     175: aload_1
     176: getfield      #492                // Field mchorse/bbs_mod/ui/framework/elements/input/keyframes/UIKeyframeSheet.channel:Lmchorse/bbs_mod/utils/keyframes/KeyframeChannel;
     179: invokevirtual #623                // Method mchorse/bbs_mod/utils/keyframes/KeyframeChannel.getKeyframes:()Ljava/util/List;
     182: aload         7
     184: invokeinterface #627,  2          // InterfaceMethod java/util/List.indexOf:(Ljava/lang/Object;)I
     189: invokevirtual #680                // Method mchorse/bbs_mod/ui/framework/elements/input/keyframes/KeyframeSelection.add:(I)V
     192: goto          149
     195: return

  public mchorse.bbs_mod.ui.framework.elements.input.keyframes.UIKeyframes backgroundRenderer(java.util.function.Consumer<mchorse.bbs_mod.ui.framework.UIContext>);
    Code:
       0: aload_0
       1: aload_1
       2: putfield      #1046               // Field backgroundRender:Ljava/util/function/Consumer;
       5: aload_0
       6: areturn

  public mchorse.bbs_mod.ui.framework.elements.input.keyframes.UIKeyframes duration(java.util.function.Supplier<java.lang.Integer>);
    Code:
       0: aload_0
       1: aload_1
       2: putfield      #1050               // Field duration:Ljava/util/function/Supplier;
       5: aload_0
       6: areturn

  public mchorse.bbs_mod.ui.framework.elements.input.keyframes.graphs.IUIKeyframeGraph getGraph();
    Code:
       0: aload_0
       1: getfield      #101                // Field currentGraph:Lmchorse/bbs_mod/ui/framework/elements/input/keyframes/graphs/IUIKeyframeGraph;
       4: areturn

  public mchorse.bbs_mod.ui.framework.elements.input.keyframes.UIKeyframes setPresetsPreview(mchorse.bbs_mod.ui.utils.presets.UICopyPasteController$IPresetPreview);
    Code:
       0: aload_0
       1: getfield      #180                // Field copyPasteController:Lmchorse/bbs_mod/ui/utils/presets/UICopyPasteController;
       4: aload_1
       5: invokevirtual #1056               // Method mchorse/bbs_mod/ui/utils/presets/UICopyPasteController.preview:(Lmchorse/bbs_mod/ui/utils/presets/UICopyPasteController$IPresetPreview;)Lmchorse/bbs_mod/ui/utils/presets/UICopyPasteController;
       8: pop
       9: aload_0
      10: areturn

  public mchorse.bbs_mod.ui.utils.Scale getXAxis();
    Code:
       0: aload_0
       1: getfield      #118                // Field xAxis:Lmchorse/bbs_mod/ui/utils/Scale;
       4: areturn

  public int getDuration();
    Code:
       0: aload_0
       1: getfield      #1050               // Field duration:Ljava/util/function/Supplier;
       4: ifnonnull     11
       7: iconst_0
       8: goto          26
      11: aload_0
      12: getfield      #1050               // Field duration:Ljava/util/function/Supplier;
      15: invokeinterface #1064,  1         // InterfaceMethod java/util/function/Supplier.get:()Ljava/lang/Object;
      20: checkcast     #1066               // class java/lang/Integer
      23: invokevirtual #1069               // Method java/lang/Integer.intValue:()I
      26: ireturn

  protected float getPlayheadTick();
    Code:
       0: fconst_0
       1: freturn

  protected boolean hasOpenPoseLimbTracks();
    Code:
       0: aload_0
       1: getfield      #101                // Field currentGraph:Lmchorse/bbs_mod/ui/framework/elements/input/keyframes/graphs/IUIKeyframeGraph;
       4: invokeinterface #460,  1          // InterfaceMethod mchorse/bbs_mod/ui/framework/elements/input/keyframes/graphs/IUIKeyframeGraph.getSheets:()Ljava/util/List;
       9: invokeinterface #466,  1          // InterfaceMethod java/util/List.iterator:()Ljava/util/Iterator;
      14: astore_1
      15: aload_1
      16: invokeinterface #471,  1          // InterfaceMethod java/util/Iterator.hasNext:()Z
      21: ifeq          53
      24: aload_1
      25: invokeinterface #474,  1          // InterfaceMethod java/util/Iterator.next:()Ljava/lang/Object;
      30: checkcast     #476                // class mchorse/bbs_mod/ui/framework/elements/input/keyframes/UIKeyframeSheet
      33: astore_2
      34: aload_2
      35: getfield      #1073               // Field mchorse/bbs_mod/ui/framework/elements/input/keyframes/UIKeyframeSheet.groupHeader:Z
      38: ifne          50
      41: aload_2
      42: invokestatic  #1079               // Method mchorse/bbs_mod/ui/framework/elements/input/keyframes/factories/UITransformKeyframeFactory.isPoseLimbTrack:(Lmchorse/bbs_mod/ui/framework/elements/input/keyframes/UIKeyframeSheet;)Z
      45: ifeq          50
      48: iconst_1
      49: ireturn
      50: goto          15
      53: iconst_0
      54: ireturn

  public boolean isSelecting();
    Code:
       0: aload_0
       1: getfield      #1082               // Field selecting:Z
       4: ireturn

  public boolean isNavigating();
    Code:
       0: aload_0
       1: getfield      #1085               // Field navigating:Z
       4: ireturn

  public void removeAllSheets();
    Code:
       0: aload_0
       1: getfield      #99                 // Field dopeSheet:Lmchorse/bbs_mod/ui/framework/elements/input/keyframes/graphs/UIKeyframeDopeSheet;
       4: invokevirtual #1088               // Method mchorse/bbs_mod/ui/framework/elements/input/keyframes/graphs/UIKeyframeDopeSheet.removeAllSheets:()V
       7: return

  public void addSheet(mchorse.bbs_mod.ui.framework.elements.input.keyframes.UIKeyframeSheet);
    Code:
       0: aload_0
       1: getfield      #99                 // Field dopeSheet:Lmchorse/bbs_mod/ui/framework/elements/input/keyframes/graphs/UIKeyframeDopeSheet;
       4: aload_1
       5: invokevirtual #1091               // Method mchorse/bbs_mod/ui/framework/elements/input/keyframes/graphs/UIKeyframeDopeSheet.addSheet:(Lmchorse/bbs_mod/ui/framework/elements/input/keyframes/UIKeyframeSheet;)V
       8: return

  public void pickKeyframe(mchorse.bbs_mod.utils.keyframes.Keyframe);
    Code:
       0: aload_0
       1: invokevirtual #454                // Method getGraph:()Lmchorse/bbs_mod/ui/framework/elements/input/keyframes/graphs/IUIKeyframeGraph;
       4: aload_1
       5: invokeinterface #1095,  2         // InterfaceMethod mchorse/bbs_mod/ui/framework/elements/input/keyframes/graphs/IUIKeyframeGraph.onCallback:(Lmchorse/bbs_mod/utils/keyframes/Keyframe;)V
      10: aload_0
      11: getfield      #120                // Field callback:Ljava/util/function/Consumer;
      14: ifnull        27
      17: aload_0
      18: getfield      #120                // Field callback:Ljava/util/function/Consumer;
      21: aload_1
      22: invokeinterface #1099,  2         // InterfaceMethod java/util/function/Consumer.accept:(Ljava/lang/Object;)V
      27: return

  public int toGraphX(double);
    Code:
       0: aload_0
       1: getfield      #118                // Field xAxis:Lmchorse/bbs_mod/ui/utils/Scale;
       4: dload_1
       5: invokevirtual #1104               // Method mchorse/bbs_mod/ui/utils/Scale.to:(D)D
       8: d2i
       9: ireturn

  public double fromGraphX(int);
    Code:
       0: aload_0
       1: getfield      #118                // Field xAxis:Lmchorse/bbs_mod/ui/utils/Scale;
       4: iload_1
       5: i2d
       6: invokevirtual #1107               // Method mchorse/bbs_mod/ui/utils/Scale.from:(D)D
       9: dreturn

  public void resetView();
    Code:
       0: aload_0
       1: getfield      #101                // Field currentGraph:Lmchorse/bbs_mod/ui/framework/elements/input/keyframes/graphs/IUIKeyframeGraph;
       4: invokeinterface #1108,  1         // InterfaceMethod mchorse/bbs_mod/ui/framework/elements/input/keyframes/graphs/IUIKeyframeGraph.resetView:()V
       9: return

  public void resetViewX();
    Code:
       0: iconst_0
       1: istore_1
       2: ldc_w         #769                // int 2147483647
       5: istore_2
       6: ldc_w         #770                // int -2147483648
       9: istore_3
      10: aload_0
      11: getfield      #101                // Field currentGraph:Lmchorse/bbs_mod/ui/framework/elements/input/keyframes/graphs/IUIKeyframeGraph;
      14: invokeinterface #460,  1          // InterfaceMethod mchorse/bbs_mod/ui/framework/elements/input/keyframes/graphs/IUIKeyframeGraph.getSheets:()Ljava/util/List;
      19: invokeinterface #466,  1          // InterfaceMethod java/util/List.iterator:()Ljava/util/Iterator;
      24: astore        4
      26: aload         4
      28: invokeinterface #471,  1          // InterfaceMethod java/util/Iterator.hasNext:()Z
      33: ifeq          133
      36: aload         4
      38: invokeinterface #474,  1          // InterfaceMethod java/util/Iterator.next:()Ljava/lang/Object;
      43: checkcast     #476                // class mchorse/bbs_mod/ui/framework/elements/input/keyframes/UIKeyframeSheet
      46: astore        5
      48: aload         5
      50: getfield      #492                // Field mchorse/bbs_mod/ui/framework/elements/input/keyframes/UIKeyframeSheet.channel:Lmchorse/bbs_mod/utils/keyframes/KeyframeChannel;
      53: invokevirtual #623                // Method mchorse/bbs_mod/utils/keyframes/KeyframeChannel.getKeyframes:()Ljava/util/List;
      56: astore        6
      58: aload         6
      60: invokeinterface #466,  1          // InterfaceMethod java/util/List.iterator:()Ljava/util/Iterator;
      65: astore        7
      67: aload         7
      69: invokeinterface #471,  1          // InterfaceMethod java/util/Iterator.hasNext:()Z
      74: ifeq          118
      77: aload         7
      79: invokeinterface #474,  1          // InterfaceMethod java/util/Iterator.next:()Ljava/lang/Object;
      84: astore        8
      86: aload         8
      88: checkcast     #499                // class mchorse/bbs_mod/utils/keyframes/Keyframe
      91: astore        9
      93: aload         9
      95: invokevirtual #698                // Method mchorse/bbs_mod/utils/keyframes/Keyframe.getTick:()F
      98: f2i
      99: iload_2
     100: invokestatic  #1110               // Method java/lang/Integer.min:(II)I
     103: istore_2
     104: aload         9
     106: invokevirtual #698                // Method mchorse/bbs_mod/utils/keyframes/Keyframe.getTick:()F
     109: f2i
     110: iload_3
     111: invokestatic  #1111               // Method java/lang/Integer.max:(II)I
     114: istore_3
     115: goto          67
     118: iload_1
     119: aload         6
     121: invokeinterface #529,  1          // InterfaceMethod java/util/List.size:()I
     126: invokestatic  #775                // Method java/lang/Math.max:(II)I
     129: istore_1
     130: goto          26
     133: iload_1
     134: iconst_1
     135: if_icmpgt     145
     138: iconst_0
     139: istore_2
     140: aload_0
     141: invokevirtual #1113               // Method getDuration:()I
     144: istore_3
     145: aload_0
     146: getfield      #101                // Field currentGraph:Lmchorse/bbs_mod/ui/framework/elements/input/keyframes/graphs/IUIKeyframeGraph;
     149: instanceof    #94                 // class mchorse/bbs_mod/ui/framework/elements/input/keyframes/graphs/UIKeyframeDopeSheet
     152: ifeq          167
     155: aload_0
     156: getfield      #101                // Field currentGraph:Lmchorse/bbs_mod/ui/framework/elements/input/keyframes/graphs/IUIKeyframeGraph;
     159: invokeinterface #1116,  1         // InterfaceMethod mchorse/bbs_mod/ui/framework/elements/input/keyframes/graphs/IUIKeyframeGraph.getSidebarWidth:()I
     164: goto          168
     167: iconst_0
     168: istore        4
     170: iload_3
     171: iload_2
     172: isub
     173: invokestatic  #1120               // Method java/lang/Math.abs:(I)I
     176: i2f
     177: ldc_w         #1121               // float 0.01f
     180: fcmpl
     181: ifle          238
     184: aload_0
     185: getfield      #118                // Field xAxis:Lmchorse/bbs_mod/ui/utils/Scale;
     188: iload_2
     189: i2d
     190: iload_3
     191: i2d
     192: aload_0
     193: getfield      #107                // Field area:Lmchorse/bbs_mod/ui/utils/Area;
     196: getfield      #1126               // Field mchorse/bbs_mod/ui/utils/Area.w:I
     199: iload         4
     201: isub
     202: i2d
     203: ldc2_w        #1127               // double 30.0d
     206: invokevirtual #1132               // Method mchorse/bbs_mod/ui/utils/Scale.viewOffset:(DDDD)V
     209: aload_0
     210: getfield      #118                // Field xAxis:Lmchorse/bbs_mod/ui/utils/Scale;
     213: aload_0
     214: getfield      #118                // Field xAxis:Lmchorse/bbs_mod/ui/utils/Scale;
     217: invokevirtual #1136               // Method mchorse/bbs_mod/ui/utils/Scale.getShift:()D
     220: iload         4
     222: i2d
     223: aload_0
     224: getfield      #118                // Field xAxis:Lmchorse/bbs_mod/ui/utils/Scale;
     227: invokevirtual #1139               // Method mchorse/bbs_mod/ui/utils/Scale.getZoom:()D
     230: ddiv
     231: dsub
     232: invokevirtual #1143               // Method mchorse/bbs_mod/ui/utils/Scale.setShift:(D)V
     235: goto          275
     238: aload_0
     239: getfield      #118                // Field xAxis:Lmchorse/bbs_mod/ui/utils/Scale;
     242: dconst_0
     243: ldc2_w        #1144               // double 2.0d
     246: invokevirtual #1149               // Method mchorse/bbs_mod/ui/utils/Scale.set:(DD)V
     249: aload_0
     250: getfield      #118                // Field xAxis:Lmchorse/bbs_mod/ui/utils/Scale;
     253: aload_0
     254: getfield      #118                // Field xAxis:Lmchorse/bbs_mod/ui/utils/Scale;
     257: invokevirtual #1136               // Method mchorse/bbs_mod/ui/utils/Scale.getShift:()D
     260: iload         4
     262: i2d
     263: aload_0
     264: getfield      #118                // Field xAxis:Lmchorse/bbs_mod/ui/utils/Scale;
     267: invokevirtual #1139               // Method mchorse/bbs_mod/ui/utils/Scale.getZoom:()D
     270: ddiv
     271: dsub
     272: invokevirtual #1143               // Method mchorse/bbs_mod/ui/utils/Scale.setShift:(D)V
     275: return

  public mchorse.bbs_mod.ui.utils.Area getGrabbingArea(mchorse.bbs_mod.ui.framework.UIContext);
    Code:
       0: new           #1123               // class mchorse/bbs_mod/ui/utils/Area
       3: dup
       4: invokespecial #1155               // Method mchorse/bbs_mod/ui/utils/Area."<init>":()V
       7: astore_2
       8: aload_2
       9: aload_0
      10: getfield      #692                // Field originalX:I
      13: aload_0
      14: getfield      #694                // Field originalY:I
      17: aload_1
      18: getfield      #593                // Field mchorse/bbs_mod/ui/framework/UIContext.mouseX:I
      21: aload_1
      22: getfield      #586                // Field mchorse/bbs_mod/ui/framework/UIContext.mouseY:I
      25: iconst_3
      26: invokevirtual #1159               // Method mchorse/bbs_mod/ui/utils/Area.setPoints:(IIIII)V
      29: aload_2
      30: areturn

  public void resize();
    Code:
       0: aload_0
       1: getfield      #118                // Field xAxis:Lmchorse/bbs_mod/ui/utils/Scale;
       4: invokevirtual #1163               // Method mchorse/bbs_mod/ui/utils/Scale.getMinValue:()D
       7: dstore_1
       8: aload_0
       9: getfield      #118                // Field xAxis:Lmchorse/bbs_mod/ui/utils/Scale;
      12: invokevirtual #1166               // Method mchorse/bbs_mod/ui/utils/Scale.getMaxValue:()D
      15: dstore_3
      16: aload_0
      17: invokespecial #1168               // Method mchorse/bbs_mod/ui/framework/elements/UIElement.resize:()V
      20: aload_0
      21: getfield      #101                // Field currentGraph:Lmchorse/bbs_mod/ui/framework/elements/input/keyframes/graphs/IUIKeyframeGraph;
      24: invokeinterface #1169,  1         // InterfaceMethod mchorse/bbs_mod/ui/framework/elements/input/keyframes/graphs/IUIKeyframeGraph.resize:()V
      29: aload_0
      30: invokevirtual #419                // Method updateSidebarResizerState:()V
      33: dload_1
      34: dload_3
      35: invokestatic  #1174               // Method mchorse/bbs_mod/math/Operation.equals:(DD)Z
      38: ifne          50
      41: aload_0
      42: getfield      #118                // Field xAxis:Lmchorse/bbs_mod/ui/utils/Scale;
      45: dload_1
      46: dload_3
      47: invokevirtual #1177               // Method mchorse/bbs_mod/ui/utils/Scale.view:(DD)V
      50: return

  protected boolean subMouseClicked(mchorse.bbs_mod.ui.framework.UIContext);
    Code:
       0: aload_0
       1: getfield      #101                // Field currentGraph:Lmchorse/bbs_mod/ui/framework/elements/input/keyframes/graphs/IUIKeyframeGraph;
       4: aload_1
       5: invokeinterface #1184,  2         // InterfaceMethod mchorse/bbs_mod/ui/framework/elements/input/keyframes/graphs/IUIKeyframeGraph.mouseClicked:(Lmchorse/bbs_mod/ui/framework/UIContext;)Z
      10: ifeq          15
      13: iconst_1
      14: ireturn
      15: aload_0
      16: getfield      #684                // Field scaling:Z
      19: ifeq          29
      22: aload_0
      23: iconst_0
      24: putfield      #684                // Field scaling:Z
      27: iconst_1
      28: ireturn
      29: aload_0
      30: getfield      #718                // Field stacking:Z
      33: ifeq          55
      36: aload_0
      37: aload_1
      38: getfield      #1187               // Field mchorse/bbs_mod/ui/framework/UIContext.mouseButton:I
      41: iconst_1
      42: if_icmpne     49
      45: iconst_1
      46: goto          50
      49: iconst_0
      50: invokevirtual #1189               // Method stackKeyframes:(Z)V
      53: iconst_1
      54: ireturn
      55: aload_0
      56: getfield      #107                // Field area:Lmchorse/bbs_mod/ui/utils/Area;
      59: aload_1
      60: invokevirtual #1192               // Method mchorse/bbs_mod/ui/utils/Area.isInside:(Lmchorse/bbs_mod/ui/framework/UIContext;)Z
      63: ifeq          176
      66: aload_0
      67: aload_0
      68: aload_1
      69: getfield      #593                // Field mchorse/bbs_mod/ui/framework/UIContext.mouseX:I
      72: dup_x1
      73: putfield      #692                // Field originalX:I
      76: putfield      #1194               // Field lastX:I
      79: aload_0
      80: aload_0
      81: aload_1
      82: getfield      #586                // Field mchorse/bbs_mod/ui/framework/UIContext.mouseY:I
      85: dup_x1
      86: putfield      #694                // Field originalY:I
      89: putfield      #1196               // Field lastY:I
      92: invokestatic  #1199               // Method mchorse/bbs_mod/graphics/window/Window.isCtrlPressed:()Z
      95: ifeq          113
      98: aload_1
      99: getfield      #1187               // Field mchorse/bbs_mod/ui/framework/UIContext.mouseButton:I
     102: ifne          113
     105: aload_0
     106: aload_1
     107: invokevirtual #1202               // Method removeOrCreateKeyframe:(Lmchorse/bbs_mod/ui/framework/UIContext;)V
     110: goto          162
     113: invokestatic  #1205               // Method mchorse/bbs_mod/graphics/window/Window.isAltPressed:()Z
     116: ifeq          134
     119: aload_1
     120: getfield      #1187               // Field mchorse/bbs_mod/ui/framework/UIContext.mouseButton:I
     123: ifne          134
     126: aload_0
     127: aload_1
     128: invokevirtual #1208               // Method duplicateOrSelectColumn:(Lmchorse/bbs_mod/ui/framework/UIContext;)V
     131: goto          162
     134: aload_1
     135: getfield      #1187               // Field mchorse/bbs_mod/ui/framework/UIContext.mouseButton:I
     138: ifne          149
     141: aload_0
     142: aload_1
     143: invokevirtual #1211               // Method pickOrStartSelectingKeyframes:(Lmchorse/bbs_mod/ui/framework/UIContext;)V
     146: goto          162
     149: aload_1
     150: getfield      #1187               // Field mchorse/bbs_mod/ui/framework/UIContext.mouseButton:I
     153: iconst_2
     154: if_icmpne     162
     157: aload_0
     158: iconst_1
     159: putfield      #1085               // Field navigating:Z
     162: aload_1
     163: getfield      #1187               // Field mchorse/bbs_mod/ui/framework/UIContext.mouseButton:I
     166: iconst_1
     167: if_icmpeq     174
     170: iconst_1
     171: goto          175
     174: iconst_0
     175: ireturn
     176: aload_0
     177: aload_1
     178: invokespecial #1213               // Method mchorse/bbs_mod/ui/framework/elements/UIElement.subMouseClicked:(Lmchorse/bbs_mod/ui/framework/UIContext;)Z
     181: ireturn

  private void removeOrCreateKeyframe(mchorse.bbs_mod.ui.framework.UIContext);
    Code:
       0: aload_0
       1: getfield      #101                // Field currentGraph:Lmchorse/bbs_mod/ui/framework/elements/input/keyframes/graphs/IUIKeyframeGraph;
       4: aload_1
       5: getfield      #593                // Field mchorse/bbs_mod/ui/framework/UIContext.mouseX:I
       8: aload_1
       9: getfield      #586                // Field mchorse/bbs_mod/ui/framework/UIContext.mouseY:I
      12: invokeinterface #666,  3          // InterfaceMethod mchorse/bbs_mod/ui/framework/elements/input/keyframes/graphs/IUIKeyframeGraph.findKeyframe:(II)Lmchorse/bbs_mod/utils/Pair;
      17: astore_2
      18: aload_2
      19: ifnull        41
      22: aload_0
      23: getfield      #101                // Field currentGraph:Lmchorse/bbs_mod/ui/framework/elements/input/keyframes/graphs/IUIKeyframeGraph;
      26: aload_2
      27: getfield      #674                // Field mchorse/bbs_mod/utils/Pair.a:Ljava/lang/Object;
      30: checkcast     #499                // class mchorse/bbs_mod/utils/keyframes/Keyframe
      33: invokeinterface #1216,  2         // InterfaceMethod mchorse/bbs_mod/ui/framework/elements/input/keyframes/graphs/IUIKeyframeGraph.removeKeyframe:(Lmchorse/bbs_mod/utils/keyframes/Keyframe;)V
      38: goto          59
      41: aload_0
      42: getfield      #101                // Field currentGraph:Lmchorse/bbs_mod/ui/framework/elements/input/keyframes/graphs/IUIKeyframeGraph;
      45: aload_1
      46: getfield      #593                // Field mchorse/bbs_mod/ui/framework/UIContext.mouseX:I
      49: aload_1
      50: getfield      #586                // Field mchorse/bbs_mod/ui/framework/UIContext.mouseY:I
      53: invokeinterface #1220,  3         // InterfaceMethod mchorse/bbs_mod/ui/framework/elements/input/keyframes/graphs/IUIKeyframeGraph.addKeyframe:(II)Z
      58: pop
      59: return

  private void duplicateOrSelectColumn(mchorse.bbs_mod.ui.framework.UIContext);
    Code:
       0: aload_0
       1: getfield      #101                // Field currentGraph:Lmchorse/bbs_mod/ui/framework/elements/input/keyframes/graphs/IUIKeyframeGraph;
       4: invokeinterface #583,  1          // InterfaceMethod mchorse/bbs_mod/ui/framework/elements/input/keyframes/graphs/IUIKeyframeGraph.getSelected:()Lmchorse/bbs_mod/utils/keyframes/Keyframe;
       9: ifnull        51
      12: invokestatic  #652                // Method mchorse/bbs_mod/graphics/window/Window.isShiftPressed:()Z
      15: ifne          51
      18: aload_0
      19: aload_1
      20: getfield      #593                // Field mchorse/bbs_mod/ui/framework/UIContext.mouseX:I
      23: invokevirtual #597                // Method fromGraphX:(I)D
      26: invokestatic  #1224               // Method java/lang/Math.round:(D)J
      29: l2i
      30: istore_2
      31: aload_0
      32: aload_0
      33: pop
      34: aload_0
      35: invokevirtual #137                // Method serializeKeyframes:()Lmchorse/bbs_mod/data/types/MapType;
      38: invokestatic  #1226               // Method parseKeyframes:(Lmchorse/bbs_mod/data/types/MapType;)Ljava/util/Map;
      41: iload_2
      42: i2f
      43: aload_1
      44: getfield      #586                // Field mchorse/bbs_mod/ui/framework/UIContext.mouseY:I
      47: invokevirtual #1228               // Method pasteKeyframes:(Ljava/util/Map;FI)V
      50: return
      51: aload_0
      52: getfield      #101                // Field currentGraph:Lmchorse/bbs_mod/ui/framework/elements/input/keyframes/graphs/IUIKeyframeGraph;
      55: aload_1
      56: getfield      #593                // Field mchorse/bbs_mod/ui/framework/UIContext.mouseX:I
      59: invokeinterface #1231,  2         // InterfaceMethod mchorse/bbs_mod/ui/framework/elements/input/keyframes/graphs/IUIKeyframeGraph.selectByX:(I)V
      64: return

  private void pickOrStartSelectingKeyframes(mchorse.bbs_mod.ui.framework.UIContext);
    Code:
       0: aload_0
       1: getfield      #101                // Field currentGraph:Lmchorse/bbs_mod/ui/framework/elements/input/keyframes/graphs/IUIKeyframeGraph;
       4: aload_1
       5: getfield      #593                // Field mchorse/bbs_mod/ui/framework/UIContext.mouseX:I
       8: aload_1
       9: getfield      #586                // Field mchorse/bbs_mod/ui/framework/UIContext.mouseY:I
      12: invokeinterface #666,  3          // InterfaceMethod mchorse/bbs_mod/ui/framework/elements/input/keyframes/graphs/IUIKeyframeGraph.findKeyframe:(II)Lmchorse/bbs_mod/utils/Pair;
      17: astore_2
      18: aload_2
      19: ifnonnull     26
      22: aconst_null
      23: goto          33
      26: aload_2
      27: getfield      #674                // Field mchorse/bbs_mod/utils/Pair.a:Ljava/lang/Object;
      30: checkcast     #499                // class mchorse/bbs_mod/utils/keyframes/Keyframe
      33: astore_3
      34: invokestatic  #652                // Method mchorse/bbs_mod/graphics/window/Window.isShiftPressed:()Z
      37: istore        4
      39: iload         4
      41: ifeq          53
      44: aload_3
      45: ifnonnull     53
      48: aload_0
      49: iconst_1
      50: putfield      #1082               // Field selecting:Z
      53: aload_3
      54: ifnull        122
      57: aload_0
      58: getfield      #101                // Field currentGraph:Lmchorse/bbs_mod/ui/framework/elements/input/keyframes/graphs/IUIKeyframeGraph;
      61: aload_3
      62: invokeinterface #1234,  2         // InterfaceMethod mchorse/bbs_mod/ui/framework/elements/input/keyframes/graphs/IUIKeyframeGraph.getSheet:(Lmchorse/bbs_mod/utils/keyframes/Keyframe;)Lmchorse/bbs_mod/ui/framework/elements/input/keyframes/UIKeyframeSheet;
      67: astore        5
      69: iload         4
      71: ifne          95
      74: aload         5
      76: getfield      #480                // Field mchorse/bbs_mod/ui/framework/elements/input/keyframes/UIKeyframeSheet.selection:Lmchorse/bbs_mod/ui/framework/elements/input/keyframes/KeyframeSelection;
      79: aload_3
      80: invokevirtual #1238               // Method mchorse/bbs_mod/ui/framework/elements/input/keyframes/KeyframeSelection.has:(Lmchorse/bbs_mod/utils/keyframes/Keyframe;)Z
      83: ifne          95
      86: aload_0
      87: getfield      #101                // Field currentGraph:Lmchorse/bbs_mod/ui/framework/elements/input/keyframes/graphs/IUIKeyframeGraph;
      90: invokeinterface #612,  1          // InterfaceMethod mchorse/bbs_mod/ui/framework/elements/input/keyframes/graphs/IUIKeyframeGraph.clearSelection:()V
      95: aload         5
      97: getfield      #480                // Field mchorse/bbs_mod/ui/framework/elements/input/keyframes/UIKeyframeSheet.selection:Lmchorse/bbs_mod/ui/framework/elements/input/keyframes/KeyframeSelection;
     100: aload_3
     101: invokevirtual #1240               // Method mchorse/bbs_mod/ui/framework/elements/input/keyframes/KeyframeSelection.add:(Lmchorse/bbs_mod/utils/keyframes/Keyframe;)V
     104: aload_0
     105: getfield      #101                // Field currentGraph:Lmchorse/bbs_mod/ui/framework/elements/input/keyframes/graphs/IUIKeyframeGraph;
     108: invokeinterface #583,  1          // InterfaceMethod mchorse/bbs_mod/ui/framework/elements/input/keyframes/graphs/IUIKeyframeGraph.getSelected:()Lmchorse/bbs_mod/utils/keyframes/Keyframe;
     113: astore_3
     114: aload_0
     115: aload_3
     116: invokevirtual #1242               // Method pickKeyframe:(Lmchorse/bbs_mod/utils/keyframes/Keyframe;)V
     119: goto          143
     122: aload_0
     123: getfield      #1082               // Field selecting:Z
     126: ifne          143
     129: aload_0
     130: getfield      #101                // Field currentGraph:Lmchorse/bbs_mod/ui/framework/elements/input/keyframes/graphs/IUIKeyframeGraph;
     133: invokeinterface #612,  1          // InterfaceMethod mchorse/bbs_mod/ui/framework/elements/input/keyframes/graphs/IUIKeyframeGraph.clearSelection:()V
     138: aload_0
     139: aconst_null
     140: invokevirtual #1242               // Method pickKeyframe:(Lmchorse/bbs_mod/utils/keyframes/Keyframe;)V
     143: aload_0
     144: getfield      #1082               // Field selecting:Z
     147: ifne          215
     150: aload_0
     151: iconst_0
     152: putfield      #87                 // Field dragging:I
     155: aload_0
     156: aload_2
     157: putfield      #1244               // Field draggingData:Lmchorse/bbs_mod/utils/Pair;
     160: aload_2
     161: ifnull        182
     164: aload_2
     165: getfield      #812                // Field mchorse/bbs_mod/utils/Pair.b:Ljava/lang/Object;
     168: getstatic     #1250               // Field mchorse/bbs_mod/ui/framework/elements/input/keyframes/graphs/KeyframeType.REGULAR:Lmchorse/bbs_mod/ui/framework/elements/input/keyframes/graphs/KeyframeType;
     171: if_acmpeq     182
     174: aload_2
     175: getfield      #674                // Field mchorse/bbs_mod/utils/Pair.a:Ljava/lang/Object;
     178: checkcast     #499                // class mchorse/bbs_mod/utils/keyframes/Keyframe
     181: astore_3
     182: aload_0
     183: invokevirtual #1252               // Method cacheKeyframes:()V
     186: aload_3
     187: ifnull        215
     190: aload_0
     191: aload_3
     192: invokevirtual #698                // Method mchorse/bbs_mod/utils/keyframes/Keyframe.getTick:()F
     195: putfield      #1254               // Field originalT:F
     198: aload_0
     199: aload_3
     200: invokevirtual #672                // Method mchorse/bbs_mod/utils/keyframes/Keyframe.getFactory:()Lmchorse/bbs_mod/utils/keyframes/factories/IKeyframeFactory;
     203: aload_3
     204: invokevirtual #543                // Method mchorse/bbs_mod/utils/keyframes/Keyframe.getValue:()Ljava/lang/Object;
     207: invokeinterface #746,  2          // InterfaceMethod mchorse/bbs_mod/utils/keyframes/factories/IKeyframeFactory.copy:(Ljava/lang/Object;)Ljava/lang/Object;
     212: putfield      #1256               // Field originalV:Ljava/lang/Object;
     215: return

  protected boolean subMouseReleased(mchorse.bbs_mod.ui.framework.UIContext);
    Code:
       0: aload_0
       1: getfield      #101                // Field currentGraph:Lmchorse/bbs_mod/ui/framework/elements/input/keyframes/graphs/IUIKeyframeGraph;
       4: aload_1
       5: invokeinterface #1262,  2         // InterfaceMethod mchorse/bbs_mod/ui/framework/elements/input/keyframes/graphs/IUIKeyframeGraph.mouseReleased:(Lmchorse/bbs_mod/ui/framework/UIContext;)V
      10: aload_0
      11: getfield      #1082               // Field selecting:Z
      14: ifeq          31
      17: aload_0
      18: getfield      #101                // Field currentGraph:Lmchorse/bbs_mod/ui/framework/elements/input/keyframes/graphs/IUIKeyframeGraph;
      21: aload_0
      22: aload_1
      23: invokevirtual #1264               // Method getGrabbingArea:(Lmchorse/bbs_mod/ui/framework/UIContext;)Lmchorse/bbs_mod/ui/utils/Area;
      26: invokeinterface #1268,  2         // InterfaceMethod mchorse/bbs_mod/ui/framework/elements/input/keyframes/graphs/IUIKeyframeGraph.selectInArea:(Lmchorse/bbs_mod/ui/utils/Area;)V
      31: aload_0
      32: getfield      #87                 // Field dragging:I
      35: ifle          51
      38: aload_0
      39: invokevirtual #1270               // Method submitKeyframes:()V
      42: aload_0
      43: getfield      #101                // Field currentGraph:Lmchorse/bbs_mod/ui/framework/elements/input/keyframes/graphs/IUIKeyframeGraph;
      46: invokeinterface #661,  1          // InterfaceMethod mchorse/bbs_mod/ui/framework/elements/input/keyframes/graphs/IUIKeyframeGraph.pickSelected:()V
      51: aload_0
      52: iconst_0
      53: putfield      #1085               // Field navigating:Z
      56: aload_0
      57: iconst_0
      58: putfield      #1082               // Field selecting:Z
      61: aload_0
      62: iconst_m1
      63: putfield      #87                 // Field dragging:I
      66: aload_0
      67: aload_1
      68: invokespecial #1272               // Method mchorse/bbs_mod/ui/framework/elements/UIElement.subMouseReleased:(Lmchorse/bbs_mod/ui/framework/UIContext;)Z
      71: ireturn

  protected boolean subMouseScrolled(mchorse.bbs_mod.ui.framework.UIContext);
    Code:
       0: aload_0
       1: getfield      #107                // Field area:Lmchorse/bbs_mod/ui/utils/Area;
       4: aload_1
       5: invokevirtual #1192               // Method mchorse/bbs_mod/ui/utils/Area.isInside:(Lmchorse/bbs_mod/ui/framework/UIContext;)Z
       8: ifeq          57
      11: aload_0
      12: getfield      #718                // Field stacking:Z
      15: ifeq          57
      18: aload_0
      19: ldc2_w        #1274               // double 0.05000000074505806d
      22: aload_0
      23: getfield      #758                // Field stackOffset:F
      26: f2d
      27: invokestatic  #652                // Method mchorse/bbs_mod/graphics/window/Window.isShiftPressed:()Z
      30: ifeq          39
      33: ldc2_w        #1274               // double 0.05000000074505806d
      36: goto          40
      39: dconst_1
      40: aload_1
      41: getfield      #1278               // Field mchorse/bbs_mod/ui/framework/UIContext.mouseWheel:D
      44: invokestatic  #1281               // Method java/lang/Math.copySign:(DD)D
      47: dadd
      48: invokestatic  #741                // Method java/lang/Math.max:(DD)D
      51: d2f
      52: putfield      #758                // Field stackOffset:F
      55: iconst_1
      56: ireturn
      57: aload_0
      58: getfield      #107                // Field area:Lmchorse/bbs_mod/ui/utils/Area;
      61: aload_1
      62: invokevirtual #1192               // Method mchorse/bbs_mod/ui/utils/Area.isInside:(Lmchorse/bbs_mod/ui/framework/UIContext;)Z
      65: ifeq          94
      68: aload_0
      69: getfield      #1085               // Field navigating:Z
      72: ifne          94
      75: aload_0
      76: getfield      #684                // Field scaling:Z
      79: ifne          94
      82: aload_0
      83: getfield      #101                // Field currentGraph:Lmchorse/bbs_mod/ui/framework/elements/input/keyframes/graphs/IUIKeyframeGraph;
      86: aload_1
      87: invokeinterface #1284,  2         // InterfaceMethod mchorse/bbs_mod/ui/framework/elements/input/keyframes/graphs/IUIKeyframeGraph.mouseScrolled:(Lmchorse/bbs_mod/ui/framework/UIContext;)V
      92: iconst_1
      93: ireturn
      94: aload_0
      95: aload_1
      96: invokespecial #1286               // Method mchorse/bbs_mod/ui/framework/elements/UIElement.subMouseScrolled:(Lmchorse/bbs_mod/ui/framework/UIContext;)Z
      99: ireturn

  protected boolean subKeyPressed(mchorse.bbs_mod.ui.framework.UIContext);
    Code:
       0: aload_0
       1: getfield      #101                // Field currentGraph:Lmchorse/bbs_mod/ui/framework/elements/input/keyframes/graphs/IUIKeyframeGraph;
       4: aload_0
       5: getfield      #99                 // Field dopeSheet:Lmchorse/bbs_mod/ui/framework/elements/input/keyframes/graphs/UIKeyframeDopeSheet;
       8: if_acmpeq     35
      11: aload_1
      12: sipush        256
      15: invokevirtual #1291               // Method mchorse/bbs_mod/ui/framework/UIContext.isPressed:(I)Z
      18: ifeq          35
      21: aload_0
      22: getfield      #427                // Field single:Z
      25: ifne          35
      28: aload_0
      29: aconst_null
      30: invokevirtual #1293               // Method editSheet:(Lmchorse/bbs_mod/ui/framework/elements/input/keyframes/UIKeyframeSheet;)V
      33: iconst_1
      34: ireturn
      35: aload_0
      36: getfield      #684                // Field scaling:Z
      39: ifne          49
      42: aload_0
      43: getfield      #718                // Field stacking:Z
      46: ifeq          140
      49: aload_1
      50: sipush        256
      53: invokevirtual #1291               // Method mchorse/bbs_mod/ui/framework/UIContext.isPressed:(I)Z
      56: ifeq          140
      59: aload_0
      60: iconst_0
      61: putfield      #684                // Field scaling:Z
      64: aload_0
      65: getfield      #718                // Field stacking:Z
      68: ifeq          76
      71: aload_0
      72: iconst_1
      73: invokevirtual #1189               // Method stackKeyframes:(Z)V
      76: aload_0
      77: getfield      #92                 // Field scaleTicks:Ljava/util/Map;
      80: invokeinterface #1013,  1         // InterfaceMethod java/util/Map.entrySet:()Ljava/util/Set;
      85: invokeinterface #851,  1          // InterfaceMethod java/util/Set.iterator:()Ljava/util/Iterator;
      90: astore_2
      91: aload_2
      92: invokeinterface #471,  1          // InterfaceMethod java/util/Iterator.hasNext:()Z
      97: ifeq          138
     100: aload_2
     101: invokeinterface #474,  1          // InterfaceMethod java/util/Iterator.next:()Ljava/lang/Object;
     106: checkcast     #20                 // class java/util/Map$Entry
     109: astore_3
     110: aload_3
     111: invokeinterface #1030,  1         // InterfaceMethod java/util/Map$Entry.getKey:()Ljava/lang/Object;
     116: checkcast     #499                // class mchorse/bbs_mod/utils/keyframes/Keyframe
     119: aload_3
     120: invokeinterface #1014,  1         // InterfaceMethod java/util/Map$Entry.getValue:()Ljava/lang/Object;
     125: checkcast     #700                // class java/lang/Float
     128: invokevirtual #1296               // Method java/lang/Float.floatValue:()F
     131: iconst_1
     132: invokevirtual #1299               // Method mchorse/bbs_mod/utils/keyframes/Keyframe.setTick:(FZ)V
     135: goto          91
     138: iconst_1
     139: ireturn
     140: aload_0
     141: aload_1
     142: invokespecial #1301               // Method mchorse/bbs_mod/ui/framework/elements/UIElement.subKeyPressed:(Lmchorse/bbs_mod/ui/framework/UIContext;)Z
     145: ireturn

  public void render(mchorse.bbs_mod.ui.framework.UIContext);
    Code:
       0: aload_0
       1: invokevirtual #419                // Method updateSidebarResizerState:()V
       4: aload_0
       5: aload_1
       6: invokespecial #1305               // Method mchorse/bbs_mod/ui/framework/elements/UIElement.render:(Lmchorse/bbs_mod/ui/framework/UIContext;)V
       9: aload_0
      10: aload_1
      11: invokevirtual #1308               // Method handleMouse:(Lmchorse/bbs_mod/ui/framework/UIContext;)V
      14: aload_1
      15: getfield      #1312               // Field mchorse/bbs_mod/ui/framework/UIContext.batcher:Lmchorse/bbs_mod/ui/framework/elements/utils/Batcher2D;
      18: aload_0
      19: getfield      #107                // Field area:Lmchorse/bbs_mod/ui/utils/Area;
      22: aload_1
      23: invokevirtual #1318               // Method mchorse/bbs_mod/ui/framework/elements/utils/Batcher2D.clip:(Lmchorse/bbs_mod/ui/utils/Area;Lmchorse/bbs_mod/ui/framework/UIContext;)V
      26: aload_0
      27: aload_1
      28: invokevirtual #1321               // Method renderBackground:(Lmchorse/bbs_mod/ui/framework/UIContext;)V
      31: aload_0
      32: getfield      #101                // Field currentGraph:Lmchorse/bbs_mod/ui/framework/elements/input/keyframes/graphs/IUIKeyframeGraph;
      35: aload_1
      36: invokeinterface #1322,  2         // InterfaceMethod mchorse/bbs_mod/ui/framework/elements/input/keyframes/graphs/IUIKeyframeGraph.render:(Lmchorse/bbs_mod/ui/framework/UIContext;)V
      41: aload_0
      42: getfield      #1082               // Field selecting:Z
      45: ifeq          84
      48: aload_1
      49: getfield      #1312               // Field mchorse/bbs_mod/ui/framework/UIContext.batcher:Lmchorse/bbs_mod/ui/framework/elements/utils/Batcher2D;
      52: aload_0
      53: getfield      #692                // Field originalX:I
      56: i2f
      57: aload_0
      58: getfield      #694                // Field originalY:I
      61: i2f
      62: aload_1
      63: getfield      #593                // Field mchorse/bbs_mod/ui/framework/UIContext.mouseX:I
      66: i2f
      67: aload_1
      68: getfield      #586                // Field mchorse/bbs_mod/ui/framework/UIContext.mouseY:I
      71: i2f
      72: ldc_w         #1323               // int 35071
      75: ldc_w         #1324               // float 0.25f
      78: invokestatic  #1330               // Method mchorse/bbs_mod/utils/colors/Colors.setA:(IF)I
      81: invokevirtual #1334               // Method mchorse/bbs_mod/ui/framework/elements/utils/Batcher2D.normalizedBox:(FFFFI)V
      84: aload_0
      85: getfield      #101                // Field currentGraph:Lmchorse/bbs_mod/ui/framework/elements/input/keyframes/graphs/IUIKeyframeGraph;
      88: aload_1
      89: invokeinterface #1337,  2         // InterfaceMethod mchorse/bbs_mod/ui/framework/elements/input/keyframes/graphs/IUIKeyframeGraph.postRender:(Lmchorse/bbs_mod/ui/framework/UIContext;)V
      94: aload_1
      95: getfield      #1312               // Field mchorse/bbs_mod/ui/framework/UIContext.batcher:Lmchorse/bbs_mod/ui/framework/elements/utils/Batcher2D;
      98: aload_1
      99: invokevirtual #1340               // Method mchorse/bbs_mod/ui/framework/elements/utils/Batcher2D.unclip:(Lmchorse/bbs_mod/ui/framework/UIContext;)V
     102: return

  protected void handleMouse(mchorse.bbs_mod.ui.framework.UIContext);
    Code:
       0: aload_0
       1: getfield      #101                // Field currentGraph:Lmchorse/bbs_mod/ui/framework/elements/input/keyframes/graphs/IUIKeyframeGraph;
       4: aload_1
       5: aload_0
       6: getfield      #1194               // Field lastX:I
       9: aload_0
      10: getfield      #1196               // Field lastY:I
      13: invokeinterface #1343,  4         // InterfaceMethod mchorse/bbs_mod/ui/framework/elements/input/keyframes/graphs/IUIKeyframeGraph.handleMouse:(Lmchorse/bbs_mod/ui/framework/UIContext;II)V
      18: aload_1
      19: getfield      #593                // Field mchorse/bbs_mod/ui/framework/UIContext.mouseX:I
      22: istore_2
      23: aload_1
      24: getfield      #586                // Field mchorse/bbs_mod/ui/framework/UIContext.mouseY:I
      27: istore_3
      28: iload_2
      29: aload_0
      30: getfield      #692                // Field originalX:I
      33: isub
      34: invokestatic  #1120               // Method java/lang/Math.abs:(I)I
      37: iconst_2
      38: if_icmpgt     54
      41: iload_3
      42: aload_0
      43: getfield      #694                // Field originalY:I
      46: isub
      47: invokestatic  #1120               // Method java/lang/Math.abs:(I)I
      50: iconst_2
      51: if_icmple     58
      54: iconst_1
      55: goto          59
      58: iconst_0
      59: istore        4
      61: aload_0
      62: getfield      #684                // Field scaling:Z
      65: ifeq          217
      68: aload_0
      69: aload_1
      70: getfield      #593                // Field mchorse/bbs_mod/ui/framework/UIContext.mouseX:I
      73: invokevirtual #597                // Method fromGraphX:(I)D
      76: d2f
      77: fstore        5
      79: aload_0
      80: aload_0
      81: getfield      #692                // Field originalX:I
      84: invokevirtual #597                // Method fromGraphX:(I)D
      87: d2f
      88: fstore        6
      90: fload         5
      92: aload_0
      93: getfield      #690                // Field scalingAnchor:F
      96: fsub
      97: fload         6
      99: aload_0
     100: getfield      #690                // Field scalingAnchor:F
     103: fsub
     104: fdiv
     105: fstore        7
     107: aload_0
     108: getfield      #92                 // Field scaleTicks:Ljava/util/Map;
     111: invokeinterface #1013,  1         // InterfaceMethod java/util/Map.entrySet:()Ljava/util/Set;
     116: invokeinterface #851,  1          // InterfaceMethod java/util/Set.iterator:()Ljava/util/Iterator;
     121: astore        8
     123: aload         8
     125: invokeinterface #471,  1          // InterfaceMethod java/util/Iterator.hasNext:()Z
     130: ifeq          214
     133: aload         8
     135: invokeinterface #474,  1          // InterfaceMethod java/util/Iterator.next:()Ljava/lang/Object;
     140: checkcast     #20                 // class java/util/Map$Entry
     143: astore        9
     145: aload         9
     147: invokeinterface #1030,  1         // InterfaceMethod java/util/Map$Entry.getKey:()Ljava/lang/Object;
     152: checkcast     #499                // class mchorse/bbs_mod/utils/keyframes/Keyframe
     155: astore        10
     157: aload         9
     159: invokeinterface #1014,  1         // InterfaceMethod java/util/Map$Entry.getValue:()Ljava/lang/Object;
     164: checkcast     #700                // class java/lang/Float
     167: invokevirtual #1296               // Method java/lang/Float.floatValue:()F
     170: fstore        11
     172: aload_0
     173: getfield      #690                // Field scalingAnchor:F
     176: fload         11
     178: aload_0
     179: getfield      #690                // Field scalingAnchor:F
     182: fsub
     183: fload         7
     185: fmul
     186: fadd
     187: fstore        12
     189: invokestatic  #1199               // Method mchorse/bbs_mod/graphics/window/Window.isCtrlPressed:()Z
     192: ifeq          203
     195: fload         12
     197: invokestatic  #1346               // Method java/lang/Math.round:(F)I
     200: i2f
     201: fstore        12
     203: aload         10
     205: fload         12
     207: iconst_1
     208: invokevirtual #1299               // Method mchorse/bbs_mod/utils/keyframes/Keyframe.setTick:(FZ)V
     211: goto          123
     214: goto          295
     217: aload_0
     218: getfield      #87                 // Field dragging:I
     221: ifne          237
     224: iload         4
     226: ifeq          237
     229: aload_0
     230: iconst_1
     231: putfield      #87                 // Field dragging:I
     234: goto          295
     237: aload_0
     238: getfield      #87                 // Field dragging:I
     241: iconst_1
     242: if_icmpne     295
     245: aload_0
     246: getfield      #101                // Field currentGraph:Lmchorse/bbs_mod/ui/framework/elements/input/keyframes/graphs/IUIKeyframeGraph;
     249: invokeinterface #583,  1          // InterfaceMethod mchorse/bbs_mod/ui/framework/elements/input/keyframes/graphs/IUIKeyframeGraph.getSelected:()Lmchorse/bbs_mod/utils/keyframes/Keyframe;
     254: ifnull        290
     257: aload_0
     258: getfield      #101                // Field currentGraph:Lmchorse/bbs_mod/ui/framework/elements/input/keyframes/graphs/IUIKeyframeGraph;
     261: aload_1
     262: aload_0
     263: getfield      #1244               // Field draggingData:Lmchorse/bbs_mod/utils/Pair;
     266: aload_0
     267: getfield      #692                // Field originalX:I
     270: aload_0
     271: getfield      #694                // Field originalY:I
     274: aload_0
     275: getfield      #1254               // Field originalT:F
     278: aload_0
     279: getfield      #1256               // Field originalV:Ljava/lang/Object;
     282: invokeinterface #1350,  7         // InterfaceMethod mchorse/bbs_mod/ui/framework/elements/input/keyframes/graphs/IUIKeyframeGraph.dragKeyframes:(Lmchorse/bbs_mod/ui/framework/UIContext;Lmchorse/bbs_mod/utils/Pair;IIFLjava/lang/Object;)V
     287: goto          295
     290: aload_0
     291: aload_1
     292: invokevirtual #1353               // Method moveNoKeyframes:(Lmchorse/bbs_mod/ui/framework/UIContext;)V
     295: aload_0
     296: iload_2
     297: putfield      #1194               // Field lastX:I
     300: aload_0
     301: iload_3
     302: putfield      #1196               // Field lastY:I
     305: return

  protected void moveNoKeyframes(mchorse.bbs_mod.ui.framework.UIContext);
    Code:
       0: return

  protected void renderBackground(mchorse.bbs_mod.ui.framework.UIContext);
    Code:
       0: aload_1
       1: getfield      #1312               // Field mchorse/bbs_mod/ui/framework/UIContext.batcher:Lmchorse/bbs_mod/ui/framework/elements/utils/Batcher2D;
       4: aload_0
       5: getfield      #107                // Field area:Lmchorse/bbs_mod/ui/utils/Area;
       8: getfield      #1360               // Field mchorse/bbs_mod/ui/utils/Area.x:I
      11: i2f
      12: aload_0
      13: getfield      #107                // Field area:Lmchorse/bbs_mod/ui/utils/Area;
      16: getfield      #1363               // Field mchorse/bbs_mod/ui/utils/Area.y:I
      19: i2f
      20: aload_0
      21: getfield      #107                // Field area:Lmchorse/bbs_mod/ui/utils/Area;
      24: invokevirtual #1366               // Method mchorse/bbs_mod/ui/utils/Area.ex:()I
      27: i2f
      28: aload_0
      29: getfield      #107                // Field area:Lmchorse/bbs_mod/ui/utils/Area;
      32: invokevirtual #1369               // Method mchorse/bbs_mod/ui/utils/Area.ey:()I
      35: i2f
      36: ldc_w         #1370               // int -301265646
      39: invokevirtual #1373               // Method mchorse/bbs_mod/ui/framework/elements/utils/Batcher2D.box:(FFFFI)V
      42: aload_1
      43: getfield      #1312               // Field mchorse/bbs_mod/ui/framework/UIContext.batcher:Lmchorse/bbs_mod/ui/framework/elements/utils/Batcher2D;
      46: aload_0
      47: getfield      #107                // Field area:Lmchorse/bbs_mod/ui/utils/Area;
      50: getfield      #1360               // Field mchorse/bbs_mod/ui/utils/Area.x:I
      53: i2f
      54: aload_0
      55: getfield      #107                // Field area:Lmchorse/bbs_mod/ui/utils/Area;
      58: getfield      #1363               // Field mchorse/bbs_mod/ui/utils/Area.y:I
      61: i2f
      62: aload_0
      63: getfield      #107                // Field area:Lmchorse/bbs_mod/ui/utils/Area;
      66: invokevirtual #1366               // Method mchorse/bbs_mod/ui/utils/Area.ex:()I
      69: i2f
      70: aload_0
      71: getfield      #107                // Field area:Lmchorse/bbs_mod/ui/utils/Area;
      74: getfield      #1363               // Field mchorse/bbs_mod/ui/utils/Area.y:I
      77: bipush        16
      79: iadd
      80: i2f
      81: ldc_w         #1374               // int -15658731
      84: invokevirtual #1373               // Method mchorse/bbs_mod/ui/framework/elements/utils/Batcher2D.box:(FFFFI)V
      87: aload_1
      88: getfield      #1312               // Field mchorse/bbs_mod/ui/framework/UIContext.batcher:Lmchorse/bbs_mod/ui/framework/elements/utils/Batcher2D;
      91: aload_0
      92: getfield      #107                // Field area:Lmchorse/bbs_mod/ui/utils/Area;
      95: getfield      #1360               // Field mchorse/bbs_mod/ui/utils/Area.x:I
      98: i2f
      99: aload_0
     100: getfield      #107                // Field area:Lmchorse/bbs_mod/ui/utils/Area;
     103: getfield      #1363               // Field mchorse/bbs_mod/ui/utils/Area.y:I
     106: bipush        16
     108: iadd
     109: iconst_1
     110: isub
     111: i2f
     112: aload_0
     113: getfield      #107                // Field area:Lmchorse/bbs_mod/ui/utils/Area;
     116: invokevirtual #1366               // Method mchorse/bbs_mod/ui/utils/Area.ex:()I
     119: i2f
     120: aload_0
     121: getfield      #107                // Field area:Lmchorse/bbs_mod/ui/utils/Area;
     124: getfield      #1363               // Field mchorse/bbs_mod/ui/utils/Area.y:I
     127: bipush        16
     129: iadd
     130: i2f
     131: ldc_w         #1375               // int 1157627903
     134: invokevirtual #1373               // Method mchorse/bbs_mod/ui/framework/elements/utils/Batcher2D.box:(FFFFI)V
     137: aload_0
     138: invokevirtual #1113               // Method getDuration:()I
     141: istore_2
     142: iload_2
     143: ifle          310
     146: aload_0
     147: dconst_0
     148: invokevirtual #1377               // Method toGraphX:(D)I
     151: istore_3
     152: aload_0
     153: iload_2
     154: i2d
     155: invokevirtual #1377               // Method toGraphX:(D)I
     158: istore        4
     160: aload_0
     161: getfield      #107                // Field area:Lmchorse/bbs_mod/ui/utils/Area;
     164: getfield      #1360               // Field mchorse/bbs_mod/ui/utils/Area.x:I
     167: aload_0
     168: getfield      #101                // Field currentGraph:Lmchorse/bbs_mod/ui/framework/elements/input/keyframes/graphs/IUIKeyframeGraph;
     171: instanceof    #94                 // class mchorse/bbs_mod/ui/framework/elements/input/keyframes/graphs/UIKeyframeDopeSheet
     174: ifeq          189
     177: aload_0
     178: getfield      #101                // Field currentGraph:Lmchorse/bbs_mod/ui/framework/elements/input/keyframes/graphs/IUIKeyframeGraph;
     181: invokeinterface #1116,  1         // InterfaceMethod mchorse/bbs_mod/ui/framework/elements/input/keyframes/graphs/IUIKeyframeGraph.getSidebarWidth:()I
     186: goto          190
     189: iconst_0
     190: iadd
     191: istore        5
     193: iload_3
     194: iload         5
     196: if_icmple     248
     199: aload_1
     200: getfield      #1312               // Field mchorse/bbs_mod/ui/framework/UIContext.batcher:Lmchorse/bbs_mod/ui/framework/elements/utils/Batcher2D;
     203: iload         5
     205: i2f
     206: aload_0
     207: getfield      #107                // Field area:Lmchorse/bbs_mod/ui/utils/Area;
     210: getfield      #1363               // Field mchorse/bbs_mod/ui/utils/Area.y:I
     213: i2f
     214: aload_0
     215: getfield      #107                // Field area:Lmchorse/bbs_mod/ui/utils/Area;
     218: invokevirtual #1366               // Method mchorse/bbs_mod/ui/utils/Area.ex:()I
     221: iload_3
     222: invokestatic  #773                // Method java/lang/Math.min:(II)I
     225: i2f
     226: aload_0
     227: getfield      #107                // Field area:Lmchorse/bbs_mod/ui/utils/Area;
     230: getfield      #1363               // Field mchorse/bbs_mod/ui/utils/Area.y:I
     233: aload_0
     234: getfield      #107                // Field area:Lmchorse/bbs_mod/ui/utils/Area;
     237: getfield      #1380               // Field mchorse/bbs_mod/ui/utils/Area.h:I
     240: iadd
     241: i2f
     242: ldc_w         #1381               // int -1727723765
     245: invokevirtual #1373               // Method mchorse/bbs_mod/ui/framework/elements/utils/Batcher2D.box:(FFFFI)V
     248: iload         4
     250: aload_0
     251: getfield      #107                // Field area:Lmchorse/bbs_mod/ui/utils/Area;
     254: invokevirtual #1366               // Method mchorse/bbs_mod/ui/utils/Area.ex:()I
     257: if_icmpge     310
     260: aload_1
     261: getfield      #1312               // Field mchorse/bbs_mod/ui/framework/UIContext.batcher:Lmchorse/bbs_mod/ui/framework/elements/utils/Batcher2D;
     264: iload         5
     266: iload         4
     268: invokestatic  #775                // Method java/lang/Math.max:(II)I
     271: i2f
     272: aload_0
     273: getfield      #107                // Field area:Lmchorse/bbs_mod/ui/utils/Area;
     276: getfield      #1363               // Field mchorse/bbs_mod/ui/utils/Area.y:I
     279: i2f
     280: aload_0
     281: getfield      #107                // Field area:Lmchorse/bbs_mod/ui/utils/Area;
     284: invokevirtual #1366               // Method mchorse/bbs_mod/ui/utils/Area.ex:()I
     287: i2f
     288: aload_0
     289: getfield      #107                // Field area:Lmchorse/bbs_mod/ui/utils/Area;
     292: getfield      #1363               // Field mchorse/bbs_mod/ui/utils/Area.y:I
     295: aload_0
     296: getfield      #107                // Field area:Lmchorse/bbs_mod/ui/utils/Area;
     299: getfield      #1380               // Field mchorse/bbs_mod/ui/utils/Area.h:I
     302: iadd
     303: i2f
     304: ldc_w         #1381               // int -1727723765
     307: invokevirtual #1373               // Method mchorse/bbs_mod/ui/framework/elements/utils/Batcher2D.box:(FFFFI)V
     310: aload_0
     311: getfield      #1046               // Field backgroundRender:Ljava/util/function/Consumer;
     314: ifnull        327
     317: aload_0
     318: getfield      #1046               // Field backgroundRender:Ljava/util/function/Consumer;
     321: aload_1
     322: invokeinterface #1099,  2         // InterfaceMethod java/util/function/Consumer.accept:(Ljava/lang/Object;)V
     327: return

  private void updateSidebarResizerState();
    Code:
       0: aload_0
       1: getfield      #412                // Field sidebarResizer:Lmchorse/bbs_mod/ui/framework/elements/utils/UIDraggable;
       4: ifnonnull     8
       7: return
       8: aload_0
       9: getfield      #101                // Field currentGraph:Lmchorse/bbs_mod/ui/framework/elements/input/keyframes/graphs/IUIKeyframeGraph;
      12: aload_0
      13: getfield      #99                 // Field dopeSheet:Lmchorse/bbs_mod/ui/framework/elements/input/keyframes/graphs/UIKeyframeDopeSheet;
      16: if_acmpne     23
      19: iconst_1
      20: goto          24
      23: iconst_0
      24: istore_1
      25: getstatic     #1390               // Field mchorse/bbs_mod/BBSSettings.editorLayoutSettings:Lmchorse/bbs_mod/settings/values/ui/ValueEditorLayout;
      28: ifnull        44
      31: getstatic     #1390               // Field mchorse/bbs_mod/BBSSettings.editorLayoutSettings:Lmchorse/bbs_mod/settings/values/ui/ValueEditorLayout;
      34: invokevirtual #1395               // Method mchorse/bbs_mod/settings/values/ui/ValueEditorLayout.isLayoutLocked:()Z
      37: ifeq          44
      40: iconst_1
      41: goto          45
      44: iconst_0
      45: istore_2
      46: iload_1
      47: ifeq          58
      50: iload_2
      51: ifne          58
      54: iconst_1
      55: goto          59
      58: iconst_0
      59: istore_3
      60: aload_0
      61: getfield      #412                // Field sidebarResizer:Lmchorse/bbs_mod/ui/framework/elements/utils/UIDraggable;
      64: iload_3
      65: invokevirtual #1400               // Method mchorse/bbs_mod/ui/framework/elements/utils/UIDraggable.setVisible:(Z)V
      68: aload_0
      69: getfield      #412                // Field sidebarResizer:Lmchorse/bbs_mod/ui/framework/elements/utils/UIDraggable;
      72: iload_3
      73: invokevirtual #1403               // Method mchorse/bbs_mod/ui/framework/elements/utils/UIDraggable.setEnabled:(Z)V
      76: iload_3
      77: ifne          81
      80: return
      81: aload_0
      82: getfield      #99                 // Field dopeSheet:Lmchorse/bbs_mod/ui/framework/elements/input/keyframes/graphs/UIKeyframeDopeSheet;
      85: aload_0
      86: getfield      #99                 // Field dopeSheet:Lmchorse/bbs_mod/ui/framework/elements/input/keyframes/graphs/UIKeyframeDopeSheet;
      89: invokevirtual #1404               // Method mchorse/bbs_mod/ui/framework/elements/input/keyframes/graphs/UIKeyframeDopeSheet.getSidebarWidth:()I
      92: invokevirtual #1407               // Method mchorse/bbs_mod/ui/framework/elements/input/keyframes/graphs/UIKeyframeDopeSheet.setSidebarWidth:(I)V
      95: aload_0
      96: getfield      #107                // Field area:Lmchorse/bbs_mod/ui/utils/Area;
      99: getfield      #1360               // Field mchorse/bbs_mod/ui/utils/Area.x:I
     102: aload_0
     103: getfield      #99                 // Field dopeSheet:Lmchorse/bbs_mod/ui/framework/elements/input/keyframes/graphs/UIKeyframeDopeSheet;
     106: invokevirtual #1404               // Method mchorse/bbs_mod/ui/framework/elements/input/keyframes/graphs/UIKeyframeDopeSheet.getSidebarWidth:()I
     109: iadd
     110: iconst_3
     111: isub
     112: istore        4
     114: aload_0
     115: getfield      #107                // Field area:Lmchorse/bbs_mod/ui/utils/Area;
     118: invokevirtual #1410               // Method mchorse/bbs_mod/ui/utils/Area.my:()I
     121: bipush        20
     123: isub
     124: istore        5
     126: aload_0
     127: getfield      #412                // Field sidebarResizer:Lmchorse/bbs_mod/ui/framework/elements/utils/UIDraggable;
     130: aload_0
     131: invokevirtual #1414               // Method mchorse/bbs_mod/ui/framework/elements/utils/UIDraggable.relative:(Lmchorse/bbs_mod/ui/framework/elements/UIElement;)Lmchorse/bbs_mod/ui/framework/elements/UIElement;
     134: iload         4
     136: aload_0
     137: getfield      #107                // Field area:Lmchorse/bbs_mod/ui/utils/Area;
     140: getfield      #1360               // Field mchorse/bbs_mod/ui/utils/Area.x:I
     143: isub
     144: invokevirtual #1417               // Method mchorse/bbs_mod/ui/framework/elements/UIElement.x:(I)Lmchorse/bbs_mod/ui/framework/elements/UIElement;
     147: iload         5
     149: aload_0
     150: getfield      #107                // Field area:Lmchorse/bbs_mod/ui/utils/Area;
     153: getfield      #1363               // Field mchorse/bbs_mod/ui/utils/Area.y:I
     156: isub
     157: invokevirtual #1419               // Method mchorse/bbs_mod/ui/framework/elements/UIElement.y:(I)Lmchorse/bbs_mod/ui/framework/elements/UIElement;
     160: bipush        6
     162: invokevirtual #1421               // Method mchorse/bbs_mod/ui/framework/elements/UIElement.w:(I)Lmchorse/bbs_mod/ui/framework/elements/UIElement;
     165: bipush        40
     167: invokevirtual #1423               // Method mchorse/bbs_mod/ui/framework/elements/UIElement.h:(I)Lmchorse/bbs_mod/ui/framework/elements/UIElement;
     170: pop
     171: aload_0
     172: getfield      #412                // Field sidebarResizer:Lmchorse/bbs_mod/ui/framework/elements/utils/UIDraggable;
     175: invokevirtual #1424               // Method mchorse/bbs_mod/ui/framework/elements/utils/UIDraggable.resize:()V
     178: return

  public mchorse.bbs_mod.ui.framework.elements.input.keyframes.KeyframeState cacheState();
    Code:
       0: new           #1430               // class mchorse/bbs_mod/ui/framework/elements/input/keyframes/KeyframeState
       3: dup
       4: invokespecial #1431               // Method mchorse/bbs_mod/ui/framework/elements/input/keyframes/KeyframeState."<init>":()V
       7: astore_1
       8: aload_1
       9: getfield      #1434               // Field mchorse/bbs_mod/ui/framework/elements/input/keyframes/KeyframeState.extra:Lmchorse/bbs_mod/data/types/MapType;
      12: ldc_w         #1436               // String x_min
      15: aload_0
      16: getfield      #118                // Field xAxis:Lmchorse/bbs_mod/ui/utils/Scale;
      19: invokevirtual #1163               // Method mchorse/bbs_mod/ui/utils/Scale.getMinValue:()D
      22: invokevirtual #1440               // Method mchorse/bbs_mod/data/types/MapType.putDouble:(Ljava/lang/String;D)V
      25: aload_1
      26: getfield      #1434               // Field mchorse/bbs_mod/ui/framework/elements/input/keyframes/KeyframeState.extra:Lmchorse/bbs_mod/data/types/MapType;
      29: ldc_w         #1442               // String x_max
      32: aload_0
      33: getfield      #118                // Field xAxis:Lmchorse/bbs_mod/ui/utils/Scale;
      36: invokevirtual #1166               // Method mchorse/bbs_mod/ui/utils/Scale.getMaxValue:()D
      39: invokevirtual #1440               // Method mchorse/bbs_mod/data/types/MapType.putDouble:(Ljava/lang/String;D)V
      42: aload_0
      43: getfield      #101                // Field currentGraph:Lmchorse/bbs_mod/ui/framework/elements/input/keyframes/graphs/IUIKeyframeGraph;
      46: aload_1
      47: getfield      #1434               // Field mchorse/bbs_mod/ui/framework/elements/input/keyframes/KeyframeState.extra:Lmchorse/bbs_mod/data/types/MapType;
      50: invokeinterface #1446,  2         // InterfaceMethod mchorse/bbs_mod/ui/framework/elements/input/keyframes/graphs/IUIKeyframeGraph.saveState:(Lmchorse/bbs_mod/data/types/MapType;)V
      55: aload_0
      56: getfield      #101                // Field currentGraph:Lmchorse/bbs_mod/ui/framework/elements/input/keyframes/graphs/IUIKeyframeGraph;
      59: invokeinterface #460,  1          // InterfaceMethod mchorse/bbs_mod/ui/framework/elements/input/keyframes/graphs/IUIKeyframeGraph.getSheets:()Ljava/util/List;
      64: invokeinterface #466,  1          // InterfaceMethod java/util/List.iterator:()Ljava/util/Iterator;
      69: astore_2
      70: aload_2
      71: invokeinterface #471,  1          // InterfaceMethod java/util/Iterator.hasNext:()Z
      76: ifeq          116
      79: aload_2
      80: invokeinterface #474,  1          // InterfaceMethod java/util/Iterator.next:()Ljava/lang/Object;
      85: checkcast     #476                // class mchorse/bbs_mod/ui/framework/elements/input/keyframes/UIKeyframeSheet
      88: astore_3
      89: aload_1
      90: getfield      #1448               // Field mchorse/bbs_mod/ui/framework/elements/input/keyframes/KeyframeState.selected:Ljava/util/List;
      93: new           #720                // class java/util/ArrayList
      96: dup
      97: aload_3
      98: getfield      #480                // Field mchorse/bbs_mod/ui/framework/elements/input/keyframes/UIKeyframeSheet.selection:Lmchorse/bbs_mod/ui/framework/elements/input/keyframes/KeyframeSelection;
     101: invokevirtual #803                // Method mchorse/bbs_mod/ui/framework/elements/input/keyframes/KeyframeSelection.getIndices:()Ljava/util/Collection;
     104: invokespecial #804                // Method java/util/ArrayList."<init>":(Ljava/util/Collection;)V
     107: invokeinterface #727,  2          // InterfaceMethod java/util/List.add:(Ljava/lang/Object;)Z
     112: pop
     113: goto          70
     116: aload_1
     117: areturn

  public void applyState(mchorse.bbs_mod.ui.framework.elements.input.keyframes.KeyframeState);
    Code:
       0: aload_0
       1: getfield      #118                // Field xAxis:Lmchorse/bbs_mod/ui/utils/Scale;
       4: aload_1
       5: getfield      #1434               // Field mchorse/bbs_mod/ui/framework/elements/input/keyframes/KeyframeState.extra:Lmchorse/bbs_mod/data/types/MapType;
       8: ldc_w         #1436               // String x_min
      11: invokevirtual #1456               // Method mchorse/bbs_mod/data/types/MapType.getDouble:(Ljava/lang/String;)D
      14: aload_1
      15: getfield      #1434               // Field mchorse/bbs_mod/ui/framework/elements/input/keyframes/KeyframeState.extra:Lmchorse/bbs_mod/data/types/MapType;
      18: ldc_w         #1442               // String x_max
      21: invokevirtual #1456               // Method mchorse/bbs_mod/data/types/MapType.getDouble:(Ljava/lang/String;)D
      24: invokevirtual #1177               // Method mchorse/bbs_mod/ui/utils/Scale.view:(DD)V
      27: aload_0
      28: getfield      #101                // Field currentGraph:Lmchorse/bbs_mod/ui/framework/elements/input/keyframes/graphs/IUIKeyframeGraph;
      31: aload_1
      32: getfield      #1434               // Field mchorse/bbs_mod/ui/framework/elements/input/keyframes/KeyframeState.extra:Lmchorse/bbs_mod/data/types/MapType;
      35: invokeinterface #1459,  2         // InterfaceMethod mchorse/bbs_mod/ui/framework/elements/input/keyframes/graphs/IUIKeyframeGraph.restoreState:(Lmchorse/bbs_mod/data/types/MapType;)V
      40: aload_0
      41: getfield      #101                // Field currentGraph:Lmchorse/bbs_mod/ui/framework/elements/input/keyframes/graphs/IUIKeyframeGraph;
      44: invokeinterface #460,  1          // InterfaceMethod mchorse/bbs_mod/ui/framework/elements/input/keyframes/graphs/IUIKeyframeGraph.getSheets:()Ljava/util/List;
      49: astore_2
      50: iconst_0
      51: istore_3
      52: iload_3
      53: aload_2
      54: invokeinterface #529,  1          // InterfaceMethod java/util/List.size:()I
      59: if_icmpge     124
      62: aload_1
      63: getfield      #1448               // Field mchorse/bbs_mod/ui/framework/elements/input/keyframes/KeyframeState.selected:Ljava/util/List;
      66: iload_3
      67: invokestatic  #1463               // Method mchorse/bbs_mod/utils/CollectionUtils.inRange:(Ljava/util/Collection;I)Z
      70: ifeq          118
      73: aload_2
      74: iload_3
      75: invokeinterface #540,  2          // InterfaceMethod java/util/List.get:(I)Ljava/lang/Object;
      80: checkcast     #476                // class mchorse/bbs_mod/ui/framework/elements/input/keyframes/UIKeyframeSheet
      83: getfield      #480                // Field mchorse/bbs_mod/ui/framework/elements/input/keyframes/UIKeyframeSheet.selection:Lmchorse/bbs_mod/ui/framework/elements/input/keyframes/KeyframeSelection;
      86: invokevirtual #742                // Method mchorse/bbs_mod/ui/framework/elements/input/keyframes/KeyframeSelection.clear:()V
      89: aload_2
      90: iload_3
      91: invokeinterface #540,  2          // InterfaceMethod java/util/List.get:(I)Ljava/lang/Object;
      96: checkcast     #476                // class mchorse/bbs_mod/ui/framework/elements/input/keyframes/UIKeyframeSheet
      99: getfield      #480                // Field mchorse/bbs_mod/ui/framework/elements/input/keyframes/UIKeyframeSheet.selection:Lmchorse/bbs_mod/ui/framework/elements/input/keyframes/KeyframeSelection;
     102: aload_1
     103: getfield      #1448               // Field mchorse/bbs_mod/ui/framework/elements/input/keyframes/KeyframeState.selected:Ljava/util/List;
     106: iload_3
     107: invokeinterface #540,  2          // InterfaceMethod java/util/List.get:(I)Ljava/lang/Object;
     112: checkcast     #823                // class java/util/Collection
     115: invokevirtual #826                // Method mchorse/bbs_mod/ui/framework/elements/input/keyframes/KeyframeSelection.addAll:(Ljava/util/Collection;)V
     118: iinc          3, 1
     121: goto          52
     124: aload_0
     125: getfield      #101                // Field currentGraph:Lmchorse/bbs_mod/ui/framework/elements/input/keyframes/graphs/IUIKeyframeGraph;
     128: invokeinterface #661,  1          // InterfaceMethod mchorse/bbs_mod/ui/framework/elements/input/keyframes/graphs/IUIKeyframeGraph.pickSelected:()V
     133: return

  public void copyViewport(mchorse.bbs_mod.ui.framework.elements.input.keyframes.UIKeyframes);
    Code:
       0: aload_0
       1: invokevirtual #1468               // Method getDopeSheet:()Lmchorse/bbs_mod/ui/framework/elements/input/keyframes/graphs/UIKeyframeDopeSheet;
       4: aload_1
       5: invokevirtual #1468               // Method getDopeSheet:()Lmchorse/bbs_mod/ui/framework/elements/input/keyframes/graphs/UIKeyframeDopeSheet;
       8: invokevirtual #1404               // Method mchorse/bbs_mod/ui/framework/elements/input/keyframes/graphs/UIKeyframeDopeSheet.getSidebarWidth:()I
      11: invokevirtual #1407               // Method mchorse/bbs_mod/ui/framework/elements/input/keyframes/graphs/UIKeyframeDopeSheet.setSidebarWidth:(I)V
      14: aload_0
      15: invokevirtual #1468               // Method getDopeSheet:()Lmchorse/bbs_mod/ui/framework/elements/input/keyframes/graphs/UIKeyframeDopeSheet;
      18: aload_1
      19: invokevirtual #1468               // Method getDopeSheet:()Lmchorse/bbs_mod/ui/framework/elements/input/keyframes/graphs/UIKeyframeDopeSheet;
      22: invokevirtual #1471               // Method mchorse/bbs_mod/ui/framework/elements/input/keyframes/graphs/UIKeyframeDopeSheet.getTrackHeight:()D
      25: invokevirtual #1474               // Method mchorse/bbs_mod/ui/framework/elements/input/keyframes/graphs/UIKeyframeDopeSheet.setTrackHeight:(D)V
      28: aload_0
      29: invokevirtual #1476               // Method getXAxis:()Lmchorse/bbs_mod/ui/utils/Scale;
      32: aload_1
      33: invokevirtual #1476               // Method getXAxis:()Lmchorse/bbs_mod/ui/utils/Scale;
      36: invokevirtual #1479               // Method mchorse/bbs_mod/ui/utils/Scale.copy:(Lmchorse/bbs_mod/ui/utils/Scale;)V
      39: aload_0
      40: invokevirtual #1468               // Method getDopeSheet:()Lmchorse/bbs_mod/ui/framework/elements/input/keyframes/graphs/UIKeyframeDopeSheet;
      43: invokevirtual #1483               // Method mchorse/bbs_mod/ui/framework/elements/input/keyframes/graphs/UIKeyframeDopeSheet.getYAxis:()Lmchorse/bbs_mod/ui/utils/Scroll;
      46: aload_1
      47: invokevirtual #1468               // Method getDopeSheet:()Lmchorse/bbs_mod/ui/framework/elements/input/keyframes/graphs/UIKeyframeDopeSheet;
      50: invokevirtual #1483               // Method mchorse/bbs_mod/ui/framework/elements/input/keyframes/graphs/UIKeyframeDopeSheet.getYAxis:()Lmchorse/bbs_mod/ui/utils/Scroll;
      53: invokevirtual #1488               // Method mchorse/bbs_mod/ui/utils/Scroll.copy:(Lmchorse/bbs_mod/ui/utils/Scroll;)V
      56: return

  private static int lambda$pasteKeyframes$0(mchorse.bbs_mod.utils.keyframes.Keyframe, mchorse.bbs_mod.utils.keyframes.Keyframe);
    Code:
       0: aload_0
       1: invokevirtual #698                // Method mchorse/bbs_mod/utils/keyframes/Keyframe.getTick:()F
       4: aload_1
       5: invokevirtual #698                // Method mchorse/bbs_mod/utils/keyframes/Keyframe.getTick:()F
       8: invokestatic  #1491               // Method java/lang/Float.compare:(FF)I
      11: ireturn

  private static mchorse.bbs_mod.ui.framework.elements.input.keyframes.UIKeyframes$PastedKeyframes lambda$parseKeyframes$0(mchorse.bbs_mod.utils.keyframes.factories.IKeyframeFactory, java.lang.String);
    Code:
       0: new           #9                  // class mchorse/bbs_mod/ui/framework/elements/input/keyframes/UIKeyframes$PastedKeyframes
       3: dup
       4: aload_0
       5: invokespecial #1495               // Method mchorse/bbs_mod/ui/framework/elements/input/keyframes/UIKeyframes$PastedKeyframes."<init>":(Lmchorse/bbs_mod/utils/keyframes/factories/IKeyframeFactory;)V
       8: areturn

  private void lambda$interpolationMenu$0(mchorse.bbs_mod.ui.utils.context.ContextMenuManager);
    Code:
       0: aload_1
       1: invokevirtual #1502               // Method mchorse/bbs_mod/ui/utils/context/ContextMenuManager.autoKeys:()Lmchorse/bbs_mod/ui/utils/context/ContextMenuManager;
       4: pop
       5: aload_1
       6: getstatic     #1508               // Field mchorse/bbs_mod/ui/utils/icons/Icons.INTERP_LINEAR:Lmchorse/bbs_mod/ui/utils/icons/Icon;
       9: getstatic     #1511               // Field mchorse/bbs_mod/ui/UIKeys.KEYFRAMES_CONTEXT_INTERPOLATION_LINEAR:Lmchorse/bbs_mod/l10n/keys/IKey;
      12: aload_0
      13: invokedynamic #1516,  0           // InvokeDynamic #31:run:(Lmchorse/bbs_mod/ui/framework/elements/input/keyframes/UIKeyframes;)Ljava/lang/Runnable;
      18: invokevirtual #1520               // Method mchorse/bbs_mod/ui/utils/context/ContextMenuManager.action:(Lmchorse/bbs_mod/ui/utils/icons/Icon;Lmchorse/bbs_mod/l10n/keys/IKey;Ljava/lang/Runnable;)Lmchorse/bbs_mod/ui/utils/context/ContextAction;
      21: pop
      22: aload_1
      23: getstatic     #1523               // Field mchorse/bbs_mod/ui/utils/icons/Icons.ARC:Lmchorse/bbs_mod/ui/utils/icons/Icon;
      26: getstatic     #1526               // Field mchorse/bbs_mod/ui/UIKeys.KEYFRAMES_CONTEXT_INTERPOLATION_BEZIER:Lmchorse/bbs_mod/l10n/keys/IKey;
      29: aload_0
      30: invokedynamic #1531,  0           // InvokeDynamic #32:run:(Lmchorse/bbs_mod/ui/framework/elements/input/keyframes/UIKeyframes;)Ljava/lang/Runnable;
      35: invokevirtual #1520               // Method mchorse/bbs_mod/ui/utils/context/ContextMenuManager.action:(Lmchorse/bbs_mod/ui/utils/icons/Icon;Lmchorse/bbs_mod/l10n/keys/IKey;Ljava/lang/Runnable;)Lmchorse/bbs_mod/ui/utils/context/ContextAction;
      38: pop
      39: aload_1
      40: getstatic     #1534               // Field mchorse/bbs_mod/ui/utils/icons/Icons.CURVES:Lmchorse/bbs_mod/ui/utils/icons/Icon;
      43: getstatic     #1537               // Field mchorse/bbs_mod/ui/UIKeys.KEYFRAMES_CONTEXT_INTERPOLATION_HERMITE:Lmchorse/bbs_mod/l10n/keys/IKey;
      46: aload_0
      47: invokedynamic #1542,  0           // InvokeDynamic #33:run:(Lmchorse/bbs_mod/ui/framework/elements/input/keyframes/UIKeyframes;)Ljava/lang/Runnable;
      52: invokevirtual #1520               // Method mchorse/bbs_mod/ui/utils/context/ContextMenuManager.action:(Lmchorse/bbs_mod/ui/utils/icons/Icon;Lmchorse/bbs_mod/l10n/keys/IKey;Ljava/lang/Runnable;)Lmchorse/bbs_mod/ui/utils/context/ContextAction;
      55: pop
      56: aload_1
      57: getstatic     #1545               // Field mchorse/bbs_mod/ui/utils/icons/Icons.INTERP_STEP:Lmchorse/bbs_mod/ui/utils/icons/Icon;
      60: getstatic     #1548               // Field mchorse/bbs_mod/ui/UIKeys.KEYFRAMES_CONTEXT_INTERPOLATION_STEP:Lmchorse/bbs_mod/l10n/keys/IKey;
      63: aload_0
      64: invokedynamic #1553,  0           // InvokeDynamic #34:run:(Lmchorse/bbs_mod/ui/framework/elements/input/keyframes/UIKeyframes;)Ljava/lang/Runnable;
      69: invokevirtual #1520               // Method mchorse/bbs_mod/ui/utils/context/ContextMenuManager.action:(Lmchorse/bbs_mod/ui/utils/icons/Icon;Lmchorse/bbs_mod/l10n/keys/IKey;Ljava/lang/Runnable;)Lmchorse/bbs_mod/ui/utils/context/ContextAction;
      72: pop
      73: return

  private void lambda$interpolationMenu$4();
    Code:
       0: aload_0
       1: getstatic     #1559               // Field mchorse/bbs_mod/utils/interps/Interpolations.STEP:Lmchorse/bbs_mod/utils/interps/IInterp;
       4: invokevirtual #1561               // Method setInterpolation:(Lmchorse/bbs_mod/utils/interps/IInterp;)V
       7: return

  private void lambda$interpolationMenu$3();
    Code:
       0: aload_0
       1: getstatic     #1564               // Field mchorse/bbs_mod/utils/interps/Interpolations.HERMITE:Lmchorse/bbs_mod/utils/interps/IInterp;
       4: invokevirtual #1561               // Method setInterpolation:(Lmchorse/bbs_mod/utils/interps/IInterp;)V
       7: return

  private void lambda$interpolationMenu$2();
    Code:
       0: aload_0
       1: getstatic     #1567               // Field mchorse/bbs_mod/utils/interps/Interpolations.BEZIER:Lmchorse/bbs_mod/utils/interps/IInterp;
       4: invokevirtual #1561               // Method setInterpolation:(Lmchorse/bbs_mod/utils/interps/IInterp;)V
       7: return

  private void lambda$interpolationMenu$1();
    Code:
       0: aload_0
       1: getstatic     #1570               // Field mchorse/bbs_mod/utils/interps/Interpolations.LINEAR:Lmchorse/bbs_mod/utils/interps/IInterp;
       4: invokevirtual #1561               // Method setInterpolation:(Lmchorse/bbs_mod/utils/interps/IInterp;)V
       7: return

  private void lambda$adjustValues$0(mchorse.bbs_mod.ui.utils.context.ContextMenuManager);
    Code:
       0: aload_1
       1: invokevirtual #1502               // Method mchorse/bbs_mod/ui/utils/context/ContextMenuManager.autoKeys:()Lmchorse/bbs_mod/ui/utils/context/ContextMenuManager;
       4: pop
       5: aload_1
       6: getstatic     #1573               // Field mchorse/bbs_mod/ui/utils/icons/Icons.ARROW_LEFT:Lmchorse/bbs_mod/ui/utils/icons/Icon;
       9: getstatic     #1576               // Field mchorse/bbs_mod/ui/UIKeys.KEYFRAMES_CONTEXT_ADJUST_VALUES_LEFT:Lmchorse/bbs_mod/l10n/keys/IKey;
      12: aload_0
      13: invokedynamic #1581,  0           // InvokeDynamic #35:run:(Lmchorse/bbs_mod/ui/framework/elements/input/keyframes/UIKeyframes;)Ljava/lang/Runnable;
      18: invokevirtual #1520               // Method mchorse/bbs_mod/ui/utils/context/ContextMenuManager.action:(Lmchorse/bbs_mod/ui/utils/icons/Icon;Lmchorse/bbs_mod/l10n/keys/IKey;Ljava/lang/Runnable;)Lmchorse/bbs_mod/ui/utils/context/ContextAction;
      21: pop
      22: aload_1
      23: getstatic     #1584               // Field mchorse/bbs_mod/ui/utils/icons/Icons.ARROW_RIGHT:Lmchorse/bbs_mod/ui/utils/icons/Icon;
      26: getstatic     #1587               // Field mchorse/bbs_mod/ui/UIKeys.KEYFRAMES_CONTEXT_ADJUST_VALUES_RIGHT:Lmchorse/bbs_mod/l10n/keys/IKey;
      29: aload_0
      30: invokedynamic #1592,  0           // InvokeDynamic #36:run:(Lmchorse/bbs_mod/ui/framework/elements/input/keyframes/UIKeyframes;)Ljava/lang/Runnable;
      35: invokevirtual #1520               // Method mchorse/bbs_mod/ui/utils/context/ContextMenuManager.action:(Lmchorse/bbs_mod/ui/utils/icons/Icon;Lmchorse/bbs_mod/l10n/keys/IKey;Ljava/lang/Runnable;)Lmchorse/bbs_mod/ui/utils/context/ContextAction;
      38: pop
      39: return

  private void lambda$adjustValues$2();
    Code:
       0: aload_0
       1: iconst_1
       2: invokevirtual #1594               // Method adjustValues:(Z)V
       5: return

  private void lambda$adjustValues$1();
    Code:
       0: aload_0
       1: iconst_0
       2: invokevirtual #1594               // Method adjustValues:(Z)V
       5: return

  private void lambda$new$26(mchorse.bbs_mod.ui.framework.UIContext);
    Code:
       0: aload_0
       1: getfield      #412                // Field sidebarResizer:Lmchorse/bbs_mod/ui/framework/elements/utils/UIDraggable;
       4: invokevirtual #1597               // Method mchorse/bbs_mod/ui/framework/elements/utils/UIDraggable.isDragging:()Z
       7: ifne          24
      10: aload_0
      11: getfield      #412                // Field sidebarResizer:Lmchorse/bbs_mod/ui/framework/elements/utils/UIDraggable;
      14: getfield      #1598               // Field mchorse/bbs_mod/ui/framework/elements/utils/UIDraggable.area:Lmchorse/bbs_mod/ui/utils/Area;
      17: aload_1
      18: invokevirtual #1192               // Method mchorse/bbs_mod/ui/utils/Area.isInside:(Lmchorse/bbs_mod/ui/framework/UIContext;)Z
      21: ifeq          30
      24: ldc_w         #1599               // float 0.75f
      27: goto          33
      30: ldc_w         #1600               // float 0.5f
      33: fstore_2
      34: getstatic     #1604               // Field mchorse/bbs_mod/BBSSettings.primaryColor:Lmchorse/bbs_mod/settings/values/numeric/ValueInt;
      37: invokevirtual #1607               // Method mchorse/bbs_mod/settings/values/numeric/ValueInt.get:()Ljava/lang/Object;
      40: checkcast     #1066               // class java/lang/Integer
      43: invokevirtual #1069               // Method java/lang/Integer.intValue:()I
      46: fload_2
      47: invokestatic  #1330               // Method mchorse/bbs_mod/utils/colors/Colors.setA:(IF)I
      50: istore_3
      51: aload_1
      52: getfield      #1312               // Field mchorse/bbs_mod/ui/framework/UIContext.batcher:Lmchorse/bbs_mod/ui/framework/elements/utils/Batcher2D;
      55: aload_0
      56: getfield      #412                // Field sidebarResizer:Lmchorse/bbs_mod/ui/framework/elements/utils/UIDraggable;
      59: getfield      #1598               // Field mchorse/bbs_mod/ui/framework/elements/utils/UIDraggable.area:Lmchorse/bbs_mod/ui/utils/Area;
      62: getfield      #1360               // Field mchorse/bbs_mod/ui/utils/Area.x:I
      65: i2f
      66: aload_0
      67: getfield      #412                // Field sidebarResizer:Lmchorse/bbs_mod/ui/framework/elements/utils/UIDraggable;
      70: getfield      #1598               // Field mchorse/bbs_mod/ui/framework/elements/utils/UIDraggable.area:Lmchorse/bbs_mod/ui/utils/Area;
      73: getfield      #1363               // Field mchorse/bbs_mod/ui/utils/Area.y:I
      76: i2f
      77: aload_0
      78: getfield      #412                // Field sidebarResizer:Lmchorse/bbs_mod/ui/framework/elements/utils/UIDraggable;
      81: getfield      #1598               // Field mchorse/bbs_mod/ui/framework/elements/utils/UIDraggable.area:Lmchorse/bbs_mod/ui/utils/Area;
      84: invokevirtual #1366               // Method mchorse/bbs_mod/ui/utils/Area.ex:()I
      87: i2f
      88: aload_0
      89: getfield      #412                // Field sidebarResizer:Lmchorse/bbs_mod/ui/framework/elements/utils/UIDraggable;
      92: getfield      #1598               // Field mchorse/bbs_mod/ui/framework/elements/utils/UIDraggable.area:Lmchorse/bbs_mod/ui/utils/Area;
      95: invokevirtual #1369               // Method mchorse/bbs_mod/ui/utils/Area.ey:()I
      98: i2f
      99: iload_3
     100: invokevirtual #1373               // Method mchorse/bbs_mod/ui/framework/elements/utils/Batcher2D.box:(FFFFI)V
     103: return

  private void lambda$new$25(mchorse.bbs_mod.ui.framework.UIContext);
    Code:
       0: aload_1
       1: getfield      #593                // Field mchorse/bbs_mod/ui/framework/UIContext.mouseX:I
       4: aload_0
       5: getfield      #107                // Field area:Lmchorse/bbs_mod/ui/utils/Area;
       8: getfield      #1360               // Field mchorse/bbs_mod/ui/utils/Area.x:I
      11: isub
      12: istore_2
      13: aload_0
      14: getfield      #99                 // Field dopeSheet:Lmchorse/bbs_mod/ui/framework/elements/input/keyframes/graphs/UIKeyframeDopeSheet;
      17: iload_2
      18: invokevirtual #1407               // Method mchorse/bbs_mod/ui/framework/elements/input/keyframes/graphs/UIKeyframeDopeSheet.setSidebarWidth:(I)V
      21: aload_0
      22: invokevirtual #419                // Method updateSidebarResizerState:()V
      25: aload_0
      26: invokevirtual #1610               // Method resize:()V
      29: return

  private void lambda$new$24();
    Code:
       0: aload_0
       1: aload_0
       2: invokevirtual #1613               // Method getPlayheadTick:()F
       5: iconst_1
       6: invokestatic  #1617               // Method mchorse/bbs_mod/ui/framework/elements/input/keyframes/factories/UITransformKeyframeFactory.keyframeOpenPoseLimbs:(Lmchorse/bbs_mod/ui/framework/elements/input/keyframes/UIKeyframes;FZ)V
       9: return

  private void lambda$new$23();
    Code:
       0: aload_0
       1: aload_0
       2: invokevirtual #1613               // Method getPlayheadTick:()F
       5: iconst_0
       6: invokestatic  #1617               // Method mchorse/bbs_mod/ui/framework/elements/input/keyframes/factories/UITransformKeyframeFactory.keyframeOpenPoseLimbs:(Lmchorse/bbs_mod/ui/framework/elements/input/keyframes/UIKeyframes;FZ)V
       9: return

  private void lambda$new$22();
    Code:
       0: aload_0
       1: iconst_1
       2: invokevirtual #1619               // Method selectNextKeyframe:(I)V
       5: return

  private void lambda$new$21();
    Code:
       0: aload_0
       1: iconst_m1
       2: invokevirtual #1619               // Method selectNextKeyframe:(I)V
       5: return

  private void lambda$new$20();
    Code:
       0: aload_0
       1: iconst_0
       2: invokevirtual #1189               // Method stackKeyframes:(Z)V
       5: return

  private void lambda$new$19();
    Code:
       0: aload_0
       1: invokevirtual #431                // Method getContext:()Lmchorse/bbs_mod/ui/framework/UIContext;
       4: astore_1
       5: aload_0
       6: aload_1
       7: getfield      #593                // Field mchorse/bbs_mod/ui/framework/UIContext.mouseX:I
      10: aload_1
      11: getfield      #586                // Field mchorse/bbs_mod/ui/framework/UIContext.mouseY:I
      14: iconst_1
      15: invokevirtual #1621               // Method selectAfter:(III)V
      18: return

  private void lambda$new$18();
    Code:
       0: aload_0
       1: invokevirtual #431                // Method getContext:()Lmchorse/bbs_mod/ui/framework/UIContext;
       4: astore_1
       5: aload_0
       6: aload_1
       7: getfield      #593                // Field mchorse/bbs_mod/ui/framework/UIContext.mouseX:I
      10: aload_1
      11: getfield      #586                // Field mchorse/bbs_mod/ui/framework/UIContext.mouseY:I
      14: iconst_m1
      15: invokevirtual #1621               // Method selectAfter:(III)V
      18: return

  private void lambda$new$17();
    Code:
       0: aload_0
       1: getfield      #101                // Field currentGraph:Lmchorse/bbs_mod/ui/framework/elements/input/keyframes/graphs/IUIKeyframeGraph;
       4: invokeinterface #1624,  1         // InterfaceMethod mchorse/bbs_mod/ui/framework/elements/input/keyframes/graphs/IUIKeyframeGraph.removeSelected:()V
       9: return

  private void lambda$new$16();
    Code:
       0: aload_0
       1: invokevirtual #431                // Method getContext:()Lmchorse/bbs_mod/ui/framework/UIContext;
       4: astore_1
       5: aload_0
       6: getfield      #180                // Field copyPasteController:Lmchorse/bbs_mod/ui/utils/presets/UICopyPasteController;
       9: invokevirtual #1627               // Method mchorse/bbs_mod/ui/utils/presets/UICopyPasteController.canPreviewPresets:()Z
      12: ifeq          34
      15: aload_0
      16: getfield      #180                // Field copyPasteController:Lmchorse/bbs_mod/ui/utils/presets/UICopyPasteController;
      19: aload_1
      20: aload_1
      21: getfield      #593                // Field mchorse/bbs_mod/ui/framework/UIContext.mouseX:I
      24: aload_1
      25: getfield      #586                // Field mchorse/bbs_mod/ui/framework/UIContext.mouseY:I
      28: invokevirtual #1630               // Method mchorse/bbs_mod/ui/utils/presets/UICopyPasteController.openPresets:(Lmchorse/bbs_mod/ui/framework/UIContext;II)V
      31: invokestatic  #1635               // Method mchorse/bbs_mod/ui/utils/UIUtils.playClick:()V
      34: return

  private void lambda$new$15();
    Code:
       0: aload_0
       1: invokevirtual #431                // Method getContext:()Lmchorse/bbs_mod/ui/framework/UIContext;
       4: astore_1
       5: aload_0
       6: getfield      #180                // Field copyPasteController:Lmchorse/bbs_mod/ui/utils/presets/UICopyPasteController;
       9: aload_1
      10: getfield      #593                // Field mchorse/bbs_mod/ui/framework/UIContext.mouseX:I
      13: aload_1
      14: getfield      #586                // Field mchorse/bbs_mod/ui/framework/UIContext.mouseY:I
      17: invokevirtual #1637               // Method mchorse/bbs_mod/ui/utils/presets/UICopyPasteController.paste:(II)Z
      20: ifeq          26
      23: invokestatic  #1635               // Method mchorse/bbs_mod/ui/utils/UIUtils.playClick:()V
      26: return

  private void lambda$new$14();
    Code:
       0: aload_0
       1: getfield      #101                // Field currentGraph:Lmchorse/bbs_mod/ui/framework/elements/input/keyframes/graphs/IUIKeyframeGraph;
       4: invokeinterface #583,  1          // InterfaceMethod mchorse/bbs_mod/ui/framework/elements/input/keyframes/graphs/IUIKeyframeGraph.getSelected:()Lmchorse/bbs_mod/utils/keyframes/Keyframe;
       9: ifnonnull     23
      12: aload_0
      13: invokevirtual #431                // Method getContext:()Lmchorse/bbs_mod/ui/framework/UIContext;
      16: getstatic     #1640               // Field mchorse/bbs_mod/ui/UIKeys.GENERAL_CUT_EMPTY:Lmchorse/bbs_mod/l10n/keys/IKey;
      19: invokevirtual #1644               // Method mchorse/bbs_mod/ui/framework/UIContext.notifyError:(Lmchorse/bbs_mod/l10n/keys/IKey;)V
      22: return
      23: aload_0
      24: getfield      #180                // Field copyPasteController:Lmchorse/bbs_mod/ui/utils/presets/UICopyPasteController;
      27: invokevirtual #1646               // Method mchorse/bbs_mod/ui/utils/presets/UICopyPasteController.copy:()Z
      30: ifeq          55
      33: aload_0
      34: getfield      #101                // Field currentGraph:Lmchorse/bbs_mod/ui/framework/elements/input/keyframes/graphs/IUIKeyframeGraph;
      37: invokeinterface #1624,  1         // InterfaceMethod mchorse/bbs_mod/ui/framework/elements/input/keyframes/graphs/IUIKeyframeGraph.removeSelected:()V
      42: invokestatic  #1635               // Method mchorse/bbs_mod/ui/utils/UIUtils.playClick:()V
      45: aload_0
      46: invokevirtual #431                // Method getContext:()Lmchorse/bbs_mod/ui/framework/UIContext;
      49: getstatic     #1649               // Field mchorse/bbs_mod/ui/UIKeys.GENERAL_CUT:Lmchorse/bbs_mod/l10n/keys/IKey;
      52: invokevirtual #1652               // Method mchorse/bbs_mod/ui/framework/UIContext.notifyInfo:(Lmchorse/bbs_mod/l10n/keys/IKey;)V
      55: return

  private void lambda$new$13();
    Code:
       0: aload_0
       1: getfield      #180                // Field copyPasteController:Lmchorse/bbs_mod/ui/utils/presets/UICopyPasteController;
       4: invokevirtual #1646               // Method mchorse/bbs_mod/ui/utils/presets/UICopyPasteController.copy:()Z
       7: ifeq          13
      10: invokestatic  #1635               // Method mchorse/bbs_mod/ui/utils/UIUtils.playClick:()V
      13: return

  private void lambda$new$12();
    Code:
       0: aload_0
       1: getfield      #101                // Field currentGraph:Lmchorse/bbs_mod/ui/framework/elements/input/keyframes/graphs/IUIKeyframeGraph;
       4: invokeinterface #1655,  1         // InterfaceMethod mchorse/bbs_mod/ui/framework/elements/input/keyframes/graphs/IUIKeyframeGraph.selectAll:()V
       9: return

  private java.lang.Boolean lambda$new$11();
    Code:
       0: aload_0
       1: getfield      #684                // Field scaling:Z
       4: ifne          11
       7: iconst_1
       8: goto          12
      11: iconst_0
      12: invokestatic  #1660               // Method java/lang/Boolean.valueOf:(Z)Ljava/lang/Boolean;
      15: areturn

  private void lambda$new$2(mchorse.bbs_mod.ui.utils.context.ContextMenuManager);
    Code:
       0: aload_0
       1: invokevirtual #431                // Method getContext:()Lmchorse/bbs_mod/ui/framework/UIContext;
       4: astore_2
       5: aload_2
       6: getfield      #593                // Field mchorse/bbs_mod/ui/framework/UIContext.mouseX:I
       9: istore_3
      10: aload_2
      11: getfield      #586                // Field mchorse/bbs_mod/ui/framework/UIContext.mouseY:I
      14: istore        4
      16: aload_0
      17: getfield      #101                // Field currentGraph:Lmchorse/bbs_mod/ui/framework/elements/input/keyframes/graphs/IUIKeyframeGraph;
      20: invokeinterface #583,  1          // InterfaceMethod mchorse/bbs_mod/ui/framework/elements/input/keyframes/graphs/IUIKeyframeGraph.getSelected:()Lmchorse/bbs_mod/utils/keyframes/Keyframe;
      25: ifnull        32
      28: iconst_1
      29: goto          33
      32: iconst_0
      33: istore        5
      35: aload_0
      36: getfield      #99                 // Field dopeSheet:Lmchorse/bbs_mod/ui/framework/elements/input/keyframes/graphs/UIKeyframeDopeSheet;
      39: aload_0
      40: invokevirtual #431                // Method getContext:()Lmchorse/bbs_mod/ui/framework/UIContext;
      43: getfield      #586                // Field mchorse/bbs_mod/ui/framework/UIContext.mouseY:I
      46: invokevirtual #1662               // Method mchorse/bbs_mod/ui/framework/elements/input/keyframes/graphs/UIKeyframeDopeSheet.getSheet:(I)Lmchorse/bbs_mod/ui/framework/elements/input/keyframes/UIKeyframeSheet;
      49: astore        6
      51: aload         6
      53: ifnull        68
      56: aload         6
      58: getfield      #1073               // Field mchorse/bbs_mod/ui/framework/elements/input/keyframes/UIKeyframeSheet.groupHeader:Z
      61: ifeq          68
      64: iconst_1
      65: goto          69
      68: iconst_0
      69: istore        7
      71: iload         7
      73: ifne          104
      76: aload_1
      77: new           #1664               // class mchorse/bbs_mod/ui/utils/presets/UIPresetContextMenu
      80: dup
      81: aload_0
      82: getfield      #180                // Field copyPasteController:Lmchorse/bbs_mod/ui/utils/presets/UICopyPasteController;
      85: iload_3
      86: iload         4
      88: invokespecial #1667               // Method mchorse/bbs_mod/ui/utils/presets/UIPresetContextMenu."<init>":(Lmchorse/bbs_mod/ui/utils/presets/UICopyPasteController;II)V
      91: getstatic     #1670               // Field mchorse/bbs_mod/ui/UIKeys.KEYFRAMES_CONTEXT_COPY:Lmchorse/bbs_mod/l10n/keys/IKey;
      94: getstatic     #1673               // Field mchorse/bbs_mod/ui/UIKeys.KEYFRAMES_CONTEXT_PASTE:Lmchorse/bbs_mod/l10n/keys/IKey;
      97: invokevirtual #1677               // Method mchorse/bbs_mod/ui/utils/presets/UIPresetContextMenu.labels:(Lmchorse/bbs_mod/l10n/keys/IKey;Lmchorse/bbs_mod/l10n/keys/IKey;)Lmchorse/bbs_mod/ui/utils/presets/UIPresetContextMenu;
     100: invokevirtual #1681               // Method mchorse/bbs_mod/ui/utils/context/ContextMenuManager.custom:(Lmchorse/bbs_mod/ui/framework/elements/context/UISimpleContextMenu;)Lmchorse/bbs_mod/ui/utils/context/ContextMenuManager;
     103: pop
     104: aload_0
     105: getfield      #427                // Field single:Z
     108: ifne          217
     111: aload_0
     112: invokevirtual #1683               // Method isEditing:()Z
     115: ifeq          138
     118: aload_1
     119: getstatic     #1686               // Field mchorse/bbs_mod/ui/utils/icons/Icons.CLOSE:Lmchorse/bbs_mod/ui/utils/icons/Icon;
     122: getstatic     #1689               // Field mchorse/bbs_mod/ui/UIKeys.KEYFRAMES_CONTEXT_EXIT_TRACK:Lmchorse/bbs_mod/l10n/keys/IKey;
     125: aload_0
     126: invokedynamic #1694,  0           // InvokeDynamic #37:run:(Lmchorse/bbs_mod/ui/framework/elements/input/keyframes/UIKeyframes;)Ljava/lang/Runnable;
     131: invokevirtual #1520               // Method mchorse/bbs_mod/ui/utils/context/ContextMenuManager.action:(Lmchorse/bbs_mod/ui/utils/icons/Icon;Lmchorse/bbs_mod/l10n/keys/IKey;Ljava/lang/Runnable;)Lmchorse/bbs_mod/ui/utils/context/ContextAction;
     134: pop
     135: goto          217
     138: aload_0
     139: getfield      #99                 // Field dopeSheet:Lmchorse/bbs_mod/ui/framework/elements/input/keyframes/graphs/UIKeyframeDopeSheet;
     142: aload_0
     143: invokevirtual #431                // Method getContext:()Lmchorse/bbs_mod/ui/framework/UIContext;
     146: getfield      #586                // Field mchorse/bbs_mod/ui/framework/UIContext.mouseY:I
     149: invokevirtual #1662               // Method mchorse/bbs_mod/ui/framework/elements/input/keyframes/graphs/UIKeyframeDopeSheet.getSheet:(I)Lmchorse/bbs_mod/ui/framework/elements/input/keyframes/UIKeyframeSheet;
     152: astore        8
     154: aload         8
     156: ifnull        217
     159: aload         8
     161: getfield      #492                // Field mchorse/bbs_mod/ui/framework/elements/input/keyframes/UIKeyframeSheet.channel:Lmchorse/bbs_mod/utils/keyframes/KeyframeChannel;
     164: invokevirtual #525                // Method mchorse/bbs_mod/utils/keyframes/KeyframeChannel.getFactory:()Lmchorse/bbs_mod/utils/keyframes/factories/IKeyframeFactory;
     167: invokestatic  #535                // Method mchorse/bbs_mod/utils/keyframes/factories/KeyframeFactories.isNumeric:(Lmchorse/bbs_mod/utils/keyframes/factories/IKeyframeFactory;)Z
     170: ifeq          217
     173: aload         8
     175: getfield      #1073               // Field mchorse/bbs_mod/ui/framework/elements/input/keyframes/UIKeyframeSheet.groupHeader:Z
     178: ifne          217
     181: aload_1
     182: getstatic     #1697               // Field mchorse/bbs_mod/ui/utils/icons/Icons.EDIT:Lmchorse/bbs_mod/ui/utils/icons/Icon;
     185: getstatic     #1700               // Field mchorse/bbs_mod/ui/UIKeys.KEYFRAMES_CONTEXT_EDIT_TRACK:Lmchorse/bbs_mod/l10n/keys/IKey;
     188: iconst_1
     189: anewarray     #1702               // class java/lang/Object
     192: dup
     193: iconst_0
     194: aload         8
     196: getfield      #961                // Field mchorse/bbs_mod/ui/framework/elements/input/keyframes/UIKeyframeSheet.id:Ljava/lang/String;
     199: aastore
     200: invokeinterface #1708,  2         // InterfaceMethod mchorse/bbs_mod/l10n/keys/IKey.format:([Ljava/lang/Object;)Lmchorse/bbs_mod/l10n/keys/IKey;
     205: aload_0
     206: aload         8
     208: invokedynamic #1715,  0           // InvokeDynamic #38:run:(Lmchorse/bbs_mod/ui/framework/elements/input/keyframes/UIKeyframes;Lmchorse/bbs_mod/ui/framework/elements/input/keyframes/UIKeyframeSheet;)Ljava/lang/Runnable;
     213: invokevirtual #1520               // Method mchorse/bbs_mod/ui/utils/context/ContextMenuManager.action:(Lmchorse/bbs_mod/ui/utils/icons/Icon;Lmchorse/bbs_mod/l10n/keys/IKey;Ljava/lang/Runnable;)Lmchorse/bbs_mod/ui/utils/context/ContextAction;
     216: pop
     217: iload         7
     219: ifne          279
     222: aload_1
     223: getstatic     #1718               // Field mchorse/bbs_mod/ui/utils/icons/Icons.SEARCH:Lmchorse/bbs_mod/ui/utils/icons/Icon;
     226: getstatic     #1721               // Field mchorse/bbs_mod/ui/UIKeys.KEYFRAMES_CONTEXT_ADJUST_VALUES:Lmchorse/bbs_mod/l10n/keys/IKey;
     229: aload_0
     230: invokedynamic #1726,  0           // InvokeDynamic #39:run:(Lmchorse/bbs_mod/ui/framework/elements/input/keyframes/UIKeyframes;)Ljava/lang/Runnable;
     235: invokevirtual #1520               // Method mchorse/bbs_mod/ui/utils/context/ContextMenuManager.action:(Lmchorse/bbs_mod/ui/utils/icons/Icon;Lmchorse/bbs_mod/l10n/keys/IKey;Ljava/lang/Runnable;)Lmchorse/bbs_mod/ui/utils/context/ContextAction;
     238: pop
     239: aload_1
     240: getstatic     #1573               // Field mchorse/bbs_mod/ui/utils/icons/Icons.ARROW_LEFT:Lmchorse/bbs_mod/ui/utils/icons/Icon;
     243: getstatic     #1729               // Field mchorse/bbs_mod/ui/UIKeys.KEYFRAMES_KEYS_SELECT_LEFT:Lmchorse/bbs_mod/l10n/keys/IKey;
     246: aload_0
     247: iload_3
     248: iload         4
     250: invokedynamic #1737,  0           // InvokeDynamic #40:run:(Lmchorse/bbs_mod/ui/framework/elements/input/keyframes/UIKeyframes;II)Ljava/lang/Runnable;
     255: invokevirtual #1520               // Method mchorse/bbs_mod/ui/utils/context/ContextMenuManager.action:(Lmchorse/bbs_mod/ui/utils/icons/Icon;Lmchorse/bbs_mod/l10n/keys/IKey;Ljava/lang/Runnable;)Lmchorse/bbs_mod/ui/utils/context/ContextAction;
     258: pop
     259: aload_1
     260: getstatic     #1584               // Field mchorse/bbs_mod/ui/utils/icons/Icons.ARROW_RIGHT:Lmchorse/bbs_mod/ui/utils/icons/Icon;
     263: getstatic     #1740               // Field mchorse/bbs_mod/ui/UIKeys.KEYFRAMES_KEYS_SELECT_RIGHT:Lmchorse/bbs_mod/l10n/keys/IKey;
     266: aload_0
     267: iload_3
     268: iload         4
     270: invokedynamic #1745,  0           // InvokeDynamic #41:run:(Lmchorse/bbs_mod/ui/framework/elements/input/keyframes/UIKeyframes;II)Ljava/lang/Runnable;
     275: invokevirtual #1520               // Method mchorse/bbs_mod/ui/utils/context/ContextMenuManager.action:(Lmchorse/bbs_mod/ui/utils/icons/Icon;Lmchorse/bbs_mod/l10n/keys/IKey;Ljava/lang/Runnable;)Lmchorse/bbs_mod/ui/utils/context/ContextAction;
     278: pop
     279: aload_1
     280: getstatic     #1748               // Field mchorse/bbs_mod/ui/utils/icons/Icons.MAXIMIZE:Lmchorse/bbs_mod/ui/utils/icons/Icon;
     283: getstatic     #1751               // Field mchorse/bbs_mod/ui/UIKeys.KEYFRAMES_CONTEXT_MAXIMIZE:Lmchorse/bbs_mod/l10n/keys/IKey;
     286: aload_0
     287: invokedynamic #226,  0            // InvokeDynamic #5:run:(Lmchorse/bbs_mod/ui/framework/elements/input/keyframes/UIKeyframes;)Ljava/lang/Runnable;
     292: invokevirtual #1520               // Method mchorse/bbs_mod/ui/utils/context/ContextMenuManager.action:(Lmchorse/bbs_mod/ui/utils/icons/Icon;Lmchorse/bbs_mod/l10n/keys/IKey;Ljava/lang/Runnable;)Lmchorse/bbs_mod/ui/utils/context/ContextAction;
     295: pop
     296: iload         7
     298: ifne          318
     301: aload_1
     302: getstatic     #1754               // Field mchorse/bbs_mod/ui/utils/icons/Icons.FULLSCREEN:Lmchorse/bbs_mod/ui/utils/icons/Icon;
     305: getstatic     #1757               // Field mchorse/bbs_mod/ui/UIKeys.KEYFRAMES_CONTEXT_SELECT_ALL:Lmchorse/bbs_mod/l10n/keys/IKey;
     308: aload_0
     309: invokedynamic #1762,  0           // InvokeDynamic #42:run:(Lmchorse/bbs_mod/ui/framework/elements/input/keyframes/UIKeyframes;)Ljava/lang/Runnable;
     314: invokevirtual #1520               // Method mchorse/bbs_mod/ui/utils/context/ContextMenuManager.action:(Lmchorse/bbs_mod/ui/utils/icons/Icon;Lmchorse/bbs_mod/l10n/keys/IKey;Ljava/lang/Runnable;)Lmchorse/bbs_mod/ui/utils/context/ContextAction;
     317: pop
     318: iload         5
     320: ifeq          391
     323: aload_1
     324: getstatic     #1534               // Field mchorse/bbs_mod/ui/utils/icons/Icons.CURVES:Lmchorse/bbs_mod/ui/utils/icons/Icon;
     327: getstatic     #1765               // Field mchorse/bbs_mod/ui/UIKeys.KEYFRAMES_CONTEXT_INTERPOLATION:Lmchorse/bbs_mod/l10n/keys/IKey;
     330: aload_0
     331: invokedynamic #1769,  0           // InvokeDynamic #43:run:(Lmchorse/bbs_mod/ui/framework/elements/input/keyframes/UIKeyframes;)Ljava/lang/Runnable;
     336: invokevirtual #1520               // Method mchorse/bbs_mod/ui/utils/context/ContextMenuManager.action:(Lmchorse/bbs_mod/ui/utils/icons/Icon;Lmchorse/bbs_mod/l10n/keys/IKey;Ljava/lang/Runnable;)Lmchorse/bbs_mod/ui/utils/context/ContextAction;
     339: pop
     340: aload_1
     341: getstatic     #1772               // Field mchorse/bbs_mod/ui/utils/icons/Icons.CONVERT:Lmchorse/bbs_mod/ui/utils/icons/Icon;
     344: getstatic     #1775               // Field mchorse/bbs_mod/ui/UIKeys.KEYFRAMES_CONTEXT_SPREAD:Lmchorse/bbs_mod/l10n/keys/IKey;
     347: aload_0
     348: invokedynamic #358,  0            // InvokeDynamic #19:run:(Lmchorse/bbs_mod/ui/framework/elements/input/keyframes/UIKeyframes;)Ljava/lang/Runnable;
     353: invokevirtual #1520               // Method mchorse/bbs_mod/ui/utils/context/ContextMenuManager.action:(Lmchorse/bbs_mod/ui/utils/icons/Icon;Lmchorse/bbs_mod/l10n/keys/IKey;Ljava/lang/Runnable;)Lmchorse/bbs_mod/ui/utils/context/ContextAction;
     356: pop
     357: aload_1
     358: getstatic     #1778               // Field mchorse/bbs_mod/ui/utils/icons/Icons.OUTLINE_SPHERE:Lmchorse/bbs_mod/ui/utils/icons/Icon;
     361: getstatic     #1781               // Field mchorse/bbs_mod/ui/UIKeys.KEYFRAMES_CONTEXT_ROUND:Lmchorse/bbs_mod/l10n/keys/IKey;
     364: aload_0
     365: invokedynamic #1786,  0           // InvokeDynamic #44:run:(Lmchorse/bbs_mod/ui/framework/elements/input/keyframes/UIKeyframes;)Ljava/lang/Runnable;
     370: invokevirtual #1520               // Method mchorse/bbs_mod/ui/utils/context/ContextMenuManager.action:(Lmchorse/bbs_mod/ui/utils/icons/Icon;Lmchorse/bbs_mod/l10n/keys/IKey;Ljava/lang/Runnable;)Lmchorse/bbs_mod/ui/utils/context/ContextAction;
     373: pop
     374: aload_1
     375: getstatic     #1789               // Field mchorse/bbs_mod/ui/utils/icons/Icons.REMOVE:Lmchorse/bbs_mod/ui/utils/icons/Icon;
     378: getstatic     #1792               // Field mchorse/bbs_mod/ui/UIKeys.KEYFRAMES_CONTEXT_REMOVE:Lmchorse/bbs_mod/l10n/keys/IKey;
     381: aload_0
     382: invokedynamic #1797,  0           // InvokeDynamic #45:run:(Lmchorse/bbs_mod/ui/framework/elements/input/keyframes/UIKeyframes;)Ljava/lang/Runnable;
     387: invokevirtual #1520               // Method mchorse/bbs_mod/ui/utils/context/ContextMenuManager.action:(Lmchorse/bbs_mod/ui/utils/icons/Icon;Lmchorse/bbs_mod/l10n/keys/IKey;Ljava/lang/Runnable;)Lmchorse/bbs_mod/ui/utils/context/ContextAction;
     390: pop
     391: return

  private void lambda$new$10();
    Code:
       0: aload_0
       1: getfield      #101                // Field currentGraph:Lmchorse/bbs_mod/ui/framework/elements/input/keyframes/graphs/IUIKeyframeGraph;
       4: invokeinterface #1624,  1         // InterfaceMethod mchorse/bbs_mod/ui/framework/elements/input/keyframes/graphs/IUIKeyframeGraph.removeSelected:()V
       9: return

  private void lambda$new$9();
    Code:
       0: aload_0
       1: invokevirtual #454                // Method getGraph:()Lmchorse/bbs_mod/ui/framework/elements/input/keyframes/graphs/IUIKeyframeGraph;
       4: invokeinterface #460,  1          // InterfaceMethod mchorse/bbs_mod/ui/framework/elements/input/keyframes/graphs/IUIKeyframeGraph.getSheets:()Ljava/util/List;
       9: invokeinterface #466,  1          // InterfaceMethod java/util/List.iterator:()Ljava/util/Iterator;
      14: astore_1
      15: aload_1
      16: invokeinterface #471,  1          // InterfaceMethod java/util/Iterator.hasNext:()Z
      21: ifeq          119
      24: aload_1
      25: invokeinterface #474,  1          // InterfaceMethod java/util/Iterator.next:()Ljava/lang/Object;
      30: checkcast     #476                // class mchorse/bbs_mod/ui/framework/elements/input/keyframes/UIKeyframeSheet
      33: astore_2
      34: aload_2
      35: getfield      #480                // Field mchorse/bbs_mod/ui/framework/elements/input/keyframes/UIKeyframeSheet.selection:Lmchorse/bbs_mod/ui/framework/elements/input/keyframes/KeyframeSelection;
      38: invokevirtual #485                // Method mchorse/bbs_mod/ui/framework/elements/input/keyframes/KeyframeSelection.getSelected:()Ljava/util/List;
      41: astore_3
      42: aload_3
      43: invokeinterface #488,  1          // InterfaceMethod java/util/List.isEmpty:()Z
      48: ifeq          54
      51: goto          15
      54: aload_2
      55: getfield      #492                // Field mchorse/bbs_mod/ui/framework/elements/input/keyframes/UIKeyframeSheet.channel:Lmchorse/bbs_mod/utils/keyframes/KeyframeChannel;
      58: invokevirtual #497                // Method mchorse/bbs_mod/utils/keyframes/KeyframeChannel.preNotify:()V
      61: aload_3
      62: invokeinterface #466,  1          // InterfaceMethod java/util/List.iterator:()Ljava/util/Iterator;
      67: astore        4
      69: aload         4
      71: invokeinterface #471,  1          // InterfaceMethod java/util/Iterator.hasNext:()Z
      76: ifeq          109
      79: aload         4
      81: invokeinterface #474,  1          // InterfaceMethod java/util/Iterator.next:()Ljava/lang/Object;
      86: checkcast     #499                // class mchorse/bbs_mod/utils/keyframes/Keyframe
      89: astore        5
      91: aload         5
      93: aload         5
      95: invokevirtual #698                // Method mchorse/bbs_mod/utils/keyframes/Keyframe.getTick:()F
      98: invokestatic  #1346               // Method java/lang/Math.round:(F)I
     101: i2f
     102: iconst_0
     103: invokevirtual #1299               // Method mchorse/bbs_mod/utils/keyframes/Keyframe.setTick:(FZ)V
     106: goto          69
     109: aload_2
     110: getfield      #492                // Field mchorse/bbs_mod/ui/framework/elements/input/keyframes/UIKeyframeSheet.channel:Lmchorse/bbs_mod/utils/keyframes/KeyframeChannel;
     113: invokevirtual #511                // Method mchorse/bbs_mod/utils/keyframes/KeyframeChannel.postNotify:()V
     116: goto          15
     119: return

  private void lambda$new$8();
    Code:
       0: aload_0
       1: getfield      #101                // Field currentGraph:Lmchorse/bbs_mod/ui/framework/elements/input/keyframes/graphs/IUIKeyframeGraph;
       4: invokeinterface #1655,  1         // InterfaceMethod mchorse/bbs_mod/ui/framework/elements/input/keyframes/graphs/IUIKeyframeGraph.selectAll:()V
       9: return

  private void lambda$new$7(int, int);
    Code:
       0: aload_0
       1: iload_1
       2: iload_2
       3: iconst_1
       4: invokevirtual #1621               // Method selectAfter:(III)V
       7: return

  private void lambda$new$6(int, int);
    Code:
       0: aload_0
       1: iload_1
       2: iload_2
       3: iconst_m1
       4: invokevirtual #1621               // Method selectAfter:(III)V
       7: return

  private void lambda$new$5();
    Code:
       0: aload_0
       1: invokevirtual #364                // Method adjustValues:()V
       4: return

  private void lambda$new$4(mchorse.bbs_mod.ui.framework.elements.input.keyframes.UIKeyframeSheet);
    Code:
       0: aload_0
       1: aload_1
       2: invokevirtual #1293               // Method editSheet:(Lmchorse/bbs_mod/ui/framework/elements/input/keyframes/UIKeyframeSheet;)V
       5: return

  private void lambda$new$3();
    Code:
       0: aload_0
       1: aconst_null
       2: invokevirtual #1293               // Method editSheet:(Lmchorse/bbs_mod/ui/framework/elements/input/keyframes/UIKeyframeSheet;)V
       5: return

  private java.lang.Boolean lambda$new$1();
    Code:
       0: aload_0
       1: getfield      #101                // Field currentGraph:Lmchorse/bbs_mod/ui/framework/elements/input/keyframes/graphs/IUIKeyframeGraph;
       4: invokeinterface #583,  1          // InterfaceMethod mchorse/bbs_mod/ui/framework/elements/input/keyframes/graphs/IUIKeyframeGraph.getSelected:()Lmchorse/bbs_mod/utils/keyframes/Keyframe;
       9: ifnull        16
      12: iconst_1
      13: goto          17
      16: iconst_0
      17: invokestatic  #1660               // Method java/lang/Boolean.valueOf:(Z)Ljava/lang/Boolean;
      20: areturn

  private void lambda$new$0(mchorse.bbs_mod.data.types.MapType, int, int);
    Code:
       0: aload_0
       1: iload_2
       2: invokevirtual #597                // Method fromGraphX:(I)D
       5: invokestatic  #1224               // Method java/lang/Math.round:(D)J
       8: l2d
       9: dstore        4
      11: aload_0
      12: aload_1
      13: invokestatic  #1226               // Method parseKeyframes:(Lmchorse/bbs_mod/data/types/MapType;)Ljava/util/Map;
      16: dload         4
      18: d2f
      19: iload_3
      20: invokevirtual #1228               // Method pasteKeyframes:(Ljava/util/Map;FI)V
      23: return
}
