Compiled from "UIReplaysEditorUtils.java"
public class mchorse.bbs_mod.ui.film.replays.UIReplaysEditorUtils {
  public mchorse.bbs_mod.ui.film.replays.UIReplaysEditorUtils();
    Code:
       0: aload_0
       1: invokespecial #19                 // Method java/lang/Object."<init>":()V
       4: return

  public static mchorse.bbs_mod.ui.framework.elements.input.UIPropTransform getEditableTransform(mchorse.bbs_mod.ui.framework.elements.input.keyframes.UIKeyframeEditor);
    Code:
       0: aload_0
       1: ifnull        11
       4: aload_0
       5: getfield      #29                 // Field mchorse/bbs_mod/ui/framework/elements/input/keyframes/UIKeyframeEditor.editor:Lmchorse/bbs_mod/ui/framework/elements/input/keyframes/factories/UIKeyframeFactory;
       8: ifnonnull     13
      11: aconst_null
      12: areturn
      13: aload_0
      14: getfield      #29                 // Field mchorse/bbs_mod/ui/framework/elements/input/keyframes/UIKeyframeEditor.editor:Lmchorse/bbs_mod/ui/framework/elements/input/keyframes/factories/UIKeyframeFactory;
      17: astore        4
      19: aload         4
      21: instanceof    #31                 // class mchorse/bbs_mod/ui/framework/elements/input/keyframes/factories/UITransformKeyframeFactory
      24: ifeq          38
      27: aload         4
      29: checkcast     #31                 // class mchorse/bbs_mod/ui/framework/elements/input/keyframes/factories/UITransformKeyframeFactory
      32: astore_1
      33: aload_1
      34: getfield      #35                 // Field mchorse/bbs_mod/ui/framework/elements/input/keyframes/factories/UITransformKeyframeFactory.transform:Lmchorse/bbs_mod/ui/framework/elements/input/UIPropTransform;
      37: areturn
      38: aload_0
      39: getfield      #29                 // Field mchorse/bbs_mod/ui/framework/elements/input/keyframes/UIKeyframeEditor.editor:Lmchorse/bbs_mod/ui/framework/elements/input/keyframes/factories/UIKeyframeFactory;
      42: astore        4
      44: aload         4
      46: instanceof    #9                  // class mchorse/bbs_mod/ui/framework/elements/input/keyframes/factories/UIPoseKeyframeFactory
      49: ifeq          66
      52: aload         4
      54: checkcast     #9                  // class mchorse/bbs_mod/ui/framework/elements/input/keyframes/factories/UIPoseKeyframeFactory
      57: astore_2
      58: aload_2
      59: getfield      #39                 // Field mchorse/bbs_mod/ui/framework/elements/input/keyframes/factories/UIPoseKeyframeFactory.poseEditor:Lmchorse/bbs_mod/ui/framework/elements/input/keyframes/factories/UIPoseKeyframeFactory$UIPoseFactoryEditor;
      62: getfield      #40                 // Field mchorse/bbs_mod/ui/framework/elements/input/keyframes/factories/UIPoseKeyframeFactory$UIPoseFactoryEditor.transform:Lmchorse/bbs_mod/ui/framework/elements/input/UIPropTransform;
      65: areturn
      66: aload_0
      67: getfield      #29                 // Field mchorse/bbs_mod/ui/framework/elements/input/keyframes/UIKeyframeEditor.editor:Lmchorse/bbs_mod/ui/framework/elements/input/keyframes/factories/UIKeyframeFactory;
      70: astore        4
      72: aload         4
      74: instanceof    #42                 // class mchorse/bbs_mod/ui/framework/elements/input/keyframes/factories/UIAnchorKeyframeFactory
      77: ifeq          91
      80: aload         4
      82: checkcast     #42                 // class mchorse/bbs_mod/ui/framework/elements/input/keyframes/factories/UIAnchorKeyframeFactory
      85: astore_3
      86: aload_3
      87: getfield      #43                 // Field mchorse/bbs_mod/ui/framework/elements/input/keyframes/factories/UIAnchorKeyframeFactory.transform:Lmchorse/bbs_mod/ui/framework/elements/input/UIPropTransform;
      90: areturn
      91: aconst_null
      92: areturn

  public static <T> void forEachSelectedKeyframe(mchorse.bbs_mod.ui.framework.elements.input.keyframes.UIKeyframes, mchorse.bbs_mod.utils.keyframes.Keyframe<?>, java.util.function.Consumer<mchorse.bbs_mod.utils.keyframes.Keyframe<T>>);
    Code:
       0: aload_0
       1: ifnull        8
       4: aload_1
       5: ifnonnull     9
       8: return
       9: aload_0
      10: invokevirtual #61                 // Method mchorse/bbs_mod/ui/framework/elements/input/keyframes/UIKeyframes.getGraph:()Lmchorse/bbs_mod/ui/framework/elements/input/keyframes/graphs/IUIKeyframeGraph;
      13: invokeinterface #67,  1           // InterfaceMethod mchorse/bbs_mod/ui/framework/elements/input/keyframes/graphs/IUIKeyframeGraph.getSheets:()Ljava/util/List;
      18: invokeinterface #73,  1           // InterfaceMethod java/util/List.iterator:()Ljava/util/Iterator;
      23: astore_3
      24: aload_3
      25: invokeinterface #79,  1           // InterfaceMethod java/util/Iterator.hasNext:()Z
      30: ifeq          113
      33: aload_3
      34: invokeinterface #83,  1           // InterfaceMethod java/util/Iterator.next:()Ljava/lang/Object;
      39: checkcast     #85                 // class mchorse/bbs_mod/ui/framework/elements/input/keyframes/UIKeyframeSheet
      42: astore        4
      44: aload         4
      46: getfield      #89                 // Field mchorse/bbs_mod/ui/framework/elements/input/keyframes/UIKeyframeSheet.channel:Lmchorse/bbs_mod/utils/keyframes/KeyframeChannel;
      49: invokevirtual #95                 // Method mchorse/bbs_mod/utils/keyframes/KeyframeChannel.getFactory:()Lmchorse/bbs_mod/utils/keyframes/factories/IKeyframeFactory;
      52: aload_1
      53: invokevirtual #98                 // Method mchorse/bbs_mod/utils/keyframes/Keyframe.getFactory:()Lmchorse/bbs_mod/utils/keyframes/factories/IKeyframeFactory;
      56: if_acmpeq     62
      59: goto          24
      62: aload         4
      64: getfield      #102                // Field mchorse/bbs_mod/ui/framework/elements/input/keyframes/UIKeyframeSheet.selection:Lmchorse/bbs_mod/ui/framework/elements/input/keyframes/KeyframeSelection;
      67: invokevirtual #107                // Method mchorse/bbs_mod/ui/framework/elements/input/keyframes/KeyframeSelection.getSelected:()Ljava/util/List;
      70: invokeinterface #73,  1           // InterfaceMethod java/util/List.iterator:()Ljava/util/Iterator;
      75: astore        5
      77: aload         5
      79: invokeinterface #79,  1           // InterfaceMethod java/util/Iterator.hasNext:()Z
      84: ifeq          110
      87: aload         5
      89: invokeinterface #83,  1           // InterfaceMethod java/util/Iterator.next:()Ljava/lang/Object;
      94: checkcast     #97                 // class mchorse/bbs_mod/utils/keyframes/Keyframe
      97: astore        6
      99: aload_2
     100: aload         6
     102: invokeinterface #113,  2          // InterfaceMethod java/util/function/Consumer.accept:(Ljava/lang/Object;)V
     107: goto          77
     110: goto          24
     113: return

  private static boolean isBonePickProperty(java.lang.String);
    Code:
       0: aload_0
       1: ldc           #126                // String pose
       3: invokevirtual #132                // Method java/lang/String.equals:(Ljava/lang/Object;)Z
       6: ifne          27
       9: aload_0
      10: ldc           #134                // String pose_overlay
      12: invokevirtual #137                // Method java/lang/String.startsWith:(Ljava/lang/String;)Z
      15: ifne          27
      18: aload_0
      19: ldc           #139                // String look_at
      21: invokevirtual #132                // Method java/lang/String.equals:(Ljava/lang/Object;)Z
      24: ifeq          31
      27: iconst_1
      28: goto          32
      31: iconst_0
      32: ireturn

  public static void pickFormProperty(mchorse.bbs_mod.ui.framework.UIContext, mchorse.bbs_mod.ui.framework.elements.input.keyframes.UIKeyframeEditor, mchorse.bbs_mod.ui.film.ICursor, mchorse.bbs_mod.forms.forms.Form, java.lang.String);
    Code:
       0: aload_3
       1: invokestatic  #152                // Method mchorse/bbs_mod/forms/FormUtils.getPath:(Lmchorse/bbs_mod/forms/forms/Form;)Ljava/lang/String;
       4: astore        5
       6: invokestatic  #157                // Method mchorse/bbs_mod/graphics/window/Window.isShiftPressed:()Z
       9: istore        6
      11: new           #159                // class mchorse/bbs_mod/ui/utils/context/ContextMenuManager
      14: dup
      15: invokespecial #160                // Method mchorse/bbs_mod/ui/utils/context/ContextMenuManager."<init>":()V
      18: astore        7
      20: aload         7
      22: invokevirtual #164                // Method mchorse/bbs_mod/ui/utils/context/ContextMenuManager.autoKeys:()Lmchorse/bbs_mod/ui/utils/context/ContextMenuManager;
      25: pop
      26: aload_3
      27: invokevirtual #170                // Method mchorse/bbs_mod/forms/forms/Form.getAllMap:()Ljava/util/Map;
      30: invokeinterface #176,  1          // InterfaceMethod java/util/Map.values:()Ljava/util/Collection;
      35: invokeinterface #179,  1          // InterfaceMethod java/util/Collection.iterator:()Ljava/util/Iterator;
      40: astore        8
      42: aload         8
      44: invokeinterface #79,  1           // InterfaceMethod java/util/Iterator.hasNext:()Z
      49: ifeq          115
      52: aload         8
      54: invokeinterface #83,  1           // InterfaceMethod java/util/Iterator.next:()Ljava/lang/Object;
      59: checkcast     #185                // class mchorse/bbs_mod/settings/values/base/BaseValueBasic
      62: astore        9
      64: aload         9
      66: invokevirtual #188                // Method mchorse/bbs_mod/settings/values/base/BaseValueBasic.isVisible:()Z
      69: ifne          75
      72: goto          42
      75: aload         7
      77: aload         9
      79: invokevirtual #192                // Method mchorse/bbs_mod/settings/values/base/BaseValueBasic.getId:()Ljava/lang/String;
      82: invokestatic  #198                // Method mchorse/bbs_mod/ui/film/replays/UIReplaysEditor.getIcon:(Ljava/lang/String;)Lmchorse/bbs_mod/ui/utils/icons/Icon;
      85: aload         9
      87: invokevirtual #192                // Method mchorse/bbs_mod/settings/values/base/BaseValueBasic.getId:()Ljava/lang/String;
      90: invokestatic  #204                // InterfaceMethod mchorse/bbs_mod/l10n/keys/IKey.constant:(Ljava/lang/String;)Lmchorse/bbs_mod/l10n/keys/IKey;
      93: aload_1
      94: aload_2
      95: aload         4
      97: aload         5
      99: aload         9
     101: iload         6
     103: invokedynamic #221,  0            // InvokeDynamic #0:run:(Lmchorse/bbs_mod/ui/framework/elements/input/keyframes/UIKeyframeEditor;Lmchorse/bbs_mod/ui/film/ICursor;Ljava/lang/String;Ljava/lang/String;Lmchorse/bbs_mod/settings/values/base/BaseValueBasic;Z)Ljava/lang/Runnable;
     108: invokevirtual #225                // Method mchorse/bbs_mod/ui/utils/context/ContextMenuManager.action:(Lmchorse/bbs_mod/ui/utils/icons/Icon;Lmchorse/bbs_mod/l10n/keys/IKey;Ljava/lang/Runnable;)Lmchorse/bbs_mod/ui/utils/context/ContextAction;
     111: pop
     112: goto          42
     115: aload_0
     116: aload         7
     118: invokevirtual #229                // Method mchorse/bbs_mod/ui/utils/context/ContextMenuManager.create:()Lmchorse/bbs_mod/ui/framework/elements/context/UISimpleContextMenu;
     121: invokevirtual #233                // Method mchorse/bbs_mod/ui/framework/UIContext.replaceContextMenu:(Lmchorse/bbs_mod/ui/framework/elements/context/UIContextMenu;)V
     124: return

  public static void pickForm(mchorse.bbs_mod.ui.framework.elements.input.keyframes.UIKeyframeEditor, mchorse.bbs_mod.ui.film.ICursor, mchorse.bbs_mod.forms.forms.Form, java.lang.String);
    Code:
       0: aload_2
       1: invokestatic  #152                // Method mchorse/bbs_mod/forms/FormUtils.getPath:(Lmchorse/bbs_mod/forms/forms/Form;)Ljava/lang/String;
       4: astore        4
       6: aload_0
       7: ifnull        17
      10: aload_3
      11: invokevirtual #249                // Method java/lang/String.isEmpty:()Z
      14: ifeq          18
      17: return
      18: aload_0
      19: getfield      #252                // Field mchorse/bbs_mod/ui/framework/elements/input/keyframes/UIKeyframeEditor.view:Lmchorse/bbs_mod/ui/framework/elements/input/keyframes/UIKeyframes;
      22: invokevirtual #61                 // Method mchorse/bbs_mod/ui/framework/elements/input/keyframes/UIKeyframes.getGraph:()Lmchorse/bbs_mod/ui/framework/elements/input/keyframes/graphs/IUIKeyframeGraph;
      25: invokeinterface #255,  1          // InterfaceMethod mchorse/bbs_mod/ui/framework/elements/input/keyframes/graphs/IUIKeyframeGraph.getSelected:()Lmchorse/bbs_mod/utils/keyframes/Keyframe;
      30: astore        5
      32: ldc           #126                // String pose
      34: astore        6
      36: aload         5
      38: ifnull        113
      41: aload         5
      43: invokevirtual #259                // Method mchorse/bbs_mod/utils/keyframes/Keyframe.getParent:()Lmchorse/bbs_mod/settings/values/base/BaseValue;
      46: invokevirtual #262                // Method mchorse/bbs_mod/settings/values/base/BaseValue.getId:()Ljava/lang/String;
      49: astore        7
      51: aload         7
      53: bipush        58
      55: invokevirtual #266                // Method java/lang/String.indexOf:(I)I
      58: istore        8
      60: iload         8
      62: iconst_m1
      63: if_icmpeq     77
      66: aload         7
      68: iconst_0
      69: iload         8
      71: invokevirtual #270                // Method java/lang/String.substring:(II)Ljava/lang/String;
      74: goto          79
      77: aload         7
      79: astore        9
      81: aload         9
      83: aload         4
      85: invokevirtual #137                // Method java/lang/String.startsWith:(Ljava/lang/String;)Z
      88: ifeq          110
      91: aload         9
      93: invokestatic  #276                // Method mchorse/bbs_mod/utils/StringUtils.fileName:(Ljava/lang/String;)Ljava/lang/String;
      96: astore        10
      98: aload         10
     100: invokestatic  #278                // Method isBonePickProperty:(Ljava/lang/String;)Z
     103: ifeq          110
     106: aload         10
     108: astore        6
     110: goto          215
     113: aload_0
     114: getfield      #252                // Field mchorse/bbs_mod/ui/framework/elements/input/keyframes/UIKeyframeEditor.view:Lmchorse/bbs_mod/ui/framework/elements/input/keyframes/UIKeyframes;
     117: invokevirtual #61                 // Method mchorse/bbs_mod/ui/framework/elements/input/keyframes/UIKeyframes.getGraph:()Lmchorse/bbs_mod/ui/framework/elements/input/keyframes/graphs/IUIKeyframeGraph;
     120: invokeinterface #282,  1          // InterfaceMethod mchorse/bbs_mod/ui/framework/elements/input/keyframes/graphs/IUIKeyframeGraph.getLastSheet:()Lmchorse/bbs_mod/ui/framework/elements/input/keyframes/UIKeyframeSheet;
     125: astore        7
     127: aload         7
     129: ifnull        201
     132: aload         7
     134: getfield      #285                // Field mchorse/bbs_mod/ui/framework/elements/input/keyframes/UIKeyframeSheet.id:Ljava/lang/String;
     137: astore        8
     139: aload         8
     141: bipush        58
     143: invokevirtual #266                // Method java/lang/String.indexOf:(I)I
     146: istore        9
     148: iload         9
     150: iconst_m1
     151: if_icmpeq     165
     154: aload         8
     156: iconst_0
     157: iload         9
     159: invokevirtual #270                // Method java/lang/String.substring:(II)Ljava/lang/String;
     162: goto          167
     165: aload         8
     167: astore        10
     169: aload         10
     171: aload         4
     173: invokevirtual #137                // Method java/lang/String.startsWith:(Ljava/lang/String;)Z
     176: ifeq          198
     179: aload         10
     181: invokestatic  #276                // Method mchorse/bbs_mod/utils/StringUtils.fileName:(Ljava/lang/String;)Ljava/lang/String;
     184: astore        11
     186: aload         11
     188: invokestatic  #278                // Method isBonePickProperty:(Ljava/lang/String;)Z
     191: ifeq          198
     194: aload         11
     196: astore        6
     198: goto          215
     201: aload_0
     202: getfield      #29                 // Field mchorse/bbs_mod/ui/framework/elements/input/keyframes/UIKeyframeEditor.editor:Lmchorse/bbs_mod/ui/framework/elements/input/keyframes/factories/UIKeyframeFactory;
     205: instanceof    #287                // class mchorse/bbs_mod/ui/framework/elements/input/keyframes/factories/UILookAtKeyframeFactory
     208: ifeq          215
     211: ldc           #139                // String look_at
     213: astore        6
     215: aload_0
     216: aload_1
     217: aload_3
     218: aload         4
     220: aload         6
     222: invokestatic  #291                // Method mchorse/bbs_mod/utils/StringUtils.combinePaths:(Ljava/lang/String;Ljava/lang/String;)Ljava/lang/String;
     225: iconst_0
     226: invokestatic  #295                // Method pickProperty:(Lmchorse/bbs_mod/ui/framework/elements/input/keyframes/UIKeyframeEditor;Lmchorse/bbs_mod/ui/film/ICursor;Ljava/lang/String;Ljava/lang/String;Z)V
     229: return

  private static void pickProperty(mchorse.bbs_mod.ui.framework.elements.input.keyframes.UIKeyframeEditor, mchorse.bbs_mod.ui.film.ICursor, java.lang.String, java.lang.String, boolean);
    Code:
       0: aload_0
       1: getfield      #252                // Field mchorse/bbs_mod/ui/framework/elements/input/keyframes/UIKeyframeEditor.view:Lmchorse/bbs_mod/ui/framework/elements/input/keyframes/UIKeyframes;
       4: invokevirtual #61                 // Method mchorse/bbs_mod/ui/framework/elements/input/keyframes/UIKeyframes.getGraph:()Lmchorse/bbs_mod/ui/framework/elements/input/keyframes/graphs/IUIKeyframeGraph;
       7: astore        5
       9: aload         5
      11: invokeinterface #255,  1          // InterfaceMethod mchorse/bbs_mod/ui/framework/elements/input/keyframes/graphs/IUIKeyframeGraph.getSelected:()Lmchorse/bbs_mod/utils/keyframes/Keyframe;
      16: astore        6
      18: aload         6
      20: ifnull        35
      23: aload         5
      25: aload         6
      27: invokeinterface #306,  2          // InterfaceMethod mchorse/bbs_mod/ui/framework/elements/input/keyframes/graphs/IUIKeyframeGraph.getSheet:(Lmchorse/bbs_mod/utils/keyframes/Keyframe;)Lmchorse/bbs_mod/ui/framework/elements/input/keyframes/UIKeyframeSheet;
      32: goto          36
      35: aconst_null
      36: astore        7
      38: aload         7
      40: ifnull        135
      43: aload         7
      45: getfield      #285                // Field mchorse/bbs_mod/ui/framework/elements/input/keyframes/UIKeyframeSheet.id:Ljava/lang/String;
      48: astore        8
      50: aload         8
      52: bipush        58
      54: invokevirtual #266                // Method java/lang/String.indexOf:(I)I
      57: istore        9
      59: iload         9
      61: iconst_m1
      62: if_icmpeq     76
      65: aload         8
      67: iconst_0
      68: iload         9
      70: invokevirtual #270                // Method java/lang/String.substring:(II)Ljava/lang/String;
      73: goto          78
      76: aload         8
      78: astore        10
      80: iload         9
      82: iconst_m1
      83: if_icmpeq     98
      86: aload         8
      88: iload         9
      90: iconst_1
      91: iadd
      92: invokevirtual #309                // Method java/lang/String.substring:(I)Ljava/lang/String;
      95: goto          99
      98: aconst_null
      99: astore        11
     101: aload         10
     103: aload_3
     104: invokevirtual #132                // Method java/lang/String.equals:(Ljava/lang/Object;)Z
     107: ifeq          135
     110: aload         11
     112: ifnull        124
     115: aload         11
     117: aload_2
     118: invokevirtual #132                // Method java/lang/String.equals:(Ljava/lang/Object;)Z
     121: ifeq          135
     124: aload_0
     125: aload_1
     126: aload_2
     127: aload         7
     129: iload         4
     131: invokestatic  #312                // Method pickProperty:(Lmchorse/bbs_mod/ui/framework/elements/input/keyframes/UIKeyframeEditor;Lmchorse/bbs_mod/ui/film/ICursor;Ljava/lang/String;Lmchorse/bbs_mod/ui/framework/elements/input/keyframes/UIKeyframeSheet;Z)V
     134: return
     135: aload_2
     136: ifnull        187
     139: aload_2
     140: invokevirtual #249                // Method java/lang/String.isEmpty:()Z
     143: ifne          187
     146: aload_3
     147: aload_2
     148: invokedynamic #323,  0            // InvokeDynamic #1:makeConcatWithConstants:(Ljava/lang/String;Ljava/lang/String;)Ljava/lang/String;
     153: astore        8
     155: aload_0
     156: getfield      #252                // Field mchorse/bbs_mod/ui/framework/elements/input/keyframes/UIKeyframeEditor.view:Lmchorse/bbs_mod/ui/framework/elements/input/keyframes/UIKeyframes;
     159: invokevirtual #61                 // Method mchorse/bbs_mod/ui/framework/elements/input/keyframes/UIKeyframes.getGraph:()Lmchorse/bbs_mod/ui/framework/elements/input/keyframes/graphs/IUIKeyframeGraph;
     162: aload         8
     164: invokeinterface #326,  2          // InterfaceMethod mchorse/bbs_mod/ui/framework/elements/input/keyframes/graphs/IUIKeyframeGraph.getSheet:(Ljava/lang/String;)Lmchorse/bbs_mod/ui/framework/elements/input/keyframes/UIKeyframeSheet;
     169: astore        9
     171: aload         9
     173: ifnull        187
     176: aload_0
     177: aload_1
     178: aload_2
     179: aload         9
     181: iload         4
     183: invokestatic  #312                // Method pickProperty:(Lmchorse/bbs_mod/ui/framework/elements/input/keyframes/UIKeyframeEditor;Lmchorse/bbs_mod/ui/film/ICursor;Ljava/lang/String;Lmchorse/bbs_mod/ui/framework/elements/input/keyframes/UIKeyframeSheet;Z)V
     186: return
     187: aload_0
     188: getfield      #252                // Field mchorse/bbs_mod/ui/framework/elements/input/keyframes/UIKeyframeEditor.view:Lmchorse/bbs_mod/ui/framework/elements/input/keyframes/UIKeyframes;
     191: invokevirtual #61                 // Method mchorse/bbs_mod/ui/framework/elements/input/keyframes/UIKeyframes.getGraph:()Lmchorse/bbs_mod/ui/framework/elements/input/keyframes/graphs/IUIKeyframeGraph;
     194: aload_3
     195: invokeinterface #326,  2          // InterfaceMethod mchorse/bbs_mod/ui/framework/elements/input/keyframes/graphs/IUIKeyframeGraph.getSheet:(Ljava/lang/String;)Lmchorse/bbs_mod/ui/framework/elements/input/keyframes/UIKeyframeSheet;
     200: astore        8
     202: aload         8
     204: ifnull        217
     207: aload_0
     208: aload_1
     209: aload_2
     210: aload         8
     212: iload         4
     214: invokestatic  #312                // Method pickProperty:(Lmchorse/bbs_mod/ui/framework/elements/input/keyframes/UIKeyframeEditor;Lmchorse/bbs_mod/ui/film/ICursor;Ljava/lang/String;Lmchorse/bbs_mod/ui/framework/elements/input/keyframes/UIKeyframeSheet;Z)V
     217: return

  private static void pickProperty(mchorse.bbs_mod.ui.framework.elements.input.keyframes.UIKeyframeEditor, mchorse.bbs_mod.ui.film.ICursor, java.lang.String, mchorse.bbs_mod.ui.framework.elements.input.keyframes.UIKeyframeSheet, boolean);
    Code:
       0: aload_0
       1: getfield      #252                // Field mchorse/bbs_mod/ui/framework/elements/input/keyframes/UIKeyframeEditor.view:Lmchorse/bbs_mod/ui/framework/elements/input/keyframes/UIKeyframes;
       4: invokevirtual #61                 // Method mchorse/bbs_mod/ui/framework/elements/input/keyframes/UIKeyframes.getGraph:()Lmchorse/bbs_mod/ui/framework/elements/input/keyframes/graphs/IUIKeyframeGraph;
       7: astore        5
       9: aload_1
      10: invokeinterface #338,  1          // InterfaceMethod mchorse/bbs_mod/ui/film/ICursor.getCursor:()I
      15: istore        6
      17: iload         4
      19: ifeq          46
      22: aload         5
      24: aload_3
      25: iload         6
      27: i2f
      28: aconst_null
      29: invokeinterface #342,  4          // InterfaceMethod mchorse/bbs_mod/ui/framework/elements/input/keyframes/graphs/IUIKeyframeGraph.addKeyframe:(Lmchorse/bbs_mod/ui/framework/elements/input/keyframes/UIKeyframeSheet;FLjava/lang/Object;)Lmchorse/bbs_mod/utils/keyframes/Keyframe;
      34: astore        7
      36: aload         5
      38: aload         7
      40: invokeinterface #346,  2          // InterfaceMethod mchorse/bbs_mod/ui/framework/elements/input/keyframes/graphs/IUIKeyframeGraph.selectKeyframe:(Lmchorse/bbs_mod/utils/keyframes/Keyframe;)V
      45: return
      46: aload_3
      47: getfield      #89                 // Field mchorse/bbs_mod/ui/framework/elements/input/keyframes/UIKeyframeSheet.channel:Lmchorse/bbs_mod/utils/keyframes/KeyframeChannel;
      50: iload         6
      52: i2f
      53: invokevirtual #350                // Method mchorse/bbs_mod/utils/keyframes/KeyframeChannel.find:(F)Lmchorse/bbs_mod/utils/keyframes/KeyframeSegment;
      56: astore        7
      58: aconst_null
      59: astore        8
      61: aload         7
      63: ifnull        76
      66: aload         7
      68: invokevirtual #355                // Method mchorse/bbs_mod/utils/keyframes/KeyframeSegment.getClosest:()Lmchorse/bbs_mod/utils/keyframes/Keyframe;
      71: astore        8
      73: goto          96
      76: aload_3
      77: getfield      #89                 // Field mchorse/bbs_mod/ui/framework/elements/input/keyframes/UIKeyframeSheet.channel:Lmchorse/bbs_mod/utils/keyframes/KeyframeChannel;
      80: invokevirtual #356                // Method mchorse/bbs_mod/utils/keyframes/KeyframeChannel.isEmpty:()Z
      83: ifne          96
      86: aload_3
      87: getfield      #89                 // Field mchorse/bbs_mod/ui/framework/elements/input/keyframes/UIKeyframeSheet.channel:Lmchorse/bbs_mod/utils/keyframes/KeyframeChannel;
      90: iconst_0
      91: invokevirtual #360                // Method mchorse/bbs_mod/utils/keyframes/KeyframeChannel.get:(I)Lmchorse/bbs_mod/utils/keyframes/Keyframe;
      94: astore        8
      96: aload         8
      98: ifnull        301
     101: aload         5
     103: invokeinterface #255,  1          // InterfaceMethod mchorse/bbs_mod/ui/framework/elements/input/keyframes/graphs/IUIKeyframeGraph.getSelected:()Lmchorse/bbs_mod/utils/keyframes/Keyframe;
     108: aload         8
     110: if_acmpeq     205
     113: iconst_1
     114: istore        10
     116: aload         5
     118: invokeinterface #67,  1           // InterfaceMethod mchorse/bbs_mod/ui/framework/elements/input/keyframes/graphs/IUIKeyframeGraph.getSheets:()Ljava/util/List;
     123: invokeinterface #73,  1           // InterfaceMethod java/util/List.iterator:()Ljava/util/Iterator;
     128: astore        11
     130: aload         11
     132: invokeinterface #79,  1           // InterfaceMethod java/util/Iterator.hasNext:()Z
     137: ifeq          179
     140: aload         11
     142: invokeinterface #83,  1           // InterfaceMethod java/util/Iterator.next:()Ljava/lang/Object;
     147: checkcast     #85                 // class mchorse/bbs_mod/ui/framework/elements/input/keyframes/UIKeyframeSheet
     150: astore        12
     152: aload         12
     154: getfield      #102                // Field mchorse/bbs_mod/ui/framework/elements/input/keyframes/UIKeyframeSheet.selection:Lmchorse/bbs_mod/ui/framework/elements/input/keyframes/KeyframeSelection;
     157: invokevirtual #107                // Method mchorse/bbs_mod/ui/framework/elements/input/keyframes/KeyframeSelection.getSelected:()Ljava/util/List;
     160: aload         8
     162: invokeinterface #363,  2          // InterfaceMethod java/util/List.contains:(Ljava/lang/Object;)Z
     167: ifeq          176
     170: iconst_0
     171: istore        10
     173: goto          179
     176: goto          130
     179: iload         10
     181: ifeq          196
     184: aload         5
     186: aload         8
     188: invokeinterface #346,  2          // InterfaceMethod mchorse/bbs_mod/ui/framework/elements/input/keyframes/graphs/IUIKeyframeGraph.selectKeyframe:(Lmchorse/bbs_mod/utils/keyframes/Keyframe;)V
     193: goto          205
     196: aload         5
     198: aload         8
     200: invokeinterface #366,  2          // InterfaceMethod mchorse/bbs_mod/ui/framework/elements/input/keyframes/graphs/IUIKeyframeGraph.pickKeyframe:(Lmchorse/bbs_mod/utils/keyframes/Keyframe;)V
     205: aload_0
     206: getfield      #29                 // Field mchorse/bbs_mod/ui/framework/elements/input/keyframes/UIKeyframeEditor.editor:Lmchorse/bbs_mod/ui/framework/elements/input/keyframes/factories/UIKeyframeFactory;
     209: astore        12
     211: aload         12
     213: instanceof    #9                  // class mchorse/bbs_mod/ui/framework/elements/input/keyframes/factories/UIPoseKeyframeFactory
     216: ifeq          256
     219: aload         12
     221: checkcast     #9                  // class mchorse/bbs_mod/ui/framework/elements/input/keyframes/factories/UIPoseKeyframeFactory
     224: astore        10
     226: invokestatic  #369                // Method mchorse/bbs_mod/graphics/window/Window.isCtrlPressed:()Z
     229: ifeq          244
     232: aload         10
     234: getfield      #39                 // Field mchorse/bbs_mod/ui/framework/elements/input/keyframes/factories/UIPoseKeyframeFactory.poseEditor:Lmchorse/bbs_mod/ui/framework/elements/input/keyframes/factories/UIPoseKeyframeFactory$UIPoseFactoryEditor;
     237: aload_2
     238: invokevirtual #373                // Method mchorse/bbs_mod/ui/framework/elements/input/keyframes/factories/UIPoseKeyframeFactory$UIPoseFactoryEditor.addBoneToSelection:(Ljava/lang/String;)V
     241: goto          286
     244: aload         10
     246: getfield      #39                 // Field mchorse/bbs_mod/ui/framework/elements/input/keyframes/factories/UIPoseKeyframeFactory.poseEditor:Lmchorse/bbs_mod/ui/framework/elements/input/keyframes/factories/UIPoseKeyframeFactory$UIPoseFactoryEditor;
     249: aload_2
     250: invokevirtual #376                // Method mchorse/bbs_mod/ui/framework/elements/input/keyframes/factories/UIPoseKeyframeFactory$UIPoseFactoryEditor.selectBone:(Ljava/lang/String;)V
     253: goto          286
     256: aload_0
     257: getfield      #29                 // Field mchorse/bbs_mod/ui/framework/elements/input/keyframes/UIKeyframeEditor.editor:Lmchorse/bbs_mod/ui/framework/elements/input/keyframes/factories/UIKeyframeFactory;
     260: astore        12
     262: aload         12
     264: instanceof    #287                // class mchorse/bbs_mod/ui/framework/elements/input/keyframes/factories/UILookAtKeyframeFactory
     267: ifeq          286
     270: aload         12
     272: checkcast     #287                // class mchorse/bbs_mod/ui/framework/elements/input/keyframes/factories/UILookAtKeyframeFactory
     275: astore        11
     277: aload         11
     279: getfield      #380                // Field mchorse/bbs_mod/ui/framework/elements/input/keyframes/factories/UILookAtKeyframeFactory.lookAtEditor:Lmchorse/bbs_mod/ui/framework/elements/input/UILookAtEditor;
     282: aload_2
     283: invokevirtual #383                // Method mchorse/bbs_mod/ui/framework/elements/input/UILookAtEditor.selectBone:(Ljava/lang/String;)V
     286: aload_1
     287: aload         8
     289: invokevirtual #387                // Method mchorse/bbs_mod/utils/keyframes/Keyframe.getTick:()F
     292: f2i
     293: invokeinterface #391,  2          // InterfaceMethod mchorse/bbs_mod/ui/film/ICursor.setCursor:(I)V
     298: goto          331
     301: aload_0
     302: getfield      #29                 // Field mchorse/bbs_mod/ui/framework/elements/input/keyframes/UIKeyframeEditor.editor:Lmchorse/bbs_mod/ui/framework/elements/input/keyframes/factories/UIKeyframeFactory;
     305: astore        10
     307: aload         10
     309: instanceof    #287                // class mchorse/bbs_mod/ui/framework/elements/input/keyframes/factories/UILookAtKeyframeFactory
     312: ifeq          331
     315: aload         10
     317: checkcast     #287                // class mchorse/bbs_mod/ui/framework/elements/input/keyframes/factories/UILookAtKeyframeFactory
     320: astore        9
     322: aload         9
     324: getfield      #380                // Field mchorse/bbs_mod/ui/framework/elements/input/keyframes/factories/UILookAtKeyframeFactory.lookAtEditor:Lmchorse/bbs_mod/ui/framework/elements/input/UILookAtEditor;
     327: aload_2
     328: invokevirtual #383                // Method mchorse/bbs_mod/ui/framework/elements/input/UILookAtEditor.selectBone:(Ljava/lang/String;)V
     331: return

  public static void animationToPoseKeyframes(mchorse.bbs_mod.ui.framework.elements.input.keyframes.UIKeyframeEditor, mchorse.bbs_mod.ui.framework.elements.input.keyframes.UIKeyframeSheet, mchorse.bbs_mod.forms.forms.ModelForm, mchorse.bbs_mod.forms.entities.IEntity, int, java.lang.String, boolean, int, int);
    Code:
       0: aload_2
       1: invokestatic  #414                // Method mchorse/bbs_mod/forms/renderers/ModelFormRenderer.getModel:(Lmchorse/bbs_mod/forms/forms/ModelForm;)Lmchorse/bbs_mod/cubic/ModelInstance;
       4: astore        9
       6: aload         9
       8: getfield      #420                // Field mchorse/bbs_mod/cubic/ModelInstance.animations:Lmchorse/bbs_mod/cubic/data/animation/Animations;
      11: aload         5
      13: invokevirtual #425                // Method mchorse/bbs_mod/cubic/data/animation/Animations.get:(Ljava/lang/String;)Lmchorse/bbs_mod/cubic/data/animation/Animation;
      16: astore        10
      18: aload         10
      20: ifnull        142
      23: aload_0
      24: getfield      #252                // Field mchorse/bbs_mod/ui/framework/elements/input/keyframes/UIKeyframeEditor.view:Lmchorse/bbs_mod/ui/framework/elements/input/keyframes/UIKeyframes;
      27: invokevirtual #429                // Method mchorse/bbs_mod/ui/framework/elements/input/keyframes/UIKeyframes.getDopeSheet:()Lmchorse/bbs_mod/ui/framework/elements/input/keyframes/graphs/UIKeyframeDopeSheet;
      30: invokevirtual #434                // Method mchorse/bbs_mod/ui/framework/elements/input/keyframes/graphs/UIKeyframeDopeSheet.clearSelection:()V
      33: iload         6
      35: ifeq          98
      38: aload         10
      40: invokestatic  #438                // Method getTicks:(Lmchorse/bbs_mod/cubic/data/animation/Animation;)Ljava/util/List;
      43: astore        11
      45: aload         11
      47: invokeinterface #73,  1           // InterfaceMethod java/util/List.iterator:()Ljava/util/Iterator;
      52: astore        12
      54: aload         12
      56: invokeinterface #79,  1           // InterfaceMethod java/util/Iterator.hasNext:()Z
      61: ifeq          95
      64: aload         12
      66: invokeinterface #83,  1           // InterfaceMethod java/util/Iterator.next:()Ljava/lang/Object;
      71: checkcast     #446                // class java/lang/Float
      74: invokevirtual #449                // Method java/lang/Float.floatValue:()F
      77: fstore        13
      79: aload_1
      80: fload         13
      82: aload         9
      84: aload_3
      85: aload         10
      87: iload         4
      89: invokestatic  #453                // Method fillAnimationPose:(Lmchorse/bbs_mod/ui/framework/elements/input/keyframes/UIKeyframeSheet;FLmchorse/bbs_mod/cubic/ModelInstance;Lmchorse/bbs_mod/forms/entities/IEntity;Lmchorse/bbs_mod/cubic/data/animation/Animation;I)V
      92: goto          54
      95: goto          132
      98: iconst_0
      99: istore        11
     101: iload         11
     103: iload         7
     105: if_icmpge     132
     108: aload_1
     109: iload         11
     111: i2f
     112: aload         9
     114: aload_3
     115: aload         10
     117: iload         4
     119: invokestatic  #453                // Method fillAnimationPose:(Lmchorse/bbs_mod/ui/framework/elements/input/keyframes/UIKeyframeSheet;FLmchorse/bbs_mod/cubic/ModelInstance;Lmchorse/bbs_mod/forms/entities/IEntity;Lmchorse/bbs_mod/cubic/data/animation/Animation;I)V
     122: iload         11
     124: iload         8
     126: iadd
     127: istore        11
     129: goto          101
     132: aload_0
     133: getfield      #252                // Field mchorse/bbs_mod/ui/framework/elements/input/keyframes/UIKeyframeEditor.view:Lmchorse/bbs_mod/ui/framework/elements/input/keyframes/UIKeyframes;
     136: invokevirtual #429                // Method mchorse/bbs_mod/ui/framework/elements/input/keyframes/UIKeyframes.getDopeSheet:()Lmchorse/bbs_mod/ui/framework/elements/input/keyframes/graphs/UIKeyframeDopeSheet;
     139: invokevirtual #456                // Method mchorse/bbs_mod/ui/framework/elements/input/keyframes/graphs/UIKeyframeDopeSheet.pickSelected:()V
     142: return

  private static java.util.List<java.lang.Float> getTicks(mchorse.bbs_mod.cubic.data.animation.Animation);
    Code:
       0: new           #470                // class java/util/HashSet
       3: dup
       4: invokespecial #471                // Method java/util/HashSet."<init>":()V
       7: astore_1
       8: aload_0
       9: getfield      #475                // Field mchorse/bbs_mod/cubic/data/animation/Animation.parts:Ljava/util/Map;
      12: invokeinterface #176,  1          // InterfaceMethod java/util/Map.values:()Ljava/util/Collection;
      17: invokeinterface #179,  1          // InterfaceMethod java/util/Collection.iterator:()Ljava/util/Iterator;
      22: astore_2
      23: aload_2
      24: invokeinterface #79,  1           // InterfaceMethod java/util/Iterator.hasNext:()Z
      29: ifeq          133
      32: aload_2
      33: invokeinterface #83,  1           // InterfaceMethod java/util/Iterator.next:()Ljava/lang/Object;
      38: checkcast     #479                // class mchorse/bbs_mod/cubic/data/animation/AnimationPart
      41: astore_3
      42: aload_3
      43: getfield      #482                // Field mchorse/bbs_mod/cubic/data/animation/AnimationPart.channels:Ljava/util/List;
      46: invokeinterface #73,  1           // InterfaceMethod java/util/List.iterator:()Ljava/util/Iterator;
      51: astore        4
      53: aload         4
      55: invokeinterface #79,  1           // InterfaceMethod java/util/Iterator.hasNext:()Z
      60: ifeq          130
      63: aload         4
      65: invokeinterface #83,  1           // InterfaceMethod java/util/Iterator.next:()Ljava/lang/Object;
      70: checkcast     #91                 // class mchorse/bbs_mod/utils/keyframes/KeyframeChannel
      73: astore        5
      75: aload         5
      77: invokevirtual #485                // Method mchorse/bbs_mod/utils/keyframes/KeyframeChannel.getKeyframes:()Ljava/util/List;
      80: invokeinterface #73,  1           // InterfaceMethod java/util/List.iterator:()Ljava/util/Iterator;
      85: astore        6
      87: aload         6
      89: invokeinterface #79,  1           // InterfaceMethod java/util/Iterator.hasNext:()Z
      94: ifeq          127
      97: aload         6
      99: invokeinterface #83,  1           // InterfaceMethod java/util/Iterator.next:()Ljava/lang/Object;
     104: checkcast     #97                 // class mchorse/bbs_mod/utils/keyframes/Keyframe
     107: astore        7
     109: aload_1
     110: aload         7
     112: invokevirtual #387                // Method mchorse/bbs_mod/utils/keyframes/Keyframe.getTick:()F
     115: invokestatic  #489                // Method java/lang/Float.valueOf:(F)Ljava/lang/Float;
     118: invokeinterface #492,  2          // InterfaceMethod java/util/Set.add:(Ljava/lang/Object;)Z
     123: pop
     124: goto          87
     127: goto          53
     130: goto          23
     133: new           #494                // class java/util/ArrayList
     136: dup
     137: aload_1
     138: invokespecial #497                // Method java/util/ArrayList."<init>":(Ljava/util/Collection;)V
     141: astore_2
     142: aload_2
     143: invokestatic  #503                // Method java/util/Collections.sort:(Ljava/util/List;)V
     146: aload_2
     147: areturn

  private static void fillAnimationPose(mchorse.bbs_mod.ui.framework.elements.input.keyframes.UIKeyframeSheet, float, mchorse.bbs_mod.cubic.ModelInstance, mchorse.bbs_mod.forms.entities.IEntity, mchorse.bbs_mod.cubic.data.animation.Animation, int);
    Code:
       0: aload_2
       1: getfield      #517                // Field mchorse/bbs_mod/cubic/ModelInstance.model:Lmchorse/bbs_mod/cubic/IModel;
       4: invokeinterface #522,  1          // InterfaceMethod mchorse/bbs_mod/cubic/IModel.resetPose:()V
       9: aload_2
      10: getfield      #517                // Field mchorse/bbs_mod/cubic/ModelInstance.model:Lmchorse/bbs_mod/cubic/IModel;
      13: aload_3
      14: aload         4
      16: fload_1
      17: fconst_1
      18: fconst_0
      19: iconst_0
      20: invokeinterface #526,  7          // InterfaceMethod mchorse/bbs_mod/cubic/IModel.apply:(Lmchorse/bbs_mod/forms/entities/IEntity;Lmchorse/bbs_mod/cubic/data/animation/Animation;FFFZ)V
      25: aload_0
      26: getfield      #89                 // Field mchorse/bbs_mod/ui/framework/elements/input/keyframes/UIKeyframeSheet.channel:Lmchorse/bbs_mod/utils/keyframes/KeyframeChannel;
      29: iload         5
      31: i2f
      32: fload_1
      33: fadd
      34: aload_2
      35: getfield      #517                // Field mchorse/bbs_mod/cubic/ModelInstance.model:Lmchorse/bbs_mod/cubic/IModel;
      38: invokeinterface #530,  1          // InterfaceMethod mchorse/bbs_mod/cubic/IModel.createPose:()Lmchorse/bbs_mod/utils/pose/Pose;
      43: invokevirtual #533                // Method mchorse/bbs_mod/utils/keyframes/KeyframeChannel.insert:(FLjava/lang/Object;)I
      46: istore        6
      48: aload_0
      49: getfield      #102                // Field mchorse/bbs_mod/ui/framework/elements/input/keyframes/UIKeyframeSheet.selection:Lmchorse/bbs_mod/ui/framework/elements/input/keyframes/KeyframeSelection;
      52: iload         6
      54: invokevirtual #535                // Method mchorse/bbs_mod/ui/framework/elements/input/keyframes/KeyframeSelection.add:(I)V
      57: return

  public static void offerAdjacent(mchorse.bbs_mod.ui.framework.UIContext, mchorse.bbs_mod.forms.forms.Form, java.lang.String, java.util.function.Consumer<java.lang.String>);
    Code:
       0: aload_2
       1: invokevirtual #249                // Method java/lang/String.isEmpty:()Z
       4: ifne          46
       7: aload_1
       8: instanceof    #440                // class mchorse/bbs_mod/forms/forms/ModelForm
      11: ifeq          46
      14: aload_1
      15: checkcast     #440                // class mchorse/bbs_mod/forms/forms/ModelForm
      18: astore        4
      20: aload         4
      22: invokestatic  #414                // Method mchorse/bbs_mod/forms/renderers/ModelFormRenderer.getModel:(Lmchorse/bbs_mod/forms/forms/ModelForm;)Lmchorse/bbs_mod/cubic/ModelInstance;
      25: astore        5
      27: aload         5
      29: ifnonnull     33
      32: return
      33: aload_0
      34: aload         5
      36: aload_2
      37: aload_3
      38: invokedynamic #549,  0            // InvokeDynamic #2:accept:(Lmchorse/bbs_mod/cubic/ModelInstance;Ljava/lang/String;Ljava/util/function/Consumer;)Ljava/util/function/Consumer;
      43: invokevirtual #552                // Method mchorse/bbs_mod/ui/framework/UIContext.replaceContextMenu:(Ljava/util/function/Consumer;)V
      46: return

  public static void offerHierarchy(mchorse.bbs_mod.ui.framework.UIContext, mchorse.bbs_mod.forms.forms.Form, java.lang.String, java.util.function.Consumer<java.lang.String>);
    Code:
       0: aload_2
       1: invokevirtual #249                // Method java/lang/String.isEmpty:()Z
       4: ifne          46
       7: aload_1
       8: instanceof    #440                // class mchorse/bbs_mod/forms/forms/ModelForm
      11: ifeq          46
      14: aload_1
      15: checkcast     #440                // class mchorse/bbs_mod/forms/forms/ModelForm
      18: astore        4
      20: aload         4
      22: invokestatic  #414                // Method mchorse/bbs_mod/forms/renderers/ModelFormRenderer.getModel:(Lmchorse/bbs_mod/forms/forms/ModelForm;)Lmchorse/bbs_mod/cubic/ModelInstance;
      25: astore        5
      27: aload         5
      29: ifnonnull     33
      32: return
      33: aload_0
      34: aload         5
      36: aload_2
      37: aload_3
      38: invokedynamic #559,  0            // InvokeDynamic #3:accept:(Lmchorse/bbs_mod/cubic/ModelInstance;Ljava/lang/String;Ljava/util/function/Consumer;)Ljava/util/function/Consumer;
      43: invokevirtual #552                // Method mchorse/bbs_mod/ui/framework/UIContext.replaceContextMenu:(Ljava/util/function/Consumer;)V
      46: return

  private static void lambda$offerHierarchy$0(mchorse.bbs_mod.cubic.ModelInstance, java.lang.String, java.util.function.Consumer, mchorse.bbs_mod.ui.utils.context.ContextMenuManager);
    Code:
       0: aload_0
       1: getfield      #517                // Field mchorse/bbs_mod/cubic/ModelInstance.model:Lmchorse/bbs_mod/cubic/IModel;
       4: aload_1
       5: invokeinterface #564,  2          // InterfaceMethod mchorse/bbs_mod/cubic/IModel.getHierarchyGroups:(Ljava/lang/String;)Ljava/util/Collection;
      10: invokeinterface #179,  1          // InterfaceMethod java/util/Collection.iterator:()Ljava/util/Iterator;
      15: astore        4
      17: aload         4
      19: invokeinterface #79,  1           // InterfaceMethod java/util/Iterator.hasNext:()Z
      24: ifeq          63
      27: aload         4
      29: invokeinterface #83,  1           // InterfaceMethod java/util/Iterator.next:()Ljava/lang/Object;
      34: checkcast     #128                // class java/lang/String
      37: astore        5
      39: aload_3
      40: getstatic     #570                // Field mchorse/bbs_mod/ui/utils/icons/Icons.LIMB:Lmchorse/bbs_mod/ui/utils/icons/Icon;
      43: aload         5
      45: invokestatic  #204                // InterfaceMethod mchorse/bbs_mod/l10n/keys/IKey.constant:(Ljava/lang/String;)Lmchorse/bbs_mod/l10n/keys/IKey;
      48: aload_2
      49: aload         5
      51: invokedynamic #578,  0            // InvokeDynamic #4:run:(Ljava/util/function/Consumer;Ljava/lang/String;)Ljava/lang/Runnable;
      56: invokevirtual #225                // Method mchorse/bbs_mod/ui/utils/context/ContextMenuManager.action:(Lmchorse/bbs_mod/ui/utils/icons/Icon;Lmchorse/bbs_mod/l10n/keys/IKey;Ljava/lang/Runnable;)Lmchorse/bbs_mod/ui/utils/context/ContextAction;
      59: pop
      60: goto          17
      63: aload_3
      64: invokevirtual #164                // Method mchorse/bbs_mod/ui/utils/context/ContextMenuManager.autoKeys:()Lmchorse/bbs_mod/ui/utils/context/ContextMenuManager;
      67: pop
      68: return

  private static void lambda$offerHierarchy$1(java.util.function.Consumer, java.lang.String);
    Code:
       0: aload_0
       1: aload_1
       2: invokeinterface #113,  2          // InterfaceMethod java/util/function/Consumer.accept:(Ljava/lang/Object;)V
       7: return

  private static void lambda$offerAdjacent$0(mchorse.bbs_mod.cubic.ModelInstance, java.lang.String, java.util.function.Consumer, mchorse.bbs_mod.ui.utils.context.ContextMenuManager);
    Code:
       0: aload_0
       1: getfield      #517                // Field mchorse/bbs_mod/cubic/ModelInstance.model:Lmchorse/bbs_mod/cubic/IModel;
       4: aload_1
       5: invokeinterface #584,  2          // InterfaceMethod mchorse/bbs_mod/cubic/IModel.getAdjacentGroups:(Ljava/lang/String;)Ljava/util/Collection;
      10: invokeinterface #179,  1          // InterfaceMethod java/util/Collection.iterator:()Ljava/util/Iterator;
      15: astore        4
      17: aload         4
      19: invokeinterface #79,  1           // InterfaceMethod java/util/Iterator.hasNext:()Z
      24: ifeq          63
      27: aload         4
      29: invokeinterface #83,  1           // InterfaceMethod java/util/Iterator.next:()Ljava/lang/Object;
      34: checkcast     #128                // class java/lang/String
      37: astore        5
      39: aload_3
      40: getstatic     #570                // Field mchorse/bbs_mod/ui/utils/icons/Icons.LIMB:Lmchorse/bbs_mod/ui/utils/icons/Icon;
      43: aload         5
      45: invokestatic  #204                // InterfaceMethod mchorse/bbs_mod/l10n/keys/IKey.constant:(Ljava/lang/String;)Lmchorse/bbs_mod/l10n/keys/IKey;
      48: aload_2
      49: aload         5
      51: invokedynamic #589,  0            // InvokeDynamic #5:run:(Ljava/util/function/Consumer;Ljava/lang/String;)Ljava/lang/Runnable;
      56: invokevirtual #225                // Method mchorse/bbs_mod/ui/utils/context/ContextMenuManager.action:(Lmchorse/bbs_mod/ui/utils/icons/Icon;Lmchorse/bbs_mod/l10n/keys/IKey;Ljava/lang/Runnable;)Lmchorse/bbs_mod/ui/utils/context/ContextAction;
      59: pop
      60: goto          17
      63: aload_3
      64: invokevirtual #164                // Method mchorse/bbs_mod/ui/utils/context/ContextMenuManager.autoKeys:()Lmchorse/bbs_mod/ui/utils/context/ContextMenuManager;
      67: pop
      68: return

  private static void lambda$offerAdjacent$1(java.util.function.Consumer, java.lang.String);
    Code:
       0: aload_0
       1: aload_1
       2: invokeinterface #113,  2          // InterfaceMethod java/util/function/Consumer.accept:(Ljava/lang/Object;)V
       7: return

  private static void lambda$pickFormProperty$0(mchorse.bbs_mod.ui.framework.elements.input.keyframes.UIKeyframeEditor, mchorse.bbs_mod.ui.film.ICursor, java.lang.String, java.lang.String, mchorse.bbs_mod.settings.values.base.BaseValueBasic, boolean);
    Code:
       0: aload_0
       1: aload_1
       2: aload_2
       3: aload_3
       4: aload         4
       6: invokevirtual #192                // Method mchorse/bbs_mod/settings/values/base/BaseValueBasic.getId:()Ljava/lang/String;
       9: invokestatic  #291                // Method mchorse/bbs_mod/utils/StringUtils.combinePaths:(Ljava/lang/String;Ljava/lang/String;)Ljava/lang/String;
      12: iload         5
      14: invokestatic  #295                // Method pickProperty:(Lmchorse/bbs_mod/ui/framework/elements/input/keyframes/UIKeyframeEditor;Lmchorse/bbs_mod/ui/film/ICursor;Ljava/lang/String;Ljava/lang/String;Z)V
      17: return
}
